Workbook

Sheet 审计结论
A1: 项目 | B1: 结果
A2: 公司/核算主体 | B2: 默认主体
A3: 报告期间 | B3: 2026-01-01 至 2026-06-30
A4: 测算范围 | B4: 已实现＋未实现
A5: 各公司按本位币分别比较；不同本位币不汇总。
A7: 公司 | B7: 记账本位币 | C7: 已实现审计测算 | D7: 未实现审计测算 | E7: 审计合计 | F7: 客户账面合计（JE） | G7: 差异 | H7: 结论
A8: SZ01 | B8: CNY | C8: 0 | D8: =SUMIFS('未实现月度测算'!$J$2:$J$97,'未实现月度测算'!$A$2:$A$97,A8,'未实现月度测算'!$K$2:$K$97,B8) -> 76664.21 | E8: =C8+D8 -> 76664.21 | F8: =SUMIFS($E$13:$E$14,$A$13:$A$14,A8,$B$13:$B$14,B8) -> -19025.97 | G8: =E8-F8 -> 95690.18 | H8: =IF(OR(NOT(ISNUMBER(F8)),NOT(ISNUMBER(G8))),"无法判断",IF(ABS(F8)<0.01,"无法判断",IF(ABS(G8/F8)<0.05,"通过","不通过"))) -> 不通过
A9: US01 | B9: USD | C9: 0 | D9: =SUMIFS('未实现月度测算'!$J$2:$J$97,'未实现月度测算'!$A$2:$A$97,A9,'未实现月度测算'!$K$2:$K$97,B9) -> 732.50203 | E9: =C9+D9 -> 732.50203 | F9: =SUMIFS($E$13:$E$14,$A$13:$A$14,A9,$B$13:$B$14,B9) -> -364 | G9: =E9-F9 -> 1096.502 | H9: =IF(OR(NOT(ISNUMBER(F9)),NOT(ISNUMBER(G9))),"无法判断",IF(ABS(F9)<0.01,"无法判断",IF(ABS(G9/F9)<0.05,"通过","不通过"))) -> 不通过
A11: 客户账面汇兑损益来源
A12: 主体 | B12: 本位币 | C12: JE源行 | D12: 汇兑损益科目 | E12: 客户账面金额 | F12: 日期 | G12: 凭证号
A13: SZ01 | B13: CNY | C13: 172 | D13: 财务费用-汇兑损益 | E13: -19025.97 | F13: 2026-06-30 | G13: SZ01-2026-06-30-FXREVAL-0630
A14: US01 | B14: USD | C14: 281 | D14: 财务费用-汇兑损益 | E14: -364 | F14: 2026-06-30 | G14: US01-2026-06-30-FXREVAL-0630
A16: 待复核凭证
A17: 凭证号 | B17: 日期 | C17: 分类 | D17: 账面汇差 | E17: 原因
A18: SZ01-2026-06-30-FXREVAL-0630 | B18: 2026-06-30 | C18: 不构成汇兑事项 | D18: -19025.97 | E18: 凭证未满足 A/B/C 已实现收付结构，也不满足原币无实际发生的未实现结构；账面汇差已从测算总体剔除
A19: US01-2026-06-30-FXREVAL-0630 | B19: 2026-06-30 | C19: 不构成汇兑事项 | D19: -364 | E19: 凭证未满足 A/B/C 已实现收付结构，也不满足原币无实际发生的未实现结构；账面汇差已从测算总体剔除
A21: 凭证分类复核
A22: 凭证号 | B22: 日期 | C22: 分类 | D22: 账面汇差 | E22: 状态 | F22: 原因
A23: SZ01-2026-06-30-FXREVAL-0630 | B23: 2026-06-30 | C23: 不构成汇兑事项 | D23: -19025.97 | E23: 不构成汇兑事项，账面汇差已剔除 | F23: 凭证未满足 A/B/C 已实现收付结构，也不满足原币无实际发生的未实现结构；账面汇差已从测算总体剔除
A24: US01-2026-06-30-FXREVAL-0630 | B24: 2026-06-30 | C24: 不构成汇兑事项 | D24: -364 | E24: 不构成汇兑事项，账面汇差已剔除 | F24: 凭证未满足 A/B/C 已实现收付结构，也不满足原币无实际发生的未实现结构；账面汇差已从测算总体剔除

Sheet 未实现月度测算
A1: 主体 | B1: 科目 | C1: 币种（原币→本位币） | D1: 月末 | E1: 期初审计余额 | F1: 本月审计发生额 | G1: 月末原币余额 | H1: 月末审计汇率 | I1: 审计月末余额 | J1: 未实现汇差
A2: SZ01 | B2: 01.13010.0000.0000.0000 其他应收款 | C2: USD→CNY | D2: 2026-01-31 | E2: 35600 | F2: 0 | G2: 5000 | H2: =INDEX('汇率表'!$A:$XFD,MATCH(D2,'汇率表'!$A:$A,0),MATCH(L2,'汇率表'!$1:$1,0)) -> 6.9678 | I2: =G2*H2 -> 34839 | J2: =E2+F2-I2 -> 761 | K2: CNY | L2: USD | M2: 5000
A3: SZ01 | B3: 01.21010.0000.0000.0000 应付账款 | C3: EUR→CNY | D3: 2026-01-31 | E3: -469800 | F3: =SUM(J101:J101) -> 40593 | G3: =M3+SUM(G101:G101) -> -55000 | H3: =INDEX('汇率表'!$A:$XFD,MATCH(D3,'汇率表'!$A:$A,0),MATCH(L3,'汇率表'!$1:$1,0)) -> 8.3244 | I3: =G3*H3 -> -457842 | J3: =E3+F3-I3 -> 28635 | K3: CNY | L3: EUR | M3: -60000
A4: SZ01 | B4: 01.21010.0000.0000.0000 应付账款 | C4: HKD→CNY | D4: 2026-01-31 | E4: -91000 | F4: =SUM(J102:J102) -> 4488.75 | G4: =M4+SUM(G102:G102) -> -95000 | H4: =INDEX('汇率表'!$A:$XFD,MATCH(D4,'汇率表'!$A:$A,0),MATCH(L4,'汇率表'!$1:$1,0)) -> 0.89262 | I4: =G4*H4 -> -84798.9 | J4: =E4+F4-I4 -> -1712.35 | K4: CNY | L4: HKD | M4: -100000
A5: SZ01 | B5: 01.21010.0000.0000.0000 应付账款 | C5: JPY→CNY | D5: 2026-01-31 | E5: 0 | F5: =SUM(J103:J103) -> -70537.6 | G5: =M5+SUM(G103:G103) -> -1600000 | H5: =INDEX('汇率表'!$A:$XFD,MATCH(D5,'汇率表'!$A:$A,0),MATCH(L5,'汇率表'!$1:$1,0)) -> 0.045464 | I5: =G5*H5 -> -72742.4 | J5: =E5+F5-I5 -> 2204.8 | K5: CNY | L5: JPY | M5: 0
A6: SZ01 | B6: 01.21010.0000.0000.0000 应付账款 | C6: USD→CNY | D6: 2026-01-31 | E6: -284800 | F6: 0 | G6: -40000 | H6: =INDEX('汇率表'!$A:$XFD,MATCH(D6,'汇率表'!$A:$A,0),MATCH(L6,'汇率表'!$1:$1,0)) -> 6.9678 | I6: =G6*H6 -> -278712 | J6: =E6+F6-I6 -> -6088 | K6: CNY | L6: USD | M6: -40000
A7: SZ01 | B7: 01.12010.0000.0000.0000 应收账款 | C7: EUR→CNY | D7: 2026-01-31 | E7: 313200 | F7: =SUM(J104:J105) -> 31431.38 | G7: =M7+SUM(G104:G105) -> 43800 | H7: =INDEX('汇率表'!$A:$XFD,MATCH(D7,'汇率表'!$A:$A,0),MATCH(L7,'汇率表'!$1:$1,0)) -> 8.3244 | I7: =G7*H7 -> 364608.72 | J7: =E7+F7-I7 -> -19977.34 | K7: CNY | L7: EUR | M7: 40000
A8: SZ01 | B8: 01.12010.0000.0000.0000 应收账款 | C8: HKD→CNY | D8: 2026-01-31 | E8: 27300 | F8: 0 | G8: 30000 | H8: =INDEX('汇率表'!$A:$XFD,MATCH(D8,'汇率表'!$A:$A,0),MATCH(L8,'汇率表'!$1:$1,0)) -> 0.89262 | I8: =G8*H8 -> 26778.6 | J8: =E8+F8-I8 -> 521.4 | K8: CNY | L8: HKD | M8: 30000
A9: SZ01 | B9: 01.12010.0000.0000.0000 应收账款 | C9: USD→CNY | D9: 2026-01-31 | E9: 1068000 | F9: =SUM(J106:J107) -> 45758.2 | G9: =M9+SUM(G106:G107) -> 156500 | H9: =INDEX('汇率表'!$A:$XFD,MATCH(D9,'汇率表'!$A:$A,0),MATCH(L9,'汇率表'!$1:$1,0)) -> 6.9678 | I9: =G9*H9 -> 1090460.7 | J9: =E9+F9-I9 -> 23297.5 | K9: CNY | L9: USD | M9: 150000
A10: SZ01 | B10: 01.11010.0000.0000.0000 银行存款 | C10: EUR→CNY | D10: 2026-01-31 | E10: 313200 | F10: =SUM(J108:J109) -> 32367.3 | G10: =M10+SUM(G108:G109) -> 44000 | H10: =INDEX('汇率表'!$A:$XFD,MATCH(D10,'汇率表'!$A:$A,0),MATCH(L10,'汇率表'!$1:$1,0)) -> 8.3244 | I10: =G10*H10 -> 366273.6 | J10: =E10+F10-I10 -> -20706.3 | K10: CNY | L10: EUR | M10: 40000
A11: SZ01 | B11: 01.11010.0000.0000.0000 银行存款 | C11: HKD→CNY | D11: 2026-01-31 | E11: 91000 | F11: =SUM(J110:J110) -> -4488.75 | G11: =M11+SUM(G110:G110) -> 95000 | H11: =INDEX('汇率表'!$A:$XFD,MATCH(D11,'汇率表'!$A:$A,0),MATCH(L11,'汇率表'!$1:$1,0)) -> 0.89262 | I11: =G11*H11 -> 84798.9 | J11: =E11+F11-I11 -> 1712.35 | K11: CNY | L11: HKD | M11: 100000
A12: SZ01 | B12: 01.11010.0000.0000.0000 银行存款 | C12: USD→CNY | D12: 2026-01-31 | E12: 712000 | F12: =SUM(J111:J112) -> 1649213 | G12: =M12+SUM(G111:G112) -> 335000 | H12: =INDEX('汇率表'!$A:$XFD,MATCH(D12,'汇率表'!$A:$A,0),MATCH(L12,'汇率表'!$1:$1,0)) -> 6.9678 | I12: =G12*H12 -> 2334213 | J12: =E12+F12-I12 -> 27000 | K12: CNY | L12: USD | M12: 100000
A13: SZ01 | B13: 01.25010.0000.0000.0000 长期借款 | C13: USD→CNY | D13: 2026-01-31 | E13: 0 | F13: =SUM(J113:J113) -> -1403940 | G13: =M13+SUM(G113:G113) -> -200000 | H13: =INDEX('汇率表'!$A:$XFD,MATCH(D13,'汇率表'!$A:$A,0),MATCH(L13,'汇率表'!$1:$1,0)) -> 6.9678 | I13: =G13*H13 -> -1393560 | J13: =E13+F13-I13 -> -10380 | K13: CNY | L13: USD | M13: 0
A14: US01 | B14: 02.13010.0000.0000.0000 其他应收款 | C14: EUR→USD | D14: 2026-01-31 | E14: 1100 | F14: 0 | G14: 1000 | H14: =INDEX('汇率表'!$A:$XFD,MATCH(D14,'汇率表'!$A:$A,0),MATCH(L14,'汇率表'!$1:$1,0))/INDEX('汇率表'!$A:$XFD,MATCH(D14,'汇率表'!$A:$A,0),MATCH(K14,'汇率表'!$1:$1,0)) -> 1.1946956 | I14: =G14*H14 -> 1194.6956 | J14: =E14+F14-I14 -> -94.6956 | K14: USD | L14: EUR | M14: 1000
A15: US01 | B15: 02.21010.0000.0000.0000 应付账款 | C15: EUR→USD | D15: 2026-01-31 | E15: -33000 | F15: =SUM(J114:J114) -> 1391.6407 | G15: =M15+SUM(G114:G114) -> -28800 | H15: =INDEX('汇率表'!$A:$XFD,MATCH(D15,'汇率表'!$A:$A,0),MATCH(L15,'汇率表'!$1:$1,0))/INDEX('汇率表'!$A:$XFD,MATCH(D15,'汇率表'!$A:$A,0),MATCH(K15,'汇率表'!$1:$1,0)) -> 1.1946956 | I15: =G15*H15 -> -34407.233 | J15: =E15+F15-I15 -> 2798.874 | K15: USD | L15: EUR | M15: -30000
A16: US01 | B16: 02.12010.0000.0000.0000 应收账款 | C16: EUR→USD | D16: 2026-01-31 | E16: 5500 | F16: =SUM(J115:J115) -> 3721.4693 | G16: =M16+SUM(G115:G115) -> 8200 | H16: =INDEX('汇率表'!$A:$XFD,MATCH(D16,'汇率表'!$A:$A,0),MATCH(L16,'汇率表'!$1:$1,0))/INDEX('汇率表'!$A:$XFD,MATCH(D16,'汇率表'!$A:$A,0),MATCH(K16,'汇率表'!$1:$1,0)) -> 1.1946956 | I16: =G16*H16 -> 9796.5039 | J16: =E16+F16-I16 -> -575.0346 | K16: USD | L16: EUR | M16: 5000
A17: US01 | B17: 02.11010.0000.0000.0000 银行存款 | C17: EUR→USD | D17: 2026-01-31 | E17: 22000 | F17: =SUM(J116:J116) -> -1391.6407 | G17: =M17+SUM(G116:G116) -> 18800 | H17: =INDEX('汇率表'!$A:$XFD,MATCH(D17,'汇率表'!$A:$A,0),MATCH(L17,'汇率表'!$1:$1,0))/INDEX('汇率表'!$A:$XFD,MATCH(D17,'汇率表'!$A:$A,0),MATCH(K17,'汇率表'!$1:$1,0)) -> 1.1946956 | I17: =G17*H17 -> 22460.277 | J17: =E17+F17-I17 -> -1851.918 | K17: USD | L17: EUR | M17: 20000
A18: SZ01 | B18: 01.13010.0000.0000.0000 其他应收款 | C18: USD→CNY | D18: 2026-02-28 | E18: =I2 -> 34839 | F18: 0 | G18: 5000 | H18: =INDEX('汇率表'!$A:$XFD,MATCH(D18,'汇率表'!$A:$A,0),MATCH(L18,'汇率表'!$1:$1,0)) -> 6.9228 | I18: =G18*H18 -> 34614 | J18: =E18+F18-I18 -> 225 | K18: CNY | L18: USD | M18: 5000
A19: SZ01 | B19: 01.21010.0000.0000.0000 应付账款 | C19: EUR→CNY | D19: 2026-02-28 | E19: =I3 -> -457842 | F19: =SUM(J117:J118) -> -370167.5 | G19: =M19+SUM(G117:G118) -> -100000 | H19: =INDEX('汇率表'!$A:$XFD,MATCH(D19,'汇率表'!$A:$A,0),MATCH(L19,'汇率表'!$1:$1,0)) -> 8.1208 | I19: =G19*H19 -> -812080 | J19: =E19+F19-I19 -> -15929.5 | K19: CNY | L19: EUR | M19: -55000
A20: SZ01 | B20: 01.21010.0000.0000.0000 应付账款 | C20: HKD→CNY | D20: 2026-02-28 | E20: =I4 -> -84798.9 | F20: =SUM(J119:J119) -> 4439.35 | G20: =M20+SUM(G119:G119) -> -90000 | H20: =INDEX('汇率表'!$A:$XFD,MATCH(D20,'汇率表'!$A:$A,0),MATCH(L20,'汇率表'!$1:$1,0)) -> 0.88484 | I20: =G20*H20 -> -79635.6 | J20: =E20+F20-I20 -> -723.95 | K20: CNY | L20: HKD | M20: -95000
A21: SZ01 | B21: 01.21010.0000.0000.0000 应付账款 | C21: JPY→CNY | D21: 2026-02-28 | E21: =I5 -> -72742.4 | F21: =SUM(J120:J120) -> -77016.8 | G21: =M21+SUM(G120:G120) -> -3300000 | H21: =INDEX('汇率表'!$A:$XFD,MATCH(D21,'汇率表'!$A:$A,0),MATCH(L21,'汇率表'!$1:$1,0)) -> 0.044216 | I21: =G21*H21 -> -145912.8 | J21: =E21+F21-I21 -> -3846.4 | K21: CNY | L21: JPY | M21: -1600000
A22: SZ01 | B22: 01.21010.0000.0000.0000 应付账款 | C22: USD→CNY | D22: 2026-02-28 | E22: =I6 -> -278712 | F22: 0 | G22: -40000 | H22: =INDEX('汇率表'!$A:$XFD,MATCH(D22,'汇率表'!$A:$A,0),MATCH(L22,'汇率表'!$1:$1,0)) -> 6.9228 | I22: =G22*H22 -> -276912 | J22: =E22+F22-I22 -> -1800 | K22: CNY | L22: USD | M22: -40000
A23: SZ01 | B23: 01.12010.0000.0000.0000 应收账款 | C23: EUR→CNY | D23: 2026-02-28 | E23: =I7 -> 364608.72 | F23: =SUM(J121:J122) -> 38242.18 | G23: =M23+SUM(G121:G122) -> 48400 | H23: =INDEX('汇率表'!$A:$XFD,MATCH(D23,'汇率表'!$A:$A,0),MATCH(L23,'汇率表'!$1:$1,0)) -> 8.1208 | I23: =G23*H23 -> 393046.72 | J23: =E23+F23-I23 -> 9804.18 | K23: CNY | L23: EUR | M23: 43800
A24: SZ01 | B24: 01.12010.0000.0000.0000 应收账款 | C24: HKD→CNY | D24: 2026-02-28 | E24: =I8 -> 26778.6 | F24: 0 | G24: 30000 | H24: =INDEX('汇率表'!$A:$XFD,MATCH(D24,'汇率表'!$A:$A,0),MATCH(L24,'汇率表'!$1:$1,0)) -> 0.88484 | I24: =G24*H24 -> 26545.2 | J24: =E24+F24-I24 -> 233.4 | K24: CNY | L24: HKD | M24: 30000
A25: SZ01 | B25: 01.12010.0000.0000.0000 应收账款 | C25: USD→CNY | D25: 2026-02-28 | E25: =I9 -> 1090460.7 | F25: =SUM(J123:J124) -> 55776.4 | G25: =M25+SUM(G123:G124) -> 164500 | H25: =INDEX('汇率表'!$A:$XFD,MATCH(D25,'汇率表'!$A:$A,0),MATCH(L25,'汇率表'!$1:$1,0)) -> 6.9228 | I25: =G25*H25 -> 1138800.6 | J25: =E25+F25-I25 -> 7436.5 | K25: CNY | L25: USD | M25: 156500
A26: SZ01 | B26: 01.11010.0000.0000.0000 银行存款 | C26: EUR→CNY | D26: 2026-02-28 | E26: =I10 -> 366273.6 | F26: =SUM(J125:J126) -> 32878 | G26: =M26+SUM(G125:G126) -> 48000 | H26: =INDEX('汇率表'!$A:$XFD,MATCH(D26,'汇率表'!$A:$A,0),MATCH(L26,'汇率表'!$1:$1,0)) -> 8.1208 | I26: =G26*H26 -> 389798.4 | J26: =E26+F26-I26 -> 9353.2 | K26: CNY | L26: EUR | M26: 44000
A27: SZ01 | B27: 01.11010.0000.0000.0000 银行存款 | C27: HKD→CNY | D27: 2026-02-28 | E27: =I11 -> 84798.9 | F27: =SUM(J127:J127) -> -4439.35 | G27: =M27+SUM(G127:G127) -> 90000 | H27: =INDEX('汇率表'!$A:$XFD,MATCH(D27,'汇率表'!$A:$A,0),MATCH(L27,'汇率表'!$1:$1,0)) -> 0.88484 | I27: =G27*H27 -> 79635.6 | J27: =E27+F27-I27 -> 723.95 | K27: CNY | L27: HKD | M27: 95000
A28: SZ01 | B28: 01.11010.0000.0000.0000 银行存款 | C28: USD→CNY | D28: 2026-02-28 | E28: =I12 -> 2334213 | F28: =SUM(J128:J128) -> 242893 | G28: =M28+SUM(G128:G128) -> 370000 | H28: =INDEX('汇率表'!$A:$XFD,MATCH(D28,'汇率表'!$A:$A,0),MATCH(L28,'汇率表'!$1:$1,0)) -> 6.9228 | I28: =G28*H28 -> 2561436 | J28: =E28+F28-I28 -> 15670 | K28: CNY | L28: USD | M28: 335000
A29: SZ01 | B29: 01.25010.0000.0000.0000 长期借款 | C29: USD→CNY | D29: 2026-02-28 | E29: =I13 -> -1393560 | F29: 0 | G29: -200000 | H29: =INDEX('汇率表'!$A:$XFD,MATCH(D29,'汇率表'!$A:$A,0),MATCH(L29,'汇率表'!$1:$1,0)) -> 6.9228 | I29: =G29*H29 -> -1384560 | J29: =E29+F29-I29 -> -9000 | K29: CNY | L29: USD | M29: -200000
A30: US01 | B30: 02.13010.0000.0000.0000 其他应收款 | C30: EUR→USD | D30: 2026-02-28 | E30: =I14 -> 1194.6956 | F30: 0 | G30: 1000 | H30: =INDEX('汇率表'!$A:$XFD,MATCH(D30,'汇率表'!$A:$A,0),MATCH(L30,'汇率表'!$1:$1,0))/INDEX('汇率表'!$A:$XFD,MATCH(D30,'汇率表'!$A:$A,0),MATCH(K30,'汇率表'!$1:$1,0)) -> 1.1730514 | I30: =G30*H30 -> 1173.0514 | J30: =E30+F30-I30 -> 21.644233 | K30: USD | L30: EUR | M30: 1000
A31: US01 | B31: 02.21010.0000.0000.0000 应付账款 | C31: EUR→USD | D31: 2026-02-28 | E31: =I15 -> -34407.233 | F31: =SUM(J129:J129) -> 1421.2802 | G31: =M31+SUM(G129:G129) -> -27600 | H31: =INDEX('汇率表'!$A:$XFD,MATCH(D31,'汇率表'!$A:$A,0),MATCH(L31,'汇率表'!$1:$1,0))/INDEX('汇率表'!$A:$XFD,MATCH(D31,'汇率表'!$A:$A,0),MATCH(K31,'汇率表'!$1:$1,0)) -> 1.1730514 | I31: =G31*H31 -> -32376.218 | J31: =E31+F31-I31 -> -609.73541 | K31: USD | L31: EUR | M31: -28800
A32: US01 | B32: 02.12010.0000.0000.0000 应收账款 | C32: EUR→USD | D32: 2026-02-28 | E32: =I16 -> 9796.5039 | F32: =SUM(J130:J130) -> 4039.0481 | G32: =M32+SUM(G130:G130) -> 11600 | H32: =INDEX('汇率表'!$A:$XFD,MATCH(D32,'汇率表'!$A:$A,0),MATCH(L32,'汇率表'!$1:$1,0))/INDEX('汇率表'!$A:$XFD,MATCH(D32,'汇率表'!$A:$A,0),MATCH(K32,'汇率表'!$1:$1,0)) -> 1.1730514 | I32: =G32*H32 -> 13607.396 | J32: =E32+F32-I32 -> 228.15612 | K32: USD | L32: EUR | M32: 8200
A33: US01 | B33: 02.11010.0000.0000.0000 银行存款 | C33: EUR→USD | D33: 2026-02-28 | E33: =I17 -> 22460.277 | F33: =SUM(J131:J131) -> -1421.2802 | G33: =M33+SUM(G131:G131) -> 17600 | H33: =INDEX('汇率表'!$A:$XFD,MATCH(D33,'汇率表'!$A:$A,0),MATCH(L33,'汇率表'!$1:$1,0))/INDEX('汇率表'!$A:$XFD,MATCH(D33,'汇率表'!$A:$A,0),MATCH(K33,'汇率表'!$1:$1,0)) -> 1.1730514 | I33: =G33*H33 -> 20645.704 | J33: =E33+F33-I33 -> 393.29307 | K33: USD | L33: EUR | M33: 18800
A34: SZ01 | B34: 01.13010.0000.0000.0000 其他应收款 | C34: USD→CNY | D34: 2026-03-31 | E34: =I18 -> 34614 | F34: 0 | G34: 5000 | H34: =INDEX('汇率表'!$A:$XFD,MATCH(D34,'汇率表'!$A:$A,0),MATCH(L34,'汇率表'!$1:$1,0)) -> 6.9194 | I34: =G34*H34 -> 34597 | J34: =E34+F34-I34 -> 17 | K34: CNY | L34: USD | M34: 5000
A35: SZ01 | B35: 01.21010.0000.0000.0000 应付账款 | C35: EUR→CNY | D35: 2026-03-31 | E35: =I19 -> -812080 | F35: =SUM(J132:J132) -> 39837.5 | G35: =M35+SUM(G132:G132) -> -95000 | H35: =INDEX('汇率表'!$A:$XFD,MATCH(D35,'汇率表'!$A:$A,0),MATCH(L35,'汇率表'!$1:$1,0)) -> 7.9302 | I35: =G35*H35 -> -753369 | J35: =E35+F35-I35 -> -18873.5 | K35: CNY | L35: EUR | M35: -100000
A36: SZ01 | B36: 01.21010.0000.0000.0000 应付账款 | C36: HKD→CNY | D36: 2026-03-31 | E36: =I20 -> -79635.6 | F36: =SUM(J133:J133) -> 4395.75 | G36: =M36+SUM(G133:G133) -> -85000 | H36: =INDEX('汇率表'!$A:$XFD,MATCH(D36,'汇率表'!$A:$A,0),MATCH(L36,'汇率表'!$1:$1,0)) -> 0.88295 | I36: =G36*H36 -> -75050.75 | J36: =E36+F36-I36 -> -189.1 | K36: CNY | L36: HKD | M36: -90000
A37: SZ01 | B37: 01.21010.0000.0000.0000 应付账款 | C37: JPY→CNY | D37: 2026-03-31 | E37: =I21 -> -145912.8 | F37: =SUM(J134:J134) -> -77911.2 | G37: =M37+SUM(G134:G134) -> -5100000 | H37: =INDEX('汇率表'!$A:$XFD,MATCH(D37,'汇率表'!$A:$A,0),MATCH(L37,'汇率表'!$1:$1,0)) -> 0.043296 | I37: =G37*H37 -> -220809.6 | J37: =E37+F37-I37 -> -3014.4 | K37: CNY | L37: JPY | M37: -3300000
A38: SZ01 | B38: 01.21010.0000.0000.0000 应付账款 | C38: USD→CNY | D38: 2026-03-31 | E38: =I22 -> -276912 | F38: 0 | G38: -40000 | H38: =INDEX('汇率表'!$A:$XFD,MATCH(D38,'汇率表'!$A:$A,0),MATCH(L38,'汇率表'!$1:$1,0)) -> 6.9194 | I38: =G38*H38 -> -276776 | J38: =E38+F38-I38 -> -136 | K38: CNY | L38: USD | M38: -40000
A39: SZ01 | B39: 01.12010.0000.0000.0000 应收账款 | C39: EUR→CNY | D39: 2026-03-31 | E39: =I23 -> 393046.72 | F39: =SUM(J135:J136) -> 44002.62 | G39: =M39+SUM(G135:G136) -> 53800 | H39: =INDEX('汇率表'!$A:$XFD,MATCH(D39,'汇率表'!$A:$A,0),MATCH(L39,'汇率表'!$1:$1,0)) -> 7.9302 | I39: =G39*H39 -> 426644.76 | J39: =E39+F39-I39 -> 10404.58 | K39: CNY | L39: EUR | M39: 48400
A40: SZ01 | B40: 01.12010.0000.0000.0000 应收账款 | C40: HKD→CNY | D40: 2026-03-31 | E40: =I24 -> 26545.2 | F40: 0 | G40: 30000 | H40: =INDEX('汇率表'!$A:$XFD,MATCH(D40,'汇率表'!$A:$A,0),MATCH(L40,'汇率表'!$1:$1,0)) -> 0.88295 | I40: =G40*H40 -> 26488.5 | J40: =E40+F40-I40 -> 56.7 | K40: CNY | L40: HKD | M40: 30000
A41: SZ01 | B41: 01.12010.0000.0000.0000 应收账款 | C41: USD→CNY | D41: 2026-03-31 | E41: =I25 -> 1138800.6 | F41: =SUM(J137:J138) -> 65788.4 | G41: =M41+SUM(G137:G138) -> 174000 | H41: =INDEX('汇率表'!$A:$XFD,MATCH(D41,'汇率表'!$A:$A,0),MATCH(L41,'汇率表'!$1:$1,0)) -> 6.9194 | I41: =G41*H41 -> 1203975.6 | J41: =E41+F41-I41 -> 613.4 | K41: CNY | L41: USD | M41: 164500
A42: SZ01 | B42: 01.11010.0000.0000.0000 银行存款 | C42: EUR→CNY | D42: 2026-03-31 | E42: =I26 -> 389798.4 | F42: =SUM(J139:J140) -> 31645 | G42: =M42+SUM(G139:G140) -> 52000 | H42: =INDEX('汇率表'!$A:$XFD,MATCH(D42,'汇率表'!$A:$A,0),MATCH(L42,'汇率表'!$1:$1,0)) -> 7.9302 | I42: =G42*H42 -> 412370.4 | J42: =E42+F42-I42 -> 9073 | K42: CNY | L42: EUR | M42: 48000
A43: SZ01 | B43: 01.11010.0000.0000.0000 银行存款 | C43: HKD→CNY | D43: 2026-03-31 | E43: =I27 -> 79635.6 | F43: =SUM(J141:J141) -> -4395.75 | G43: =M43+SUM(G141:G141) -> 85000 | H43: =INDEX('汇率表'!$A:$XFD,MATCH(D43,'汇率表'!$A:$A,0),MATCH(L43,'汇率表'!$1:$1,0)) -> 0.88295 | I43: =G43*H43 -> 75050.75 | J43: =E43+F43-I43 -> 189.1 | K43: CNY | L43: HKD | M43: 90000
A44: SZ01 | B44: 01.11010.0000.0000.0000 银行存款 | C44: USD→CNY | D44: 2026-03-31 | E44: =I28 -> 2561436 | F44: =SUM(J142:J143) -> -103308.5 | G44: =M44+SUM(G142:G143) -> 355000 | H44: =INDEX('汇率表'!$A:$XFD,MATCH(D44,'汇率表'!$A:$A,0),MATCH(L44,'汇率表'!$1:$1,0)) -> 6.9194 | I44: =G44*H44 -> 2456387 | J44: =E44+F44-I44 -> 1740.5 | K44: CNY | L44: USD | M44: 370000
A45: SZ01 | B45: 01.25010.0000.0000.0000 长期借款 | C45: USD→CNY | D45: 2026-03-31 | E45: =I29 -> -1384560 | F45: =SUM(J144:J144) -> 344490 | G45: =M45+SUM(G144:G144) -> -150000 | H45: =INDEX('汇率表'!$A:$XFD,MATCH(D45,'汇率表'!$A:$A,0),MATCH(L45,'汇率表'!$1:$1,0)) -> 6.9194 | I45: =G45*H45 -> -1037910 | J45: =E45+F45-I45 -> -2160 | K45: CNY | L45: USD | M45: -200000
A46: US01 | B46: 02.13010.0000.0000.0000 其他应收款 | C46: EUR→USD | D46: 2026-03-31 | E46: =I30 -> 1173.0514 | F46: 0 | G46: 1000 | H46: =INDEX('汇率表'!$A:$XFD,MATCH(D46,'汇率表'!$A:$A,0),MATCH(L46,'汇率表'!$1:$1,0))/INDEX('汇率表'!$A:$XFD,MATCH(D46,'汇率表'!$A:$A,0),MATCH(K46,'汇率表'!$1:$1,0)) -> 1.146082 | I46: =G46*H46 -> 1146.082 | J46: =E46+F46-I46 -> 26.969336 | K46: USD | L46: EUR | M46: 1000
A47: US01 | B47: 02.21010.0000.0000.0000 应付账款 | C47: EUR→USD | D47: 2026-03-31 | E47: =I31 -> -32376.218 | F47: =SUM(J145:J145) -> 1387.7036 | G47: =M47+SUM(G145:G145) -> -26400 | H47: =INDEX('汇率表'!$A:$XFD,MATCH(D47,'汇率表'!$A:$A,0),MATCH(L47,'汇率表'!$1:$1,0))/INDEX('汇率表'!$A:$XFD,MATCH(D47,'汇率表'!$A:$A,0),MATCH(K47,'汇率表'!$1:$1,0)) -> 1.146082 | I47: =G47*H47 -> -30256.566 | J47: =E47+F47-I47 -> -731.94856 | K47: USD | L47: EUR | M47: -27600
A48: US01 | B48: 02.12010.0000.0000.0000 应收账款 | C48: EUR→USD | D48: 2026-03-31 | E48: =I32 -> 13607.396 | F48: =SUM(J146:J146) -> 4185.3353 | G48: =M48+SUM(G146:G146) -> 15200 | H48: =INDEX('汇率表'!$A:$XFD,MATCH(D48,'汇率表'!$A:$A,0),MATCH(L48,'汇率表'!$1:$1,0))/INDEX('汇率表'!$A:$XFD,MATCH(D48,'汇率表'!$A:$A,0),MATCH(K48,'汇率表'!$1:$1,0)) -> 1.146082 | I48: =G48*H48 -> 17420.447 | J48: =E48+F48-I48 -> 372.2843 | K48: USD | L48: EUR | M48: 11600
A49: US01 | B49: 02.11010.0000.0000.0000 银行存款 | C49: EUR→USD | D49: 2026-03-31 | E49: =I33 -> 20645.704 | F49: =SUM(J147:J147) -> -1387.7036 | G49: =M49+SUM(G147:G147) -> 16400 | H49: =INDEX('汇率表'!$A:$XFD,MATCH(D49,'汇率表'!$A:$A,0),MATCH(L49,'汇率表'!$1:$1,0))/INDEX('汇率表'!$A:$XFD,MATCH(D49,'汇率表'!$A:$A,0),MATCH(K49,'汇率表'!$1:$1,0)) -> 1.146082 | I49: =G49*H49 -> 18795.745 | J49: =E49+F49-I49 -> 462.25519 | K49: USD | L49: EUR | M49: 17600
A50: SZ01 | B50: 01.13010.0000.0000.0000 其他应收款 | C50: USD→CNY | D50: 2026-04-30 | E50: =I34 -> 34597 | F50: 0 | G50: 5000 | H50: =INDEX('汇率表'!$A:$XFD,MATCH(D50,'汇率表'!$A:$A,0),MATCH(L50,'汇率表'!$1:$1,0)) -> 6.8628 | I50: =G50*H50 -> 34314 | J50: =E50+F50-I50 -> 283 | K50: CNY | L50: USD | M50: 5000
A51: SZ01 | B51: 01.21010.0000.0000.0000 应付账款 | C51: EUR→CNY | D51: 2026-04-30 | E51: =I35 -> -753369 | F51: =SUM(J148:J148) -> 40201 | G51: =M51+SUM(G148:G148) -> -90000 | H51: =INDEX('汇率表'!$A:$XFD,MATCH(D51,'汇率表'!$A:$A,0),MATCH(L51,'汇率表'!$1:$1,0)) -> 8.0057 | I51: =G51*H51 -> -720513 | J51: =E51+F51-I51 -> 7345 | K51: CNY | L51: EUR | M51: -95000
A52: SZ01 | B52: 01.21010.0000.0000.0000 应付账款 | C52: HKD→CNY | D52: 2026-04-30 | E52: =I36 -> -75050.75 | F52: =SUM(J149:J149) -> 4383.15 | G52: =M52+SUM(G149:G149) -> -80000 | H52: =INDEX('汇率表'!$A:$XFD,MATCH(D52,'汇率表'!$A:$A,0),MATCH(L52,'汇率表'!$1:$1,0)) -> 0.87581 | I52: =G52*H52 -> -70064.8 | J52: =E52+F52-I52 -> -602.8 | K52: CNY | L52: HKD | M52: -85000
A53: SZ01 | B53: 01.21010.0000.0000.0000 应付账款 | C53: JPY→CNY | D53: 2026-04-30 | E53: =I37 -> -220809.6 | F53: =SUM(J150:J150) -> -81758.9 | G53: =M53+SUM(G150:G150) -> -7000000 | H53: =INDEX('汇率表'!$A:$XFD,MATCH(D53,'汇率表'!$A:$A,0),MATCH(L53,'汇率表'!$1:$1,0)) -> 0.042812 | I53: =G53*H53 -> -299684 | J53: =E53+F53-I53 -> -2884.5 | K53: CNY | L53: JPY | M53: -5100000
A54: SZ01 | B54: 01.21010.0000.0000.0000 应付账款 | C54: USD→CNY | D54: 2026-04-30 | E54: =I38 -> -276776 | F54: 0 | G54: -40000 | H54: =INDEX('汇率表'!$A:$XFD,MATCH(D54,'汇率表'!$A:$A,0),MATCH(L54,'汇率表'!$1:$1,0)) -> 6.8628 | I54: =G54*H54 -> -274512 | J54: =E54+F54-I54 -> -2264 | K54: CNY | L54: USD | M54: -40000
A55: SZ01 | B55: 01.12010.0000.0000.0000 应收账款 | C55: EUR→CNY | D55: 2026-04-30 | E55: =I39 -> 426644.76 | F55: =SUM(J151:J152) -> 49089.4 | G55: =M55+SUM(G151:G152) -> 60000 | H55: =INDEX('汇率表'!$A:$XFD,MATCH(D55,'汇率表'!$A:$A,0),MATCH(L55,'汇率表'!$1:$1,0)) -> 8.0057 | I55: =G55*H55 -> 480342 | J55: =E55+F55-I55 -> -4607.84 | K55: CNY | L55: EUR | M55: 53800
A56: SZ01 | B56: 01.12010.0000.0000.0000 应收账款 | C56: HKD→CNY | D56: 2026-04-30 | E56: =I40 -> 26488.5 | F56: 0 | G56: 30000 | H56: =INDEX('汇率表'!$A:$XFD,MATCH(D56,'汇率表'!$A:$A,0),MATCH(L56,'汇率表'!$1:$1,0)) -> 0.87581 | I56: =G56*H56 -> 26274.3 | J56: =E56+F56-I56 -> 214.2 | K56: CNY | L56: HKD | M56: 30000
A57: SZ01 | B57: 01.12010.0000.0000.0000 应收账款 | C57: USD→CNY | D57: 2026-04-30 | E57: =I41 -> 1203975.6 | F57: =SUM(J153:J154) -> 75631.4 | G57: =M57+SUM(G153:G154) -> 185000 | H57: =INDEX('汇率表'!$A:$XFD,MATCH(D57,'汇率表'!$A:$A,0),MATCH(L57,'汇率表'!$1:$1,0)) -> 6.8628 | I57: =G57*H57 -> 1269618 | J57: =E57+F57-I57 -> 9989 | K57: CNY | L57: USD | M57: 174000
A58: SZ01 | B58: 01.11010.0000.0000.0000 银行存款 | C58: EUR→CNY | D58: 2026-04-30 | E58: =I42 -> 412370.4 | F58: =SUM(J155:J156) -> 32355.2 | G58: =M58+SUM(G155:G156) -> 56000 | H58: =INDEX('汇率表'!$A:$XFD,MATCH(D58,'汇率表'!$A:$A,0),MATCH(L58,'汇率表'!$1:$1,0)) -> 8.0057 | I58: =G58*H58 -> 448319.2 | J58: =E58+F58-I58 -> -3593.6 | K58: CNY | L58: EUR | M58: 52000
A59: SZ01 | B59: 01.11010.0000.0000.0000 银行存款 | C59: HKD→CNY | D59: 2026-04-30 | E59: =I43 -> 75050.75 | F59: =SUM(J157:J157) -> -4383.15 | G59: =M59+SUM(G157:G157) -> 80000 | H59: =INDEX('汇率表'!$A:$XFD,MATCH(D59,'汇率表'!$A:$A,0),MATCH(L59,'汇率表'!$1:$1,0)) -> 0.87581 | I59: =G59*H59 -> 70064.8 | J59: =E59+F59-I59 -> 602.8 | K59: CNY | L59: HKD | M59: 85000
A60: SZ01 | B60: 01.11010.0000.0000.0000 银行存款 | C60: USD→CNY | D60: 2026-04-30 | E60: =I44 -> 2456387 | F60: =SUM(J158:J158) -> 240177 | G60: =M60+SUM(G158:G158) -> 390000 | H60: =INDEX('汇率表'!$A:$XFD,MATCH(D60,'汇率表'!$A:$A,0),MATCH(L60,'汇率表'!$1:$1,0)) -> 6.8628 | I60: =G60*H60 -> 2676492 | J60: =E60+F60-I60 -> 20072 | K60: CNY | L60: USD | M60: 355000
A61: SZ01 | B61: 01.25010.0000.0000.0000 长期借款 | C61: USD→CNY | D61: 2026-04-30 | E61: =I45 -> -1037910 | F61: 0 | G61: -150000 | H61: =INDEX('汇率表'!$A:$XFD,MATCH(D61,'汇率表'!$A:$A,0),MATCH(L61,'汇率表'!$1:$1,0)) -> 6.8628 | I61: =G61*H61 -> -1029420 | J61: =E61+F61-I61 -> -8490 | K61: CNY | L61: USD | M61: -150000
A62: US01 | B62: 02.13010.0000.0000.0000 其他应收款 | C62: EUR→USD | D62: 2026-04-30 | E62: =I46 -> 1146.082 | F62: 0 | G62: 1000 | H62: =INDEX('汇率表'!$A:$XFD,MATCH(D62,'汇率表'!$A:$A,0),MATCH(L62,'汇率表'!$1:$1,0))/INDEX('汇率表'!$A:$XFD,MATCH(D62,'汇率表'!$A:$A,0),MATCH(K62,'汇率表'!$1:$1,0)) -> 1.1665355 | I62: =G62*H62 -> 1166.5355 | J62: =E62+F62-I62 -> -20.453495 | K62: USD | L62: EUR | M62: 1000
A63: US01 | B63: 02.21010.0000.0000.0000 应付账款 | C63: EUR→USD | D63: 2026-04-30 | E63: =I47 -> -30256.566 | F63: =SUM(J159:J159) -> 1405.4656 | G63: =M63+SUM(G159:G159) -> -25200 | H63: =INDEX('汇率表'!$A:$XFD,MATCH(D63,'汇率表'!$A:$A,0),MATCH(L63,'汇率表'!$1:$1,0))/INDEX('汇率表'!$A:$XFD,MATCH(D63,'汇率表'!$A:$A,0),MATCH(K63,'汇率表'!$1:$1,0)) -> 1.1665355 | I63: =G63*H63 -> -29396.695 | J63: =E63+F63-I63 -> 545.59519 | K63: USD | L63: EUR | M63: -26400
A64: US01 | B64: 02.12010.0000.0000.0000 应收账款 | C64: EUR→USD | D64: 2026-04-30 | E64: =I48 -> 17420.447 | F64: =SUM(J160:J160) -> 4429.6618 | G64: =M64+SUM(G160:G160) -> 19000 | H64: =INDEX('汇率表'!$A:$XFD,MATCH(D64,'汇率表'!$A:$A,0),MATCH(L64,'汇率表'!$1:$1,0))/INDEX('汇率表'!$A:$XFD,MATCH(D64,'汇率表'!$A:$A,0),MATCH(K64,'汇率表'!$1:$1,0)) -> 1.1665355 | I64: =G64*H64 -> 22164.175 | J64: =E64+F64-I64 -> -314.06633 | K64: USD | L64: EUR | M64: 15200
A65: US01 | B65: 02.11010.0000.0000.0000 银行存款 | C65: EUR→USD | D65: 2026-04-30 | E65: =I49 -> 18795.745 | F65: =SUM(J161:J161) -> -1405.4656 | G65: =M65+SUM(G161:G161) -> 15200 | H65: =INDEX('汇率表'!$A:$XFD,MATCH(D65,'汇率表'!$A:$A,0),MATCH(L65,'汇率表'!$1:$1,0))/INDEX('汇率表'!$A:$XFD,MATCH(D65,'汇率表'!$A:$A,0),MATCH(K65,'汇率表'!$1:$1,0)) -> 1.1665355 | I65: =G65*H65 -> 17731.34 | J65: =E65+F65-I65 -> -341.06025 | K65: USD | L65: EUR | M65: 16400
A66: SZ01 | B66: 01.13010.0000.0000.0000 其他应收款 | C66: USD→CNY | D66: 2026-05-31 | E66: =I50 -> 34314 | F66: 0 | G66: 5000 | H66: =INDEX('汇率表'!$A:$XFD,MATCH(D66,'汇率表'!$A:$A,0),MATCH(L66,'汇率表'!$1:$1,0)) -> 6.8176 | I66: =G66*H66 -> 34088 | J66: =E66+F66-I66 -> 226 | K66: CNY | L66: USD | M66: 5000
A67: SZ01 | B67: 01.21010.0000.0000.0000 应付账款 | C67: EUR→CNY | D67: 2026-05-31 | E67: =I51 -> -720513 | F67: =SUM(J162:J162) -> 39603.5 | G67: =M67+SUM(G162:G162) -> -85000 | H67: =INDEX('汇率表'!$A:$XFD,MATCH(D67,'汇率表'!$A:$A,0),MATCH(L67,'汇率表'!$1:$1,0)) -> 7.916 | I67: =G67*H67 -> -672860 | J67: =E67+F67-I67 -> -8049.5 | K67: CNY | L67: EUR | M67: -90000
A68: SZ01 | B68: 01.21010.0000.0000.0000 应付账款 | C68: HKD→CNY | D68: 2026-05-31 | E68: =I52 -> -70064.8 | F68: =SUM(J163:J163) -> 4365.3 | G68: =M68+SUM(G163:G163) -> -75000 | H68: =INDEX('汇率表'!$A:$XFD,MATCH(D68,'汇率表'!$A:$A,0),MATCH(L68,'汇率表'!$1:$1,0)) -> 0.87029 | I68: =G68*H68 -> -65271.75 | J68: =E68+F68-I68 -> -427.75 | K68: CNY | L68: HKD | M68: -80000
A69: SZ01 | B69: 01.21010.0000.0000.0000 应付账款 | C69: JPY→CNY | D69: 2026-05-31 | E69: =I53 -> -299684 | F69: =SUM(J164:J164) -> -86252 | G69: =M69+SUM(G164:G164) -> -9000000 | H69: =INDEX('汇率表'!$A:$XFD,MATCH(D69,'汇率表'!$A:$A,0),MATCH(L69,'汇率表'!$1:$1,0)) -> 0.042718 | I69: =G69*H69 -> -384462 | J69: =E69+F69-I69 -> -1474 | K69: CNY | L69: JPY | M69: -7000000
A70: SZ01 | B70: 01.21010.0000.0000.0000 应付账款 | C70: USD→CNY | D70: 2026-05-31 | E70: =I54 -> -274512 | F70: 0 | G70: -40000 | H70: =INDEX('汇率表'!$A:$XFD,MATCH(D70,'汇率表'!$A:$A,0),MATCH(L70,'汇率表'!$1:$1,0)) -> 6.8176 | I70: =G70*H70 -> -272704 | J70: =E70+F70-I70 -> -1808 | K70: CNY | L70: USD | M70: -40000
A71: SZ01 | B71: 01.12010.0000.0000.0000 应收账款 | C71: EUR→CNY | D71: 2026-05-31 | E71: =I55 -> 480342 | F71: =SUM(J165:J166) -> 56856.9 | G71: =M71+SUM(G165:G166) -> 67000 | H71: =INDEX('汇率表'!$A:$XFD,MATCH(D71,'汇率表'!$A:$A,0),MATCH(L71,'汇率表'!$1:$1,0)) -> 7.916 | I71: =G71*H71 -> 530372 | J71: =E71+F71-I71 -> 6826.9 | K71: CNY | L71: EUR | M71: 60000
A72: SZ01 | B72: 01.12010.0000.0000.0000 应收账款 | C72: HKD→CNY | D72: 2026-05-31 | E72: =I56 -> 26274.3 | F72: 0 | G72: 30000 | H72: =INDEX('汇率表'!$A:$XFD,MATCH(D72,'汇率表'!$A:$A,0),MATCH(L72,'汇率表'!$1:$1,0)) -> 0.87029 | I72: =G72*H72 -> 26108.7 | J72: =E72+F72-I72 -> 165.6 | K72: CNY | L72: HKD | M72: 30000
A73: SZ01 | B73: 01.12010.0000.0000.0000 应收账款 | C73: USD→CNY | D73: 2026-05-31 | E73: =I57 -> 1269618 | F73: =SUM(J167:J168) -> 85862 | G73: =M73+SUM(G167:G168) -> 197500 | H73: =INDEX('汇率表'!$A:$XFD,MATCH(D73,'汇率表'!$A:$A,0),MATCH(L73,'汇率表'!$1:$1,0)) -> 6.8176 | I73: =G73*H73 -> 1346476 | J73: =E73+F73-I73 -> 9004 | K73: CNY | L73: USD | M73: 185000
A74: SZ01 | B74: 01.11010.0000.0000.0000 银行存款 | C74: EUR→CNY | D74: 2026-05-31 | E74: =I58 -> 448319.2 | F74: =SUM(J169:J170) -> 31762 | G74: =M74+SUM(G169:G170) -> 60000 | H74: =INDEX('汇率表'!$A:$XFD,MATCH(D74,'汇率表'!$A:$A,0),MATCH(L74,'汇率表'!$1:$1,0)) -> 7.916 | I74: =G74*H74 -> 474960 | J74: =E74+F74-I74 -> 5121.2 | K74: CNY | L74: EUR | M74: 56000
A75: SZ01 | B75: 01.11010.0000.0000.0000 银行存款 | C75: HKD→CNY | D75: 2026-05-31 | E75: =I59 -> 70064.8 | F75: =SUM(J171:J171) -> -4365.3 | G75: =M75+SUM(G171:G171) -> 75000 | H75: =INDEX('汇率表'!$A:$XFD,MATCH(D75,'汇率表'!$A:$A,0),MATCH(L75,'汇率表'!$1:$1,0)) -> 0.87029 | I75: =G75*H75 -> 65271.75 | J75: =E75+F75-I75 -> 427.75 | K75: CNY | L75: HKD | M75: 80000
A76: SZ01 | B76: 01.11010.0000.0000.0000 银行存款 | C76: USD→CNY | D76: 2026-05-31 | E76: =I60 -> 2676492 | F76: =SUM(J172:J172) -> 239522.5 | G76: =M76+SUM(G172:G172) -> 425000 | H76: =INDEX('汇率表'!$A:$XFD,MATCH(D76,'汇率表'!$A:$A,0),MATCH(L76,'汇率表'!$1:$1,0)) -> 6.8176 | I76: =G76*H76 -> 2897480 | J76: =E76+F76-I76 -> 18534.5 | K76: CNY | L76: USD | M76: 390000
A77: SZ01 | B77: 01.25010.0000.0000.0000 长期借款 | C77: USD→CNY | D77: 2026-05-31 | E77: =I61 -> -1029420 | F77: 0 | G77: -150000 | H77: =INDEX('汇率表'!$A:$XFD,MATCH(D77,'汇率表'!$A:$A,0),MATCH(L77,'汇率表'!$1:$1,0)) -> 6.8176 | I77: =G77*H77 -> -1022640 | J77: =E77+F77-I77 -> -6780 | K77: CNY | L77: USD | M77: -150000
A78: US01 | B78: 02.13010.0000.0000.0000 其他应收款 | C78: EUR→USD | D78: 2026-05-31 | E78: =I62 -> 1166.5355 | F78: 0 | G78: 1000 | H78: =INDEX('汇率表'!$A:$XFD,MATCH(D78,'汇率表'!$A:$A,0),MATCH(L78,'汇率表'!$1:$1,0))/INDEX('汇率表'!$A:$XFD,MATCH(D78,'汇率表'!$A:$A,0),MATCH(K78,'汇率表'!$1:$1,0)) -> 1.1611124 | I78: =G78*H78 -> 1161.1124 | J78: =E78+F78-I78 -> 5.4231099 | K78: USD | L78: EUR | M78: 1000
A79: US01 | B79: 02.21010.0000.0000.0000 应付账款 | C79: EUR→USD | D79: 2026-05-31 | E79: =I63 -> -29396.695 | F79: =SUM(J173:J173) -> 1389.6574 | G79: =M79+SUM(G173:G173) -> -24000 | H79: =INDEX('汇率表'!$A:$XFD,MATCH(D79,'汇率表'!$A:$A,0),MATCH(L79,'汇率表'!$1:$1,0))/INDEX('汇率表'!$A:$XFD,MATCH(D79,'汇率表'!$A:$A,0),MATCH(K79,'汇率表'!$1:$1,0)) -> 1.1611124 | I79: =G79*H79 -> -27866.698 | J79: =E79+F79-I79 -> -140.33983 | K79: USD | L79: EUR | M79: -25200
A80: US01 | B80: 02.12010.0000.0000.0000 应收账款 | C80: EUR→USD | D80: 2026-05-31 | E80: =I64 -> 22164.175 | F80: =SUM(J174:J174) -> 4679.513 | G80: =M80+SUM(G174:G174) -> 23000 | H80: =INDEX('汇率表'!$A:$XFD,MATCH(D80,'汇率表'!$A:$A,0),MATCH(L80,'汇率表'!$1:$1,0))/INDEX('汇率表'!$A:$XFD,MATCH(D80,'汇率表'!$A:$A,0),MATCH(K80,'汇率表'!$1:$1,0)) -> 1.1611124 | I80: =G80*H80 -> 26705.586 | J80: =E80+F80-I80 -> 138.10244 | K80: USD | L80: EUR | M80: 19000
A81: US01 | B81: 02.11010.0000.0000.0000 银行存款 | C81: EUR→USD | D81: 2026-05-31 | E81: =I65 -> 17731.34 | F81: =SUM(J175:J175) -> -1389.6574 | G81: =M81+SUM(G175:G175) -> 14000 | H81: =INDEX('汇率表'!$A:$XFD,MATCH(D81,'汇率表'!$A:$A,0),MATCH(L81,'汇率表'!$1:$1,0))/INDEX('汇率表'!$A:$XFD,MATCH(D81,'汇率表'!$A:$A,0),MATCH(K81,'汇率表'!$1:$1,0)) -> 1.1611124 | I81: =G81*H81 -> 16255.574 | J81: =E81+F81-I81 -> 86.108728 | K81: USD | L81: EUR | M81: 15200
A82: SZ01 | B82: 01.13010.0000.0000.0000 其他应收款 | C82: USD→CNY | D82: 2026-06-30 | E82: =I66 -> 34088 | F82: =SUM(J176:J176) -> 284.5594 | G82: =M82+SUM(G176:G176) -> 5041.78 | H82: =INDEX('汇率表'!$A:$XFD,MATCH(D82,'汇率表'!$A:$A,0),MATCH(L82,'汇率表'!$1:$1,0)) -> 6.8109 | I82: =G82*H82 -> 34339.059 | J82: =E82+F82-I82 -> 33.5 | K82: CNY | L82: USD | M82: 5000
A83: SZ01 | B83: 01.21010.0000.0000.0000 应付账款 | C83: EUR→CNY | D83: 2026-06-30 | E83: =I67 -> -672860 | F83: =SUM(J177:J178) -> 33581.213 | G83: =M83+SUM(G177:G178) -> -80708.86 | H83: =INDEX('汇率表'!$A:$XFD,MATCH(D83,'汇率表'!$A:$A,0),MATCH(L83,'汇率表'!$1:$1,0)) -> 7.7671 | I83: =G83*H83 -> -626873.79 | J83: =E83+F83-I83 -> -12405 | K83: CNY | L83: EUR | M83: -85000
A84: SZ01 | B84: 01.21010.0000.0000.0000 应付账款 | C84: HKD→CNY | D84: 2026-06-30 | E84: =I68 -> -65271.75 | F84: =SUM(J179:J180) -> 4015.1709 | G84: =M84+SUM(G179:G180) -> -70382.51 | H84: =INDEX('汇率表'!$A:$XFD,MATCH(D84,'汇率表'!$A:$A,0),MATCH(L84,'汇率表'!$1:$1,0)) -> 0.86855 | I84: =G84*H84 -> -61130.729 | J84: =E84+F84-I84 -> -125.85 | K84: CNY | L84: HKD | M84: -75000
A85: SZ01 | B85: 01.21010.0000.0000.0000 应付账款 | C85: JPY→CNY | D85: 2026-06-30 | E85: =I69 -> -384462 | F85: =SUM(J181:J182) -> -101347.15 | G85: =M85+SUM(G181:G182) -> -11391515 | H85: =INDEX('汇率表'!$A:$XFD,MATCH(D85,'汇率表'!$A:$A,0),MATCH(L85,'汇率表'!$1:$1,0)) -> 0.042045 | I85: =G85*H85 -> -478956.25 | J85: =E85+F85-I85 -> -6852.9 | K85: CNY | L85: JPY | M85: -9000000
A86: SZ01 | B86: 01.21010.0000.0000.0000 应付账款 | C86: USD→CNY | D86: 2026-06-30 | E86: =I70 -> -272704 | F86: =SUM(J183:J183) -> -2276.6114 | G86: =M86+SUM(G183:G183) -> -40334.26 | H86: =INDEX('汇率表'!$A:$XFD,MATCH(D86,'汇率表'!$A:$A,0),MATCH(L86,'汇率表'!$1:$1,0)) -> 6.8109 | I86: =G86*H86 -> -274712.61 | J86: =E86+F86-I86 -> -268 | K86: CNY | L86: USD | M86: -40000
A87: SZ01 | B87: 01.12010.0000.0000.0000 应收账款 | C87: EUR→CNY | D87: 2026-06-30 | E87: =I71 -> 530372 | F87: =SUM(J184:J186) -> 66489.839 | G87: =M87+SUM(G184:G186) -> 75462.78 | H87: =INDEX('汇率表'!$A:$XFD,MATCH(D87,'汇率表'!$A:$A,0),MATCH(L87,'汇率表'!$1:$1,0)) -> 7.7671 | I87: =G87*H87 -> 586126.96 | J87: =E87+F87-I87 -> 10734.88 | K87: CNY | L87: EUR | M87: 67000
A88: SZ01 | B88: 01.12010.0000.0000.0000 应收账款 | C88: HKD→CNY | D88: 2026-06-30 | E88: =I72 -> 26108.7 | F88: =SUM(J187:J187) -> 142.3814 | G88: =M88+SUM(G187:G187) -> 30163.93 | H88: =INDEX('汇率表'!$A:$XFD,MATCH(D88,'汇率表'!$A:$A,0),MATCH(L88,'汇率表'!$1:$1,0)) -> 0.86855 | I88: =G88*H88 -> 26198.881 | J88: =E88+F88-I88 -> 52.2 | K88: CNY | L88: HKD | M88: 30000
A89: SZ01 | B89: 01.12010.0000.0000.0000 应收账款 | C89: USD→CNY | D89: 2026-06-30 | E89: =I73 -> 1346476 | F89: =SUM(J188:J190) -> 107419.65 | G89: =M89+SUM(G188:G190) -> 213267.41 | H89: =INDEX('汇率表'!$A:$XFD,MATCH(D89,'汇率表'!$A:$A,0),MATCH(L89,'汇率表'!$1:$1,0)) -> 6.8109 | I89: =G89*H89 -> 1452543 | J89: =E89+F89-I89 -> 1352.65 | K89: CNY | L89: USD | M89: 197500
A90: SZ01 | B90: 01.11010.0000.0000.0000 银行存款 | C90: EUR→CNY | D90: 2026-06-30 | E90: =I74 -> 474960 | F90: =SUM(J191:J193) -> 35674.245 | G90: =M90+SUM(G191:G193) -> 64567.09 | H90: =INDEX('汇率表'!$A:$XFD,MATCH(D90,'汇率表'!$A:$A,0),MATCH(L90,'汇率表'!$1:$1,0)) -> 7.7671 | I90: =G90*H90 -> 501499.04 | J90: =E90+F90-I90 -> 9135.2 | K90: CNY | L90: EUR | M90: 60000
A91: SZ01 | B91: 01.11010.0000.0000.0000 银行存款 | C91: HKD→CNY | D91: 2026-06-30 | E91: =I75 -> 65271.75 | F91: =SUM(J194:J195) -> -4015.1709 | G91: =M91+SUM(G194:G195) -> 70382.51 | H91: =INDEX('汇率表'!$A:$XFD,MATCH(D91,'汇率表'!$A:$A,0),MATCH(L91,'汇率表'!$1:$1,0)) -> 0.86855 | I91: =G91*H91 -> 61130.729 | J91: =E91+F91-I91 -> 125.85 | K91: CNY | L91: HKD | M91: 75000
A92: SZ01 | B92: 01.11010.0000.0000.0000 银行存款 | C92: USD→CNY | D92: 2026-06-30 | E92: =I76 -> 2897480 | F92: =SUM(J196:J197) -> 264636.17 | G92: =M92+SUM(G196:G197) -> 463844.01 | H92: =INDEX('汇率表'!$A:$XFD,MATCH(D92,'汇率表'!$A:$A,0),MATCH(L92,'汇率表'!$1:$1,0)) -> 6.8109 | I92: =G92*H92 -> 3159195.2 | J92: =E92+F92-I92 -> 2921 | K92: CNY | L92: USD | M92: 425000
A93: SZ01 | B93: 01.25010.0000.0000.0000 长期借款 | C93: USD→CNY | D93: 2026-06-30 | E93: =I77 -> -1022640 | F93: =SUM(J198:J198) -> -8537.3269 | G93: =M93+SUM(G198:G198) -> -151253.48 | H93: =INDEX('汇率表'!$A:$XFD,MATCH(D93,'汇率表'!$A:$A,0),MATCH(L93,'汇率表'!$1:$1,0)) -> 6.8109 | I93: =G93*H93 -> -1030172.3 | J93: =E93+F93-I93 -> -1005 | K93: CNY | L93: USD | M93: -150000
A94: US01 | B94: 02.13010.0000.0000.0000 其他应收款 | C94: EUR→USD | D94: 2026-06-30 | E94: =I78 -> 1161.1124 | F94: =SUM(J199:J199) -> 20.367412 | G94: =M94+SUM(G199:G199) -> 1017.86 | H94: =INDEX('汇率表'!$A:$XFD,MATCH(D94,'汇率表'!$A:$A,0),MATCH(L94,'汇率表'!$1:$1,0))/INDEX('汇率表'!$A:$XFD,MATCH(D94,'汇率表'!$A:$A,0),MATCH(K94,'汇率表'!$1:$1,0)) -> 1.1403926 | I94: =G94*H94 -> 1160.76 | J94: =E94+F94-I94 -> 20.719809 | K94: USD | L94: EUR | M94: 1000
A95: US01 | B95: 02.21010.0000.0000.0000 应付账款 | C95: EUR→USD | D95: 2026-06-30 | E95: =I79 -> -27866.698 | F95: =SUM(J200:J202) -> 7099.1106 | G95: =M95+SUM(G200:G202) -> -17760.71 | H95: =INDEX('汇率表'!$A:$XFD,MATCH(D95,'汇率表'!$A:$A,0),MATCH(L95,'汇率表'!$1:$1,0))/INDEX('汇率表'!$A:$XFD,MATCH(D95,'汇率表'!$A:$A,0),MATCH(K95,'汇率表'!$1:$1,0)) -> 1.1403926 | I95: =G95*H95 -> -20254.182 | J95: =E95+F95-I95 -> -513.40502 | K95: USD | L95: EUR | M95: -24000
A96: US01 | B96: 02.12010.0000.0000.0000 应收账款 | C96: EUR→USD | D96: 2026-06-30 | E96: =I80 -> 26705.586 | F96: =SUM(J203:J204) -> 5386.5201 | G96: =M96+SUM(G203:G204) -> 27685.71 | H96: =INDEX('汇率表'!$A:$XFD,MATCH(D96,'汇率表'!$A:$A,0),MATCH(L96,'汇率表'!$1:$1,0))/INDEX('汇率表'!$A:$XFD,MATCH(D96,'汇率表'!$A:$A,0),MATCH(K96,'汇率表'!$1:$1,0)) -> 1.1403926 | I96: =G96*H96 -> 31572.579 | J96: =E96+F96-I96 -> 519.52665 | K96: USD | L96: EUR | M96: 23000
A97: US01 | B97: 02.11010.0000.0000.0000 银行存款 | C97: EUR→USD | D97: 2026-06-30 | E97: =I81 -> 16255.574 | F97: =SUM(J205:J207) -> -7302.7505 | G97: =M97+SUM(G205:G207) -> 7582.14 | H97: =INDEX('汇率表'!$A:$XFD,MATCH(D97,'汇率表'!$A:$A,0),MATCH(L97,'汇率表'!$1:$1,0))/INDEX('汇率表'!$A:$XFD,MATCH(D97,'汇率表'!$A:$A,0),MATCH(K97,'汇率表'!$1:$1,0)) -> 1.1403926 | I97: =G97*H97 -> 8646.6164 | J97: =E97+F97-I97 -> 306.20693 | K97: USD | L97: EUR | M97: 14000
A99: 逐笔发生额
A100: 主体 | B100: 科目 | C100: 月末 | D100: 凭证号 | E100: JE源行 | F100: 交易日 | G100: 原币发生额 | H100: 客户JE本位币发生额 | I100: 审计交易日汇率 | J100: 审计本位币发生额 | L100: 原币 | M100: 本位币
A101: SZ01 | B101: 01.21010.0000.0000.0000 应付账款 | C101: 2026-01-31 | D101: SZ01-2026-01-20-PAY-AP-EUR | E101: 18 | F101: 2026-01-20 | G101: 5000 | H101: 39150 | I101: =INDEX('汇率表'!$A:$XFD,MATCH(F101,'汇率表'!$A:$A,0),MATCH(L101,'汇率表'!$1:$1,0)) -> 8.1186 | J101: =G101*I101 -> 40593 | L101: EUR | M101: CNY
...

Sheet 客户与审计汇率比较
A1: 类型 | B1: 日期 | C1: 凭证号 | D1: 主体 | E1: 科目 | F1: 币种（原币→本位币） | G1: 原币基础 | H1: 客户本位币金额 | I1: 客户隐含汇率 | J1: 审计适用汇率 | K1: 汇率差（客户－审计） | L1: 反推依据 | M1: 本位币（公式辅助） | N1: 原币（公式辅助）
A2: 未实现 | B2: 2026-01-31 | D2: SZ01 | E2: 01.13010.0000.0000.0000 其他应收款 | F2: USD→CNY | G2: 5000 | H2: 35600 | I2: =H2/G2 -> 7.12 | J2: =INDEX('汇率表'!$A:$XFD,MATCH(B2,'汇率表'!$A:$A,0),MATCH(N2,'汇率表'!$1:$1,0)) -> 6.9678 | K2: =I2-J2 -> 0.1522 | L2: TB期初本位币及JE滚动后账面余额÷月末原币余额反推 | M2: CNY | N2: USD
A3: 未实现 | B3: 2026-01-31 | D3: SZ01 | E3: 01.21010.0000.0000.0000 应付账款 | F3: EUR→CNY | G3: -55000 | H3: -430650 | I3: =H3/G3 -> 7.83 | J3: =INDEX('汇率表'!$A:$XFD,MATCH(B3,'汇率表'!$A:$A,0),MATCH(N3,'汇率表'!$1:$1,0)) -> 8.3244 | K3: =I3-J3 -> -0.4944 | L3: TB期初本位币及JE滚动后账面余额÷月末原币余额反推 | M3: CNY | N3: EUR
A4: 未实现 | B4: 2026-01-31 | D4: SZ01 | E4: 01.21010.0000.0000.0000 应付账款 | F4: HKD→CNY | G4: -95000 | H4: -86450 | I4: =H4/G4 -> 0.91 | J4: =INDEX('汇率表'!$A:$XFD,MATCH(B4,'汇率表'!$A:$A,0),MATCH(N4,'汇率表'!$1:$1,0)) -> 0.89262 | K4: =I4-J4 -> 0.01738 | L4: TB期初本位币及JE滚动后账面余额÷月末原币余额反推 | M4: CNY | N4: HKD
A5: 未实现 | B5: 2026-01-31 | D5: SZ01 | E5: 01.21010.0000.0000.0000 应付账款 | F5: JPY→CNY | G5: -1600000 | H5: -77120 | I5: =H5/G5 -> 0.0482 | J5: =INDEX('汇率表'!$A:$XFD,MATCH(B5,'汇率表'!$A:$A,0),MATCH(N5,'汇率表'!$1:$1,0)) -> 0.045464 | K5: =I5-J5 -> 0.002736 | L5: TB期初本位币及JE滚动后账面余额÷月末原币余额反推 | M5: CNY | N5: JPY
A6: 未实现 | B6: 2026-01-31 | D6: SZ01 | E6: 01.21010.0000.0000.0000 应付账款 | F6: USD→CNY | G6: -40000 | H6: -284800 | I6: =H6/G6 -> 7.12 | J6: =INDEX('汇率表'!$A:$XFD,MATCH(B6,'汇率表'!$A:$A,0),MATCH(N6,'汇率表'!$1:$1,0)) -> 6.9678 | K6: =I6-J6 -> 0.1522 | L6: TB期初本位币及JE滚动后账面余额÷月末原币余额反推 | M6: CNY | N6: USD
A7: 未实现 | B7: 2026-01-31 | D7: SZ01 | E7: 01.12010.0000.0000.0000 应收账款 | F7: EUR→CNY | G7: 43800 | H7: 342954 | I7: =H7/G7 -> 7.83 | J7: =INDEX('汇率表'!$A:$XFD,MATCH(B7,'汇率表'!$A:$A,0),MATCH(N7,'汇率表'!$1:$1,0)) -> 8.3244 | K7: =I7-J7 -> -0.4944 | L7: TB期初本位币及JE滚动后账面余额÷月末原币余额反推 | M7: CNY | N7: EUR
A8: 未实现 | B8: 2026-01-31 | D8: SZ01 | E8: 01.12010.0000.0000.0000 应收账款 | F8: HKD→CNY | G8: 30000 | H8: 27300 | I8: =H8/G8 -> 0.91 | J8: =INDEX('汇率表'!$A:$XFD,MATCH(B8,'汇率表'!$A:$A,0),MATCH(N8,'汇率表'!$1:$1,0)) -> 0.89262 | K8: =I8-J8 -> 0.01738 | L8: TB期初本位币及JE滚动后账面余额÷月末原币余额反推 | M8: CNY | N8: HKD
A9: 未实现 | B9: 2026-01-31 | D9: SZ01 | E9: 01.12010.0000.0000.0000 应收账款 | F9: USD→CNY | G9: 156500 | H9: 1114280 | I9: =H9/G9 -> 7.12 | J9: =INDEX('汇率表'!$A:$XFD,MATCH(B9,'汇率表'!$A:$A,0),MATCH(N9,'汇率表'!$1:$1,0)) -> 6.9678 | K9: =I9-J9 -> 0.1522 | L9: TB期初本位币及JE滚动后账面余额÷月末原币余额反推 | M9: CNY | N9: USD
A10: 未实现 | B10: 2026-01-31 | D10: SZ01 | E10: 01.11010.0000.0000.0000 银行存款 | F10: EUR→CNY | G10: 44000 | H10: 344520 | I10: =H10/G10 -> 7.83 | J10: =INDEX('汇率表'!$A:$XFD,MATCH(B10,'汇率表'!$A:$A,0),MATCH(N10,'汇率表'!$1:$1,0)) -> 8.3244 | K10: =I10-J10 -> -0.4944 | L10: TB期初本位币及JE滚动后账面余额÷月末原币余额反推 | M10: CNY | N10: EUR
A11: 未实现 | B11: 2026-01-31 | D11: SZ01 | E11: 01.11010.0000.0000.0000 银行存款 | F11: HKD→CNY | G11: 95000 | H11: 86450 | I11: =H11/G11 -> 0.91 | J11: =INDEX('汇率表'!$A:$XFD,MATCH(B11,'汇率表'!$A:$A,0),MATCH(N11,'汇率表'!$1:$1,0)) -> 0.89262 | K11: =I11-J11 -> 0.01738 | L11: TB期初本位币及JE滚动后账面余额÷月末原币余额反推 | M11: CNY | N11: HKD
A12: 未实现 | B12: 2026-01-31 | D12: SZ01 | E12: 01.11010.0000.0000.0000 银行存款 | F12: USD→CNY | G12: 335000 | H12: 2385200 | I12: =H12/G12 -> 7.12 | J12: =INDEX('汇率表'!$A:$XFD,MATCH(B12,'汇率表'!$A:$A,0),MATCH(N12,'汇率表'!$1:$1,0)) -> 6.9678 | K12: =I12-J12 -> 0.1522 | L12: TB期初本位币及JE滚动后账面余额÷月末原币余额反推 | M12: CNY | N12: USD
A13: 未实现 | B13: 2026-01-31 | D13: SZ01 | E13: 01.25010.0000.0000.0000 长期借款 | F13: USD→CNY | G13: -200000 | H13: -1424000 | I13: =H13/G13 -> 7.12 | J13: =INDEX('汇率表'!$A:$XFD,MATCH(B13,'汇率表'!$A:$A,0),MATCH(N13,'汇率表'!$1:$1,0)) -> 6.9678 | K13: =I13-J13 -> 0.1522 | L13: TB期初本位币及JE滚动后账面余额÷月末原币余额反推 | M13: CNY | N13: USD
A14: 未实现 | B14: 2026-01-31 | D14: US01 | E14: 02.13010.0000.0000.0000 其他应收款 | F14: EUR→USD | G14: 1000 | H14: 1100 | I14: =H14/G14 -> 1.1 | J14: =INDEX('汇率表'!$A:$XFD,MATCH(B14,'汇率表'!$A:$A,0),MATCH(N14,'汇率表'!$1:$1,0))/INDEX('汇率表'!$A:$XFD,MATCH(B14,'汇率表'!$A:$A,0),MATCH(M14,'汇率表'!$1:$1,0)) -> 1.1946956 | K14: =I14-J14 -> -0.0946956 | L14: TB期初本位币及JE滚动后账面余额÷月末原币余额反推 | M14: USD | N14: EUR
A15: 未实现 | B15: 2026-01-31 | D15: US01 | E15: 02.21010.0000.0000.0000 应付账款 | F15: EUR→USD | G15: -28800 | H15: -31680 | I15: =H15/G15 -> 1.1 | J15: =INDEX('汇率表'!$A:$XFD,MATCH(B15,'汇率表'!$A:$A,0),MATCH(N15,'汇率表'!$1:$1,0))/INDEX('汇率表'!$A:$XFD,MATCH(B15,'汇率表'!$A:$A,0),MATCH(M15,'汇率表'!$1:$1,0)) -> 1.1946956 | K15: =I15-J15 -> -0.0946956 | L15: TB期初本位币及JE滚动后账面余额÷月末原币余额反推 | M15: USD | N15: EUR
A16: 未实现 | B16: 2026-01-31 | D16: US01 | E16: 02.12010.0000.0000.0000 应收账款 | F16: EUR→USD | G16: 8200 | H16: 9020 | I16: =H16/G16 -> 1.1 | J16: =INDEX('汇率表'!$A:$XFD,MATCH(B16,'汇率表'!$A:$A,0),MATCH(N16,'汇率表'!$1:$1,0))/INDEX('汇率表'!$A:$XFD,MATCH(B16,'汇率表'!$A:$A,0),MATCH(M16,'汇率表'!$1:$1,0)) -> 1.1946956 | K16: =I16-J16 -> -0.0946956 | L16: TB期初本位币及JE滚动后账面余额÷月末原币余额反推 | M16: USD | N16: EUR
A17: 未实现 | B17: 2026-01-31 | D17: US01 | E17: 02.11010.0000.0000.0000 银行存款 | F17: EUR→USD | G17: 18800 | H17: 20680 | I17: =H17/G17 -> 1.1 | J17: =INDEX('汇率表'!$A:$XFD,MATCH(B17,'汇率表'!$A:$A,0),MATCH(N17,'汇率表'!$1:$1,0))/INDEX('汇率表'!$A:$XFD,MATCH(B17,'汇率表'!$A:$A,0),MATCH(M17,'汇率表'!$1:$1,0)) -> 1.1946956 | K17: =I17-J17 -> -0.0946956 | L17: TB期初本位币及JE滚动后账面余额÷月末原币余额反推 | M17: USD | N17: EUR
A18: 未实现 | B18: 2026-02-28 | D18: SZ01 | E18: 01.13010.0000.0000.0000 其他应收款 | F18: USD→CNY | G18: 5000 | H18: 35600 | I18: =H18/G18 -> 7.12 | J18: =INDEX('汇率表'!$A:$XFD,MATCH(B18,'汇率表'!$A:$A,0),MATCH(N18,'汇率表'!$1:$1,0)) -> 6.9228 | K18: =I18-J18 -> 0.1972 | L18: TB期初本位币及JE滚动后账面余额÷月末原币余额反推 | M18: CNY | N18: USD
A19: 未实现 | B19: 2026-02-28 | D19: SZ01 | E19: 01.21010.0000.0000.0000 应付账款 | F19: EUR→CNY | G19: -100000 | H19: -783000 | I19: =H19/G19 -> 7.83 | J19: =INDEX('汇率表'!$A:$XFD,MATCH(B19,'汇率表'!$A:$A,0),MATCH(N19,'汇率表'!$1:$1,0)) -> 8.1208 | K19: =I19-J19 -> -0.2908 | L19: TB期初本位币及JE滚动后账面余额÷月末原币余额反推 | M19: CNY | N19: EUR
A20: 未实现 | B20: 2026-02-28 | D20: SZ01 | E20: 01.21010.0000.0000.0000 应付账款 | F20: HKD→CNY | G20: -90000 | H20: -81900 | I20: =H20/G20 -> 0.91 | J20: =INDEX('汇率表'!$A:$XFD,MATCH(B20,'汇率表'!$A:$A,0),MATCH(N20,'汇率表'!$1:$1,0)) -> 0.88484 | K20: =I20-J20 -> 0.02516 | L20: TB期初本位币及JE滚动后账面余额÷月末原币余额反推 | M20: CNY | N20: HKD
A21: 未实现 | B21: 2026-02-28 | D21: SZ01 | E21: 01.21010.0000.0000.0000 应付账款 | F21: JPY→CNY | G21: -3300000 | H21: -159060 | I21: =H21/G21 -> 0.0482 | J21: =INDEX('汇率表'!$A:$XFD,MATCH(B21,'汇率表'!$A:$A,0),MATCH(N21,'汇率表'!$1:$1,0)) -> 0.044216 | K21: =I21-J21 -> 0.003984 | L21: TB期初本位币及JE滚动后账面余额÷月末原币余额反推 | M21: CNY | N21: JPY
A22: 未实现 | B22: 2026-02-28 | D22: SZ01 | E22: 01.21010.0000.0000.0000 应付账款 | F22: USD→CNY | G22: -40000 | H22: -284800 | I22: =H22/G22 -> 7.12 | J22: =INDEX('汇率表'!$A:$XFD,MATCH(B22,'汇率表'!$A:$A,0),MATCH(N22,'汇率表'!$1:$1,0)) -> 6.9228 | K22: =I22-J22 -> 0.1972 | L22: TB期初本位币及JE滚动后账面余额÷月末原币余额反推 | M22: CNY | N22: USD
A23: 未实现 | B23: 2026-02-28 | D23: SZ01 | E23: 01.12010.0000.0000.0000 应收账款 | F23: EUR→CNY | G23: 48400 | H23: 378972 | I23: =H23/G23 -> 7.83 | J23: =INDEX('汇率表'!$A:$XFD,MATCH(B23,'汇率表'!$A:$A,0),MATCH(N23,'汇率表'!$1:$1,0)) -> 8.1208 | K23: =I23-J23 -> -0.2908 | L23: TB期初本位币及JE滚动后账面余额÷月末原币余额反推 | M23: CNY | N23: EUR
A24: 未实现 | B24: 2026-02-28 | D24: SZ01 | E24: 01.12010.0000.0000.0000 应收账款 | F24: HKD→CNY | G24: 30000 | H24: 27300 | I24: =H24/G24 -> 0.91 | J24: =INDEX('汇率表'!$A:$XFD,MATCH(B24,'汇率表'!$A:$A,0),MATCH(N24,'汇率表'!$1:$1,0)) -> 0.88484 | K24: =I24-J24 -> 0.02516 | L24: TB期初本位币及JE滚动后账面余额÷月末原币余额反推 | M24: CNY | N24: HKD
A25: 未实现 | B25: 2026-02-28 | D25: SZ01 | E25: 01.12010.0000.0000.0000 应收账款 | F25: USD→CNY | G25: 164500 | H25: 1171240 | I25: =H25/G25 -> 7.12 | J25: =INDEX('汇率表'!$A:$XFD,MATCH(B25,'汇率表'!$A:$A,0),MATCH(N25,'汇率表'!$1:$1,0)) -> 6.9228 | K25: =I25-J25 -> 0.1972 | L25: TB期初本位币及JE滚动后账面余额÷月末原币余额反推 | M25: CNY | N25: USD
A26: 未实现 | B26: 2026-02-28 | D26: SZ01 | E26: 01.11010.0000.0000.0000 银行存款 | F26: EUR→CNY | G26: 48000 | H26: 375840 | I26: =H26/G26 -> 7.83 | J26: =INDEX('汇率表'!$A:$XFD,MATCH(B26,'汇率表'!$A:$A,0),MATCH(N26,'汇率表'!$1:$1,0)) -> 8.1208 | K26: =I26-J26 -> -0.2908 | L26: TB期初本位币及JE滚动后账面余额÷月末原币余额反推 | M26: CNY | N26: EUR
A27: 未实现 | B27: 2026-02-28 | D27: SZ01 | E27: 01.11010.0000.0000.0000 银行存款 | F27: HKD→CNY | G27: 90000 | H27: 81900 | I27: =H27/G27 -> 0.91 | J27: =INDEX('汇率表'!$A:$XFD,MATCH(B27,'汇率表'!$A:$A,0),MATCH(N27,'汇率表'!$1:$1,0)) -> 0.88484 | K27: =I27-J27 -> 0.02516 | L27: TB期初本位币及JE滚动后账面余额÷月末原币余额反推 | M27: CNY | N27: HKD
A28: 未实现 | B28: 2026-02-28 | D28: SZ01 | E28: 01.11010.0000.0000.0000 银行存款 | F28: USD→CNY | G28: 370000 | H28: 2634400 | I28: =H28/G28 -> 7.12 | J28: =INDEX('汇率表'!$A:$XFD,MATCH(B28,'汇率表'!$A:$A,0),MATCH(N28,'汇率表'!$1:$1,0)) -> 6.9228 | K28: =I28-J28 -> 0.1972 | L28: TB期初本位币及JE滚动后账面余额÷月末原币余额反推 | M28: CNY | N28: USD
A29: 未实现 | B29: 2026-02-28 | D29: SZ01 | E29: 01.25010.0000.0000.0000 长期借款 | F29: USD→CNY | G29: -200000 | H29: -1424000 | I29: =H29/G29 -> 7.12 | J29: =INDEX('汇率表'!$A:$XFD,MATCH(B29,'汇率表'!$A:$A,0),MATCH(N29,'汇率表'!$1:$1,0)) -> 6.9228 | K29: =I29-J29 -> 0.1972 | L29: TB期初本位币及JE滚动后账面余额÷月末原币余额反推 | M29: CNY | N29: USD
A30: 未实现 | B30: 2026-02-28 | D30: US01 | E30: 02.13010.0000.0000.0000 其他应收款 | F30: EUR→USD | G30: 1000 | H30: 1100 | I30: =H30/G30 -> 1.1 | J30: =INDEX('汇率表'!$A:$XFD,MATCH(B30,'汇率表'!$A:$A,0),MATCH(N30,'汇率表'!$1:$1,0))/INDEX('汇率表'!$A:$XFD,MATCH(B30,'汇率表'!$A:$A,0),MATCH(M30,'汇率表'!$1:$1,0)) -> 1.1730514 | K30: =I30-J30 -> -0.073051366 | L30: TB期初本位币及JE滚动后账面余额÷月末原币余额反推 | M30: USD | N30: EUR
A31: 未实现 | B31: 2026-02-28 | D31: US01 | E31: 02.21010.0000.0000.0000 应付账款 | F31: EUR→USD | G31: -27600 | H31: -30360 | I31: =H31/G31 -> 1.1 | J31: =INDEX('汇率表'!$A:$XFD,MATCH(B31,'汇率表'!$A:$A,0),MATCH(N31,'汇率表'!$1:$1,0))/INDEX('汇率表'!$A:$XFD,MATCH(B31,'汇率表'!$A:$A,0),MATCH(M31,'汇率表'!$1:$1,0)) -> 1.1730514 | K31: =I31-J31 -> -0.073051366 | L31: TB期初本位币及JE滚动后账面余额÷月末原币余额反推 | M31: USD | N31: EUR
A32: 未实现 | B32: 2026-02-28 | D32: US01 | E32: 02.12010.0000.0000.0000 应收账款 | F32: EUR→USD | G32: 11600 | H32: 12760 | I32: =H32/G32 -> 1.1 | J32: =INDEX('汇率表'!$A:$XFD,MATCH(B32,'汇率表'!$A:$A,0),MATCH(N32,'汇率表'!$1:$1,0))/INDEX('汇率表'!$A:$XFD,MATCH(B32,'汇率表'!$A:$A,0),MATCH(M32,'汇率表'!$1:$1,0)) -> 1.1730514 | K32: =I32-J32 -> -0.073051366 | L32: TB期初本位币及JE滚动后账面余额÷月末原币余额反推 | M32: USD | N32: EUR
A33: 未实现 | B33: 2026-02-28 | D33: US01 | E33: 02.11010.0000.0000.0000 银行存款 | F33: EUR→USD | G33: 17600 | H33: 19360 | I33: =H33/G33 -> 1.1 | J33: =INDEX('汇率表'!$A:$XFD,MATCH(B33,'汇率表'!$A:$A,0),MATCH(N33,'汇率表'!$1:$1,0))/INDEX('汇率表'!$A:$XFD,MATCH(B33,'汇率表'!$A:$A,0),MATCH(M33,'汇率表'!$1:$1,0)) -> 1.1730514 | K33: =I33-J33 -> -0.073051366 | L33: TB期初本位币及JE滚动后账面余额÷月末原币余额反推 | M33: USD | N33: EUR
A34: 未实现 | B34: 2026-03-31 | D34: SZ01 | E34: 01.13010.0000.0000.0000 其他应收款 | F34: USD→CNY | G34: 5000 | H34: 35600 | I34: =H34/G34 -> 7.12 | J34: =INDEX('汇率表'!$A:$XFD,MATCH(B34,'汇率表'!$A:$A,0),MATCH(N34,'汇率表'!$1:$1,0)) -> 6.9194 | K34: =I34-J34 -> 0.2006 | L34: TB期初本位币及JE滚动后账面余额÷月末原币余额反推 | M34: CNY | N34: USD
A35: 未实现 | B35: 2026-03-31 | D35: SZ01 | E35: 01.21010.0000.0000.0000 应付账款 | F35: EUR→CNY | G35: -95000 | H35: -743850 | I35: =H35/G35 -> 7.83 | J35: =INDEX('汇率表'!$A:$XFD,MATCH(B35,'汇率表'!$A:$A,0),MATCH(N35,'汇率表'!$1:$1,0)) -> 7.9302 | K35: =I35-J35 -> -0.1002 | L35: TB期初本位币及JE滚动后账面余额÷月末原币余额反推 | M35: CNY | N35: EUR
A36: 未实现 | B36: 2026-03-31 | D36: SZ01 | E36: 01.21010.0000.0000.0000 应付账款 | F36: HKD→CNY | G36: -85000 | H36: -77350 | I36: =H36/G36 -> 0.91 | J36: =INDEX('汇率表'!$A:$XFD,MATCH(B36,'汇率表'!$A:$A,0),MATCH(N36,'汇率表'!$1:$1,0)) -> 0.88295 | K36: =I36-J36 -> 0.02705 | L36: TB期初本位币及JE滚动后账面余额÷月末原币余额反推 | M36: CNY | N36: HKD
A37: 未实现 | B37: 2026-03-31 | D37: SZ01 | E37: 01.21010.0000.0000.0000 应付账款 | F37: JPY→CNY | G37: -5100000 | H37: -245820 | I37: =H37/G37 -> 0.0482 | J37: =INDEX('汇率表'!$A:$XFD,MATCH(B37,'汇率表'!$A:$A,0),MATCH(N37,'汇率表'!$1:$1,0)) -> 0.043296 | K37: =I37-J37 -> 0.004904 | L37: TB期初本位币及JE滚动后账面余额÷月末原币余额反推 | M37: CNY | N37: JPY
A38: 未实现 | B38: 2026-03-31 | D38: SZ01 | E38: 01.21010.0000.0000.0000 应付账款 | F38: USD→CNY | G38: -40000 | H38: -284800 | I38: =H38/G38 -> 7.12 | J38: =INDEX('汇率表'!$A:$XFD,MATCH(B38,'汇率表'!$A:$A,0),MATCH(N38,'汇率表'!$1:$1,0)) -> 6.9194 | K38: =I38-J38 -> 0.2006 | L38: TB期初本位币及JE滚动后账面余额÷月末原币余额反推 | M38: CNY | N38: USD
A39: 未实现 | B39: 2026-03-31 | D39: SZ01 | E39: 01.12010.0000.0000.0000 应收账款 | F39: EUR→CNY | G39: 53800 | H39: 421254 | I39: =H39/G39 -> 7.83 | J39: =INDEX('汇率表'!$A:$XFD,MATCH(B39,'汇率表'!$A:$A,0),MATCH(N39,'汇率表'!$1:$1,0)) -> 7.9302 | K39: =I39-J39 -> -0.1002 | L39: TB期初本位币及JE滚动后账面余额÷月末原币余额反推 | M39: CNY | N39: EUR
A40: 未实现 | B40: 2026-03-31 | D40: SZ01 | E40: 01.12010.0000.0000.0000 应收账款 | F40: HKD→CNY | G40: 30000 | H40: 27300 | I40: =H40/G40 -> 0.91 | J40: =INDEX('汇率表'!$A:$XFD,MATCH(B40,'汇率表'!$A:$A,0),MATCH(N40,'汇率表'!$1:$1,0)) -> 0.88295 | K40: =I40-J40 -> 0.02705 | L40: TB期初本位币及JE滚动后账面余额÷月末原币余额反推 | M40: CNY | N40: HKD
A41: 未实现 | B41: 2026-03-31 | D41: SZ01 | E41: 01.12010.0000.0000.0000 应收账款 | F41: USD→CNY | G41: 174000 | H41: 1238880 | I41: =H41/G41 -> 7.12 | J41: =INDEX('汇率表'!$A:$XFD,MATCH(B41,'汇率表'!$A:$A,0),MATCH(N41,'汇率表'!$1:$1,0)) -> 6.9194 | K41: =I41-J41 -> 0.2006 | L41: TB期初本位币及JE滚动后账面余额÷月末原币余额反推 | M41: CNY | N41: USD
A42: 未实现 | B42: 2026-03-31 | D42: SZ01 | E42: 01.11010.0000.0000.0000 银行存款 | F42: EUR→CNY | G42: 52000 | H42: 407160 | I42: =H42/G42 -> 7.83 | J42: =INDEX('汇率表'!$A:$XFD,MATCH(B42,'汇率表'!$A:$A,0),MATCH(N42,'汇率表'!$1:$1,0)) -> 7.9302 | K42: =I42-J42 -> -0.1002 | L42: TB期初本位币及JE滚动后账面余额÷月末原币余额反推 | M42: CNY | N42: EUR
A43: 未实现 | B43: 2026-03-31 | D43: SZ01 | E43: 01.11010.0000.0000.0000 银行存款 | F43: HKD→CNY | G43: 85000 | H43: 77350 | I43: =H43/G43 -> 0.91 | J43: =INDEX('汇率表'!$A:$XFD,MATCH(B43,'汇率表'!$A:$A,0),MATCH(N43,'汇率表'!$1:$1,0)) -> 0.88295 | K43: =I43-J43 -> 0.02705 | L43: TB期初本位币及JE滚动后账面余额÷月末原币余额反推 | M43: CNY | N43: HKD
A44: 未实现 | B44: 2026-03-31 | D44: SZ01 | E44: 01.11010.0000.0000.0000 银行存款 | F44: USD→CNY | G44: 355000 | H44: 2527600 | I44: =H44/G44 -> 7.12 | J44: =INDEX('汇率表'!$A:$XFD,MATCH(B44,'汇率表'!$A:$A,0),MATCH(N44,'汇率表'!$1:$1,0)) -> 6.9194 | K44: =I44-J44 -> 0.2006 | L44: TB期初本位币及JE滚动后账面余额÷月末原币余额反推 | M44: CNY | N44: USD
A45: 未实现 | B45: 2026-03-31 | D45: SZ01 | E45: 01.25010.0000.0000.0000 长期借款 | F45: USD→CNY | G45: -150000 | H45: -1068000 | I45: =H45/G45 -> 7.12 | J45: =INDEX('汇率表'!$A:$XFD,MATCH(B45,'汇率表'!$A:$A,0),MATCH(N45,'汇率表'!$1:$1,0)) -> 6.9194 | K45: =I45-J45 -> 0.2006 | L45: TB期初本位币及JE滚动后账面余额÷月末原币余额反推 | M45: CNY | N45: USD
A46: 未实现 | B46: 2026-03-31 | D46: US01 | E46: 02.13010.0000.0000.0000 其他应收款 | F46: EUR→USD | G46: 1000 | H46: 1100 | I46: =H46/G46 -> 1.1 | J46: =INDEX('汇率表'!$A:$XFD,MATCH(B46,'汇率表'!$A:$A,0),MATCH(N46,'汇率表'!$1:$1,0))/INDEX('汇率表'!$A:$XFD,MATCH(B46,'汇率表'!$A:$A,0),MATCH(M46,'汇率表'!$1:$1,0)) -> 1.146082 | K46: =I46-J46 -> -0.04608203 | L46: TB期初本位币及JE滚动后账面余额÷月末原币余额反推 | M46: USD | N46: EUR
A47: 未实现 | B47: 2026-03-31 | D47: US01 | E47: 02.21010.0000.0000.0000 应付账款 | F47: EUR→USD | G47: -26400 | H47: -29040 | I47: =H47/G47 -> 1.1 | J47: =INDEX('汇率表'!$A:$XFD,MATCH(B47,'汇率表'!$A:$A,0),MATCH(N47,'汇率表'!$1:$1,0))/INDEX('汇率表'!$A:$XFD,MATCH(B47,'汇率表'!$A:$A,0),MATCH(M47,'汇率表'!$1:$1,0)) -> 1.146082 | K47: =I47-J47 -> -0.04608203 | L47: TB期初本位币及JE滚动后账面余额÷月末原币余额反推 | M47: USD | N47: EUR
A48: 未实现 | B48: 2026-03-31 | D48: US01 | E48: 02.12010.0000.0000.0000 应收账款 | F48: EUR→USD | G48: 15200 | H48: 16720 | I48: =H48/G48 -> 1.1 | J48: =INDEX('汇率表'!$A:$XFD,MATCH(B48,'汇率表'!$A:$A,0),MATCH(N48,'汇率表'!$1:$1,0))/INDEX('汇率表'!$A:$XFD,MATCH(B48,'汇率表'!$A:$A,0),MATCH(M48,'汇率表'!$1:$1,0)) -> 1.146082 | K48: =I48-J48 -> -0.04608203 | L48: TB期初本位币及JE滚动后账面余额÷月末原币余额反推 | M48: USD | N48: EUR
A49: 未实现 | B49: 2026-03-31 | D49: US01 | E49: 02.11010.0000.0000.0000 银行存款 | F49: EUR→USD | G49: 16400 | H49: 18040 | I49: =H49/G49 -> 1.1 | J49: =INDEX('汇率表'!$A:$XFD,MATCH(B49,'汇率表'!$A:$A,0),MATCH(N49,'汇率表'!$1:$1,0))/INDEX('汇率表'!$A:$XFD,MATCH(B49,'汇率表'!$A:$A,0),MATCH(M49,'汇率表'!$1:$1,0)) -> 1.146082 | K49: =I49-J49 -> -0.04608203 | L49: TB期初本位币及JE滚动后账面余额÷月末原币余额反推 | M49: USD | N49: EUR
A50: 未实现 | B50: 2026-04-30 | D50: SZ01 | E50: 01.13010.0000.0000.0000 其他应收款 | F50: USD→CNY | G50: 5000 | H50: 35600 | I50: =H50/G50 -> 7.12 | J50: =INDEX('汇率表'!$A:$XFD,MATCH(B50,'汇率表'!$A:$A,0),MATCH(N50,'汇率表'!$1:$1,0)) -> 6.8628 | K50: =I50-J50 -> 0.2572 | L50: TB期初本位币及JE滚动后账面余额÷月末原币余额反推 | M50: CNY | N50: USD
A51: 未实现 | B51: 2026-04-30 | D51: SZ01 | E51: 01.21010.0000.0000.0000 应付账款 | F51: EUR→CNY | G51: -90000 | H51: -704700 | I51: =H51/G51 -> 7.83 | J51: =INDEX('汇率表'!$A:$XFD,MATCH(B51,'汇率表'!$A:$A,0),MATCH(N51,'汇率表'!$1:$1,0)) -> 8.0057 | K51: =I51-J51 -> -0.1757 | L51: TB期初本位币及JE滚动后账面余额÷月末原币余额反推 | M51: CNY | N51: EUR
A52: 未实现 | B52: 2026-04-30 | D52: SZ01 | E52: 01.21010.0000.0000.0000 应付账款 | F52: HKD→CNY | G52: -80000 | H52: -72800 | I52: =H52/G52 -> 0.91 | J52: =INDEX('汇率表'!$A:$XFD,MATCH(B52,'汇率表'!$A:$A,0),MATCH(N52,'汇率表'!$1:$1,0)) -> 0.87581 | K52: =I52-J52 -> 0.03419 | L52: TB期初本位币及JE滚动后账面余额÷月末原币余额反推 | M52: CNY | N52: HKD
A53: 未实现 | B53: 2026-04-30 | D53: SZ01 | E53: 01.21010.0000.0000.0000 应付账款 | F53: JPY→CNY | G53: -7000000 | H53: -337400 | I53: =H53/G53 -> 0.0482 | J53: =INDEX('汇率表'!$A:$XFD,MATCH(B53,'汇率表'!$A:$A,0),MATCH(N53,'汇率表'!$1:$1,0)) -> 0.042812 | K53: =I53-J53 -> 0.005388 | L53: TB期初本位币及JE滚动后账面余额÷月末原币余额反推 | M53: CNY | N53: JPY
A54: 未实现 | B54: 2026-04-30 | D54: SZ01 | E54: 01.21010.0000.0000.0000 应付账款 | F54: USD→CNY | G54: -40000 | H54: -284800 | I54: =H54/G54 -> 7.12 | J54: =INDEX('汇率表'!$A:$XFD,MATCH(B54,'汇率表'!$A:$A,0),MATCH(N54,'汇率表'!$1:$1,0)) -> 6.8628 | K54: =I54-J54 -> 0.2572 | L54: TB期初本位币及JE滚动后账面余额÷月末原币余额反推 | M54: CNY | N54: USD
A55: 未实现 | B55: 2026-04-30 | D55: SZ01 | E55: 01.12010.0000.0000.0000 应收账款 | F55: EUR→CNY | G55: 60000 | H55: 469800 | I55: =H55/G55 -> 7.83 | J55: =INDEX('汇率表'!$A:$XFD,MATCH(B55,'汇率表'!$A:$A,0),MATCH(N55,'汇率表'!$1:$1,0)) -> 8.0057 | K55: =I55-J55 -> -0.1757 | L55: TB期初本位币及JE滚动后账面余额÷月末原币余额反推 | M55: CNY | N55: EUR
A56: 未实现 | B56: 2026-04-30 | D56: SZ01 | E56: 01.12010.0000.0000.0000 应收账款 | F56: HKD→CNY | G56: 30000 | H56: 27300 | I56: =H56/G56 -> 0.91 | J56: =INDEX('汇率表'!$A:$XFD,MATCH(B56,'汇率表'!$A:$A,0),MATCH(N56,'汇率表'!$1:$1,0)) -> 0.87581 | K56: =I56-J56 -> 0.03419 | L56: TB期初本位币及JE滚动后账面余额÷月末原币余额反推 | M56: CNY | N56: HKD
A57: 未实现 | B57: 2026-04-30 | D57: SZ01 | E57: 01.12010.0000.0000.0000 应收账款 | F57: USD→CNY | G57: 185000 | H57: 1317200 | I57: =H57/G57 -> 7.12 | J57: =INDEX('汇率表'!$A:$XFD,MATCH(B57,'汇率表'!$A:$A,0),MATCH(N57,'汇率表'!$1:$1,0)) -> 6.8628 | K57: =I57-J57 -> 0.2572 | L57: TB期初本位币及JE滚动后账面余额÷月末原币余额反推 | M57: CNY | N57: USD
A58: 未实现 | B58: 2026-04-30 | D58: SZ01 | E58: 01.11010.0000.0000.0000 银行存款 | F58: EUR→CNY | G58: 56000 | H58: 438480 | I58: =H58/G58 -> 7.83 | J58: =INDEX('汇率表'!$A:$XFD,MATCH(B58,'汇率表'!$A:$A,0),MATCH(N58,'汇率表'!$1:$1,0)) -> 8.0057 | K58: =I58-J58 -> -0.1757 | L58: TB期初本位币及JE滚动后账面余额÷月末原币余额反推 | M58: CNY | N58: EUR
A59: 未实现 | B59: 2026-04-30 | D59: SZ01 | E59: 01.11010.0000.0000.0000 银行存款 | F59: HKD→CNY | G59: 80000 | H59: 72800 | I59: =H59/G59 -> 0.91 | J59: =INDEX('汇率表'!$A:$XFD,MATCH(B59,'汇率表'!$A:$A,0),MATCH(N59,'汇率表'!$1:$1,0)) -> 0.87581 | K59: =I59-J59 -> 0.03419 | L59: TB期初本位币及JE滚动后账面余额÷月末原币余额反推 | M59: CNY | N59: HKD
A60: 未实现 | B60: 2026-04-30 | D60: SZ01 | E60: 01.11010.0000.0000.0000 银行存款 | F60: USD→CNY | G60: 390000 | H60: 2776800 | I60: =H60/G60 -> 7.12 | J60: =INDEX('汇率表'!$A:$XFD,MATCH(B60,'汇率表'!$A:$A,0),MATCH(N60,'汇率表'!$1:$1,0)) -> 6.8628 | K60: =I60-J60 -> 0.2572 | L60: TB期初本位币及JE滚动后账面余额÷月末原币余额反推 | M60: CNY | N60: USD
A61: 未实现 | B61: 2026-04-30 | D61: SZ01 | E61: 01.25010.0000.0000.0000 长期借款 | F61: USD→CNY | G61: -150000 | H61: -1068000 | I61: =H61/G61 -> 7.12 | J61: =INDEX('汇率表'!$A:$XFD,MATCH(B61,'汇率表'!$A:$A,0),MATCH(N61,'汇率表'!$1:$1,0)) -> 6.8628 | K61: =I61-J61 -> 0.2572 | L61: TB期初本位币及JE滚动后账面余额÷月末原币余额反推 | M61: CNY | N61: USD
A62: 未实现 | B62: 2026-04-30 | D62: US01 | E62: 02.13010.0000.0000.0000 其他应收款 | F62: EUR→USD | G62: 1000 | H62: 1100 | I62: =H62/G62 -> 1.1 | J62: =INDEX('汇率表'!$A:$XFD,MATCH(B62,'汇率表'!$A:$A,0),MATCH(N62,'汇率表'!$1:$1,0))/INDEX('汇率表'!$A:$XFD,MATCH(B62,'汇率表'!$A:$A,0),MATCH(M62,'汇率表'!$1:$1,0)) -> 1.1665355 | K62: =I62-J62 -> -0.066535525 | L62: TB期初本位币及JE滚动后账面余额÷月末原币余额反推 | M62: USD | N62: EUR
A63: 未实现 | B63: 2026-04-30 | D63: US01 | E63: 02.21010.0000.0000.0000 应付账款 | F63: EUR→USD | G63: -25200 | H63: -27720 | I63: =H63/G63 -> 1.1 | J63: =INDEX('汇率表'!$A:$XFD,MATCH(B63,'汇率表'!$A:$A,0),MATCH(N63,'汇率表'!$1:$1,0))/INDEX('汇率表'!$A:$XFD,MATCH(B63,'汇率表'!$A:$A,0),MATCH(M63,'汇率表'!$1:$1,0)) -> 1.1665355 | K63: =I63-J63 -> -0.066535525 | L63: TB期初本位币及JE滚动后账面余额÷月末原币余额反推 | M63: USD | N63: EUR
A64: 未实现 | B64: 2026-04-30 | D64: US01 | E64: 02.12010.0000.0000.0000 应收账款 | F64: EUR→USD | G64: 19000 | H64: 20900 | I64: =H64/G64 -> 1.1 | J64: =INDEX('汇率表'!$A:$XFD,MATCH(B64,'汇率表'!$A:$A,0),MATCH(N64,'汇率表'!$1:$1,0))/INDEX('汇率表'!$A:$XFD,MATCH(B64,'汇率表'!$A:$A,0),MATCH(M64,'汇率表'!$1:$1,0)) -> 1.1665355 | K64: =I64-J64 -> -0.066535525 | L64: TB期初本位币及JE滚动后账面余额÷月末原币余额反推 | M64: USD | N64: EUR
A65: 未实现 | B65: 2026-04-30 | D65: US01 | E65: 02.11010.0000.0000.0000 银行存款 | F65: EUR→USD | G65: 15200 | H65: 16720 | I65: =H65/G65 -> 1.1 | J65: =INDEX('汇率表'!$A:$XFD,MATCH(B65,'汇率表'!$A:$A,0),MATCH(N65,'汇率表'!$1:$1,0))/INDEX('汇率表'!$A:$XFD,MATCH(B65,'汇率表'!$A:$A,0),MATCH(M65,'汇率表'!$1:$1,0)) -> 1.1665355 | K65: =I65-J65 -> -0.066535525 | L65: TB期初本位币及JE滚动后账面余额÷月末原币余额反推 | M65: USD | N65: EUR
A66: 未实现 | B66: 2026-05-31 | D66: SZ01 | E66: 01.13010.0000.0000.0000 其他应收款 | F66: USD→CNY | G66: 5000 | H66: 35600 | I66: =H66/G66 -> 7.12 | J66: =INDEX('汇率表'!$A:$XFD,MATCH(B66,'汇率表'!$A:$A,0),MATCH(N66,'汇率表'!$1:$1,0)) -> 6.8176 | K66: =I66-J66 -> 0.3024 | L66: TB期初本位币及JE滚动后账面余额÷月末原币余额反推 | M66: CNY | N66: USD
A67: 未实现 | B67: 2026-05-31 | D67: SZ01 | E67: 01.21010.0000.0000.0000 应付账款 | F67: EUR→CNY | G67: -85000 | H67: -665550 | I67: =H67/G67 -> 7.83 | J67: =INDEX('汇率表'!$A:$XFD,MATCH(B67,'汇率表'!$A:$A,0),MATCH(N67,'汇率表'!$1:$1,0)) -> 7.916 | K67: =I67-J67 -> -0.086 | L67: TB期初本位币及JE滚动后账面余额÷月末原币余额反推 | M67: CNY | N67: EUR
A68: 未实现 | B68: 2026-05-31 | D68: SZ01 | E68: 01.21010.0000.0000.0000 应付账款 | F68: HKD→CNY | G68: -75000 | H68: -68250 | I68: =H68/G68 -> 0.91 | J68: =INDEX('汇率表'!$A:$XFD,MATCH(B68,'汇率表'!$A:$A,0),MATCH(N68,'汇率表'!$1:$1,0)) -> 0.87029 | K68: =I68-J68 -> 0.03971 | L68: TB期初本位币及JE滚动后账面余额÷月末原币余额反推 | M68: CNY | N68: HKD
A69: 未实现 | B69: 2026-05-31 | D69: SZ01 | E69: 01.21010.0000.0000.0000 应付账款 | F69: JPY→CNY | G69: -9000000 | H69: -433800 | I69: =H69/G69 -> 0.0482 | J69: =INDEX('汇率表'!$A:$XFD,MATCH(B69,'汇率表'!$A:$A,0),MATCH(N69,'汇率表'!$1:$1,0)) -> 0.042718 | K69: =I69-J69 -> 0.005482 | L69: TB期初本位币及JE滚动后账面余额÷月末原币余额反推 | M69: CNY | N69: JPY
A70: 未实现 | B70: 2026-05-31 | D70: SZ01 | E70: 01.21010.0000.0000.0000 应付账款 | F70: USD→CNY | G70: -40000 | H70: -284800 | I70: =H70/G70 -> 7.12 | J70: =INDEX('汇率表'!$A:$XFD,MATCH(B70,'汇率表'!$A:$A,0),MATCH(N70,'汇率表'!$1:$1,0)) -> 6.8176 | K70: =I70-J70 -> 0.3024 | L70: TB期初本位币及JE滚动后账面余额÷月末原币余额反推 | M70: CNY | N70: USD
A71: 未实现 | B71: 2026-05-31 | D71: SZ01 | E71: 01.12010.0000.0000.0000 应收账款 | F71: EUR→CNY | G71: 67000 | H71: 524610 | I71: =H71/G71 -> 7.83 | J71: =INDEX('汇率表'!$A:$XFD,MATCH(B71,'汇率表'!$A:$A,0),MATCH(N71,'汇率表'!$1:$1,0)) -> 7.916 | K71: =I71-J71 -> -0.086 | L71: TB期初本位币及JE滚动后账面余额÷月末原币余额反推 | M71: CNY | N71: EUR
A72: 未实现 | B72: 2026-05-31 | D72: SZ01 | E72: 01.12010.0000.0000.0000 应收账款 | F72: HKD→CNY | G72: 30000 | H72: 27300 | I72: =H72/G72 -> 0.91 | J72: =INDEX('汇率表'!$A:$XFD,MATCH(B72,'汇率表'!$A:$A,0),MATCH(N72,'汇率表'!$1:$1,0)) -> 0.87029 | K72: =I72-J72 -> 0.03971 | L72: TB期初本位币及JE滚动后账面余额÷月末原币余额反推 | M72: CNY | N72: HKD
A73: 未实现 | B73: 2026-05-31 | D73: SZ01 | E73: 01.12010.0000.0000.0000 应收账款 | F73: USD→CNY | G73: 197500 | H73: 1406200 | I73: =H73/G73 -> 7.12 | J73: =INDEX('汇率表'!$A:$XFD,MATCH(B73,'汇率表'!$A:$A,0),MATCH(N73,'汇率表'!$1:$1,0)) -> 6.8176 | K73: =I73-J73 -> 0.3024 | L73: TB期初本位币及JE滚动后账面余额÷月末原币余额反推 | M73: CNY | N73: USD
A74: 未实现 | B74: 2026-05-31 | D74: SZ01 | E74: 01.11010.0000.0000.0000 银行存款 | F74: EUR→CNY | G74: 60000 | H74: 469800 | I74: =H74/G74 -> 7.83 | J74: =INDEX('汇率表'!$A:$XFD,MATCH(B74,'汇率表'!$A:$A,0),MATCH(N74,'汇率表'!$1:$1,0)) -> 7.916 | K74: =I74-J74 -> -0.086 | L74: TB期初本位币及JE滚动后账面余额÷月末原币余额反推 | M74: CNY | N74: EUR
A75: 未实现 | B75: 2026-05-31 | D75: SZ01 | E75: 01.11010.0000.0000.0000 银行存款 | F75: HKD→CNY | G75: 75000 | H75: 68250 | I75: =H75/G75 -> 0.91 | J75: =INDEX('汇率表'!$A:$XFD,MATCH(B75,'汇率表'!$A:$A,0),MATCH(N75,'汇率表'!$1:$1,0)) -> 0.87029 | K75: =I75-J75 -> 0.03971 | L75: TB期初本位币及JE滚动后账面余额÷月末原币余额反推 | M75: CNY | N75: HKD
A76: 未实现 | B76: 2026-05-31 | D76: SZ01 | E76: 01.11010.0000.0000.0000 银行存款 | F76: USD→CNY | G76: 425000 | H76: 3026000 | I76: =H76/G76 -> 7.12 | J76: =INDEX('汇率表'!$A:$XFD,MATCH(B76,'汇率表'!$A:$A,0),MATCH(N76,'汇率表'!$1:$1,0)) -> 6.8176 | K76: =I76-J76 -> 0.3024 | L76: TB期初本位币及JE滚动后账面余额÷月末原币余额反推 | M76: CNY | N76: USD
A77: 未实现 | B77: 2026-05-31 | D77: SZ01 | E77: 01.25010.0000.0000.0000 长期借款 | F77: USD→CNY | G77: -150000 | H77: -1068000 | I77: =H77/G77 -> 7.12 | J77: =INDEX('汇率表'!$A:$XFD,MATCH(B77,'汇率表'!$A:$A,0),MATCH(N77,'汇率表'!$1:$1,0)) -> 6.8176 | K77: =I77-J77 -> 0.3024 | L77: TB期初本位币及JE滚动后账面余额÷月末原币余额反推 | M77: CNY | N77: USD
A78: 未实现 | B78: 2026-05-31 | D78: US01 | E78: 02.13010.0000.0000.0000 其他应收款 | F78: EUR→USD | G78: 1000 | H78: 1100 | I78: =H78/G78 -> 1.1 | J78: =INDEX('汇率表'!$A:$XFD,MATCH(B78,'汇率表'!$A:$A,0),MATCH(N78,'汇率表'!$1:$1,0))/INDEX('汇率表'!$A:$XFD,MATCH(B78,'汇率表'!$A:$A,0),MATCH(M78,'汇率表'!$1:$1,0)) -> 1.1611124 | K78: =I78-J78 -> -0.061112415 | L78: TB期初本位币及JE滚动后账面余额÷月末原币余额反推 | M78: USD | N78: EUR
A79: 未实现 | B79: 2026-05-31 | D79: US01 | E79: 02.21010.0000.0000.0000 应付账款 | F79: EUR→USD | G79: -24000 | H79: -26400 | I79: =H79/G79 -> 1.1 | J79: =INDEX('汇率表'!$A:$XFD,MATCH(B79,'汇率表'!$A:$A,0),MATCH(N79,'汇率表'!$1:$1,0))/INDEX('汇率表'!$A:$XFD,MATCH(B79,'汇率表'!$A:$A,0),MATCH(M79,'汇率表'!$1:$1,0)) -> 1.1611124 | K79: =I79-J79 -> -0.061112415 | L79: TB期初本位币及JE滚动后账面余额÷月末原币余额反推 | M79: USD | N79: EUR
A80: 未实现 | B80: 2026-05-31 | D80: US01 | E80: 02.12010.0000.0000.0000 应收账款 | F80: EUR→USD | G80: 23000 | H80: 25300 | I80: =H80/G80 -> 1.1 | J80: =INDEX('汇率表'!$A:$XFD,MATCH(B80,'汇率表'!$A:$A,0),MATCH(N80,'汇率表'!$1:$1,0))/INDEX('汇率表'!$A:$XFD,MATCH(B80,'汇率表'!$A:$A,0),MATCH(M80,'汇率表'!$1:$1,0)) -> 1.1611124 | K80: =I80-J80 -> -0.061112415 | L80: TB期初本位币及JE滚动后账面余额÷月末原币余额反推 | M80: USD | N80: EUR
A81: 未实现 | B81: 2026-05-31 | D81: US01 | E81: 02.11010.0000.0000.0000 银行存款 | F81: EUR→USD | G81: 14000 | H81: 15400 | I81: =H81/G81 -> 1.1 | J81: =INDEX('汇率表'!$A:$XFD,MATCH(B81,'汇率表'!$A:$A,0),MATCH(N81,'汇率表'!$1:$1,0))/INDEX('汇率表'!$A:$XFD,MATCH(B81,'汇率表'!$A:$A,0),MATCH(M81,'汇率表'!$1:$1,0)) -> 1.1611124 | K81: =I81-J81 -> -0.061112415 | L81: TB期初本位币及JE滚动后账面余额÷月末原币余额反推 | M81: USD | N81: EUR
A82: 未实现 | B82: 2026-06-30 | D82: SZ01 | E82: 01.13010.0000.0000.0000 其他应收款 | F82: USD→CNY | G82: 5041.78 | H82: 35899.98 | I82: =H82/G82 -> 7.1204971 | J82: =INDEX('汇率表'!$A:$XFD,MATCH(B82,'汇率表'!$A:$A,0),MATCH(N82,'汇率表'!$1:$1,0)) -> 6.8109 | K82: =I82-J82 -> 0.30959713 | L82: TB期初本位币及JE滚动后账面余额÷月末原币余额反推 | M82: CNY | N82: USD
A83: 未实现 | B83: 2026-06-30 | D83: SZ01 | E83: 01.21010.0000.0000.0000 应付账款 | F83: EUR→CNY | G83: -80708.86 | H83: -631999.99 | I83: =H83/G83 -> 7.8306148 | J83: =INDEX('汇率表'!$A:$XFD,MATCH(B83,'汇率表'!$A:$A,0),MATCH(N83,'汇率表'!$1:$1,0)) -> 7.7671 | K83: =I83-J83 -> 0.063514755 | L83: TB期初本位币及JE滚动后账面余额÷月末原币余额反推 | M83: CNY | N83: EUR
A84: 未实现 | B84: 2026-06-30 | D84: SZ01 | E84: 01.21010.0000.0000.0000 应付账款 | F84: HKD→CNY | G84: -70382.51 | H84: -64050 | I84: =H84/G84 -> 0.91002722 | J84: =INDEX('汇率表'!$A:$XFD,MATCH(B84,'汇率表'!$A:$A,0),MATCH(N84,'汇率表'!$1:$1,0)) -> 0.86855 | K84: =I84-J84 -> 0.041477221 | L84: TB期初本位币及JE滚动后账面余额÷月末原币余额反推 | M84: CNY | N84: HKD
A85: 未实现 | B85: 2026-06-30 | D85: SZ01 | E85: 01.21010.0000.0000.0000 应付账款 | F85: JPY→CNY | G85: -11391515 | H85: -549450 | I85: =H85/G85 -> 0.048233268 | J85: =INDEX('汇率表'!$A:$XFD,MATCH(B85,'汇率表'!$A:$A,0),MATCH(N85,'汇率表'!$1:$1,0)) -> 0.042045 | K85: =I85-J85 -> 0.0061882677 | L85: TB期初本位币及JE滚动后账面余额÷月末原币余额反推 | M85: CNY | N85: JPY
A86: 未实现 | B86: 2026-06-30 | D86: SZ01 | E86: 01.21010.0000.0000.0000 应付账款 | F86: USD→CNY | G86: -40334.26 | H86: -287199.99 | I86: =H86/G86 -> 7.1204973 | J86: =INDEX('汇率表'!$A:$XFD,MATCH(B86,'汇率表'!$A:$A,0),MATCH(N86,'汇率表'!$1:$1,0)) -> 6.8109 | K86: =I86-J86 -> 0.30959731 | L86: TB期初本位币及JE滚动后账面余额÷月末原币余额反推 | M86: CNY | N86: USD
A87: 未实现 | B87: 2026-06-30 | D87: SZ01 | E87: 01.12010.0000.0000.0000 应收账款 | F87: EUR→CNY | G87: 75462.78 | H87: 590919.96 | I87: =H87/G87 -> 7.8306148 | J87: =INDEX('汇率表'!$A:$XFD,MATCH(B87,'汇率表'!$A:$A,0),MATCH(N87,'汇率表'!$1:$1,0)) -> 7.7671 | K87: =I87-J87 -> 0.063514775 | L87: TB期初本位币及JE滚动后账面余额÷月末原币余额反推 | M87: CNY | N87: EUR
A88: 未实现 | B88: 2026-06-30 | D88: SZ01 | E88: 01.12010.0000.0000.0000 应收账款 | F88: HKD→CNY | G88: 30163.93 | H88: 27450 | I88: =H88/G88 -> 0.91002731 | J88: =INDEX('汇率表'!$A:$XFD,MATCH(B88,'汇率表'!$A:$A,0),MATCH(N88,'汇率表'!$1:$1,0)) -> 0.86855 | K88: =I88-J88 -> 0.041477307 | L88: TB期初本位币及JE滚动后账面余额÷月末原币余额反推 | M88: CNY | N88: HKD
A89: 未实现 | B89: 2026-06-30 | D89: SZ01 | E89: 01.12010.0000.0000.0000 应收账款 | F89: USD→CNY | G89: 213267.41 | H89: 1518570 | I89: =H89/G89 -> 7.1204972 | J89: =INDEX('汇率表'!$A:$XFD,MATCH(B89,'汇率表'!$A:$A,0),MATCH(N89,'汇率表'!$1:$1,0)) -> 6.8109 | K89: =I89-J89 -> 0.30959722 | L89: TB期初本位币及JE滚动后账面余额÷月末原币余额反推 | M89: CNY | N89: USD
A90: 未实现 | B90: 2026-06-30 | D90: SZ01 | E90: 01.11010.0000.0000.0000 银行存款 | F90: EUR→CNY | G90: 64567.09 | H90: 505600.01 | I90: =H90/G90 -> 7.8306148 | J90: =INDEX('汇率表'!$A:$XFD,MATCH(B90,'汇率表'!$A:$A,0),MATCH(N90,'汇率表'!$1:$1,0)) -> 7.7671 | K90: =I90-J90 -> 0.063514792 | L90: TB期初本位币及JE滚动后账面余额÷月末原币余额反推 | M90: CNY | N90: EUR
A91: 未实现 | B91: 2026-06-30 | D91: SZ01 | E91: 01.11010.0000.0000.0000 银行存款 | F91: HKD→CNY | G91: 70382.51 | H91: 64050 | I91: =H91/G91 -> 0.91002722 | J91: =INDEX('汇率表'!$A:$XFD,MATCH(B91,'汇率表'!$A:$A,0),MATCH(N91,'汇率表'!$1:$1,0)) -> 0.86855 | K91: =I91-J91 -> 0.041477221 | L91: TB期初本位币及JE滚动后账面余额÷月末原币余额反推 | M91: CNY | N91: HKD
A92: 未实现 | B92: 2026-06-30 | D92: SZ01 | E92: 01.11010.0000.0000.0000 银行存款 | F92: USD→CNY | G92: 463844.01 | H92: 3302800 | I92: =H92/G92 -> 7.1204972 | J92: =INDEX('汇率表'!$A:$XFD,MATCH(B92,'汇率表'!$A:$A,0),MATCH(N92,'汇率表'!$1:$1,0)) -> 6.8109 | K92: =I92-J92 -> 0.30959723 | L92: TB期初本位币及JE滚动后账面余额÷月末原币余额反推 | M92: CNY | N92: USD
A93: 未实现 | B93: 2026-06-30 | D93: SZ01 | E93: 01.25010.0000.0000.0000 长期借款 | F93: USD→CNY | G93: -151253.48 | H93: -1077000 | I93: =H93/G93 -> 7.1204973 | J93: =INDEX('汇率表'!$A:$XFD,MATCH(B93,'汇率表'!$A:$A,0),MATCH(N93,'汇率表'!$1:$1,0)) -> 6.8109 | K93: =I93-J93 -> 0.30959726 | L93: TB期初本位币及JE滚动后账面余额÷月末原币余额反推 | M93: CNY | N93: USD
A94: 未实现 | B94: 2026-06-30 | D94: US01 | E94: 02.13010.0000.0000.0000 其他应收款 | F94: EUR→USD | G94: 1017.86 | H94: 1120 | I94: =H94/G94 -> 1.1003478 | J94: =INDEX('汇率表'!$A:$XFD,MATCH(B94,'汇率表'!$A:$A,0),MATCH(N94,'汇率表'!$1:$1,0))/INDEX('汇率表'!$A:$XFD,MATCH(B94,'汇率表'!$A:$A,0),MATCH(M94,'汇率表'!$1:$1,0)) -> 1.1403926 | K94: =I94-J94 -> -0.040044817 | L94: TB期初本位币及JE滚动后账面余额÷月末原币余额反推 | M94: USD | N94: EUR
A95: 未实现 | B95: 2026-06-30 | D95: US01 | E95: 02.21010.0000.0000.0000 应付账款 | F95: EUR→USD | G95: -17760.71 | H95: -19936 | I95: =H95/G95 -> 1.1224776 | J95: =INDEX('汇率表'!$A:$XFD,MATCH(B95,'汇率表'!$A:$A,0),MATCH(N95,'汇率表'!$1:$1,0))/INDEX('汇率表'!$A:$XFD,MATCH(B95,'汇率表'!$A:$A,0),MATCH(M95,'汇率表'!$1:$1,0)) -> 1.1403926 | K95: =I95-J95 -> -0.017914957 | L95: TB期初本位币及JE滚动后账面余额÷月末原币余额反推 | M95: USD | N95: EUR
A96: 未实现 | B96: 2026-06-30 | D96: US01 | E96: 02.12010.0000.0000.0000 应收账款 | F96: EUR→USD | G96: 27685.71 | H96: 30464 | I96: =H96/G96 -> 1.100351 | J96: =INDEX('汇率表'!$A:$XFD,MATCH(B96,'汇率表'!$A:$A,0),MATCH(N96,'汇率表'!$1:$1,0))/INDEX('汇率表'!$A:$XFD,MATCH(B96,'汇率表'!$A:$A,0),MATCH(M96,'汇率表'!$1:$1,0)) -> 1.1403926 | K96: =I96-J96 -> -0.040041558 | L96: TB期初本位币及JE滚动后账面余额÷月末原币余额反推 | M96: USD | N96: EUR
A97: 未实现 | B97: 2026-06-30 | D97: US01 | E97: 02.11010.0000.0000.0000 银行存款 | F97: EUR→USD | G97: 7582.14 | H97: 8736 | I97: =H97/G97 -> 1.1521813 | J97: =INDEX('汇率表'!$A:$XFD,MATCH(B97,'汇率表'!$A:$A,0),MATCH(N97,'汇率表'!$1:$1,0))/INDEX('汇率表'!$A:$XFD,MATCH(B97,'汇率表'!$A:$A,0),MATCH(M97,'汇率表'!$1:$1,0)) -> 1.1403926 | K97: =I97-J97 -> 0.011788704 | L97: TB期初本位币及JE滚动后账面余额÷月末原币余额反推 | M97: USD | N97: EUR

Sheet 汇率表
A1: 日期 | B1: AED | C1: AUD | D1: CAD | E1: CHF | F1: CNY | G1: DKK | H1: EUR | I1: GBP | J1: HKD | K1: HUF | L1: JPY | M1: KRW | N1: MOP | O1: MXN | P1: MYR | Q1: NOK | R1: NZD | S1: PLN | T1: RUB | U1: SAR | V1: SEK | W1: SGD | X1: THB | Y1: TRY | Z1: USD | AA1: ZAR | AC1: 本次审计汇率来源
A2: 2025-11-27 | B2: 1.9256692 | C2: 4.6134 | D2: 5.0378 | E2: 8.8005 | F2: 1 | G2: 1.0986596 | H2: 8.2056 | I2: 9.3671 | J2: 0.90998 | K2: 0.021477894 | L2: 0.045267 | M2: 0.0048146365 | N2: 0.8828463 | O2: 0.38563881 | P2: 1.7108933 | Q2: 0.69352937 | R2: 4.0339 | S2: 1.9385856 | T2: 0.090088467 | U2: 1.8857962 | V2: 0.74526755 | W2: 5.4565 | X2: 0.21959682 | Y2: 0.16663862 | Z2: 7.0779 | AA2: 0.41272855 | AC2: 程序内置牌价表（国家外汇管理局人民币汇率中间价，2022-11-28~2026-08-31，随程序打包；超期区间自动回落在线抓取）
A3: 2025-11-28 | B3: 1.9268937 | C3: 4.6243 | D3: 5.046 | E3: 8.7971 | F3: 1 | G3: 1.0990219 | H3: 8.2078 | I3: 9.3697 | J3: 0.9099 | K3: 0.021522455 | L3: 0.045293 | M3: 0.0048360576 | N3: 0.88269044 | O3: 0.38583224 | P3: 1.7139723 | Q3: 0.69657286 | R3: 4.0533 | S3: 1.9417476 | T3: 0.090797657 | U3: 1.8865077 | V3: 0.74710497 | W3: 5.4589 | X3: 0.2196547 | Y3: 0.16657422 | Z3: 7.0789 | AA3: 0.41262637
A4: 2025-11-29 | B4: 1.9268937 | C4: 4.6243 | D4: 5.046 | E4: 8.7971 | F4: 1 | G4: 1.0990219 | H4: 8.2078 | I4: 9.3697 | J4: 0.9099 | K4: 0.021522455 | L4: 0.045293 | M4: 0.0048360576 | N4: 0.88269044 | O4: 0.38583224 | P4: 1.7139723 | Q4: 0.69657286 | R4: 4.0533 | S4: 1.9417476 | T4: 0.090797657 | U4: 1.8865077 | V4: 0.74710497 | W4: 5.4589 | X4: 0.2196547 | Y4: 0.16657422 | Z4: 7.0789 | AA4: 0.41262637
A5: 2025-11-30 | B5: 1.9268937 | C5: 4.6243 | D5: 5.046 | E5: 8.7971 | F5: 1 | G5: 1.0990219 | H5: 8.2078 | I5: 9.3697 | J5: 0.9099 | K5: 0.021522455 | L5: 0.045293 | M5: 0.0048360576 | N5: 0.88269044 | O5: 0.38583224 | P5: 1.7139723 | Q5: 0.69657286 | R5: 4.0533 | S5: 1.9417476 | T5: 0.090797657 | U5: 1.8865077 | V5: 0.74710497 | W5: 5.4589 | X5: 0.2196547 | Y5: 0.16657422 | Z5: 7.0789 | AA5: 0.41262637
A6: 2025-12-01 | B6: 1.9255209 | C6: 4.6302 | D6: 5.0621 | E6: 8.8013 | F6: 1 | G6: 1.0985389 | H6: 8.2052 | I6: 9.3616 | J6: 0.90877 | K6: 0.021500568 | L6: 0.045331 | M6: 0.0048192771 | N6: 0.88160099 | O6: 0.38678734 | P6: 1.7125927 | Q6: 0.69920291 | R6: 4.0535 | S6: 1.9374588 | T6: 0.091256696 | U6: 1.8854051 | V6: 0.74850299 | W6: 5.4569 | X6: 0.22010917 | Y6: 0.16644834 | Z6: 7.0759 | AA6: 0.41324022
A7: 2025-12-02 | B7: 1.9262998 | C7: 4.6292 | D7: 5.0539 | E7: 8.7915 | F7: 1 | G7: 1.0995052 | H7: 8.2113 | I7: 9.3451 | J7: 0.9088 | K7: 0.021563714 | L7: 0.045495 | M7: 0.0048095421 | N7: 0.88191199 | O7: 0.38647343 | P7: 1.7131208 | Q7: 0.69837279 | R7: 4.0512 | S7: 1.942351 | T7: 0.091027427 | U7: 1.8849786 | V7: 0.74833495 | W7: 5.4576 | X7: 0.22106287 | Y7: 0.16668722 | Z7: 7.0794 | AA7: 0.41399296
A8: 2025-12-03 | B8: 1.9245944 | C8: 4.6437 | D8: 5.0589 | E8: 8.8047 | F8: 1 | G8: 1.1004732 | H8: 8.221 | I8: 9.3429 | J8: 0.90897 | K8: 0.021577254 | L8: 0.04536 | M8: 0.0048144047 | N8: 0.88214538 | O8: 0.38677238 | P8: 1.7116547 | Q8: 0.69793412 | R8: 4.0567 | S8: 1.9417476 | T8: 0.091262526 | U8: 1.8830973 | V8: 0.74985003 | W8: 5.4544 | X8: 0.22092124 | Y8: 0.16641759 | Z8: 7.0754 | AA8: 0.41312071
A9: 2025-12-04 | B9: 1.9215618 | C9: 4.6586 | D9: 5.0597 | E9: 8.8252 | F9: 1 | G9: 1.1025358 | H9: 8.2373 | I9: 9.4207 | J9: 0.90891 | K9: 0.021635843 | L9: 0.045468 | M9: 0.0048139412 | N9: 0.88198977 | O9: 0.38608548 | P9: 1.7142074 | Q9: 0.70126227 | R9: 4.0715 | S9: 1.9498499 | T9: 0.091377609 | U9: 1.8808306 | V9: 0.75284198 | W9: 5.4573 | X9: 0.22134667 | Y9: 0.16629915 | Z9: 7.0733 | AA9: 0.41430169
A10: 2025-12-05 | B10: 1.9258917 | C10: 4.6754 | D10: 5.0682 | E10: 8.8016 | F10: 1 | G10: 1.102779 | H10: 8.2376 | I10: 9.4269 | J10: 0.90906 | K10: 0.021508198 | L10: 0.045597 | M10: 0.0047991553 | N10: 0.88261253 | O10: 0.38791264 | P10: 1.7198383 | Q10: 0.6993007 | R10: 4.0767 | S10: 1.9453361 | T10: 0.092223698 | U10: 1.8847654 | V10: 0.7505817 | W10: 5.4573 | X10: 0.22079442 | Y10: 0.16645139 | Z10: 7.0749 | AA10: 0.41637174
A11: 2025-12-06 | B11: 1.9258917 | C11: 4.6754 | D11: 5.0682 | E11: 8.8016 | F11: 1 | G11: 1.102779 | H11: 8.2376 | I11: 9.4269 | J11: 0.90906 | K11: 0.021508198 | L11: 0.045597 | M11: 0.0047991553 | N11: 0.88261253 | O11: 0.38791264 | P11: 1.7198383 | Q11: 0.6993007 | R11: 4.0767 | S11: 1.9453361 | T11: 0.092223698 | U11: 1.8847654 | V11: 0.7505817 | W11: 5.4573 | X11: 0.22079442 | Y11: 0.16645139 | Z11: 7.0749 | AA11: 0.41637174
A12: 2025-12-07 | B12: 1.9258917 | C12: 4.6754 | D12: 5.0682 | E12: 8.8016 | F12: 1 | G12: 1.102779 | H12: 8.2376 | I12: 9.4269 | J12: 0.90906 | K12: 0.021508198 | L12: 0.045597 | M12: 0.0047991553 | N12: 0.88261253 | O12: 0.38791264 | P12: 1.7198383 | Q12: 0.6993007 | R12: 4.0767 | S12: 1.9453361 | T12: 0.092223698 | U12: 1.8847654 | V12: 0.7505817 | W12: 5.4573 | X12: 0.22079442 | Y12: 0.16645139 | Z12: 7.0749 | AA12: 0.41637174
A13: 2025-12-08 | B13: 1.9258917 | C13: 4.6954 | D13: 5.1153 | E13: 8.7914 | F13: 1 | G13: 1.102779 | H13: 8.2374 | I13: 9.4271 | J13: 0.90919 | K13: 0.021581771 | L13: 0.045563 | M13: 0.0048051511 | N13: 0.8822232 | O13: 0.38919592 | P13: 1.720075 | Q13: 0.6997411 | R13: 4.0861 | S13: 1.9476852 | T13: 0.092470155 | U13: 1.8846234 | V13: 0.75261534 | W13: 5.4599 | X13: 0.22161647 | Y13: 0.16623418 | Z13: 7.0764 | AA13: 0.41771094
A14: 2025-12-09 | B14: 1.9264853 | C14: 4.688 | D14: 5.1092 | E14: 8.7713 | F14: 1 | G14: 1.102779 | H14: 8.2372 | I14: 9.4298 | J14: 0.90981 | K14: 0.021416119 | L14: 0.045391 | M14: 0.004812088 | N14: 0.88331419 | O14: 0.3874017 | P14: 1.7194835 | Q14: 0.69895855 | R14: 4.0869 | S14: 1.9435213 | T14: 0.09218714 | U14: 1.885334 | V14: 0.75318219 | W14: 5.4532 | X14: 0.22171966 | Y14: 0.16631214 | Z14: 7.0773 | AA14: 0.41526515
... A217: 2026-06-30 | B217: 1.8510634 | C217: 4.6804 | D217: 4.7847 | E217: 8.4228 | F217: 1 | G217: 1.039177 | H217: 7.7671 | I217: 9.0145 | J217: 0.86855 | K217: 0.021961177 | L217: 0.042045 | M217: 0.0044029588 | N217: 0.84324142 | O217: 0.38968124 | P217: 1.6734161 | Q217: 0.68493151 | R217: 3.8414 | S217: 1.8121195 | T217: 0.088266707 | U217: 1.8103807 | V217: 0.70032915 | W217: 5.2605 | X217: 0.20424419 | Y217: 0.14580788 | Z217: 6.8109 | AA217: 0.41440471
