Workbook

Sheet 审计结论
A1: 项目 | B1: 结果
A2: 公司/核算主体 | B2: 默认主体
A3: 报告期间 | B3: 2026-01-01 至 2026-06-30
A4: 测算范围 | B4: 已实现＋未实现
A5: 已实现汇兑损益测算 | B5: =SUMIF('汇兑损益测算明细'!$C:$C,"已实现",'汇兑损益测算明细'!$P:$P) -> -14206.473
A6: 未实现汇兑损益测算 | B6: =SUM('未实现汇兑损益测算'!$L:$L) -> 130910.07
A7: 审计测算合计 | B7: =SUM(B5:B6) -> 116703.6
A8: 客户账面汇兑损益净额（未区分已实现/未实现） | B8: -7930
A9: 测算与客户账面差异 | B9: =B7-B8 -> 124633.6
A10: 待复核项目（账面金额） | B10: =SUMIF('汇兑损益测算明细'!$C:$C,"待复核",'汇兑损益测算明细'!$P:$P) -> 2400
A11: 差异率 | B11: =IFERROR(ABS(B9/B8),0) -> 15.716721
A12: 审计结论 | B12: =IF(ABS(B8)<0.01,"无法判断",IF(B11<0.05,"通过","不通过")) -> 不通过
A13: 限制与提示 | B13: 尚有2张凭证需披露，其中不构成汇兑事项 2 张、账面汇差 2400.00（结构上不含外币货币性项目，详见「汇兑事项复核」页，属科目使用问题，建议重分类复核）；账面金额见B10；详见“汇兑事项复核”。

Sheet 汇兑损益测算明细
A1: 日期 | B1: 凭证匹配ID | C1: 测算类型 | D1: 待复核分路 | E1: 摘要 | F1: 科目代码 | G1: 原始科目名称 | H1: 币种 | I1: JE原币金额 | J1: JE本位币金额 | K1: 是否测算行 | L1: 测算原币金额 | M1: 测算采用汇率 | N1: 测算前账面金额 | O1: 审计测算金额 | P1: 测算/待复核金额 | Q1: 计算逻辑 | R1: 测算方法与数据来源 | S1: JE源文件行号 | T1: 余额 | U1: 余额方向 | V1: 借方原币 | W1: 借方本位币 | X1: 凭证字号 | Y1: 币种 | Z1: 摘要 | AA1: 日期 | AB1: 汇率 | AC1: 科目名称 | AD1: 科目编码 | AE1: 贷方原币 | AF1: 贷方本位币
A2: 2026-01-12 | B2: 默认主体-2026-01-12-记-0004 | C2: 已实现 | E2: 收到美国客户A货款 | F2: 1002.02 | G2: 美元户 | H2: 美元 | I2: 100000 | J2: 712000 | K2: 是 | L2: 100000 | M2: 7.0108 | N2: 708181.54 | O2: =L2*M2 -> 701080 | P2: =N2-O2 -> 7101.5385 | Q2: 账面金额－审计金额 | R2: 已实现：滚动审计本位币基础与本次结算价值比较；汇率来源：国家外汇管理局人民币汇率中间价查询（数据由中国外汇交易中心公布）；央行交易日中间价：7.010800 | S2: 11 | T2: 912000 | U2: 借 | V2: 100000 | W2: 712000 | X2: 记-0004 | Y2: 美元 | Z2: 收到美国客户A货款 | AA2: 2026-01-12 | AB2: 7.12 | AC2: 美元户 | AD2: 1002.02
A3: 2026-01-12 | B3: 默认主体-2026-01-12-记-0004 | C3: 已实现 | E3: 收到美国客户A货款 | F3: 1122.02 | G3: 应收账款-美元客户 | H3: 美元 | I3: -100000 | J3: -712000 | K3: 否 | S3: 12 | T3: 1032000 | U3: 借 | X3: 记-0004 | Y3: 美元 | Z3: 收到美国客户A货款 | AA3: 2026-01-12 | AB3: 7.12 | AC3: 应收账款-美元客户 | AD3: 1122.02 | AE3: 100000 | AF3: 712000
A4: 2026-01-22 | B4: 默认主体-2026-01-22-记-0010 | C4: 已实现 | E4: 支付美元供应商货款 | F4: 2202.02 | G4: 应付账款-美元供应商 | H4: 美元 | I4: 50000 | J4: 356000 | K4: 是 | L4: 50000 | M4: 7.0019 | N4: 354597.5 | O4: =L4*M4 -> 350095 | P4: =O4-N4 -> -4502.5 | Q4: 审计金额－账面金额 | R4: 已实现：滚动审计本位币基础与本次结算价值比较；汇率来源：国家外汇管理局人民币汇率中间价查询（数据由中国外汇交易中心公布）；央行交易日中间价：7.001900 | S4: 25 | T4: 251200 | U4: 贷 | V4: 50000 | W4: 356000 | X4: 记-0010 | Y4: 美元 | Z4: 支付美元供应商货款 | AA4: 2026-01-22 | AB4: 7.12 | AC4: 应付账款-美元供应商 | AD4: 2202.02
A5: 2026-01-22 | B5: 默认主体-2026-01-22-记-0010 | C5: 已实现 | E5: 支付美元供应商货款 | F5: 1002.02 | G5: 美元户 | H5: 美元 | I5: -50000 | J5: -356000 | K5: 否 | S5: 26 | T5: 556000 | U5: 借 | X5: 记-0010 | Y5: 美元 | Z5: 支付美元供应商货款 | AA5: 2026-01-22 | AB5: 7.12 | AC5: 美元户 | AD5: 1002.02 | AE5: 50000 | AF5: 356000
A6: 2026-01-24 | B6: 默认主体-2026-01-24-记-0012 | C6: 已实现 | E6: 支付香港货代运费 | F6: 2202.03 | G6: 应付账款-港币供应商 | H6: 港币 | I6: 40000 | J6: 36400 | K6: 是 | L6: 40000 | M6: 0.89676 | N6: 36337.694 | O6: =L6*M6 -> 35870.4 | P6: =O6-N6 -> -467.29412 | Q6: 审计金额－账面金额 | R6: 已实现：滚动审计本位币基础与本次结算价值比较；汇率来源：国家外汇管理局人民币汇率中间价查询（数据由中国外汇交易中心公布）；央行交易日中间价：0.896760 | S6: 29 | T6: 300000 | U6: 贷 | V6: 40000 | W6: 36400 | X6: 记-0012 | Y6: 港币 | Z6: 支付香港货代运费 | AA6: 2026-01-24 | AB6: 0.91 | AC6: 应付账款-港币供应商 | AD6: 2202.03
A7: 2026-01-24 | B7: 默认主体-2026-01-24-记-0012 | C7: 已实现 | E7: 支付香港货代运费 | F7: 1002.03 | G7: 港币户 | H7: 港币 | I7: -40000 | J7: -36400 | K7: 否 | S7: 30 | T7: 463600 | U7: 借 | X7: 记-0012 | Y7: 港币 | Z7: 支付香港货代运费 | AA7: 2026-01-24 | AB7: 0.91 | AC7: 港币户 | AD7: 1002.03 | AE7: 40000 | AF7: 36400
A8: 2026-01-25 | B8: 默认主体-2026-01-25-记-0013 | C8: 已实现 | E8: 美元结汇 | F8: 1002.01 | G8: 人民币户 | H8: 人民币 | I8: 0 | J8: 429000 | K8: 是 | L8: 60000 | M8: 7.15 | N8: 425996.4 | O8: =L8*M8 -> 429000 | P8: =N8-O8 -> -3003.6 | Q8: 账面金额－审计金额 | R8: 已实现：滚动审计本位币基础与本次结算价值比较；汇率来源：国家外汇管理局人民币汇率中间价查询（数据由中国外汇交易中心公布）；央行交易日中间价：6.992900 | S8: 31 | T8: 3844800 | U8: 借 | W8: 429000 | X8: 记-0013 | Y8: 人民币 | Z8: 美元结汇 | AA8: 2026-01-25 | AC8: 人民币户 | AD8: 1002.01
A9: 2026-01-25 | B9: 默认主体-2026-01-25-记-0013 | C9: 已实现 | E9: 美元结汇 | F9: 1002.02 | G9: 美元户 | H9: 美元 | I9: -60000 | J9: -427200 | K9: 否 | S9: 32 | T9: 128800 | U9: 借 | X9: 记-0013 | Y9: 美元 | Z9: 美元结汇 | AA9: 2026-01-25 | AB9: 7.12 | AC9: 美元户 | AD9: 1002.02 | AE9: 60000 | AF9: 427200
A10: 2026-01-25 | B10: 默认主体-2026-01-25-记-0013 | C10: 已实现 | E10: 美元结汇 | F10: 6603.02 | G10: 财务费用-汇兑损益 | H10: 人民币 | I10: 0 | J10: -1800 | K10: 否 | S10: 33 | T10: 1800 | U10: 贷 | X10: 记-0013 | Y10: 人民币 | Z10: 美元结汇 | AA10: 2026-01-25 | AC10: 财务费用-汇兑损益 | AD10: 6603.02 | AF10: 1800
A11: 2026-01-26 | B11: 默认主体-2026-01-26-记-0014 | C11: 已实现 | E11: 购汇美元 | F11: 1002.02 | G11: 美元户 | H11: 美元 | I11: 30000 | J11: 213600 | K11: 是 | L11: 30000 | M11: 6.9843 | N11: 209529 | O11: =L11*M11 -> 209529 | P11: =O11-N11 -> 4671 | Q11: 审计金额－账面金额 | R11: 购汇：实际支付本位币减去交易日官方牌价折算额；汇率来源：国家外汇管理局人民币汇率中间价查询（数据由中国外汇交易中心公布）；央行交易日中间价：6.984300 | S11: 34 | T11: 342400 | U11: 借 | V11: 30000 | W11: 213600 | X11: 记-0014 | Y11: 美元 | Z11: 购汇美元 | AA11: 2026-01-26 | AB11: 7.12 | AC11: 美元户 | AD11: 1002.02
A12: 2026-01-26 | B12: 默认主体-2026-01-26-记-0014 | C12: 已实现 | E12: 购汇美元 | F12: 1002.01 | G12: 人民币户 | H12: 人民币 | I12: 0 | J12: -214200 | K12: 否 | S12: 35 | T12: 3630600 | U12: 借 | X12: 记-0014 | Y12: 人民币 | Z12: 购汇美元 | AA12: 2026-01-26 | AC12: 人民币户 | AD12: 1002.01 | AF12: 214200
A13: 2026-01-26 | B13: 默认主体-2026-01-26-记-0014 | C13: 已实现 | E13: 购汇美元 | F13: 6603.02 | G13: 财务费用-汇兑损益 | H13: 人民币 | I13: 0 | J13: 600 | K13: 否 | S13: 36 | T13: 1200 | U13: 贷 | W13: 600 | X13: 记-0014 | Y13: 人民币 | Z13: 购汇美元 | AA13: 2026-01-26 | AC13: 财务费用-汇兑损益 | AD13: 6603.02
A14: 2026-02-12 | B14: 默认主体-2026-02-12-记-0022 | C14: 已实现 | E14: 收到美国客户A货款 | F14: 1002.02 | G14: 美元户 | H14: usd | I14: 100000 | J14: 712000 | K14: 是 | L14: 100000 | M14: 6.9457 | N14: 696607.2 | O14: =L14*M14 -> 694570 | P14: =N14-O14 -> 2037.2 | Q14: 账面金额－审计金额 | R14: 已实现：滚动审计本位币基础与本次结算价值比较；汇率来源：国家外汇管理局人民币汇率中间价查询（数据由中国外汇交易中心公布）；央行交易日中间价：6.945700 | S14: 59 | T14: 1125600 | U14: 借 | V14: 100000 | W14: 712000 | X14: 记-0022 | Y14: usd | Z14: 收到美国客户A货款 | AA14: 2026-02-12 | AB14: 7.12 | AC14: 美元户 | AD14: 1002.02
A15: 2026-02-12 | B15: 默认主体-2026-02-12-记-0022 | C15: 已实现 | E15: 收到美国客户A货款 | F15: 1122.02 | G15: 应收账款-美元客户 | H15: 美元 | I15: -100000 | J15: -712000 | K15: 否 | S15: 60 | T15: 889600 | U15: 借 | X15: 记-0022 | Y15: 美元 | Z15: 收到美国客户A货款 | AA15: 2026-02-12 | AB15: 7.12 | AC15: 应收账款-美元客户 | AD15: 1122.02 | AE15: 100000 | AF15: 712000
A16: 2026-02-17 | B16: 默认主体-2026-02-17-记-0026 | C16: 已实现 | E16: 收到欧元客户货款并结汇 | F16: 1002.01 | G16: 人民币户 | H16: 人民币 | I16: 0 | J16: 196250 | K16: 是 | L16: 25000 | M16: 7.85 | N16: 208110 | O16: =L16*M16 -> 196250 | P16: =N16-O16 -> 11860 | Q16: 账面金额－审计金额 | R16: 已实现：滚动审计本位币基础与本次结算价值比较；汇率来源：国家外汇管理局人民币汇率中间价查询（数据由中国外汇交易中心公布）；央行交易日中间价：8.219500 | S16: 68 | T16: 3603950 | U16: 借 | W16: 196250 | X16: 记-0026 | Y16: 人民币 | Z16: 收到欧元客户货款并结汇 | AA16: 2026-02-17 | AC16: 人民币户 | AD16: 1002.01
A17: 2026-02-17 | B17: 默认主体-2026-02-17-记-0026 | C17: 已实现 | E17: 收到欧元客户货款并结汇 | F17: 1122.03 | G17: 应收账款-欧元客户 | H17: 欧元 | I17: -25000 | J17: -195750 | K17: 否 | S17: 69 | T17: 45750 | U17: 贷 | X17: 记-0026 | Y17: 欧元 | Z17: 收到欧元客户货款并结汇 | AA17: 2026-02-17 | AB17: 7.83 | AC17: 应收账款-欧元客户 | AD17: 1122.03 | AE17: 25000 | AF17: 195750
A18: 2026-02-17 | B18: 默认主体-2026-02-17-记-0026 | C18: 已实现 | E18: 收到欧元客户货款并结汇 | F18: 6603.02 | G18: 财务费用-汇兑损益 | H18: 人民币 | I18: 0 | J18: -500 | K18: 否 | S18: 70 | T18: 500 | U18: 贷 | X18: 记-0026 | Y18: 人民币 | Z18: 收到欧元客户货款并结汇 | AA18: 2026-02-17 | AC18: 财务费用-汇兑损益 | AD18: 6603.02 | AF18: 500
A19: 2026-02-22 | B19: 默认主体-2026-02-22-记-0029 | C19: 已实现 | E19: 支付美元供应商货款 | F19: 2202.02 | G19: 应付账款-美元供应商 | H19: 美元 | I19: 30000 | J19: 213600 | K19: 是 | L19: 30000 | M19: 6.9398 | N19: 208887.91 | O19: =L19*M19 -> 208194 | P19: =O19-N19 -> -693.91304 | Q19: 审计金额－账面金额 | R19: 已实现：滚动审计本位币基础与本次结算价值比较；汇率来源：国家外汇管理局人民币汇率中间价查询（数据由中国外汇交易中心公布）；央行交易日中间价：6.939800 | S19: 76 | T19: 322400 | U19: 贷 | V19: 30000 | W19: 213600 | X19: 记-0029 | Y19: 美元 | Z19: 支付美元供应商货款 | AA19: 2026-02-22 | AB19: 7.12 | AC19: 应付账款-美元供应商 | AD19: 2202.02
A20: 2026-02-22 | B20: 默认主体-2026-02-22-记-0029 | C20: 已实现 | E20: 支付美元供应商货款 | F20: 1002.02 | G20: 美元户 | H20: 美元 | I20: -30000 | J20: -213600 | K20: 否 | S20: 77 | T20: 912000 | U20: 借 | X20: 记-0029 | Y20: 美元 | Z20: 支付美元供应商货款 | AA20: 2026-02-22 | AB20: 7.12 | AC20: 美元户 | AD20: 1002.02 | AE20: 30000 | AF20: 213600
A21: 2026-02-24 | B21: 默认主体-2026-02-24-记-0031 | C21: 已实现 | E21: 支付香港货代运费 | F21: 2202.03 | G21: 应付账款-港币供应商 | H21: 港币 | I21: 30000 | J21: 27300 | K21: 是 | L21: 30000 | M21: 0.88773 | N21: 26765.645 | O21: =L21*M21 -> 26631.9 | P21: =O21-N21 -> -133.74545 | Q21: 审计金额－账面金额 | R21: 已实现：滚动审计本位币基础与本次结算价值比较；汇率来源：国家外汇管理局人民币汇率中间价查询（数据由中国外汇交易中心公布）；央行交易日中间价：0.887730 | S21: 80 | T21: 300000 | U21: 贷 | V21: 30000 | W21: 27300 | X21: 记-0031 | Y21: 港币 | Z21: 支付香港货代运费 | AA21: 2026-02-24 | AB21: 0.91 | AC21: 应付账款-港币供应商 | AD21: 2202.03
A22: 2026-02-24 | B22: 默认主体-2026-02-24-记-0031 | C22: 已实现 | E22: 支付香港货代运费 | F22: 1002.03 | G22: 港币户 | H22: 港币 | I22: -30000 | J22: -27300 | K22: 否 | S22: 81 | T22: 436300 | U22: 借 | X22: 记-0031 | Y22: 港币 | Z22: 支付香港货代运费 | AA22: 2026-02-24 | AB22: 0.91 | AC22: 港币户 | AD22: 1002.03 | AE22: 30000 | AF22: 27300
A23: 2026-02-25 | B23: 默认主体-2026-02-25-记-0032 | C23: 已实现 | E23: 美元结汇 | F23: 1002.01 | G23: 人民币户 | H23: 人民币 | I23: 0 | J23: 285600 | K23: 是 | L23: 40000 | M23: 7.14 | N23: 278526.53 | O23: =L23*M23 -> 285600 | P23: =N23-O23 -> -7073.4667 | Q23: 账面金额－审计金额 | R23: 已实现：滚动审计本位币基础与本次结算价值比较；汇率来源：国家外汇管理局人民币汇率中间价查询（数据由中国外汇交易中心公布）；央行交易日中间价：6.932100 | S23: 82 | T23: 3889550 | U23: 借 | W23: 285600 | X23: 记-0032 | Y23: 人民币 | Z23: 美元结汇 | AA23: 2026-02-25 | AC23: 人民币户 | AD23: 1002.01
A24: 2026-02-25 | B24: 默认主体-2026-02-25-记-0032 | C24: 已实现 | E24: 美元结汇 | F24: 1002.02 | G24: 美元户 | H24: 美元 | I24: -40000 | J24: -284800 | K24: 否 | S24: 83 | T24: 627200 | U24: 借 | X24: 记-0032 | Y24: 美元 | Z24: 美元结汇 | AA24: 2026-02-25 | AB24: 7.12 | AC24: 美元户 | AD24: 1002.02 | AE24: 40000 | AF24: 284800
A25: 2026-02-25 | B25: 默认主体-2026-02-25-记-0032 | C25: 已实现 | E25: 美元结汇 | F25: 6603.02 | G25: 财务费用-汇兑损益 | H25: 人民币 | I25: 0 | J25: -800 | K25: 否 | S25: 84 | T25: 1300 | U25: 贷 | X25: 记-0032 | Y25: 人民币 | Z25: 美元结汇 | AA25: 2026-02-25 | AC25: 财务费用-汇兑损益 | AD25: 6603.02 | AF25: 800
A26: 2026-03-12 | B26: 默认主体-2026-03-12-记-0040 | C26: 已实现 | E26: 收到美国客户A货款 | F26: 1002.02 | G26: 美元户 | H26: 美元 | I26: 120000 | J26: 854400 | K26: 是 | L26: 120000 | M26: 6.8959 | N26: 829880.8 | O26: =L26*M26 -> 827508 | P26: =N26-O26 -> 2372.8 | Q26: 账面金额－审计金额 | R26: 已实现：滚动审计本位币基础与本次结算价值比较；汇率来源：国家外汇管理局人民币汇率中间价查询（数据由中国外汇交易中心公布）；央行交易日中间价：6.895900 | S26: 108 | T26: 1481600 | U26: 借 | V26: 120000 | W26: 854400 | X26: 记-0040 | Y26: 美元 | Z26: 收到美国客户A货款 | AA26: 2026-03-12 | AB26: 7.12 | AC26: 美元户 | AD26: 1002.02
A27: 2026-03-12 | B27: 默认主体-2026-03-12-记-0040 | C27: 已实现 | E27: 收到美国客户A货款 | F27: 1122.02 | G27: 应收账款-美元客户 | H27: 美元 | I27: -120000 | J27: -854400 | K27: 否 | S27: 109 | T27: 1459200 | U27: 借 | X27: 记-0040 | Y27: 美元 | Z27: 收到美国客户A货款 | AA27: 2026-03-12 | AB27: 7.12 | AC27: 应收账款-美元客户 | AD27: 1122.02 | AE27: 120000 | AF27: 854400
A28: 2026-03-13 | B28: 默认主体-2026-03-13-记-0041 | C28: 待复核 | D28: 非货币性项目/异常复核 | E28: 购汇日元预付日本供应商货款 | F28: 1123.02 | G28: 预付款项-日元 | H28: 日元 | I28: 2000000 | J28: 96400 | K28: 是 | L28: 0 | M28: 0 | N28: 1200 | P28: =N28 -> 1200 | Q28: 账面金额仅供参考，不纳入审计测算 | R28: 对方科目为预付款、存货、固定资产等非货币性项目，不产生外币汇兑损益；账面汇差建议重分类复核 | S28: 110 | T28: 5096400 | U28: 借 | V28: 2000000 | W28: 96400 | X28: 记-0041 | Y28: 日元 | Z28: 购汇日元预付日本供应商货款 | AA28: 2026-03-13 | AB28: 0.0482 | AC28: 预付款项-日元 | AD28: 1123.02
A29: 2026-03-13 | B29: 默认主体-2026-03-13-记-0041 | C29: 待复核 | D29: 非货币性项目/异常复核 | E29: 购汇日元预付日本供应商货款 | F29: 1002.01 | G29: 人民币户 | H29: 人民币 | I29: 0 | J29: -97600 | K29: 否 | S29: 111 | T29: 3492150 | U29: 借 | X29: 记-0041 | Y29: 人民币 | Z29: 购汇日元预付日本供应商货款 | AA29: 2026-03-13 | AC29: 人民币户 | AD29: 1002.01 | AF29: 97600
A30: 2026-03-13 | B30: 默认主体-2026-03-13-记-0041 | C30: 待复核 | D30: 非货币性项目/异常复核 | E30: 购汇日元预付日本供应商货款 | F30: 6603.02 | G30: 财务费用-汇兑损益 | H30: 人民币 | I30: 0 | J30: 1200 | K30: 否 | S30: 112 | T30: 1200 | U30: 借 | W30: 1200 | X30: 记-0041 | Y30: 人民币 | Z30: 购汇日元预付日本供应商货款 | AA30: 2026-03-13 | AC30: 财务费用-汇兑损益 | AD30: 6603.02
A31: 2026-03-22 | B31: 默认主体-2026-03-22-记-0048 | C31: 已实现 | E31: 支付美元供应商货款 | F31: 2202.02 | G31: 应付账款-美元供应商 | H31: 美元 | I31: 50000 | J31: 356000 | K31: 是 | L31: 50000 | M31: 6.8898 | N31: 345771.92 | O31: =L31*M31 -> 344490 | P31: =O31-N31 -> -1281.9231 | Q31: 审计金额－账面金额 | R31: 已实现：滚动审计本位币基础与本次结算价值比较；汇率来源：国家外汇管理局人民币汇率中间价查询（数据由中国外汇交易中心公布）；央行交易日中间价：6.889800 | S31: 127 | T31: 393600 | U31: 贷 | V31: 50000 | W31: 356000 | X31: 记-0048 | Y31: 美元 | Z31: 支付美元供应商货款 | AA31: 2026-03-22 | AB31: 7.12 | AC31: 应付账款-美元供应商 | AD31: 2202.02
A32: 2026-03-22 | B32: 默认主体-2026-03-22-记-0048 | C32: 已实现 | E32: 支付美元供应商货款 | F32: 1002.02 | G32: 美元户 | H32: 美元 | I32: -50000 | J32: -356000 | K32: 否 | S32: 128 | T32: 1125600 | U32: 借 | X32: 记-0048 | Y32: 美元 | Z32: 支付美元供应商货款 | AA32: 2026-03-22 | AB32: 7.12 | AC32: 美元户 | AD32: 1002.02 | AE32: 50000 | AF32: 356000
A33: 2026-03-24 | B33: 默认主体-2026-03-24-记-0050 | C33: 已实现 | E33: 支付香港货代运费 | F33: 2202.03 | G33: 应付账款-港币供应商 | H33: 港币 | I33: 40000 | J33: 36400 | K33: 是 | L33: 40000 | M33: 0.88015 | N33: 35376.188 | O33: =L33*M33 -> 35206 | P33: =O33-N33 -> -170.18824 | Q33: 审计金额－账面金额 | R33: 已实现：滚动审计本位币基础与本次结算价值比较；汇率来源：国家外汇管理局人民币汇率中间价查询（数据由中国外汇交易中心公布）；央行交易日中间价：0.880150 | S33: 131 | T33: 300000 | U33: 贷 | V33: 40000 | W33: 36400 | X33: 记-0050 | Y33: 港币 | Z33: 支付香港货代运费 | AA33: 2026-03-24 | AB33: 0.91 | AC33: 应付账款-港币供应商 | AD33: 2202.03
A34: 2026-03-24 | B34: 默认主体-2026-03-24-记-0050 | C34: 已实现 | E34: 支付香港货代运费 | F34: 1002.03 | G34: 港币户 | H34: 港币 | I34: -40000 | J34: -36400 | K34: 否 | S34: 132 | T34: 399900 | U34: 借 | X34: 记-0050 | Y34: 港币 | Z34: 支付香港货代运费 | AA34: 2026-03-24 | AB34: 0.91 | AC34: 港币户 | AD34: 1002.03 | AE34: 40000 | AF34: 36400
A35: 2026-03-25 | B35: 默认主体-2026-03-25-记-0051 | C35: 已实现 | E35: 美元结汇 | F35: 1002.01 | G35: 人民币户 | H35: 人民币 | I35: 0 | J35: 429000 | K35: 是 | L35: 60000 | M35: 7.15 | N35: 415081.09 | O35: =L35*M35 -> 429000 | P35: =N35-O35 -> -13918.909 | Q35: 账面金额－审计金额 | R35: 已实现：滚动审计本位币基础与本次结算价值比较；汇率来源：国家外汇管理局人民币汇率中间价查询（数据由中国外汇交易中心公布）；央行交易日中间价：6.891100 | S35: 133 | T35: 3836950 | U35: 借 | W35: 429000 | X35: 记-0051 | Y35: 人民币 | Z35: 美元结汇 | AA35: 2026-03-25 | AC35: 人民币户 | AD35: 1002.01
A36: 2026-03-25 | B36: 默认主体-2026-03-25-记-0051 | C36: 已实现 | E36: 美元结汇 | F36: 1002.02 | G36: 美元户 | H36: 美元 | I36: -60000 | J36: -427200 | K36: 否 | S36: 134 | T36: 698400 | U36: 借 | X36: 记-0051 | Y36: 美元 | Z36: 美元结汇 | AA36: 2026-03-25 | AB36: 7.12 | AC36: 美元户 | AD36: 1002.02 | AE36: 60000 | AF36: 427200
A37: 2026-03-25 | B37: 默认主体-2026-03-25-记-0051 | C37: 已实现 | E37: 美元结汇 | F37: 6603.02 | G37: 财务费用-汇兑损益 | H37: 人民币 | I37: 0 | J37: -1800 | K37: 否 | S37: 135 | T37: 600 | U37: 贷 | X37: 记-0051 | Y37: 人民币 | Z37: 美元结汇 | AA37: 2026-03-25 | AC37: 财务费用-汇兑损益 | AD37: 6603.02 | AF37: 1800
A38: 2026-03-26 | B38: 默认主体-2026-03-26-记-0052 | C38: 已实现 | E38: 购汇美元 | F38: 1002.02 | G38: 美元户 | H38: 美元 | I38: 30000 | J38: 213600 | K38: 是 | L38: 30000 | M38: 6.9056 | N38: 207168 | O38: =L38*M38 -> 207168 | P38: =O38-N38 -> 7032 | Q38: 审计金额－账面金额 | R38: 购汇：实际支付本位币减去交易日官方牌价折算额；汇率来源：国家外汇管理局人民币汇率中间价查询（数据由中国外汇交易中心公布）；央行交易日中间价：6.905600 | S38: 136 | T38: 912000 | U38: 借 | V38: 30000 | W38: 213600 | X38: 记-0052 | Y38: 美元 | Z38: 购汇美元 | AA38: 2026-03-26 | AB38: 7.12 | AC38: 美元户 | AD38: 1002.02
A39: 2026-03-26 | B39: 默认主体-2026-03-26-记-0052 | C39: 已实现 | E39: 购汇美元 | F39: 1002.01 | G39: 人民币户 | H39: 人民币 | I39: 0 | J39: -214200 | K39: 否 | S39: 137 | T39: 3622750 | U39: 借 | X39: 记-0052 | Y39: 人民币 | Z39: 购汇美元 | AA39: 2026-03-26 | AC39: 人民币户 | AD39: 1002.01 | AF39: 214200
A40: 2026-03-26 | B40: 默认主体-2026-03-26-记-0052 | C40: 已实现 | E40: 购汇美元 | F40: 6603.02 | G40: 财务费用-汇兑损益 | H40: 人民币 | I40: 0 | J40: 600 | K40: 否 | S40: 138 | T40: 0 | U40: 平 | W40: 600 | X40: 记-0052 | Y40: 人民币 | Z40: 购汇美元 | AA40: 2026-03-26 | AC40: 财务费用-汇兑损益 | AD40: 6603.02
A41: 2026-04-12 | B41: 默认主体-2026-04-12-记-0060 | C41: 已实现 | E41: 收到美国客户A货款 | F41: 1002.02 | G41: 美元户 | H41: 美元 | I41: 160000 | J41: 1139200 | K41: 是 | L41: 160000 | M41: 6.8654 | N41: 1105771.4 | O41: =L41*M41 -> 1098464 | P41: =N41-O41 -> 7307.4286 | Q41: 账面金额－审计金额 | R41: 已实现：滚动审计本位币基础与本次结算价值比较；汇率来源：国家外汇管理局人民币汇率中间价查询（数据由中国外汇交易中心公布）；央行交易日中间价：6.865400 | S41: 160 | T41: 2051200 | U41: 借 | V41: 160000 | W41: 1139200 | X41: 记-0060 | Y41: 美元 | Z41: 收到美国客户A货款 | AA41: 2026-04-12 | AB41: 7.12 | AC41: 美元户 | AD41: 1002.02
A42: 2026-04-12 | B42: 默认主体-2026-04-12-记-0060 | C42: 已实现 | E42: 收到美国客户A货款 | F42: 1122.02 | G42: 应收账款-美元客户 | H42: 美元 | I42: -160000 | J42: -1139200 | K42: 否 | S42: 161 | T42: 1886400 | U42: 借 | X42: 记-0060 | Y42: 美元 | Z42: 收到美国客户A货款 | AA42: 2026-04-12 | AB42: 7.12 | AC42: 应收账款-美元客户 | AD42: 1122.02 | AE42: 160000 | AF42: 1139200
A43: 2026-04-17 | B43: 默认主体-2026-04-17-记-0064 | C43: 已实现 | E43: 收到欧元客户货款并结汇 | F43: 1002.01 | G43: 人民币户 | H43: 人民币 | I43: 0 | J43: 196750 | K43: 是 | L43: 25000 | M43: 7.87 | N43: 198255 | O43: =L43*M43 -> 196750 | P43: =N43-O43 -> 1505 | Q43: 账面金额－审计金额 | R43: 已实现：滚动审计本位币基础与本次结算价值比较；汇率来源：国家外汇管理局人民币汇率中间价查询（数据由中国外汇交易中心公布）；央行交易日中间价：8.061800 | S43: 169 | T43: 3596000 | U43: 借 | W43: 196750 | X43: 记-0064 | Y43: 人民币 | Z43: 收到欧元客户货款并结汇 | AA43: 2026-04-17 | AC43: 人民币户 | AD43: 1002.01
A44: 2026-04-17 | B44: 默认主体-2026-04-17-记-0064 | C44: 已实现 | E44: 收到欧元客户货款并结汇 | F44: 1122.03 | G44: 应收账款-欧元客户 | H44: 欧元 | I44: -25000 | J44: -195750 | K44: 否 | S44: 170 | T44: 241500 | U44: 贷 | X44: 记-0064 | Y44: 欧元 | Z44: 收到欧元客户货款并结汇 | AA44: 2026-04-17 | AB44: 7.83 | AC44: 应收账款-欧元客户 | AD44: 1122.03 | AE44: 25000 | AF44: 195750
A45: 2026-04-17 | B45: 默认主体-2026-04-17-记-0064 | C45: 已实现 | E45: 收到欧元客户货款并结汇 | F45: 6603.02 | G45: 财务费用-汇兑损益 | H45: 人民币 | I45: 0 | J45: -1000 | K45: 否 | S45: 171 | T45: 1000 | U45: 贷 | X45: 记-0064 | Y45: 人民币 | Z45: 收到欧元客户货款并结汇 | AA45: 2026-04-17 | AC45: 财务费用-汇兑损益 | AD45: 6603.02 | AF45: 1000
A46: 2026-04-22 | B46: 默认主体-2026-04-22-记-0067 | C46: 已实现 | E46: 支付美元供应商货款 | F46: 2202.02 | G46: 应付账款-美元供应商 | H46: 美元 | I46: 50000 | J46: 356000 | K46: 是 | L46: 50000 | M46: 6.8635 | N46: 345334.44 | O46: =L46*M46 -> 343175 | P46: =O46-N46 -> -2159.4444 | Q46: 审计金额－账面金额 | R46: 已实现：滚动审计本位币基础与本次结算价值比较；汇率来源：国家外汇管理局人民币汇率中间价查询（数据由中国外汇交易中心公布）；央行交易日中间价：6.863500 | S46: 177 | T46: 464800 | U46: 贷 | V46: 50000 | W46: 356000 | X46: 记-0067 | Y46: 美元 | Z46: 支付美元供应商货款 | AA46: 2026-04-22 | AB46: 7.12 | AC46: 应付账款-美元供应商 | AD46: 2202.02
A47: 2026-04-22 | B47: 默认主体-2026-04-22-记-0067 | C47: 已实现 | E47: 支付美元供应商货款 | F47: 1002.02 | G47: 美元户 | H47: 美元 | I47: -50000 | J47: -356000 | K47: 否 | S47: 178 | T47: 1695200 | U47: 借 | X47: 记-0067 | Y47: 美元 | Z47: 支付美元供应商货款 | AA47: 2026-04-22 | AB47: 7.12 | AC47: 美元户 | AD47: 1002.02 | AE47: 50000 | AF47: 356000
A48: 2026-04-24 | B48: 默认主体-2026-04-24-记-0069 | C48: 已实现 | E48: 支付香港货代运费 | F48: 2202.03 | G48: 应付账款-港币供应商 | H48: 港币 | I48: 40000 | J48: 36400 | K48: 是 | L48: 40000 | M48: 0.87666 | N48: 35287.553 | O48: =L48*M48 -> 35066.4 | P48: =O48-N48 -> -221.15294 | Q48: 审计金额－账面金额 | R48: 已实现：滚动审计本位币基础与本次结算价值比较；汇率来源：国家外汇管理局人民币汇率中间价查询（数据由中国外汇交易中心公布）；央行交易日中间价：0.876660 | S48: 181 | T48: 300000 | U48: 贷 | V48: 40000 | W48: 36400 | X48: 记-0069 | Y48: 港币 | Z48: 支付香港货代运费 | AA48: 2026-04-24 | AB48: 0.91 | AC48: 应付账款-港币供应商 | AD48: 2202.03
A49: 2026-04-24 | B49: 默认主体-2026-04-24-记-0069 | C49: 已实现 | E49: 支付香港货代运费 | F49: 1002.03 | G49: 港币户 | H49: 港币 | I49: -40000 | J49: -36400 | K49: 否 | S49: 182 | T49: 363500 | U49: 借 | X49: 记-0069 | Y49: 港币 | Z49: 支付香港货代运费 | AA49: 2026-04-24 | AB49: 0.91 | AC49: 港币户 | AD49: 1002.03 | AE49: 40000 | AF49: 36400
A50: 2026-04-25 | B50: 默认主体-2026-04-25-记-0070 | C50: 已实现 | E50: 美元结汇 | F50: 1002.01 | G50: 人民币户 | H50: 人民币 | I50: 0 | J50: 429600 | K50: 是 | L50: 60000 | M50: 7.16 | N50: 414308.63 | O50: =L50*M50 -> 429600 | P50: =N50-O50 -> -15291.366 | Q50: 账面金额－审计金额 | R50: 已实现：滚动审计本位币基础与本次结算价值比较；汇率来源：国家外汇管理局人民币汇率中间价查询（数据由中国外汇交易中心公布）；央行交易日中间价：6.867400 | S50: 183 | T50: 4025600 | U50: 借 | W50: 429600 | X50: 记-0070 | Y50: 人民币 | Z50: 美元结汇 | AA50: 2026-04-25 | AC50: 人民币户 | AD50: 1002.01
A51: 2026-04-25 | B51: 默认主体-2026-04-25-记-0070 | C51: 已实现 | E51: 美元结汇 | F51: 1002.02 | G51: 美元户 | H51: Usd | I51: -60000 | J51: -427200 | K51: 否 | S51: 184 | T51: 1268000 | U51: 借 | X51: 记-0070 | Y51: Usd | Z51: 美元结汇 | AA51: 2026-04-25 | AB51: 7.12 | AC51: 美元户 | AD51: 1002.02 | AE51: 60000 | AF51: 427200
A52: 2026-04-25 | B52: 默认主体-2026-04-25-记-0070 | C52: 已实现 | E52: 美元结汇 | F52: 6603.02 | G52: 财务费用-汇兑损益 | H52: 人民币 | I52: 0 | J52: -2400 | K52: 否 | S52: 185 | T52: 3400 | U52: 贷 | X52: 记-0070 | Y52: 人民币 | Z52: 美元结汇 | AA52: 2026-04-25 | AC52: 财务费用-汇兑损益 | AD52: 6603.02 | AF52: 2400
A53: 2026-04-26 | B53: 默认主体-2026-04-26-记-0071 | C53: 已实现 | E53: 购汇美元 | F53: 1002.02 | G53: 美元户 | H53: 美元 | I53: 30000 | J53: 213600 | K53: 是 | L53: 30000 | M53: 6.8674 | N53: 206022 | O53: =L53*M53 -> 206022 | P53: =O53-N53 -> 8478 | Q53: 审计金额－账面金额 | R53: 购汇：实际支付本位币减去交易日官方牌价折算额；汇率来源：国家外汇管理局人民币汇率中间价查询（数据由中国外汇交易中心公布）；央行交易日中间价：6.867400 | S53: 186 | T53: 1481600 | U53: 借 | V53: 30000 | W53: 213600 | X53: 记-0071 | Y53: 美元 | Z53: 购汇美元 | AA53: 2026-04-26 | AB53: 7.12 | AC53: 美元户 | AD53: 1002.02
A54: 2026-04-26 | B54: 默认主体-2026-04-26-记-0071 | C54: 已实现 | E54: 购汇美元 | F54: 1002.01 | G54: 人民币户 | H54: 人民币 | I54: 0 | J54: -214500 | K54: 否 | S54: 187 | T54: 3811100 | U54: 借 | X54: 记-0071 | Y54: 人民币 | Z54: 购汇美元 | AA54: 2026-04-26 | AC54: 人民币户 | AD54: 1002.01 | AF54: 214500
A55: 2026-04-26 | B55: 默认主体-2026-04-26-记-0071 | C55: 已实现 | E55: 购汇美元 | F55: 6603.02 | G55: 财务费用-汇兑损益 | H55: 人民币 | I55: 0 | J55: 900 | K55: 否 | S55: 188 | T55: 2500 | U55: 贷 | W55: 900 | X55: 记-0071 | Y55: 人民币 | Z55: 购汇美元 | AA55: 2026-04-26 | AC55: 财务费用-汇兑损益 | AD55: 6603.02
A56: 2026-05-12 | B56: 默认主体-2026-05-12-记-0077 | C56: 已实现 | E56: 收到美国客户A货款 | F56: 1002.02 | G56: 美元户 | H56: 美元 | I56: 160000 | J56: 1139200 | K56: 是 | L56: 160000 | M56: 6.8426 | N56: 1098048 | O56: =L56*M56 -> 1094816 | P56: =N56-O56 -> 3232 | Q56: 账面金额－审计金额 | R56: 已实现：滚动审计本位币基础与本次结算价值比较；汇率来源：国家外汇管理局人民币汇率中间价查询（数据由中国外汇交易中心公布）；央行交易日中间价：6.842600 | S56: 207 | T56: 2620800 | U56: 借 | V56: 160000 | W56: 1139200 | X56: 记-0077 | Y56: 美元 | Z56: 收到美国客户A货款 | AA56: 2026-05-12 | AB56: 7.12 | AC56: 美元户 | AD56: 1002.02
A57: 2026-05-12 | B57: 默认主体-2026-05-12-记-0077 | C57: 已实现 | E57: 收到美国客户A货款 | F57: 1122.02 | G57: 应收账款-美元客户 | H57: 美元 | I57: -160000 | J57: -1139200 | K57: 否 | S57: 208 | T57: 1815200 | U57: 借 | X57: 记-0077 | Y57: 美元 | Z57: 收到美国客户A货款 | AA57: 2026-05-12 | AB57: 7.12 | AC57: 应收账款-美元客户 | AD57: 1122.02 | AE57: 160000 | AF57: 1139200
A58: 2026-05-22 | B58: 默认主体-2026-05-22-记-0083 | C58: 已实现 | E58: 支付美元供应商货款 | F58: 2202.02 | G58: 应付账款-美元供应商 | H58: 美元 | I58: 60000 | J58: 427200 | K58: 是 | L58: 60000 | M58: 6.8373 | N58: 411488.48 | O58: =L58*M58 -> 410238 | P58: =O58-N58 -> -1250.4828 | Q58: 审计金额－账面金额 | R58: 已实现：滚动审计本位币基础与本次结算价值比较；汇率来源：国家外汇管理局人民币汇率中间价查询（数据由中国外汇交易中心公布）；央行交易日中间价：6.837300 | S58: 221 | T58: 536000 | U58: 贷 | V58: 60000 | W58: 427200 | X58: 记-0083 | Y58: 美元 | Z58: 支付美元供应商货款 | AA58: 2026-05-22 | AB58: 7.12 | AC58: 应付账款-美元供应商 | AD58: 2202.02
A59: 2026-05-22 | B59: 默认主体-2026-05-22-记-0083 | C59: 已实现 | E59: 支付美元供应商货款 | F59: 1002.02 | G59: 美元户 | H59: 美元 | I59: -60000 | J59: -427200 | K59: 否 | S59: 222 | T59: 2193600 | U59: 借 | X59: 记-0083 | Y59: 美元 | Z59: 支付美元供应商货款 | AA59: 2026-05-22 | AB59: 7.12 | AC59: 美元户 | AD59: 1002.02 | AE59: 60000 | AF59: 427200
A60: 2026-05-25 | B60: 默认主体-2026-05-25-记-0084 | C60: 已实现 | E60: 美元结汇 | F60: 1002.01 | G60: 人民币户 | H60: 人民币 | I60: 0 | J60: 500500 | K60: 是 | L60: 70000 | M60: 7.15 | N60: 480147.79 | O60: =L60*M60 -> 500500 | P60: =N60-O60 -> -20352.208 | Q60: 账面金额－审计金额 | R60: 已实现：滚动审计本位币基础与本次结算价值比较；汇率来源：国家外汇管理局人民币汇率中间价查询（数据由中国外汇交易中心公布）；央行交易日中间价：6.831800 | S60: 223 | T60: 3865800 | U60: 借 | W60: 500500 | X60: 记-0084 | Y60: 人民币 | Z60: 美元结汇 | AA60: 2026-05-25 | AC60: 人民币户 | AD60: 1002.01
A61: 2026-05-25 | B61: 默认主体-2026-05-25-记-0084 | C61: 已实现 | E61: 美元结汇 | F61: 1002.02 | G61: 美元户 | H61: 美元 | I61: -70000 | J61: -498400 | K61: 否 | S61: 224 | T61: 1695200 | U61: 借 | X61: 记-0084 | Y61: 美元 | Z61: 美元结汇 | AA61: 2026-05-25 | AB61: 7.12 | AC61: 美元户 | AD61: 1002.02 | AE61: 70000 | AF61: 498400
A62: 2026-05-25 | B62: 默认主体-2026-05-25-记-0084 | C62: 已实现 | E62: 美元结汇 | F62: 6603.02 | G62: 财务费用-汇兑损益 | H62: 人民币 | I62: 0 | J62: -2100 | K62: 否 | S62: 225 | T62: 2100 | U62: 贷 | X62: 记-0084 | Y62: 人民币 | Z62: 美元结汇 | AA62: 2026-05-25 | AC62: 财务费用-汇兑损益 | AD62: 6603.02 | AF62: 2100
A63: 2026-05-26 | B63: 默认主体-2026-05-26-记-0085 | C63: 已实现 | E63: 购汇美元 | F63: 1002.02 | G63: 美元户 | H63: 美元 | I63: 30000 | J63: 213600 | K63: 是 | L63: 30000 | M63: 6.8288 | N63: 204864 | O63: =L63*M63 -> 204864 | P63: =O63-N63 -> 9336 | Q63: 审计金额－账面金额 | R63: 购汇：实际支付本位币减去交易日官方牌价折算额；汇率来源：国家外汇管理局人民币汇率中间价查询（数据由中国外汇交易中心公布）；央行交易日中间价：6.828800 | S63: 226 | T63: 1908800 | U63: 借 | V63: 30000 | W63: 213600 | X63: 记-0085 | Y63: 美元 | Z63: 购汇美元 | AA63: 2026-05-26 | AB63: 7.12 | AC63: 美元户 | AD63: 1002.02
A64: 2026-05-26 | B64: 默认主体-2026-05-26-记-0085 | C64: 已实现 | E64: 购汇美元 | F64: 1002.01 | G64: 人民币户 | H64: 人民币 | I64: 0 | J64: -214200 | K64: 否 | S64: 227 | T64: 3651600 | U64: 借 | X64: 记-0085 | Y64: 人民币 | Z64: 购汇美元 | AA64: 2026-05-26 | AC64: 人民币户 | AD64: 1002.01 | AF64: 214200
A65: 2026-05-26 | B65: 默认主体-2026-05-26-记-0085 | C65: 已实现 | E65: 购汇美元 | F65: 6603.02 | G65: 财务费用-汇兑损益 | H65: 人民币 | I65: 0 | J65: 600 | K65: 否 | S65: 228 | T65: 1500 | U65: 贷 | W65: 600 | X65: 记-0085 | Y65: 人民币 | Z65: 购汇美元 | AA65: 2026-05-26 | AC65: 财务费用-汇兑损益 | AD65: 6603.02
A66: 2026-05-26 | B66: 默认主体-2026-05-26-记-0086 | C66: 已实现 | E66: 购汇港币 | F66: 1002.03 | G66: 港币户 | H66: 港币 | I66: 80000 | J66: 72800 | K66: 是 | L66: 80000 | M66: 0.87155 | N66: 69724 | O66: =L66*M66 -> 69724 | P66: =O66-N66 -> 3796 | Q66: 审计金额－账面金额 | R66: 购汇：实际支付本位币减去交易日官方牌价折算额；汇率来源：国家外汇管理局人民币汇率中间价查询（数据由中国外汇交易中心公布）；央行交易日中间价：0.871550 | S66: 229 | T66: 436300 | U66: 借 | V66: 80000 | W66: 72800 | X66: 记-0086 | Y66: 港币 | Z66: 购汇港币 | AA66: 2026-05-26 | AB66: 0.91 | AC66: 港币户 | AD66: 1002.03
A67: 2026-05-26 | B67: 默认主体-2026-05-26-记-0086 | C67: 已实现 | E67: 购汇港币 | F67: 1002.01 | G67: 人民币户 | H67: 人民币 | I67: 0 | J67: -73520 | K67: 否 | S67: 230 | T67: 3578080 | U67: 借 | X67: 记-0086 | Y67: 人民币 | Z67: 购汇港币 | AA67: 2026-05-26 | AC67: 人民币户 | AD67: 1002.01 | AF67: 73520
A68: 2026-05-26 | B68: 默认主体-2026-05-26-记-0086 | C68: 已实现 | E68: 购汇港币 | F68: 6603.02 | G68: 财务费用-汇兑损益 | H68: 人民币 | I68: 0 | J68: 720 | K68: 否 | S68: 231 | T68: 780 | U68: 贷 | W68: 720 | X68: 记-0086 | Y68: 人民币 | Z68: 购汇港币 | AA68: 2026-05-26 | AC68: 财务费用-汇兑损益 | AD68: 6603.02
A69: 2026-06-12 | B69: 默认主体-2026-06-12-记-0093 | C69: 已实现 | E69: 收到美国客户A货款 | F69: 1002.02 | G69: 美元户 | H69: 美元 | I69: 180000 | J69: 1281600 | K69: 是 | L69: 180000 | M69: 6.8109 | N69: 1227055.4 | O69: =L69*M69 -> 1225962 | P69: =N69-O69 -> 1093.443 | Q69: 账面金额－审计金额 | R69: 已实现：滚动审计本位币基础与本次结算价值比较；汇率来源：国家外汇管理局人民币汇率中间价查询（数据由中国外汇交易中心公布）；央行交易日中间价：6.810900 | S69: 252 | T69: 3190400 | U69: 借 | V69: 180000 | W69: 1281600 | X69: 记-0093 | Y69: 美元 | Z69: 收到美国客户A货款 | AA69: 2026-06-12 | AB69: 7.12 | AC69: 美元户 | AD69: 1002.02
A70: 2026-06-12 | B70: 默认主体-2026-06-12-记-0093 | C70: 已实现 | E70: 收到美国客户A货款 | F70: 1122.02 | G70: 应收账款-美元客户 | H70: usd | I70: -180000 | J70: -1281600 | K70: 否 | S70: 253 | T70: 2384800 | U70: 借 | X70: 记-0093 | Y70: usd | Z70: 收到美国客户A货款 | AA70: 2026-06-12 | AB70: 7.12 | AC70: 应收账款-美元客户 | AD70: 1122.02 | AE70: 180000 | AF70: 1281600
A71: 2026-06-13 | B71: 默认主体-2026-06-13-记-0094 | C71: 待复核 | D71: 非货币性项目/异常复核 | E71: 购汇日元预付日本供应商货款 | F71: 1123.02 | G71: 预付款项-日元 | H71: 日元 | I71: 2000000 | J71: 96400 | K71: 是 | L71: 0 | M71: 0 | N71: 1200 | P71: =N71 -> 1200 | Q71: 账面金额仅供参考，不纳入审计测算 | R71: 对方科目为预付款、存货、固定资产等非货币性项目，不产生外币汇兑损益；账面汇差建议重分类复核 | S71: 254 | T71: 5192800 | U71: 借 | V71: 2000000 | W71: 96400 | X71: 记-0094 | Y71: 日元 | Z71: 购汇日元预付日本供应商货款 | AA71: 2026-06-13 | AB71: 0.0482 | AC71: 预付款项-日元 | AD71: 1123.02
A72: 2026-06-13 | B72: 默认主体-2026-06-13-记-0094 | C72: 待复核 | D72: 非货币性项目/异常复核 | E72: 购汇日元预付日本供应商货款 | F72: 1002.01 | G72: 人民币户 | H72: 人民币 | I72: 0 | J72: -97600 | K72: 否 | S72: 255 | T72: 3090280 | U72: 借 | X72: 记-0094 | Y72: 人民币 | Z72: 购汇日元预付日本供应商货款 | AA72: 2026-06-13 | AC72: 人民币户 | AD72: 1002.01 | AF72: 97600
A73: 2026-06-13 | B73: 默认主体-2026-06-13-记-0094 | C73: 待复核 | D73: 非货币性项目/异常复核 | E73: 购汇日元预付日本供应商货款 | F73: 6603.02 | G73: 财务费用-汇兑损益 | H73: 人民币 | I73: 0 | J73: 1200 | K73: 否 | S73: 256 | T73: 1200 | U73: 借 | W73: 1200 | X73: 记-0094 | Y73: 人民币 | Z73: 购汇日元预付日本供应商货款 | AA73: 2026-06-13 | AC73: 财务费用-汇兑损益 | AD73: 6603.02
A74: 2026-06-17 | B74: 默认主体-2026-06-17-记-0098 | C74: 已实现 | E74: 收到欧元客户货款并结汇 | F74: 1002.01 | G74: 人民币户 | H74: 人民币 | I74: 0 | J74: 196500 | K74: 是 | L74: 25000 | M74: 7.86 | N74: 197900 | O74: =L74*M74 -> 196500 | P74: =N74-O74 -> 1400 | Q74: 账面金额－审计金额 | R74: 已实现：滚动审计本位币基础与本次结算价值比较；汇率来源：国家外汇管理局人民币汇率中间价查询（数据由中国外汇交易中心公布）；央行交易日中间价：7.877600 | S74: 264 | T74: 3202280 | U74: 借 | W74: 196500 | X74: 记-0098 | Y74: 人民币 | Z74: 收到欧元客户货款并结汇 | AA74: 2026-06-17 | AC74: 人民币户 | AD74: 1002.01
A75: 2026-06-17 | B75: 默认主体-2026-06-17-记-0098 | C75: 已实现 | E75: 收到欧元客户货款并结汇 | F75: 1122.03 | G75: 应收账款-欧元客户 | H75: 欧元 | I75: -25000 | J75: -195750 | K75: 否 | S75: 265 | T75: 437250 | U75: 贷 | X75: 记-0098 | Y75: 欧元 | Z75: 收到欧元客户货款并结汇 | AA75: 2026-06-17 | AB75: 7.83 | AC75: 应收账款-欧元客户 | AD75: 1122.03 | AE75: 25000 | AF75: 195750
A76: 2026-06-17 | B76: 默认主体-2026-06-17-记-0098 | C76: 已实现 | E76: 收到欧元客户货款并结汇 | F76: 6603.02 | G76: 财务费用-汇兑损益 | H76: 人民币 | I76: 0 | J76: -750 | K76: 否 | S76: 266 | T76: 450 | U76: 借 | X76: 记-0098 | Y76: 人民币 | Z76: 收到欧元客户货款并结汇 | AA76: 2026-06-17 | AC76: 财务费用-汇兑损益 | AD76: 6603.02 | AF76: 750
A77: 2026-06-22 | B77: 默认主体-2026-06-22-记-0102 | C77: 已实现 | E77: 支付美元供应商货款 | F77: 2202.02 | G77: 应付账款-美元供应商 | H77: 美元 | I77: 60000 | J77: 427200 | K77: 是 | L77: 60000 | M77: 6.815 | N77: 408991.6 | O77: =L77*M77 -> 408900 | P77: =O77-N77 -> -91.6 | Q77: 审计金额－账面金额 | R77: 已实现：滚动审计本位币基础与本次结算价值比较；汇率来源：国家外汇管理局人民币汇率中间价查询（数据由中国外汇交易中心公布）；央行交易日中间价：6.815000 | S77: 274 | T77: 607200 | U77: 贷 | V77: 60000 | W77: 427200 | X77: 记-0102 | Y77: 美元 | Z77: 支付美元供应商货款 | AA77: 2026-06-22 | AB77: 7.12 | AC77: 应付账款-美元供应商 | AD77: 2202.02
A78: 2026-06-22 | B78: 默认主体-2026-06-22-记-0102 | C78: 已实现 | E78: 支付美元供应商货款 | F78: 1002.02 | G78: 美元户 | H78: 美元 | I78: -60000 | J78: -427200 | K78: 否 | S78: 275 | T78: 2763200 | U78: 借 | X78: 记-0102 | Y78: 美元 | Z78: 支付美元供应商货款 | AA78: 2026-06-22 | AB78: 7.12 | AC78: 美元户 | AD78: 1002.02 | AE78: 60000 | AF78: 427200
A79: 2026-06-24 | B79: 默认主体-2026-06-24-记-0104 | C79: 已实现 | E79: 支付香港货代运费 | F79: 2202.03 | G79: 应付账款-港币供应商 | H79: 港币 | I79: 45000 | J79: 40950 | K79: 是 | L79: 45000 | M79: 0.86975 | N79: 39158.589 | O79: =L79*M79 -> 39138.75 | P79: =O79-N79 -> -19.83913 | Q79: 审计金额－账面金额 | R79: 已实现：滚动审计本位币基础与本次结算价值比较；汇率来源：国家外汇管理局人民币汇率中间价查询（数据由中国外汇交易中心公布）；央行交易日中间价：0.869750 | S79: 278 | T79: 300000 | U79: 贷 | V79: 45000 | W79: 40950 | X79: 记-0104 | Y79: 港币 | Z79: 支付香港货代运费 | AA79: 2026-06-24 | AB79: 0.91 | AC79: 应付账款-港币供应商 | AD79: 2202.03
A80: 2026-06-24 | B80: 默认主体-2026-06-24-记-0104 | C80: 已实现 | E80: 支付香港货代运费 | F80: 1002.03 | G80: 港币户 | H80: 港币 | I80: -45000 | J80: -40950 | K80: 否 | S80: 279 | T80: 395350 | U80: 借 | X80: 记-0104 | Y80: 港币 | Z80: 支付香港货代运费 | AA80: 2026-06-24 | AB80: 0.91 | AC80: 港币户 | AD80: 1002.03 | AE80: 45000 | AF80: 40950
A81: 2026-06-25 | B81: 默认主体-2026-06-25-记-0105 | C81: 已实现 | E81: 美元结汇 | F81: 1002.01 | G81: 人民币户 | H81: 人民币 | I81: 0 | J81: 501900 | K81: 是 | L81: 70000 | M81: 7.17 | N81: 477100.75 | O81: =L81*M81 -> 501900 | P81: =N81-O81 -> -24799.25 | Q81: 账面金额－审计金额 | R81: 已实现：滚动审计本位币基础与本次结算价值比较；汇率来源：国家外汇管理局人民币汇率中间价查询（数据由中国外汇交易中心公布）；央行交易日中间价：6.820900 | S81: 280 | T81: 3704180 | U81: 借 | W81: 501900 | X81: 记-0105 | Y81: 人民币 | Z81: 美元结汇 | AA81: 2026-06-25 | AC81: 人民币户 | AD81: 1002.01
A82: 2026-06-25 | B82: 默认主体-2026-06-25-记-0105 | C82: 已实现 | E82: 美元结汇 | F82: 1002.02 | G82: 美元户 | H82: 美元 | I82: -70000 | J82: -498400 | K82: 否 | S82: 281 | T82: 2264800 | U82: 借 | X82: 记-0105 | Y82: 美元 | Z82: 美元结汇 | AA82: 2026-06-25 | AB82: 7.12 | AC82: 美元户 | AD82: 1002.02 | AE82: 70000 | AF82: 498400
A83: 2026-06-25 | B83: 默认主体-2026-06-25-记-0105 | C83: 已实现 | E83: 美元结汇 | F83: 6603.02 | G83: 财务费用-汇兑损益 | H83: 人民币 | I83: 0 | J83: -3500 | K83: 否 | S83: 282 | T83: 3050 | U83: 贷 | X83: 记-0105 | Y83: 人民币 | Z83: 美元结汇 | AA83: 2026-06-25 | AC83: 财务费用-汇兑损益 | AD83: 6603.02 | AF83: 3500
A84: 2026-06-26 | B84: 默认主体-2026-06-26-记-0106 | C84: 已实现 | E84: 购汇美元 | F84: 1002.02 | G84: 美元户 | H84: 美元 | I84: 30000 | J84: 213600 | K84: 是 | L84: 30000 | M84: 6.8166 | N84: 204498 | O84: =L84*M84 -> 204498 | P84: =O84-N84 -> 10002 | Q84: 审计金额－账面金额 | R84: 购汇：实际支付本位币减去交易日官方牌价折算额；汇率来源：国家外汇管理局人民币汇率中间价查询（数据由中国外汇交易中心公布）；央行交易日中间价：6.816600 | S84: 283 | T84: 2478400 | U84: 借 | V84: 30000 | W84: 213600 | X84: 记-0106 | Y84: 美元 | Z84: 购汇美元 | AA84: 2026-06-26 | AB84: 7.12 | AC84: 美元户 | AD84: 1002.02
A85: 2026-06-26 | B85: 默认主体-2026-06-26-记-0106 | C85: 已实现 | E85: 购汇美元 | F85: 1002.01 | G85: 人民币户 | H85: 人民币 | I85: 0 | J85: -214500 | K85: 否 | S85: 284 | T85: 3489680 | U85: 借 | X85: 记-0106 | Y85: 人民币 | Z85: 购汇美元 | AA85: 2026-06-26 | AC85: 人民币户 | AD85: 1002.01 | AF85: 214500
A86: 2026-06-26 | B86: 默认主体-2026-06-26-记-0106 | C86: 已实现 | E86: 购汇美元 | F86: 6603.02 | G86: 财务费用-汇兑损益 | H86: 人民币 | I86: 0 | J86: 900 | K86: 否 | S86: 285 | T86: 2150 | U86: 贷 | W86: 900 | X86: 记-0106 | Y86: 人民币 | Z86: 购汇美元 | AA86: 2026-06-26 | AC86: 财务费用-汇兑损益 | AD86: 6603.02

Sheet 客户与审计汇率比较
A1: 类型 | B1: 日期/月末 | C1: 凭证号 | D1: 主体 | E1: 科目 | F1: 币种 | G1: 客户隐含汇率 | H1: 反推依据 | I1: 可靠性 | J1: 审计期初/月初汇率 | K1: 审计交易日/月末汇率 | L1: 客户与审计期初/月初汇率差 | M1: 客户与审计交易日/月末汇率差 | N1: 原币基础 | O1: 汇率基础影响 | P1: 说明
A2: 已实现 | B2: 2026-01-12 | C2: 默认主体-2026-01-12-记-0004 | D2: 默认主体 | E2: 1122.02 应收账款-美元客户 | F2: USD | G2: 7.12 | H2: JE本位币金额÷原币金额反推 | I2: 反推 | J2: 7.0288 | K2: 7.0108 | L2: 0.0912 | M2: 0.1092 | N2: 100000 | O2: -3818.4615 | P2: 已实现项目的反推值只表示JE账面隐含汇率，不表示客户明确申明的政策汇率。
A3: 已实现 | B3: 2026-01-22 | C3: 默认主体-2026-01-22-记-0010 | D3: 默认主体 | E3: 2202.02 应付账款-美元供应商 | F3: USD | G3: 7.12 | H3: JE本位币金额÷原币金额反推 | I3: 反推 | J3: 7.0288 | K3: 7.0019 | L3: 0.0912 | M3: 0.1181 | N3: 50000 | O3: -1402.5 | P3: 已实现项目的反推值只表示JE账面隐含汇率，不表示客户明确申明的政策汇率。
A4: 已实现 | B4: 2026-01-24 | C4: 默认主体-2026-01-24-记-0012 | D4: 默认主体 | E4: 2202.03 应付账款-港币供应商 | F4: HKD | G4: 0.91 | H4: JE本位币金额÷原币金额反推 | I4: 反推 | J4: 0.90322 | K4: 0.89676 | L4: 0.00678 | M4: 0.01324 | N4: 40000 | O4: -62.305882 | P4: 已实现项目的反推值只表示JE账面隐含汇率，不表示客户明确申明的政策汇率。
A5: 已实现 | B5: 2026-01-25 | C5: 默认主体-2026-01-25-记-0013 | D5: 默认主体 | E5: 1002.02 美元户 | F5: USD | G5: 7.12 | H5: JE本位币金额÷原币金额反推 | I5: 反推 | J5: 7.0288 | K5: 6.9929 | L5: 0.0912 | M5: 0.1271 | N5: 60000 | O5: -1203.6 | P5: 已实现项目的反推值只表示JE账面隐含汇率，不表示客户明确申明的政策汇率。
A6: 已实现 | B6: 2026-02-12 | C6: 默认主体-2026-02-12-记-0022 | D6: 默认主体 | E6: 1122.02 应收账款-美元客户 | F6: USD | G6: 7.12 | H6: JE本位币金额÷原币金额反推 | I6: 反推 | J6: 6.9678 | K6: 6.9457 | L6: 0.1522 | M6: 0.1743 | N6: 100000 | O6: -15392.8 | P6: 已实现项目的反推值只表示JE账面隐含汇率，不表示客户明确申明的政策汇率。
A7: 已实现 | B7: 2026-02-17 | C7: 默认主体-2026-02-17-记-0026 | D7: 默认主体 | E7: 1122.03 应收账款-欧元客户 | F7: EUR | G7: 7.83 | H7: JE本位币金额÷原币金额反推 | I7: 反推 | J7: 8.3244 | K7: 8.2195 | L7: -0.4944 | M7: -0.3895 | N7: 25000 | O7: 12360 | P7: 已实现项目的反推值只表示JE账面隐含汇率，不表示客户明确申明的政策汇率。
A8: 已实现 | B8: 2026-02-22 | C8: 默认主体-2026-02-22-记-0029 | D8: 默认主体 | E8: 2202.02 应付账款-美元供应商 | F8: USD | G8: 7.12 | H8: JE本位币金额÷原币金额反推 | I8: 反推 | J8: 6.9678 | K8: 6.9398 | L8: 0.1522 | M8: 0.1802 | N8: 30000 | O8: -4712.087 | P8: 已实现项目的反推值只表示JE账面隐含汇率，不表示客户明确申明的政策汇率。
A9: 已实现 | B9: 2026-02-24 | C9: 默认主体-2026-02-24-记-0031 | D9: 默认主体 | E9: 2202.03 应付账款-港币供应商 | F9: HKD | G9: 0.91 | H9: JE本位币金额÷原币金额反推 | I9: 反推 | J9: 0.89262 | K9: 0.88773 | L9: 0.01738 | M9: 0.02227 | N9: 30000 | O9: -534.35455 | P9: 已实现项目的反推值只表示JE账面隐含汇率，不表示客户明确申明的政策汇率。
A10: 已实现 | B10: 2026-02-25 | C10: 默认主体-2026-02-25-记-0032 | D10: 默认主体 | E10: 1002.02 美元户 | F10: USD | G10: 7.12 | H10: JE本位币金额÷原币金额反推 | I10: 反推 | J10: 6.9678 | K10: 6.9321 | L10: 0.1522 | M10: 0.1879 | N10: 40000 | O10: -6273.4667 | P10: 已实现项目的反推值只表示JE账面隐含汇率，不表示客户明确申明的政策汇率。
A11: 已实现 | B11: 2026-03-12 | C11: 默认主体-2026-03-12-记-0040 | D11: 默认主体 | E11: 1122.02 应收账款-美元客户 | F11: USD | G11: 7.12 | H11: JE本位币金额÷原币金额反推 | I11: 反推 | J11: 6.9228 | K11: 6.8959 | L11: 0.1972 | M11: 0.2241 | N11: 120000 | O11: -24519.2 | P11: 已实现项目的反推值只表示JE账面隐含汇率，不表示客户明确申明的政策汇率。
A12: 已实现 | B12: 2026-03-22 | C12: 默认主体-2026-03-22-记-0048 | D12: 默认主体 | E12: 2202.02 应付账款-美元供应商 | F12: USD | G12: 7.12 | H12: JE本位币金额÷原币金额反推 | I12: 反推 | J12: 6.9228 | K12: 6.8898 | L12: 0.1972 | M12: 0.2302 | N12: 50000 | O12: -10228.077 | P12: 已实现项目的反推值只表示JE账面隐含汇率，不表示客户明确申明的政策汇率。
A13: 已实现 | B13: 2026-03-24 | C13: 默认主体-2026-03-24-记-0050 | D13: 默认主体 | E13: 2202.03 应付账款-港币供应商 | F13: HKD | G13: 0.91 | H13: JE本位币金额÷原币金额反推 | I13: 反推 | J13: 0.88484 | K13: 0.88015 | L13: 0.02516 | M13: 0.02985 | N13: 40000 | O13: -1023.8118 | P13: 已实现项目的反推值只表示JE账面隐含汇率，不表示客户明确申明的政策汇率。
... A27: 已实现 | B27: 2026-06-25 | C27: 默认主体-2026-06-25-记-0105 | D27: 默认主体 | E27: 1002.02 美元户 | F27: USD | G27: 7.12 | H27: JE本位币金额÷原币金额反推 | I27: 反推 | J27: 6.8176 | K27: 6.8209 | L27: 0.3024 | M27: 0.2991 | N27: 70000 | O27: -21299.25 | P27: 已实现项目的反推值只表示JE账面隐含汇率，不表示客户明确申明的政策汇率。
A28: 未实现 | B28: 2026-01-31 | D28: 默认主体 | E28: 1002.02 美元户 | F28: USD | G28: 7.12 | H28: TB期初本位币及JE滚动后账面余额÷月末原币余额反推 | I28: 反推 | K28: 6.9678 | M28: 0.1522 | N28: 220000 | O28: -33484 | P28: 客户隐含汇率仅作差异解释；审计未实现损益始终按官方月末汇率独立测算。
A29: 未实现 | B29: 2026-01-31 | D29: 默认主体 | E29: 1002.03 港币户 | F29: HKD | G29: 0.91 | H29: TB期初本位币及JE滚动后账面余额÷月末原币余额反推 | I29: 反推 | K29: 0.89262 | M29: 0.01738 | N29: 460000 | O29: -7994.8 | P29: 客户隐含汇率仅作差异解释；审计未实现损益始终按官方月末汇率独立测算。
A30: 未实现 | B30: 2026-01-31 | D30: 默认主体 | E30: 1122.02 应收账款-美元客户 | F30: USD | G30: 7.12 | H30: TB期初本位币及JE滚动后账面余额÷月末原币余额反推 | I30: 反推 | K30: 6.9678 | M30: 0.1522 | N30: 420000 | O30: -63924 | P30: 客户隐含汇率仅作差异解释；审计未实现损益始终按官方月末汇率独立测算。
A31: 未实现 | B31: 2026-01-31 | D31: 默认主体 | E31: 1122.03 应收账款-欧元客户 | F31: EUR | G31: 7.83 | H31: TB期初本位币及JE滚动后账面余额÷月末原币余额反推 | I31: 反推 | K31: 8.3244 | M31: -0.4944 | N31: 150000 | O31: 74160 | P31: 客户隐含汇率仅作差异解释；审计未实现损益始终按官方月末汇率独立测算。
A32: 未实现 | B32: 2026-01-31 | D32: 默认主体 | E32: 2202.02 应付账款-美元供应商 | F32: USD | G32: 7.12 | H32: TB期初本位币及JE滚动后账面余额÷月末原币余额反推 | I32: 反推 | K32: 6.9678 | M32: 0.1522 | N32: -190000 | O32: 28918 | P32: 客户隐含汇率仅作差异解释；审计未实现损益始终按官方月末汇率独立测算。
A33: 未实现 | B33: 2026-01-31 | D33: 默认主体 | E33: 2202.03 应付账款-港币供应商 | F33: HKD | G33: 0.91 | H33: TB期初本位币及JE滚动后账面余额÷月末原币余额反推 | I33: 反推 | K33: 0.89262 | M33: 0.01738 | N33: -300000 | O33: 5214 | P33: 客户隐含汇率仅作差异解释；审计未实现损益始终按官方月末汇率独立测算。
A34: 未实现 | B34: 2026-02-28 | D34: 默认主体 | E34: 1002.02 美元户 | F34: USD | G34: 7.12 | H34: TB期初本位币及JE滚动后账面余额÷月末原币余额反推 | I34: 反推 | K34: 6.9228 | M34: 0.1972 | N34: 260000 | O34: -51272 | P34: 客户隐含汇率仅作差异解释；审计未实现损益始终按官方月末汇率独立测算。
A35: 未实现 | B35: 2026-02-28 | D35: 默认主体 | E35: 1002.03 港币户 | F35: HKD | G35: 0.91 | H35: TB期初本位币及JE滚动后账面余额÷月末原币余额反推 | I35: 反推 | K35: 0.88484 | M35: 0.02516 | N35: 430000 | O35: -10818.8 | P35: 客户隐含汇率仅作差异解释；审计未实现损益始终按官方月末汇率独立测算。
A36: 未实现 | B36: 2026-02-28 | D36: 默认主体 | E36: 1122.02 应收账款-美元客户 | F36: USD | G36: 7.12 | H36: TB期初本位币及JE滚动后账面余额÷月末原币余额反推 | I36: 反推 | K36: 6.9228 | M36: 0.1972 | N36: 400000 | O36: -78880 | P36: 客户隐含汇率仅作差异解释；审计未实现损益始终按官方月末汇率独立测算。
A37: 未实现 | B37: 2026-02-28 | D37: 默认主体 | E37: 1122.03 应收账款-欧元客户 | F37: EUR | G37: 7.83 | H37: TB期初本位币及JE滚动后账面余额÷月末原币余额反推 | I37: 反推 | K37: 8.1208 | M37: -0.2908 | N37: 125000 | O37: 36350 | P37: 客户隐含汇率仅作差异解释；审计未实现损益始终按官方月末汇率独立测算。
A38: 未实现 | B38: 2026-02-28 | D38: 默认主体 | E38: 2202.02 应付账款-美元供应商 | F38: USD | G38: 7.12 | H38: TB期初本位币及JE滚动后账面余额÷月末原币余额反推 | I38: 反推 | K38: 6.9228 | M38: 0.1972 | N38: -200000 | O38: 39440 | P38: 客户隐含汇率仅作差异解释；审计未实现损益始终按官方月末汇率独立测算。
A39: 未实现 | B39: 2026-02-28 | D39: 默认主体 | E39: 2202.03 应付账款-港币供应商 | F39: HKD | G39: 0.91 | H39: TB期初本位币及JE滚动后账面余额÷月末原币余额反推 | I39: 反推 | K39: 0.88484 | M39: 0.02516 | N39: -300000 | O39: 7548 | P39: 客户隐含汇率仅作差异解释；审计未实现损益始终按官方月末汇率独立测算。
... A63: 未实现 | B63: 2026-06-30 | D63: 默认主体 | E63: 2202.03 应付账款-港币供应商 | F63: HKD | G63: 0.91 | H63: TB期初本位币及JE滚动后账面余额÷月末原币余额反推 | I63: 反推 | K63: 0.86855 | M63: 0.04145 | N63: -300000 | O63: 12435 | P63: 客户隐含汇率仅作差异解释；审计未实现损益始终按官方月末汇率独立测算。

Sheet 使用说明
A1: 项目 | B1: 内容
A2: 底稿用途 | B2: 汇兑损益审计重算；结果需结合业务资料与审计判断复核。
A3: 测算模式 | B3: 已实现＋未实现
A4: 汇率口径 | B4: 程序内置牌价表（国家外汇管理局人民币汇率中间价，2022-11-28~2026-08-31，随程序打包；超期区间自动回落在线抓取）
A5: 重要说明 | B5: 已实现仅按单张凭证内的资金结构识别：货币资金净额非零，且对方货币性项目净额非零；未实现按外币原币净额为零、本位币净额非零识别。汇兑损益科目、凭证类型和摘要不参与定性。

Sheet 执行摘要
A1: 项目 | B1: 内容
A2: 是否启用科目名称翻译 | B2: 否
A3: 审计测算汇兑损益 | B3: 116703.6
A4: 自动测算合计 | B4: 116703.6
A5: JE账面净额是否可区分 | B5: 是
A6: 账面汇兑损益取数来源 | B6: JE剔除损益结转后的净额
A7: 客户已入账未实现汇兑损益 | B7: 0
A8: 自动测算覆盖的账面汇兑损益 | B8: -10330
A9: 已覆盖账面已实现汇兑损益 | B9: -10330
A10: 已覆盖项目测算差异 | B10: 127033.6
A11: diagnosticMeasuredFxGainLoss | B11: 116703.6
A12: 测算与客户账面差异 | B12: 124633.6
A13: 差异率 | B13: 15.716721
A14: 是否可形成正式测算结果 | B14: 是
A15: 正式测算受限原因 | B15: []
A16: 低置信度事件数 | B16: 0
A17: 自动测算金额差异 | B17: 127033.6
A18: 零结果是否需要复核 | B18: 否
A19: notFxEventAmount | B19: 2400
A20: notFxEventCount | B20: 2
A21: 待复核项目账面金额 | B21: 2400
A22: 待复核项目数 | B22: 2
A23: pendingUnclassifiedCount | B23: 0
A24: pendingUnmeasurableCount | B24: 0
A25: 已实现测算事件数 | B25: 32
A26: 已实现汇兑损益 | B26: -14206.473
A27: 已实现测算差异 | B27: -3876.4731
A28: 勾稽是否通过 | B28: 否
A29: rollforwardIssueCount | B29: 0
A30: rollforwardPassed | B30: 是
A31: TB汇兑损益诊断金额（不作为净损益） | B31: 14650
A32: tbFxGainAmount | B32: 0
A33: TB汇兑损益发生额 | B33: -7930
A34: tbFxGainLossPresentation | B34: 已实现＋未实现
A35: tbFxLossAmount | B35: 14650
A36: tbRealizedGainLoss
A37: tbUnrealizedGainLoss
A38: 已翻译英文科目数 | B38: 0
A39: 未覆盖账面金额 | B39: 2400
A40: 未实现汇兑损益 | B40: 130910.07
A41: unrealizedBalanceBasisComplete | B41: 是
A42: 未实现测算差异 | B42: 130910.07
A43: unrealizedMissingBalanceKeys | B43: 0
A44: 未实现测算行数 | B44: 36

Sheet 参数与口径
A1: 项目 | B1: 内容
A2: 报告期开始 | B2: 2026-01-01
A3: 报告期结束 | B3: 2026-06-30
A4: 测算模式 | B4: 已实现＋未实现
A5: 汇率口径 | B5: 程序内置牌价表（国家外汇管理局人民币汇率中间价，2022-11-28~2026-08-31，随程序打包；超期区间自动回落在线抓取）

Sheet JE字段映射
A1: 字段角色 | B1: 最终映射 | C1: 校验结果 | D1: 识别方式
A2: __signConvention | B2: unsigned | C2: 后端再次验证 | D2: 硬编码 + LLM复核 + 用户确认
A3: 科目编码 | B3: 科目编码 | C3: 后端再次验证 | D3: 硬编码 + LLM复核 + 用户确认
A4: 科目名称 | B4: ["科目名称"] | C4: 后端再次验证 | D4: 硬编码 + LLM复核 + 用户确认
A5: 币种 | B5: 币种 | C5: 后端再次验证 | D5: 硬编码 + LLM复核 + 用户确认
A6: 日期 | B6: 日期 | C6: 后端再次验证 | D6: 硬编码 + LLM复核 + 用户确认
A7: direction | B7: 余额方向 | C7: 后端再次验证 | D7: 硬编码 + LLM复核 + 用户确认
A8: foreignCredit | B8: 贷方原币 | C8: 后端再次验证 | D8: 硬编码 + LLM复核 + 用户确认
A9: foreignDebit | B9: 借方原币 | C9: 后端再次验证 | D9: 硬编码 + LLM复核 + 用户确认
A10: functionalCredit | B10: 贷方本位币 | C10: 后端再次验证 | D10: 硬编码 + LLM复核 + 用户确认
A11: functionalDebit | B11: 借方本位币 | C11: 后端再次验证 | D11: 硬编码 + LLM复核 + 用户确认
A12: 凭证识别字段 | B12: ["凭证字号"] | C12: 后端再次验证 | D12: 硬编码 + LLM复核 + 用户确认
A13: 摘要 | B13: 摘要 | C13: 后端再次验证 | D13: 硬编码 + LLM复核 + 用户确认

Sheet TB字段映射
A1: 字段角色 | B1: 最终映射 | C1: 校验结果 | D1: 识别方式
A2: __balanceSelfSigned_closingForeign | B2: 否 | C2: 后端再次验证 | D2: 硬编码 + LLM复核 + 用户确认
A3: __balanceSelfSigned_closingFunctional | B3: 否 | C3: 后端再次验证 | D3: 硬编码 + LLM复核 + 用户确认
A4: __balanceSelfSigned_openingForeign | B4: 否 | C4: 后端再次验证 | D4: 硬编码 + LLM复核 + 用户确认
A5: __balanceSelfSigned_openingFunctional | B5: 否 | C5: 后端再次验证 | D5: 硬编码 + LLM复核 + 用户确认
A6: __signConvention | B6: unsigned | C6: 后端再次验证 | D6: 硬编码 + LLM复核 + 用户确认
A7: 科目编码 | B7: 科目编码 | C7: 后端再次验证 | D7: 硬编码 + LLM复核 + 用户确认
A8: 科目名称 | B8: ["科目名称"] | C8: 后端再次验证 | D8: 硬编码 + LLM复核 + 用户确认
A9: closingDirection | B9: 方向 | C9: 后端再次验证 | D9: 硬编码 + LLM复核 + 用户确认
A10: closingForeignAmount | B10: 期末余额(原币) | C10: 后端再次验证 | D10: 硬编码 + LLM复核 + 用户确认
A11: closingFunctionalAmount | B11: 期末余额(本位币) | C11: 后端再次验证 | D11: 硬编码 + LLM复核 + 用户确认
A12: 币种 | B12: 币种 | C12: 后端再次验证 | D12: 硬编码 + LLM复核 + 用户确认
... A17: ytdFunctionalDebit | B17: 本期发生借方(本位币) | C17: 后端再次验证 | D17: 硬编码 + LLM复核 + 用户确认

Sheet 数据质量

Sheet 待复核项目
A1: accounts | B1: 账面汇兑损益 | C1: 分类 | D1: 涉及币种 | E1: 日期 | F1: 识别证据 | G1: 汇兑损益科目 | H1: 待复核分路 | I1: 待复核原因 | J1: 当前分类（结构判定） | K1: 凭证匹配ID | L1: 凭证类型
A2: ["1002.01 人民币户","1123.02 预付款项-日元","6603.02 财务费用-汇兑损益"] | B2: 1200 | C2: 不构成汇兑事项 | D2: ["CNY","JPY"] | E2: 2026-03-13 | F2: 购汇日元预付日本供应商货款 | G2: ["6603.02 财务费用-汇兑损益"] | H2: 非货币性项目/异常复核 | I2: 对方科目为预付款、存货、固定资产等非货币性项目，不产生外币汇兑损益；账面汇差建议重分类复核 | J2: 不构成汇兑事项 | K2: 默认主体-2026-03-13-记-0041
A3: ["1002.01 人民币户","1123.02 预付款项-日元","6603.02 财务费用-汇兑损益"] | B3: 1200 | C3: 不构成汇兑事项 | D3: ["CNY","JPY"] | E3: 2026-06-13 | F3: 购汇日元预付日本供应商货款 | G3: ["6603.02 财务费用-汇兑损益"] | H3: 非货币性项目/异常复核 | I3: 对方科目为预付款、存货、固定资产等非货币性项目，不产生外币汇兑损益；账面汇差建议重分类复核 | J3: 不构成汇兑事项 | K3: 默认主体-2026-06-13-记-0094

Sheet 科目角色
A1: 字段角色 | B1: 最终映射 | C1: 校验结果 | D1: 识别方式
A2: 1002.01 人民币户 | B2: 货币性资产—货币资金 | C2: 后端再次验证 | D2: 硬编码 + LLM复核 + 用户确认
A3: 1002.02 美元户 | B3: 货币性资产—货币资金 | C3: 后端再次验证 | D3: 硬编码 + LLM复核 + 用户确认
A4: 1002.03 港币户 | B4: 货币性资产—货币资金 | C4: 后端再次验证 | D4: 硬编码 + LLM复核 + 用户确认
A5: 1122.01 应收账款-国内 | B5: 货币性资产—非货币资金 | C5: 后端再次验证 | D5: 硬编码 + LLM复核 + 用户确认
A6: 1122.02 应收账款-美元客户 | B6: 货币性资产—非货币资金 | C6: 后端再次验证 | D6: 硬编码 + LLM复核 + 用户确认
A7: 1122.03 应收账款-欧元客户 | B7: 货币性资产—非货币资金 | C7: 后端再次验证 | D7: 硬编码 + LLM复核 + 用户确认
A8: 1123.01 预付款项-国内 | B8: 非货币性项目 | C8: 后端再次验证 | D8: 硬编码 + LLM复核 + 用户确认
A9: 1123.02 预付款项-日元 | B9: 非货币性项目 | C9: 后端再次验证 | D9: 硬编码 + LLM复核 + 用户确认
A10: 1123.03 预付款项-美元 | B10: 非货币性项目 | C10: 后端再次验证 | D10: 硬编码 + LLM复核 + 用户确认
A11: 1405 库存商品 | B11: 非货币性项目 | C11: 后端再次验证 | D11: 硬编码 + LLM复核 + 用户确认
A12: 2202.01 应付账款-国内 | B12: 货币性负债 | C12: 后端再次验证 | D12: 硬编码 + LLM复核 + 用户确认
... A31: 6603.02 财务费用-汇兑损益 | B31: 汇兑损益 | C31: 后端再次验证 | D31: 硬编码 + LLM复核 + 用户确认

Sheet 央行汇率
A1: 每单位外币折合人民币 | B1: 币种 | C1: 汇率公布日期 | D1: 请求日期
A2: 7.0779 | B2: USD | C2: 2025-11-27 | D2: 2025-11-27
A3: 8.2056 | B3: EUR | C3: 2025-11-27 | D3: 2025-11-27
A4: 0.045267 | B4: JPY | C4: 2025-11-27 | D4: 2025-11-27
A5: 0.90998 | B5: HKD | C5: 2025-11-27 | D5: 2025-11-27
A6: 9.3671 | B6: GBP | C6: 2025-11-27 | D6: 2025-11-27
A7: 4.6134 | B7: AUD | C7: 2025-11-27 | D7: 2025-11-27
A8: 4.0339 | B8: NZD | C8: 2025-11-27 | D8: 2025-11-27
A9: 5.4565 | B9: SGD | C9: 2025-11-27 | D9: 2025-11-27
A10: 8.8005 | B10: CHF | C10: 2025-11-27 | D10: 2025-11-27
A11: 5.0378 | B11: CAD | C11: 2025-11-27 | D11: 2025-11-27
A12: 0.8828463 | B12: MOP | C12: 2025-11-27 | D12: 2025-11-27
A13: 1.7108933 | B13: MYR | C13: 2025-11-27 | D13: 2025-11-27
... A5617: 1 | B5617: CNY | C5617: 2026-06-30 | D5617: 2026-06-30

Sheet 汇率表
A1: 日期 | B1: AED | C1: AUD | D1: CAD | E1: CHF | F1: CNY | G1: DKK | H1: EUR | I1: GBP | J1: HKD | K1: HUF | L1: JPY | M1: KRW | N1: MOP | O1: MXN | P1: MYR | Q1: NOK | R1: NZD | S1: PLN | T1: RUB | U1: SAR | V1: SEK | W1: SGD | X1: THB | Y1: TRY | Z1: USD | AA1: ZAR
A2: 2025-11-27 | B2: 1.9256692 | C2: 4.6134 | D2: 5.0378 | E2: 8.8005 | F2: 1 | G2: 1.0986596 | H2: 8.2056 | I2: 9.3671 | J2: 0.90998 | K2: 0.021477894 | L2: 0.045267 | M2: 0.0048146365 | N2: 0.8828463 | O2: 0.38563881 | P2: 1.7108933 | Q2: 0.69352937 | R2: 4.0339 | S2: 1.9385856 | T2: 0.090088467 | U2: 1.8857962 | V2: 0.74526755 | W2: 5.4565 | X2: 0.21959682 | Y2: 0.16663862 | Z2: 7.0779 | AA2: 0.41272855
A3: 2025-11-28 | B3: 1.9268937 | C3: 4.6243 | D3: 5.046 | E3: 8.7971 | F3: 1 | G3: 1.0990219 | H3: 8.2078 | I3: 9.3697 | J3: 0.9099 | K3: 0.021522455 | L3: 0.045293 | M3: 0.0048360576 | N3: 0.88269044 | O3: 0.38583224 | P3: 1.7139723 | Q3: 0.69657286 | R3: 4.0533 | S3: 1.9417476 | T3: 0.090797657 | U3: 1.8865077 | V3: 0.74710497 | W3: 5.4589 | X3: 0.2196547 | Y3: 0.16657422 | Z3: 7.0789 | AA3: 0.41262637
A4: 2025-11-29 | B4: 1.9268937 | C4: 4.6243 | D4: 5.046 | E4: 8.7971 | F4: 1 | G4: 1.0990219 | H4: 8.2078 | I4: 9.3697 | J4: 0.9099 | K4: 0.021522455 | L4: 0.045293 | M4: 0.0048360576 | N4: 0.88269044 | O4: 0.38583224 | P4: 1.7139723 | Q4: 0.69657286 | R4: 4.0533 | S4: 1.9417476 | T4: 0.090797657 | U4: 1.8865077 | V4: 0.74710497 | W4: 5.4589 | X4: 0.2196547 | Y4: 0.16657422 | Z4: 7.0789 | AA4: 0.41262637
A5: 2025-11-30 | B5: 1.9268937 | C5: 4.6243 | D5: 5.046 | E5: 8.7971 | F5: 1 | G5: 1.0990219 | H5: 8.2078 | I5: 9.3697 | J5: 0.9099 | K5: 0.021522455 | L5: 0.045293 | M5: 0.0048360576 | N5: 0.88269044 | O5: 0.38583224 | P5: 1.7139723 | Q5: 0.69657286 | R5: 4.0533 | S5: 1.9417476 | T5: 0.090797657 | U5: 1.8865077 | V5: 0.74710497 | W5: 5.4589 | X5: 0.2196547 | Y5: 0.16657422 | Z5: 7.0789 | AA5: 0.41262637
A6: 2025-12-01 | B6: 1.9255209 | C6: 4.6302 | D6: 5.0621 | E6: 8.8013 | F6: 1 | G6: 1.0985389 | H6: 8.2052 | I6: 9.3616 | J6: 0.90877 | K6: 0.021500568 | L6: 0.045331 | M6: 0.0048192771 | N6: 0.88160099 | O6: 0.38678734 | P6: 1.7125927 | Q6: 0.69920291 | R6: 4.0535 | S6: 1.9374588 | T6: 0.091256696 | U6: 1.8854051 | V6: 0.74850299 | W6: 5.4569 | X6: 0.22010917 | Y6: 0.16644834 | Z6: 7.0759 | AA6: 0.41324022
A7: 2025-12-02 | B7: 1.9262998 | C7: 4.6292 | D7: 5.0539 | E7: 8.7915 | F7: 1 | G7: 1.0995052 | H7: 8.2113 | I7: 9.3451 | J7: 0.9088 | K7: 0.021563714 | L7: 0.045495 | M7: 0.0048095421 | N7: 0.88191199 | O7: 0.38647343 | P7: 1.7131208 | Q7: 0.69837279 | R7: 4.0512 | S7: 1.942351 | T7: 0.091027427 | U7: 1.8849786 | V7: 0.74833495 | W7: 5.4576 | X7: 0.22106287 | Y7: 0.16668722 | Z7: 7.0794 | AA7: 0.41399296
A8: 2025-12-03 | B8: 1.9245944 | C8: 4.6437 | D8: 5.0589 | E8: 8.8047 | F8: 1 | G8: 1.1004732 | H8: 8.221 | I8: 9.3429 | J8: 0.90897 | K8: 0.021577254 | L8: 0.04536 | M8: 0.0048144047 | N8: 0.88214538 | O8: 0.38677238 | P8: 1.7116547 | Q8: 0.69793412 | R8: 4.0567 | S8: 1.9417476 | T8: 0.091262526 | U8: 1.8830973 | V8: 0.74985003 | W8: 5.4544 | X8: 0.22092124 | Y8: 0.16641759 | Z8: 7.0754 | AA8: 0.41312071
A9: 2025-12-04 | B9: 1.9215618 | C9: 4.6586 | D9: 5.0597 | E9: 8.8252 | F9: 1 | G9: 1.1025358 | H9: 8.2373 | I9: 9.4207 | J9: 0.90891 | K9: 0.021635843 | L9: 0.045468 | M9: 0.0048139412 | N9: 0.88198977 | O9: 0.38608548 | P9: 1.7142074 | Q9: 0.70126227 | R9: 4.0715 | S9: 1.9498499 | T9: 0.091377609 | U9: 1.8808306 | V9: 0.75284198 | W9: 5.4573 | X9: 0.22134667 | Y9: 0.16629915 | Z9: 7.0733 | AA9: 0.41430169
A10: 2025-12-05 | B10: 1.9258917 | C10: 4.6754 | D10: 5.0682 | E10: 8.8016 | F10: 1 | G10: 1.102779 | H10: 8.2376 | I10: 9.4269 | J10: 0.90906 | K10: 0.021508198 | L10: 0.045597 | M10: 0.0047991553 | N10: 0.88261253 | O10: 0.38791264 | P10: 1.7198383 | Q10: 0.6993007 | R10: 4.0767 | S10: 1.9453361 | T10: 0.092223698 | U10: 1.8847654 | V10: 0.7505817 | W10: 5.4573 | X10: 0.22079442 | Y10: 0.16645139 | Z10: 7.0749 | AA10: 0.41637174
A11: 2025-12-06 | B11: 1.9258917 | C11: 4.6754 | D11: 5.0682 | E11: 8.8016 | F11: 1 | G11: 1.102779 | H11: 8.2376 | I11: 9.4269 | J11: 0.90906 | K11: 0.021508198 | L11: 0.045597 | M11: 0.0047991553 | N11: 0.88261253 | O11: 0.38791264 | P11: 1.7198383 | Q11: 0.6993007 | R11: 4.0767 | S11: 1.9453361 | T11: 0.092223698 | U11: 1.8847654 | V11: 0.7505817 | W11: 5.4573 | X11: 0.22079442 | Y11: 0.16645139 | Z11: 7.0749 | AA11: 0.41637174
A12: 2025-12-07 | B12: 1.9258917 | C12: 4.6754 | D12: 5.0682 | E12: 8.8016 | F12: 1 | G12: 1.102779 | H12: 8.2376 | I12: 9.4269 | J12: 0.90906 | K12: 0.021508198 | L12: 0.045597 | M12: 0.0047991553 | N12: 0.88261253 | O12: 0.38791264 | P12: 1.7198383 | Q12: 0.6993007 | R12: 4.0767 | S12: 1.9453361 | T12: 0.092223698 | U12: 1.8847654 | V12: 0.7505817 | W12: 5.4573 | X12: 0.22079442 | Y12: 0.16645139 | Z12: 7.0749 | AA12: 0.41637174
A13: 2025-12-08 | B13: 1.9258917 | C13: 4.6954 | D13: 5.1153 | E13: 8.7914 | F13: 1 | G13: 1.102779 | H13: 8.2374 | I13: 9.4271 | J13: 0.90919 | K13: 0.021581771 | L13: 0.045563 | M13: 0.0048051511 | N13: 0.8822232 | O13: 0.38919592 | P13: 1.720075 | Q13: 0.6997411 | R13: 4.0861 | S13: 1.9476852 | T13: 0.092470155 | U13: 1.8846234 | V13: 0.75261534 | W13: 5.4599 | X13: 0.22161647 | Y13: 0.16623418 | Z13: 7.0764 | AA13: 0.41771094
... A217: 2026-06-30 | B217: 1.8510634 | C217: 4.6804 | D217: 4.7847 | E217: 8.4228 | F217: 1 | G217: 1.039177 | H217: 7.7671 | I217: 9.0145 | J217: 0.86855 | K217: 0.021961177 | L217: 0.042045 | M217: 0.0044029588 | N217: 0.84324142 | O217: 0.38968124 | P217: 1.6734161 | Q217: 0.68493151 | R217: 3.8414 | S217: 1.8121195 | T217: 0.088266707 | U217: 1.8103807 | V217: 0.70032915 | W217: 5.2605 | X217: 0.20424419 | Y217: 0.14580788 | Z217: 6.8109 | AA217: 0.41440471

Sheet 异常与限制

Sheet _rate_snapshot
A1: 项目 | B1: 内容
A2: 汇率快照结束日 | B2: 2026-06-30
A3: 汇率抓取时间 | B3: 2026-09-29T08:15:50.976302300+00:00
A4: 缺失币种/日期 | B4: []
A5: 汇率明细 | B5: [{"币种":"USD","每单位外币折合人民币":7.0779,"汇率公布日期":"2025-11-27","请求日期":"2025-11-27"},{"币种":"EUR","每单位外币折合人民币":8.205599999999999,"汇率公布日期":"2025-11-27","请求日期":"2025-11-27"},{"币种":"JPY","每单位外币折合人民币":0.045267,"汇率公布日期":"2025-11-27","请求日期":"2025-11-27"},{"币种":"HKD","每单位外币折合人民币":0.90998,"汇率公布日期":"2025-11-27","请求日期":"2025-11-27"},{"币种":"GBP","每单位外币折合人民币":9.3671,"汇率公布日期":"2025-11-27","请求日期":"2025-11-27"},{"币种":"AUD","每单位外币折合人民币":4.6133999999999995,"汇率公布日期":"2025-11-27","请求日期":"2025-11-27"},{"币种":"NZD","每单位外币折合人民币":4.0339,"汇率公布日期":"2025-11-27","请求日期":"2025-11-27"},{"币种":"SGD","每单位外币折合人民币":5.4565,"汇率公布日期":"2025-11-27","请求日期":"2025-11-27"},{"币种":"CHF","每单位外币折合人民币":8.8005,"汇率公布日期":"2025-11-27","请求日期":"2025-11-27"},{"币种":"CAD","每单位外币折合人民币":5.0378,"汇率公布日期":"2025-11-27","请求日期":"2025-11-27"},{"币种":"MOP","每单位外币折合人民币":0.8828462964597864,"汇率公布日期":"2025-11-27","请求日期":"2025-11-27"},{"币种":"MYR","每单位外币折合人民币":1.710893257369673,"汇率公布日期":"2025-11-27","请求日期":"2025-11-27"},{"币种":"RUB","每单位外币折合人民币":0.09008846687447074,"汇率公布日期":"2025-11-27","请求日期":"2025-11-27"},{"币种":"ZAR","每单位外币折合人民币":0.4127285484336952,"汇率公布日期":"2025-11-27","请求日期":"2025-11-27"},{"币种":"KRW","每单位外币折合人民币":0.004814636494944632,"汇率公布日期":"2025-11-27","请求日期":"2025-11-27"},{"币种":"AED","每单位外币折合人民币":1.925669170036588,"汇率公布日期":"2025-11-27","请求日期":"2025-11-27"},{"币种":"SAR","每单位外币折合人民币":1.8857961831485253,"汇率公布日期":"2025-11-27","请求日期":"2025-11-27"},{"币种":"HUF","每单位外币折合人民币":0.02147789387772635,"汇率公布日期":"2025-11-27","请求日期":"2025-11-27"},{"币种":"PLN","每单位外币折合人民币":1.9385856079404464,"汇率公布日期":"2025-11-27","请求日期":"2025-11-27"},{"币种":"DKK","每单位外币折合人民币":1.098659635245001,"汇率公布日期":"2025-11-27","请求日期":"2025-11-27"},{"币种":"SEK","每单位外币折合人民币":0.7452675510508272,"汇率公布日期":"2025-11-27","请求日期":"2025-11-27"},{"币种":"NOK","每单位外币折合人民币":0.6935293709688606,"汇率公布日期":"2025-11-27","请求日期":"2025-11-27"},{"币种":"TRY","每单位外币折合人民币":0.16663861583300144,"汇率公布日期":"2025-11-27","请求日期":"2025-11-27"},{"币种":"MXN","每单位外币折合人民币":0.38563881068990785,"汇率公布日期":"2025-11-27","请求日期":"2025-11-27"},{"币种":"THB","每单位外币折合人民币":0.21959682023804297,"汇率公布日期":"2025-11-27","请求日期":"2025-11-27"},{"币种":"CNY","每单位外币折合人民币":1.0,"汇率公布日期":"2025-11-27","请求日期":"2025-11-27"},{"币种":"USD","每单位外币折合人民币":7.0789,"汇率公布日期":"2025-11-28","请求日期":"2025-11-28"},{"币种":"EUR","每单位外币折合人民币":8.207799999999999,"汇率公布日期":"2025-11-28","请求日期":"2025-11-28"},{"币种":"JPY","每单位外币折合人民币":0.045293,"汇率公布日期":"2025-11-28","请求日期":"2025-11-28"},{"币种":"HKD","每单位外币折合人民币":0.9099,"汇率公布日期":"2025-11-28","请求日期":"2025-11-28"},{"币种":"GBP","每单位外币折合人民币":9.3697,"汇率公布日期":"2025-11-28","请求日期":"2025-11-28"},{"币种":"AUD","每单位外币折合人民币":4.6243,"汇率公布日期":"2025-11-28","请求日期":"2025-11-28"},{"币种":"NZD","每单位外币折合人民币":4.0533,"汇率公布日期":"2025-11-28","请求日期":"2025-11-28"},{"币种":"SGD","每单位外币折合人民币":5.4589,"汇率公布日期":"2025-11-28","请求日期":"2025-11-28"},{"币种":"CHF","每单位外币折合人民币":8.7971,"汇率公布日期":"2025-11-28","请求日期":"2025-11-28"},{"币种":"CAD","每单位外币折合人民币":5.046,"汇率公布日期":"2025-11-28","请求日期":"2025-11-28"},{"币种":"MOP","每单位外币折合人民币":0.8826904404625298,"汇率公布日期":"2025-11-28","请求日期":"2025-11-28"},{"币种":"MYR","每单位外币折合人民币":1.7139723022075963,"汇率公布日期":"2025-11-28","请求日期":"2025-11-28"},{"币种":"RUB","每单位外币折合人民币":0.09079765742043856,"汇率公布日期":"2025-11-28","请求日期":"2025-11-28"},{"币种":"ZAR","每单位外币折合人民币":0.4126263668248401,"汇率公布日期":"2025-11-28","请求日期":"2025-11-28"},{"币种":"KRW","每单位外币折合人民币":0.004836057645807138,"汇率公布日期":"2025-11-28","请求日期":"2025-11-28"},{"币种":"AED","每单位外币折合人民币":1.926893654739195,"汇率公布日期":"2025-11-28","请求日期":"2025-11-28"},{"币种":"SAR","每单位外币折合人民币":1.8865076969514032,"汇率公布日期":"2025-11-28","请求日期":"2025-11-28"},{"币种":"HUF","每单位外币折合人民币":0.02152245545389782,"汇率公布日期":"2025-11-28","请求日期":"2025-11-28"},{"币种":"PLN","每单位外币折合人民币":1.941747572815534,"汇率公布日期":"2025-11-28","请求日期":"2025-11-28"},{"币种":"DKK","每单位外币折合人民币":1.0990218705352237,"汇率公布日期":"2025-11-28","请求日期":"2025-11-28"},{"币种":"SEK","每单位外币折合人民币":0.7471049682480388,"汇率公布日期":"2025-11-28","请求日期":"2025-11-28"},{"币种":"NOK","每单位外币折合人民币":0.6965728615213151,"汇率公布日期":"2025-11-28","请求日期":"2025-11-28"},{"币种":"TRY","每单位外币折合人民币":0.16657421797569016,"汇率公布日期":"2025-11-28","请求日期":"2025-11-28"},{"币种":"MXN","每单位外币折合人民币":0.38583224014198625,"汇率公布日期":"2025-11-28","请求日期":"2025-11-28"},{"币种":"THB","每单位外币折合人民币":0.2196547028071871,"汇率公布日期":"2025-11-28","请求日期":"2025-11-28"},{"币种":"CNY","每单位外币折合人民币":1.0,"汇率公布日期":"2025-11-28","请求日期":"2025-11-28"},{"币种":"USD","每单位外币折合人民币":7.0789,"汇率公布日期":"2025-11-28","请求日期":"2025-11-29"},{"币种":"EUR","每单位外币折合人民币":8.207799999999999,"汇率公布日期":"2025-11-28","请求日期":"2025-11-29"},{"币种":"JPY","每单位外币折合人民币":0.045293,"汇率公布日期":"2025-11-28","请求日期":"2025-11-29"},{"币种":"HKD","每单位外币折合人民币":0.9099,"汇率公布日期":"2025-11-28","请求日期":"2025-11-29"},{"币种":"GBP","每单位外币折合人民币":9.3697,"汇率公布日期":"2025-11-28","请求日期":"2025-11-29"},{"币种":"AUD","每单位外币折合人民币":4.6243,"汇率公布日期":"2025-11-28","请求日期":"2025-11-29"},{"币种":"NZD","每单位外币折合人民币":4.0533,"汇率公布日期":"2025-11-28","请求日期":"2025-11-29"},{"币种":"SGD","每单位外币折合人民币":5.4589,"汇率公布日期":"2025-11-28","请求日期":"2025-11-29"},{"币种":"CHF","每单位外币折合人民币":8.7971,"汇率公布日期":"2025-11-28","请求日期":"2025-11-29"},{"币种":"CAD","每单位外币折合人民币":5.046,"汇率公布日期":"2025-11-28","请求日期":"2025-11-29"},{"币种":"MOP","每单位外币折合人民币":0.8826904404625298,"汇率公布日期":"2025-11-28","请求日期":"2025-11-29"},{"币种":"MYR","每单位外币折合人民币":1.7139723022075963,"汇率公布日期":"2025-11-28","请求日期":"2025-11-29"},{"币种":"RUB","每单位外币折合人民币":0.09079765742043856,"汇率公布日期":"2025-11-28","请求日期":"2025-11-29"},{"币种":"ZAR","每单位外币折合人民币":0.4126263668248401,"汇率公布日期":"2025-11-28","请求日期":"2025-11-29"},{"币种":"KRW","每单位外币折合人民币":0.004836057645807138,"汇率公布日期":"2025-11-28","请求日期":"2025-11-29"},{"币种":"AED","每单位外币折合人民币":1.926893654739195,"汇率公布日期":"2025-11-28","请求日期":"2025-11-29"},{"币种":"SAR","每单位外币折合人民币":1.8865076969514032,"汇率公布日期":"2025-11-28","请求日期":"2025-11-29"},{"币种":"HUF","每单位外币折合人民币":0.02152245545389782,"汇率公布日期":"2025-11-28","请求日期":"2025-11-29"},{"币种":"PLN","每单位外币折合人民币":1.941747572815534,"汇率公布日期":"2025-11-28","请求日期":"2025-11-29"},{"币种":"DKK","每单位外币折合人民币":1.0990218705352237,"汇率公布日期":"2025-11-28","请求日期":"2025-11-29"},{"币种":"SEK","每单位外币折合人民币":0.7471049682480388,"汇率公布日期":"2025-11-28","请求日期":"2025-11-29"},{"币种":"NOK","每单位外币折合人民币":0.6965728615213151,"汇率公布日期":"2025-11-28","请求日期":"2025-11-29"},{"币种":"TRY","每单位外币折合人民币":0.16657421797569016,"汇率公布日期":"2025-11-28","请求日期":"2025-11-29"},{"币种":"MXN","每单位外币折合人民币":0.38583224014198625,"汇率公布日期":"2025-11-28","请求日期":"2025-11-29"},{"币种":"THB","每单位外币折合人民币":0.2196547028071871,"汇率公布日期":"2025-11-28","请求日期":"2025-11-29"},{"币种":"CNY","每单位外币折合人民币":1.0,"汇率公布日期":"2025-11-29","请求日期":"2025-11-29"},{"币种":"USD","每单位外币折合人民币":7.0789,"汇率公布日期":"2025-11-28","请求日期":"2025-11-30"},{"币种":"EUR","每单位外币折合人民币":8.207799999999999,"汇率公布日期":"2025-11-28","请求日期":"2025-11-30"},{"币种":"JPY","每单位外币折合人民币":0.045293,"汇率公布日期":"2025-11-28","请求日期":"2025-11-30"},{"币种":"HKD","每单位外币折合人民币":0.9099,"汇率公布日期":"2025-11-28","请求日期":"2025-11-30"},{"币种":"GBP","每单位外币折合人民币":9.3697,"汇率公布日期":"2025-11-28","请求日期":"2025-11-30"},{"币种":"AUD","每单位外币折合人民币":4.6243,"汇率公布日期":"2025-11-28","请求日期":"2025-11-30"},{"币种":"NZD","每单位外币折合人民币":4.0533,"汇率公布日期":"2025-11-28","请求日期":"2025-11-30"},{"币种":"SGD","每单位外币折合人民币":5.4589,"汇率公布日期":"2025-11-28","请求日期":"2025-11-30"},{"币种":"CHF","每单位外币折合人民币":8.7971,"汇率公布日期":"2025-11-28","请求日期":"2025-11-30"},{"币种":"CAD","每单位外币折合人民币":5.046,"汇率公布日期":"2025-11-28","请求日期":"2025-11-30"},{"币种":"MOP","每单位外币折合人民币":0.8826904404625298,"汇率公布日期":"2025-11-28","请求日期":"2025-11-30"},{"币种":"MYR","每单位外币折合人民币":1.7139723022075963,"汇率公布日期":"2025-11-28","请求日期":"2025-11-30"},{"币种":"RUB","每单位外币折合人民币":0.09079765742043856,"汇率公布日期":"2025-11-28","请求日期":"2025-11-30"},{"币种":"ZAR","每单位外币折合人民币":0.4126263668248401,"汇率公布日期":"2025-11-28","请求日期":"2025-11-30"},{"币种":"KRW","每单位外币折合人民币":0.004836057645807138,"汇率公布日期":"2025-11-28","请求日期":"2025-11-30"},{"币种":"AED","每单位外币折合人民币":1.926893654739195,"汇率公布日期":"2025-11-28","请求日期":"2025-11-30"},{"币种":"SAR","每单位外币折合人民币":1.8865076969514032,"汇率公布日期":"2025-11-28","请求日期":"2025-11-30"},{"币种":"HUF","每单位外币折合人民币":0.02152245545389782,"汇率公布日期":"2025-11-28","请求日期":"2025-11-30"},{"币种":"PLN","每单位外币折合人民币":1.941747572815534,"汇率公布日期":"2025-11-28","请求日期":"2025-11-30"},{"币种":"DKK","每单位外币折合人民币":1.0990218705352237,"汇率公布日期":"2025-11-28","请求日期":"2025-11-30"},{"币种":"SEK","每单位外币折合人民币":0.7471049682480388,"汇率公布日期":"2025-11-28","请求日期":"2025-11-30"},{"币种":"NOK","每单位外币折合人民币":0.6965728615213151,"汇率公布日期":"2025-11-28","请求日期":"2025-11-30"},{"币种":"TRY","每单位外币折合人民币":0.16657421797569016,"汇率公布日期":"2025-11-28","请求日期":"2025-11-30"},{"币种":"MXN","每单位外币折合人民币":0.38583224014198625,"汇率公布日期":"2025-11-28","请求日期":"2025-11-30"},{"币种":"THB","每单位外币折合人民币":0.2196547028071871,"汇率公布日期":"2025-11-28","请求日期":"2025-11-30"},{"币种":"CNY","每单位外币折合人民币":1.0,"汇率公布日期":"2025-11-30","请求日期":"2025-11-30"},{"币种":"USD","每单位外币折合人民币":7.075900000000001,"汇率公布日期":"2025-12-01","请求日期":"2025-12-01"},{"币种":"EUR","每单位外币折合人民币":8.2052,"汇率公布日期":"2025-12-01","请求日期":"2025-12-01"},{"币种":"JPY","每单位外币折合人民币":0.045331,"汇率公布日期":"2025-12-01","请求日期":"2025-12-01"},{"币种":"HKD","每单位外币折合人民币":0.90877,"汇率公布日期":"2025-12-01","请求日期":"2025-12-01"},{"币种":"GBP","每单位外币折合人民币":9.3616,"汇率公布日期":"2025-12-01","请求日期":"2025-12-01"},{"币种":"AUD","每单位外币折合人民币":4.630199999999999,"汇率公布日期":"2025-12-01","请求日期":"2025-12-01"},{"币种":"NZD","每单位外币折合人民币":4.0535000000000005,"汇率公布日期":"2025-12-01","请求日期":"2025-12-01"},{"币种":"SGD","每单位外币折合人民币":5.456900000000001,"汇率公布日期":"2025-12-01","请求日期":"2025-12-01"},{"币种":"CHF","每单位外币折合人民币":8.8013,"汇率公布日期":"2025-12-01","请求日期":"2025-12-01"},{"币种":"CAD","每单位外币折合人民币":5.0621,"汇率公布日期":"2025-12-01","请求日期":"2025-12-01"},{"币种":"MOP","每单位外币折合人民币":0.8816009873931058,"汇率公布日期":"2025-12-01","请求日期":"2025-12-01"},{"币种":"MYR","每单位外币折合人民币":1.712592694079567,"汇率公布日期":"2025-12-01","请求日期":"2025-12-01"},{"币种":"RUB","每单位外币折合人民币":0.09125669596006608,"汇率公布日期":"2025-12-01","请求日期":"2025-12-01"},{"币种":"ZAR","每单位外币折合人民币":0.41324021653787346,"汇率公布日期":"2025-12-01","请求日期":"2025-12-01"},{"币种":"KRW","每单位外币折合人民币":0.004819277108433735,"汇率公布日期":"2025-12-01","请求日期":"2025-12-01"},{"币种":"AED","每单位外币折合人民币":1.9255208533908423,"汇率公布日期":"2025-12-01","请求日期":"2025-12-01"},{"币种":"SAR","每单位外币折合人民币":1.8854050792812835,"汇率公布日期":"2025-12-01","请求日期":"2025-12-01"},{"币种":"HUF","每单位外币折合人民币":0.021500567614985037,"汇率公布日期":"2025-12-01","请求日期":"2025-12-01"},{"币种":"PLN","每单位外币折合人民币":1.937458828999884,"汇率公布日期":"2025-12-01","请求日期":"2025-12-01"},{"币种":"DKK","每单位外币折合人民币":1.0985389432055366,"汇率公布日期":"2025-12-01","请求日期":"2025-12-01"},{"币种":"SEK","每单位外币折合人民币":0.7485029940119761,"汇率公布日期":"2025-12-01","请求日期":"2025-12-01"},{"币种":"NOK","每单位外币折合人民币":0.6992029086841001,"汇率公布日期":"2025-12-01","请求日期":"2025-12-01"},{"币种":"TRY","每单位外币折合人民币":0.1664483419248419,"汇率公布日期":"2025-12-01","请求日期":"2025-12-01"},{"币种":"MXN","每单位外币折合人民币":0.38678734431809386,"汇率公布日期":"2025-12-01","请求日期":"2025-12-01"},{"币种":"THB","每单位外币折合人民币":0.2201091741503786,"汇率公布日期":"2025-12-01","请求日期":"2025-12-01"},{"币种":"CNY","每单位外币折合人民币":1.0,"汇率公布日期":"2025-12-01","请求日期":"2025-12-01"},{"币种":"USD","每单位外币折合人民币":7.079400000000001,"汇率公布日期":"2025-12-02","请求日期":"2025-12-02"},{"币种":"EUR","每单位外币折合人民币":8.2113,"汇率公布日期":"2025-12-02","请求日期":"2025-12-02"},{"币种":"JPY","每单位外币折合人民币":0.045495,"汇率公布日期":"2025-12-02","请求日期":"2025-12-02"},{"币种":"HKD","每单位外币折合人民币":0.9088,"汇率公布日期":"2025-12-02","请求日期":"2025-12-02"},{"币种":"GBP","每单位外币折合人民币":9.3451,"汇率公布日期":"2025-12-02","请求日期":"2025-12-02"},{"币种":"AUD","每单位外币折合人民币":4.6292,"汇率公布日期":"2025-12-02","请求日期":"2025-12-02"},{"币种":"NZD","每单位外币折合人民币":4.0512,"汇率公布日期":"2025-12-02","请求日期":"2025-12-02"},{"币种":"SGD","每单位外币折合人民币":5.4576,"汇率公布日期":"2025-12-02","请求日期":"2025-12-02"},{"币种":"CHF","每单位外币折合人民币":8.7915,"汇率公布日期":"2025-12-02","请求日期":"2025-12-02"},{"币种":"CAD","每单位外币折合人民币":5.0539,"汇率公布日期":"2025-12-02","请求日期":"2025-12-02"},{"币种":"MOP","每单位外币折合人民币":0.8819119851838787,"汇率公布日期":"2025-12-02","请求日期":"2025-12-02"},{"币种":"MYR","每单位外币折合人民币":1.7131207921470544,"汇率公布日期":"2025-12-02","请求日期":"2025-12-02"},{"币种":"RUB","每单位外币折合人民币":0.09102742656362364,"汇率公布日期":"2025-12-02","请求日期":"2025-12-02"},{"币种":"ZAR","每单位外币折合人民币":0.4139929621196439,"汇率公布日期":"2025-12-02","请求日期":"2025-12-02"},{"币种":"KRW","每单位外币折合人民币":0.004809542131589073,"汇率公布日期":"2025-12-02","请求日期":"2025-12-02"},{"币种":"AED","每单位外币折合人民币":1.926299770770327,"汇率公布日期":"2025-12-02","请求日期":"2025-12-02"},{"币种":"SAR","每单位外币折合人民币":1.8849786054928277,"汇率公布日期":"2025-12-02","请求日期":"2025-12-02"},{"币种":"HUF","每单位外币折合人民币":0.021563714306661895,"汇率公布日期":"2025-12-02","请求日期":"2025-12-02"},{"币种":"PLN","每单位外币折合人民币":1.942351021676637,"汇率公布日期":"2025-12-02","请求日期":"2025-12-02"},{"币种":"DKK","每单位外币折合人民币":1.0995052226498077,"汇率公布日期":"2025-12-02","请求日期":"2025-12-02"},{"币种":"SEK","每单位外币折合人民币":0.7483349547257353,"汇率公布日期":"2025-12-02","请求日期":"2025-12-02"},{"币种":"NOK","每单位外币折合人民币":0.6983727913960472,"汇率公布日期":"2025-12-02","请求日期":"2025-12-02"},{"币种":"TRY","每单位外币折合人民币":0.1666872247577201,"汇率公布日期":"2025-12-02","请求日期":"2025-12-02"},{"币种":"MXN","每单位外币折合人民币":0.3864734299516908,"汇率公布日期":"2025-12-02","请求日期":"2025-12-02"},{"币种":"THB","每单位外币折合人民币":0.22106287028030772,"汇率公布日期":"2025-12-02","请求日期":"2025-12-02"},{"币种":"CNY","每单位外币折合人民币":1.0,"汇率公布日期":"2025-12-02","请求日期":"2025-12-02"},{"币种":"USD","每单位外币折合人民币":7.075399999999999,"汇率公布日期":"2025-12-03","请求日期":"2025-12-03"},{"币种":"EUR","每单位外币折合人民币":8.221,"汇率公布日期":"2025-12-03","请求日期":"2025-12-03"},{"币种":"JPY","每单位外币折合人民币":0.04536,"汇率公布日期":"2025-12-03","请求日期":"2025-12-03"},{"币种":"HKD","每单位外币折合人民币":0.90897,"汇率公布日期":"2025-12-03","请求日期":"2025-12-03"},{"币种":"GBP","每单位外币折合人民币":9.3429,"汇率公布日期":"2025-12-03","请求日期":"2025-12-03"},{"币种":"AUD","每单位外币折合人民币":4.6437,"汇率公布日期":"2025-12-03","请求日期":"2025-12-03"},{"币种":"NZD","每单位外币折合人民币":4.0567,"汇率公布日期":"2025-12-03","请求日期":"2025-12-03"},{"币种":"SGD","每单位外币折合人民币":5.454400000000001,"汇率公布日期":"2025-12-03","请求日期":"2025-12-03"},{"币种":"CHF","每单位外币折合人民币":8.8047,"汇率公布日期":"2025-12-03","请求日期":"2025-12-03"},{"币种":"CAD","每单位外币折合人民币":5.0588999999999995,"汇率公布日期":"2025-12-03","请求日期":"2025-12-03"},{"币种":"MOP","每单位外币折合人民币":0.8821453775582216,"汇率公布日期":"2025-12-03","请求日期":"2025-12-03"},{"币种":"MYR","每单位外币折合人民币":1.7116546565564932,"汇率公布日期":"2025-12-03","请求日期":"2025-12-03"},{"币种":"RUB","每单位外币折合人民币":0.09126252578166354,"汇率公布日期":"2025-12-03","请求日期":"2025-12-03"},{"币种":"ZAR","每单位外币折合人民币":0.4131207138725936,"汇率公布日期":"2025-12-03","请求日期":"2025-12-03"},{"币种":"KRW","每单位外币折合人民币":0.004814404698858986,"汇率公布日期":"2025-12-03","请求日期":"2025-12-03"},{"币种":"AED","每单位外币折合人民币":1.9245943917319424,"汇率公布日期":"2025-12-03","请求日期":"2025-12-03"},{"币种":"SAR","每单位外币折合人民币":1.8830973184694184,"汇率公布日期":"2025-12-03","请求日期":"2025-12-03"},{"币种":"HUF","每单位外币折合人民币":0.021577254121794967,"汇率公布日期":"2025-12-03","请求日期":"2025-12-03"},{"币种":"PLN","每单位外币折合人民币":1.941747572815534,"汇率公布日期":"2025-12-03","请求日期":"2025-12-03"},{"币种":"DKK","每单位外币折合人民币":1.100473203477495,"汇率公布日期":"2025-12-03","请求日期":"2025-12-03"},{"币种":"SEK","每单位外币折合人民币":0.7498500299940011,"汇率公布日期":"2025-12-03","请求日期":"2025-12-03"},{"币种":"NOK","每单位外币折合人民币":0.6979341150195422,"汇率公布日期":"2025-12-03","请求日期":"2025-12-03"},{"币种":"TRY","每单位外币折合人民币":0.1664175949994841,"汇率公布日期":"2025-12-03","请求日期":"2025-12-03"},{"币种":"MXN","每单位外币折合人民币":0.3867723844517501,"汇率公布日期":"2025-12-03","请求日期":"2025-12-03"},{"币种":"THB","每单位外币折合人民币":0.2209212415773777,"汇率公布日期":"2025-12-03","请求日期":"2025-12-03"},{"币种":"CNY","每单位外币折合人民币":1.0,"汇率公布日期":"2025-12-03","请求日期":"2025-12-03"},{"币种":"USD","每单位外币折合人民币":7.073300000000001,"汇率公布日期":"2025-12-04","请求日期":"2025-12-04"},{"币种":"EUR","每单位外币折合人民币":8.2373,"汇率公布日期":"2025-12-04","请求日期":"2025-12-04"},{"币种":"JPY","每单位外币折合人民币":0.045468,"汇率公布日期":"2025-12-04","请求日期":"2025-12-04"},{"币种":"HKD","每单位外币折合人民币":0.90891,"汇率公布日期":"2025-12-04","请求日期":"2025-12-04"},{"币种":"GBP","每单位外币折合人民币":9.4207,"汇率公布日期":"2025-12-04","请求日期":"2025-12-04"},{"币种":"AUD","每单位外币折合人民币":4.6586,"汇率公布日期":"2025-12-04","请求日期":"2025-12-04"},{"币种":"NZD","每单位外币折合人民币":4.0714999999999995,"汇率公布日期":"2025-12-04","请求日期":"2025-12-04"},{"币种":"SGD","每单位外币折合人民币":5.4573,"汇率公布日期":"2025-12-04","请求日期":"2025-12-04"},{"币种":"CHF","每单位外币折合人民币":8.8252,"汇率公布日期":"2025-12-04","请求日期":"2025-12-04"},{"币种":"CAD","每单位外币折合人民币":5.0597,"汇率公布日期":"2025-12-04","请求日期":"2025-12-04"},{"币种":"MOP","每单位外币折合人民币":0.8819897689186805,"汇率公布日期":"2025-12-04","请求日期":"2025-12-04"},{"币种":"MYR","每单位外币折合人民币":1.714207350521119,"汇率公布日期":"2025-12-04","请求日期":"2025-12-04"},{"币种":"RUB","每单位外币折合人民币":0.09137760883073212,"汇率公布日期":"2025-12-04","请求日期":"2025-12-04"},{"币种":"ZAR","每单位外币折合人民币":0.4143016944939305,"汇率公布日期":"2025-12-04","请求日期":"2025-12-04"},{"币种":"KRW","每单位外币折合人民币":0.004813941173638858,"汇率公布日期":"2025-12-04","请求日期":"2025-12-04"},{"币种":"AED","每单位外币折合人民币":1.9215618454679968,"汇率公布日期":"2025-12-04","请求日期":"2025-12-04"},{"币种":"SAR","每单位外币折合人民币":1.8808305747818237,"汇率公布日期":"2025-12-04","请求日期":"2025-12-04"},{"币种":"HUF","每单位外币折合人民币":0.02163584280262053,"汇率公布日期":"2025-12-04","请求日期":"2025-12-04"},{"币种":"PLN","每单位外币折合人民币":1.94984986156066,"汇率公布日期":"2025-12-04","请求日期":"2025-12-04"},{"币种":"DKK","每单位外币折合人民币":1.102535832414553,"汇率公布日期":"2025-12-04","请求日期":"2025-12-04"},{"币种":"SEK","每单位外币折合人民币":0.7528419784687194,"汇率公布日期":"2025-12-04","请求日期":"2025-12-04"},{"币种":"NOK","每单位外币折合人民币":0.7012622720897616,"汇率公布日期":"2025-12-04","请求日期":"2025-12-04"},{"币种":"TRY","每单位外币折合人民币":0.16629914555499012,"汇率公布日期":"2025-12-04","请求日期":"2025-12-04"},{"币种":"MXN","每单位外币折合人民币":0.3860854793251226,"汇率公布日期":"2025-12-04","请求日期":"2025-12-04"},{"币种":"THB","每单位外币折合人民币":0.22134667315950243,"汇率公布日期":"2025-12-04","请求日期":"2025-12-04"},{"币种":"CNY","每单位外币折合人民币":1.0,"汇率公布日期":"2025-12-04","请求日期":"2025-12-04"},{"币种":"USD","每单位外币折合人民币":7.0749,"汇率公布日期":"2025-12-05","请求日期":"2025-12-05"},{"币种":"EUR","每单位外币折合人民币":8.2376,"汇率公布日期":"2025-12-05","请求日期":"2025-12-05"},{"币种":"JPY","每单位外币折合人民币":0.045597000000000006,"汇率公布日期":"2025-12-05","请求日期":"2025-12-05"},{"币种":"HKD","每单位外币折合人民币":0.90906,"汇率公布日期":"2025-12-05","请求日期":"2025-12-05"},{"币种":"GBP","每单位外币折合人民币":9.4269,"汇率公布日期":"2025-12-05","请求日期":"2025-12-05"},{"币种":"AUD","每单位外币折合人民币":4.6754,"汇率公布日期":"2025-12-05","请求日期":"2025-12-05"},{"币种":"NZD","每单位外币折合人民币":4.0767,"汇率公布日期":"2025-12-05","请求日期":"2025-12-05"},{"币种":"SGD","每单位外币折合人民币":5.4573,"汇率公布日期":"2025-12-05","请求日期":"2025-12-05"},{"币种":"CHF","每单位外币折合人民币":8.8016,"汇率公布日期":"2025-12-05","请求日期":"2025-12-05"},{"币种":"CAD","每单位外币折合人民币":5.0682,"汇率公布日期":"2025-12-05","请求日期":"2025-12-05"},{"币种":"MOP","每单位外币折合人民币":0.88261253309797,"汇率公布日期":"2025-12-05","请求日期":"2025-12-05"},{"币种":"MYR","每单位外币折合人民币":1.7198383351964914,"汇率公布日期":"2025-12-05","请求日期":"2025-12-05"},{"币种":"RUB","每单位外币折合人民币":0.09222369780138703,"汇率公布日期":"2025-12-05","请求日期":"2025-12-05"},{"币种":"ZAR","每单位外币折合人民币":0.4163717366865137,"汇率公布日期":"2025-12-05","请求日期":"2025-12-05"},{"币种":"KRW","每单位外币折合人民币":0.004799155348658636,"汇率公布日期":"2025-12-05","请求日期":"2025-12-05"},{"币种":"AED","每单位外币折合人民币":1.9258916878514751,"汇率公布日期":"2025-12-05","请求日期":"2025-12-05"},{"币种":"SAR","每单位外币折合人民币":1.8847654409408747,"汇率公布日期":"2025-12-05","请求日期":"2025-12-05"},{"币种":"HUF","每单位外币折合人民币":0.02150819784961038,"汇率公布日期":"2025-12-05","请求日期":"2025-12-05"},{"币种":"PLN","每单位外币折合人民币":1.9453360568038127,"汇率公布日期":"2025-12-05","请求日期":"2025-12-05"},{"币种":"DKK","每单位外币折合人民币":1.102779003087781,"汇率公布日期":"2025-12-05","请求日期":"2025-12-05"},{"币种":"SEK","每单位外币折合人民币":0.7505817008181341,"汇率公布日期":"2025-12-05","请求日期":"2025-12-05"},{"币种":"NOK","每单位外币折合人民币":0.6993006993006993,"汇率公布日期":"2025-12-05","请求日期":"2025-12-05"},{"币种":"TRY","每单位外币折合人民币":0.16645138953619987,"汇率公布日期":"2025-12-05","请求日期":"2025-12-05"},{"币种":"MXN","每单位外币折合人民币":0.38791264207300513,"汇率公布日期":"2025-12-05","请求日期":"2025-12-05"},{"币种":"THB","每单位外币折合人民币":0.22079441831710492,"汇率公布日期":"2025-12-05","请求日期":"2025-12-05"},{"币种":"CNY","每单位外币折合人民币":1.0,"汇率公布日期":"2025-12-05","请求日期":"2025-12-05"},{"币种":"USD","每单位外币折合人民币":7.0749,"汇率公布日期":"2025-12-05","请求日期":"2025-12-06"},{"币种":"EUR","每单位外币折合人民币":8.2376,"汇率公布日期":"2025-12-05","请求日期":"2025-12-06"},{"币种":"JPY","每单位外币折合人民币":0.045597000000000006,"汇率公布日期":"2025-12-05","请求日期":"2025-12-06"},{"币种":"HKD","每单位外币折合人民币":0.90906,"汇率公布日期":"2025-12-05","请求日期":"2025-12-06"},{"币种":"GBP","每单位外币折合人民币":9.4269,"汇率公布日期":"2025-12-05","请求日期":"2025-12-06"},{"币种":"AUD","每单位外币折合人民币":4.6754,"汇率公布日期":"2025-12-05","请求日期":"2025-12-06"},{"币种":"NZD","每单位外币折合人民币":4.0767,"汇率公布日期":"2025-12-05","请求日期":"2025-12-06"},{"币种":"SGD","每单位外币折合人民币":5.4573,"汇率公布日期":"2025-12-05","请求日期":"2025-12-06"},{"币种":"CHF","每单位外币折合人民币":8.8016,"汇率公布日期":"2025-12-05","请求日期":"2025-12-06"},{"币种":"CAD","每单位外币折合人民币":5.0682,"汇率公布日期":"2025-12-05","请求日期":"2025-12-06"},{"币种":"MOP","每单位外币折合人民币":0.88261253309797,"汇率公布日期":"2025-12-05","请求日期":"2025-12-06"},{"币种":"MYR","每单位外币折合人民币":1.7198383351964914,"汇率公布日期":"2025-12-05","请求日期":"2025-12-06"},{"币种":"RUB","每单位外币折合人民币":0.09222369780138703,"汇率公布日期":"2025-12-05","请求日期":"2025-12-06"},{"币种":"ZAR","每单位外币折合人民币":0.4163717366865137,"汇率公布日期":"2025-12-05","请求日期":"2025-12-06"},{"币种":"KRW","每单位外币折合人民币":0.004799155348658636,"汇率公布日期":"2025-12-05","请求日期":"2025-12-06"},{"币种":"AED","每单位外币折合人民币":1.9258916878514751,"汇率公布日期":"2025-12-05","请求日期":"2025-12-06"},{"币种":"SAR","每单位外币折合人民币":1.8847654409408747,"汇率公布日期":"2025-12-05","请求日期":"2025-12-06"},{"币种":"HUF","每单位外币折合人民币":0.02150819784961038,"汇率公布日期":"2025-12-05","请求日期":"2025-12-06"},{"币种":"PLN","每单位外币折合人民币":1.9453360568038127,"汇率公布日期":"2025-12-05","请求日期":"2025-12-06"},{"币种":"DKK","每单位外币折合人民币":1.102779003087781,"汇率公布日期":"2025-12-05","请求日期":"2025-12-06"},{"币种":"SEK","每单位外币折合人民币":0.7505817008181341,"汇率公布日期":"2025-12-05","请求日期":"2025-12-06"},{"币种":"NOK","每单位外币折合人民币":0.6993006993006993,"汇率公布日期":"2025-12-05","请求日期":"2025-12-06"},{"币种":"TRY","每单位外币折合人民币":0.16645138953619987,"汇率公布日期":"2025-12-05","请求日期":"2025-12-06"},{"币种":"MXN","每单位外币折合人民币":0.38791264207300513,"汇率公布日期":"2025-12-05","请求日期":"2025-12-06"},{"币种":"THB","每单位外币折合人民币":0.22079441831710492,"汇率公布日期":"2025-12-05","请求日期":"2025-12-06"},{"币种":"CNY","每单位外币折合人民币":1.0,"汇率公布日期":"2025-12-06","请求日期":"2025-12-06"},{"币种":"USD","每单位外币折合人民币":7.0749,"汇率公布日期":"2025-12-05","请求日期":"2025-12-07"},{"币种":"EUR","每单位外币折合人民币":8.2376,"汇率公布日期":"2025-12-05","请求日期":"2025-12-07"},{"币种":"JPY","每单位外币折合人民币":0.045597000000000006,"汇率公布日期":"2025-12-05","请求日期":"2025-12-07"},{"币种":"HKD","每单位外币折合人民币":0.90906,"汇率公布日期":"2025-12-05","请求日期":"2025-12-07"},{"币种":"GBP","每单位外币折合人民币":9.4269,"汇率公布日期":"2025-12-05","请求日期":"2025-12-07"},{"币种":"AUD","每单位外币折合人民币":4.6754,"汇率公布日期":"2025-12-05","请求日期":"2025-12-07"},{"币种":"NZD","每单位外币折合人民币":4.0767,"汇率公布日期":"2025-12-05","请求日期":"2025-12-07"},{"币种":"SGD","每单位外币折合人民币":5.4573,"汇率公布日期":"2025-12-05","请求日期":"2025-12-07"},{"币种":"CHF","每单位外币折合人民币":8.8016,"汇率公布日期":"2025-12-05","请求日期":"2025-12-07"},{"币种":"CAD","每单位外币折合人民币":5.0682,"汇率公布日期":"2025-12-05","请求日期":"2025-12-07"},{"币种":"MOP","每单位外币折合人民币":0.88261253309797,"汇率公布日期":"2025-12-05","请求日期":"2025-12-07"},{"币种":"MYR","每单位外币折合人民币":1.7198383351964914,"汇率公布日期":"2025-12-05","请求日期":"2025-12-07"},{"币种":"RUB","每单位外币折合人民币":0.09222369780138703,"汇率公布日期":"2025-12-05","请求日期":"2025-12-07"},{"币种":"ZAR","每单位外币折合人民币":0.4163717366865137,"汇率公布日期":"2025-12-05","请求日期":"2025-12-07"},{"币种":"KRW","每单位外币折合人民币":0.004799155348658636,"汇率公布日期":"2025-12-05","请求日期":"2025-12-07"},{"币种":"AED","每单位外币折合人民币":1.9258916878514751,"汇率公布日期":"2025-12-05","请求日期":"2025-12-07"},{"币种":"SAR","每单位外币折合人民币":1.8847654409408747,"汇率公布日期":"2025-12-05","请求日期":"2025-12-07"},{"币种":"HUF","每单位外币折合人民币":0.02150819784961038,"汇率公布日期":"2025-12-05","请求日期":"2025-12-07"},{"币种":"PLN","每单位外币折合人民币":1.9453360568038127,"汇率公布日期":"2025-12-05","请求日期":"2025-12-07"},{"币种":"DKK","每单位外币折合人民币":1.102779003087781,"汇率公布日期":"2025-12-05","请求日期":"2025-12-07"},{"币种":"SEK","每单位外币折合人民币":0.7505817008181341,"汇率公布日期":"2025-12-05","请求日期":"2025-12-07"},{"币种":"NOK","每单位外币折合人民币":0.6993006993006993,"汇率公布日期":"2025-12-05","请求日期":"2025-12-07"},{"币种":"TRY","每单位外币折合人民币":0.16645138953619987,"汇率公布日期":"2025-12-05","请求日期":"2025-12-07"},{"币种":"MXN","每单位外币折合人民币":0.38791264207300513,"汇率公布日期":"2025-12-05","请求日期":"2025-12-07"},{"币种":"THB","每单位外币折合人民币":0.22079441831710492,"汇率公布日期":"2025-12-05","请求日期":"2025-12-07"},{"币种":"CNY","每单位外币折合人民币":1.0,"汇率公布日期":"2025-12-07","请求日期":"2025-12-07"},{"币种":"USD","每单位外币折合人民币":7.0764,"汇率公布日期":"2025-12-08","请求日期":"2025-12-08"},{"币种":"EUR","每单位外币折合人民币":8.237400000000001,"汇率公布日期":"2025-12-08","请求日期":"2025-12-08"},{"币种":"JPY","每单位外币折合人民币":0.045563,"汇率公布日期":"2025-12-08","请求日期":"2025-12-08"},{"币种":"HKD","每单位外币折合人民币":0.90919,"汇率公布日期":"2025-12-08","请求日期":"2025-12-08"},{"币种":"GBP","每单位外币折合人民币":9.4271,"汇率公布日期":"2025-12-08","请求日期":"2025-12-08"},{"币种":"AUD","每单位外币折合人民币":4.6954,"汇率公布日期":"2025-12-08","请求日期":"2025-12-08"},{"币种":"NZD","每单位外币折合人民币":4.0861,"汇率公布日期":"2025-12-08","请求日期":"2025-12-08"},{"币种":"SGD","每单位外币折合人民币":5.4599,"汇率公布日期":"2025-12-08","请求日期":"2025-12-08"},{"币种":"CHF","每单位外币折合人民币":8.7914,"汇率公布日期":"2025-12-08","请求日期":"2025-12-08"},{"币种":"CAD","每单位外币折合人民币":5.1152999999999995,"汇率公布日期":"2025-12-08","请求日期":"2025-12-08"},{"币种":"MOP","每单位外币折合人民币":0.882223202470225,"汇率公布日期":"2025-12-08","请求日期":"2025-12-08"},{"币种":"MYR","每单位外币折合人民币":1.7200749952697938,"汇率公布日期":"2025-12-08","请求日期":"2025-12-08"},{"币种":"RUB","每单位外币折合人民币":0.09247015525739068,"汇率公布日期":"2025-12-08","请求日期":"2025-12-08"},{"币种":"ZAR","每单位外币折合人民币":0.4177109440267335,"汇率公布日期":"2025-12-08","请求日期":"2025-12-08"},{"币种":"KRW","每单位外币折合人民币":0.004805151122002787,"汇率公布日期":"2025-12-08","请求日期":"2025-12-08"},{"币种":"AED","每单位外币折合人民币":1.9258916878514751,"汇率公布日期":"2025-12-08","请求日期":"2025-12-08"},{"币种":"SAR","每单位外币折合人民币":1.8846233580218992,"汇率公布日期":"2025-12-08","请求日期":"2025-12-08"},{"币种":"HUF","每单位外币折合人民币":0.02158177117279661,"汇率公布日期":"2025-12-08","请求日期":"2025-12-08"},{"币种":"PLN","每单位外币折合人民币":1.947685176168124,"汇率公布日期":"2025-12-08","请求日期":"2025-12-08"},{"币种":"DKK","每单位外币折合人民币":1.102779003087781,"汇率公布日期":"2025-12-08","请求日期":"2025-12-08"},{"币种":"SEK","每单位外币折合人民币":0.7526153383005946,"汇率公布日期":"2025-12-08","请求日期":"2025-12-08"},{"币种":"NOK","每单位外币折合人民币":0.699741095794556,"汇率公布日期":"2025-12-08","请求日期":"2025-12-08"},{"币种":"TRY","每单位外币折合人民币":0.16623418073977533,"汇率公布日期":"2025-12-08","请求日期":"2025-12-08"},{"币种":"MXN","每单位外币折合人民币":0.3891959212267456,"汇率公布日期":"2025-12-08","请求日期":"2025-12-08"},{"币种":"THB","每单位外币折合人民币":0.22161647053609024,"汇率公布日期":"2025-12-08","请求日期":"2025-12-08"},{"币种":"CNY","每单位外币折合人民币":1.0,"汇率公布日期":"2025-12-08","请求日期":"2025-12-08"},{"币种":"USD","每单位外币折合人民币":7.0773,"汇率公布日期":"2025-12-09","请求日期":"2025-12-09"},{"币种":"EUR","每单位外币折合人民币":8.2372,"汇率公布日期":"2025-12-09","请求日期":"2025-12-09"},{"币种":"JPY","每单位外币折合人民币":0.045391,"汇率公布日期":"2025-12-09","请求日期":"2025-12-09"},{"币种":"HKD","每单位外币折合人民币":0.90981,"汇率公布日期":"2025-12-09","请求日期":"2025-12-09"},{"币种":"GBP","每单位外币折合人民币":9.4298,"汇率公布日期":"2025-12-09","请求日期":"2025-12-09"},{"币种":"AUD","每单位外币折合人民币":4.688,"汇率公布日期":"2025-12-09","请求日期":"2025-12-09"},{"币种":"NZD","每单位外币折合人民币":4.0869,"汇率公布日期":"2025-12-09","请求日期":"2025-12-09"},{"币种":"SGD","每单位外币折合人民币":5.453200000000001,"汇率公布日期":"2025-12-09","请求日期":"2025-12-09"},{"币种":"CHF","每单位外币折合人民币":8.7713,"汇率公布日期":"2025-12-09","请求日期":"2025-12-09"},{"币种":"CAD","每单位外币折合人民币":5.1092,"汇率公布日期":"2025-12-09","请求日期":"2025-12-09"},{"币种":"MOP","每单位外币折合人民币":0.8833141948591114,"汇率公布日期":"2025-12-09","请求日期":"2025-12-09"},{"币种":"MYR","每单位外币折合人民币":1.7194834671664634,"汇率公布日期":"2025-12-09","请求日期":"2025-12-09"},{"币种":"RUB","每单位外币折合人民币":0.0921871398939848,"汇率公布日期":"2025-12-09","请求日期":"2025-12-09"},{"币种":"ZAR","每单位外币折合人民币":0.4152651467962294,"汇率公布日期":"2025-12-09","请求日期":"2025-12-09"},{"币种":"KRW","每单位外币折合人民币":0.004812087964967999,"汇率公布日期":"2025-12-09","请求日期":"2025-12-09"},{"币种":"AED","每单位外币折合人民币":1.92648532018186,"汇率公布日期":"2025-12-09","请求日期":"2025-12-09"},{"币种":"SAR","每单位外币折合人民币":1.885333986915782,"汇率公布日期":"2025-12-09","请求日期":"2025-12-09"},{"币种":"HUF","每单位外币折合人民币":0.02141611948481383,"汇率公布日期":"2025-12-09","请求日期":"2025-12-09"},{"币种":"PLN","每单位外币折合人民币":1.94352127184032,"汇率公布日期":"2025-12-09","请求日期":"2025-12-09"},{"币种":"DKK","每单位外币折合人民币":1.102779003087781,"汇率公布日期":"2025-12-09","请求日期":"2025-12-09"},{"币种":"SEK","每单位外币折合人民币":0.7531821947729155,"汇率公布日期":"2025-12-09","请求日期":"2025-12-09"},{"币种":"NOK","每单位外币折合人民币":0.6989585517578808,"汇率公布日期":"2025-12-09","请求日期":"2025-12-09"},{"币种":"TRY","每单位外币折合人民币":0.166312144611736,"汇率公布日期":"2025-12-09","请求日期":"2025-12-09"},{"币种":"MXN","每单位外币折合人民币":0.3874016968194321,"汇率公布日期":"2025-12-09","请求日期":"2025-12-09"},{"币种":"THB","每单位外币折合人民币":0.22171965766484855,"汇率公布日期":"2025-12-09","请求日期":"2025-12-09"},{"币种":"CNY","每单位外币折合人民币":1.0,"汇率公布日期":"2025-12-09","请求日期":"2025-12-09"},{"币种":"USD","每单位外币折合人民币":7.0752999999999995,"汇率公布日期":"2025-12-10","请求日期":"2025-12-10"},{"币种":"EUR","每单位外币折合人民币":8.2258,"汇率公布日期":"2025-12-10","请求日期":"2025-12-10"},{"币种":"JPY","每单位外币折合人民币":0.045096,"汇率公布日期":"2025-12-10","请求日期":"2025-12-10"},{"币种":"HKD","每单位外币折合人民币":0.90928,"汇率公布日期":"2025-12-10","请求日期":"2025-12-10"},{"币种":"GBP","每单位外币折合人民币":9.4107,"汇率公布日期":"2025-12-10","请求日期":"2025-12-10"},{"币种":"AUD","每单位外币折合人民币":4.6973,"汇率公布日期":"2025-12-10","请求日期":"2025-12-10"},{"币种":"NZD","每单位外币折合人民币":4.0877,"汇率公布日期":"2025-12-10","请求日期":"2025-12-10"},{"币种":"SGD","每单位外币折合人民币":5.455,"汇率公布日期":"2025-12-10","请求日期":"2025-12-10"},{"币种":"CHF","每单位外币折合人民币":8.7759,"汇率公布日期":"2025-12-10","请求日期":"2025-12-10"},{"币种":"CAD","每单位外币折合人民币":5.1093,"汇率公布日期":"2025-12-10","请求日期":"2025-12-10"},{"币种":"MOP","每单位外币折合人民币":0.882223202470225,"汇率公布日期":"2025-12-10","请求日期":"2025-12-10"},{"币种":"MYR","每单位外币折合人民币":1.7188332559858368,"汇率公布日期":"2025-12-10","请求日期":"2025-12-10"},{"币种":"RUB","每单位外币折合人民币":0.09147791723078048,"汇率公布日期":"2025-12-10","请求日期":"2025-12-10"},{"币种":"ZAR","每单位外币折合人民币":0.4148861137617724,"汇率公布日期":"2025-12-10","请求日期":"2025-12-10"},{"币种":"KRW","每单位外币折合人民币":0.004810930433945925,"汇率公布日期":"2025-12-10","请求日期":"2025-12-10"},{"币种":"AED","每单位外币折合人民币":1.926114257097731,"汇率公布日期":"2025-12-10","请求日期":"2025-12-10"},{"币种":"SAR","每单位外币折合人民币":1.8850496710588325,"汇率公布日期":"2025-12-10","请求日期":"2025-12-10"},{"币种":"HUF","每单位外币折合人民币":0.021435997470552297,"汇率公布日期":"2025-12-10","请求日期":"2025-12-10"},{"币种":"PLN","每单位外币折合人民币":1.9453739008637456,"汇率公布日期":"2025-12-10","请求日期":"2025-12-10"},{"币种":"DKK","每单位外币折合人民币":1.1013215859030838,"汇率公布日期":"2025-12-10","请求日期":"2025-12-10"},{"币种":"SEK","每单位外币折合人民币":0.7558007709167863,"汇率公布日期":"2025-12-10","请求日期":"2025-12-10"},{"币种":"NOK","每单位外币折合人民币":0.6970584134950508,"汇率公布日期":"2025-12-10","请求日期":"2025-12-10"},{"币种":"TRY","每单位外币折合人民币":0.16623860226583215,"汇率公布日期":"2025-12-10","请求日期":"2025-12-10"},{"币种":"MXN","每单位外币折合人民币":0.3886664852889735,"汇率公布日期":"2025-12-10","请求日期":"2025-12-10"},{"币种":"THB","每单位外币折合人民币":0.22226173541963015,"汇率公布日期":"2025-12-10","请求日期":"2025-12-10"},{"币种":"CNY","每单位外币折合人民币":1.0,"汇率公布日期":"2025-12-10","请求日期":"2025-12-10"},{"币种":"USD","每单位外币折合人民币":7.0686,"汇率公布日期":"2025-12-11","请求日期":"2025-12-11"},{"币种":"EUR","每单位外币折合人民币":8.2593,"汇率公布日期":"2025-12-11","请求日期":"2025-12-11"},{"币种":"JPY","每单位外币折合人民币":0.045304,"汇率公布日期":"2025-12-11","请求日期":"2025-12-11"},{"币种":"HKD","每单位外币折合人民币":0.90862,"汇率公布日期":"2025-12-11","请求日期":"2025-12-11"},{"币种":"GBP","每单位外币折合人民币":9.4482,"汇率公布日期":"2025-12-11","请求日期":"2025-12-11"},{"币种":"AUD","每单位外币折合人民币":4.7084,"汇率公布日期":"2025-12-11","请求日期":"2025-12-11"},{"币种":"NZD","每单位外币折合人民币":4.1015,"汇率公布日期":"2025-12-11","请求日期":"2025-12-11"},{"币种":"SGD","每单位外币折合人民币":5.464600000000001,"汇率公布日期":"2025-12-11","请求日期":"2025-12-11"},{"币种":"CHF","每单位外币折合人民币":8.8282,"汇率公布日期":"2025-12-11","请求日期":"2025-12-11"},{"币种":"CAD","每单位外币折合人民币":5.1167,"汇率公布日期":"2025-12-11","请求日期":"2025-12-11"},{"币种":"MOP","每单位外币折合人民币":0.8820675663755844,"汇率公布日期":"2025-12-11","请求日期":"2025-12-11"},{"币种":"MYR","每单位外币折合人民币":1.7170034855170755,"汇率公布日期":"2025-12-11","请求日期":"2025-12-11"},{"币种":"RUB","每单位外币折合人民币":0.09008116312797831,"汇率公布日期":"2025-12-11","请求日期":"2025-12-11"},{"币种":"ZAR","每单位外币折合人民币":0.4169446297531688,"汇率公布日期":"2025-12-11","请求日期":"2025-12-11"},{"币种":"KRW","每单位外币折合人民币":0.004807230074031344,"汇率公布日期":"2025-12-11","请求日期":"2025-12-11"},{"币种":"AED","每单位外币折合人民币":1.921451079855507,"汇率公布日期":"2025-12-11","请求日期":"2025-12-11"},{"币种":"SAR","每单位外币折合人民币":1.880759826970096,"汇率公布日期":"2025-12-11","请求日期":"2025-12-11"},{"币种":"HUF","每单位外币折合人民币":0.02158885324329342,"汇率公布日期":"2025-12-11","请求日期":"2025-12-11"},{"币种":"PLN","每单位外币折合人民币":1.9550724354337328,"汇率公布日期":"2025-12-11","请求日期":"2025-12-11"},{"币种":"DKK","每单位外币折合人民币":1.105583195135434,"汇率公布日期":"2025-12-11","请求日期":"2025-12-11"},{"币种":"SEK","每单位外币折合人民币":0.7617306520414382,"汇率公布日期":"2025-12-11","请求日期":"2025-12-11"},{"币种":"NOK","每单位外币折合人民币":0.6995942353435007,"汇率公布日期":"2025-12-11","请求日期":"2025-12-11"},{"币种":"TRY","每单位外币折合人民币":0.1656375…[内容超出Excel单元格上限，完整明细见对应明细页]
A6: 汇率响应哈希 | B6: 6223c76d77d301342e20128834dd1ca6abd0b7a3777ffe6d1531296ed166284e
A7: 来源/识别方式 | B7: 程序内置牌价表（国家外汇管理局人民币汇率中间价，2022-11-28~2026-08-31，随程序打包；超期区间自动回落在线抓取）
A8: 汇率来源网址 | B8: https://www.safe.gov.cn/AppStructured/hlw/RMBQuery.do
A9: 汇率快照开始日 | B9: 2026-01-01

Sheet _source_trace
A1: 项目 | B1: 内容
A2: JE来源 | B2: C:\Users\lenovo\Downloads\审计工具箱\audit-toolbox-main\tauri-app\tests\fixtures\汇率损益测试集\用友\用友_序时账.xlsx
A3: TB来源 | B3: C:\Users\lenovo\Downloads\审计工具箱\audit-toolbox-main\tauri-app\tests\fixtures\汇率损益测试集\用友\用友_科目余额表.xlsx
A4: 汇率响应哈希 | B4: 6223c76d77d301342e20128834dd1ca6abd0b7a3777ffe6d1531296ed166284e

Sheet JE完整明细
A1: 源文件行号 | B1: 余额 | C1: 余额方向 | D1: 借方原币 | E1: 借方本位币 | F1: 凭证字号 | G1: 币种 | H1: 摘要 | I1: 日期 | J1: 汇率 | K1: 科目名称 | L1: 科目编码 | M1: 贷方原币 | N1: 贷方本位币
A2: 4 | B2: 1174400 | C2: 借 | D2: 120000 | E2: 854400 | F2: 记-0001 | G2: 美元 | H2: 出口销售-美国客户A | I2: 2026-01-05 | J2: 7.12 | K2: 应收账款-美元客户 | L2: 1122.02
A3: 5 | B3: 854400 | C3: 贷 | F3: 记-0001 | G3: 美元 | H3: 出口销售-美国客户A | I3: 2026-01-05 | J3: 7.12 | K3: 出口收入(美元) | L3: 6001.01 | M3: 120000 | N3: 854400
A4: 6 | B4: 1744000 | C4: 借 | D4: 80000 | E4: 569600 | F4: 记-0002 | G4: 美元 | H4: 出口销售-美国客户B | I4: 2026-01-06 | J4: 7.12 | K4: 应收账款-美元客户 | L4: 1122.02
A5: 7 | B5: 1424000 | C5: 贷 | F5: 记-0002 | G5: 美元 | H5: 出口销售-美国客户B | I5: 2026-01-06 | J5: 7.12 | K5: 出口收入(美元) | L5: 6001.01 | M5: 80000 | N5: 569600
A6: 8 | B6: 1086000 | C6: 借 | E6: 226000 | F6: 记-0003 | G6: 人民币 | H6: 内销商品收入(含税226,000.00) | I6: 2026-01-10 | K6: 应收账款-国内 | L6: 1122.01
A7: 9 | B7: 200000 | C7: 贷 | F7: 记-0003 | G7: 人民币 | H7: 内销商品收入(含税226,000.00) | I7: 2026-01-10 | K7: 内销收入(人民币) | L7: 6001.02 | N7: 200000
A8: 10 | B8: 26000 | C8: 贷 | F8: 记-0003 | G8: 人民币 | H8: 内销商品收入(含税226,000.00) | I8: 2026-01-10 | K8: 应交增值税-销项税额 | L8: 2221.02 | N8: 26000
A9: 11 | B9: 912000 | C9: 借 | D9: 100000 | E9: 712000 | F9: 记-0004 | G9: 美元 | H9: 收到美国客户A货款 | I9: 2026-01-12 | J9: 7.12 | K9: 美元户 | L9: 1002.02
A10: 12 | B10: 1032000 | C10: 借 | F10: 记-0004 | G10: 美元 | H10: 收到美国客户A货款 | I10: 2026-01-12 | J10: 7.12 | K10: 应收账款-美元客户 | L10: 1122.02 | M10: 100000 | N10: 712000
A11: 13 | B11: 60000 | C11: 借 | E11: 60000 | F11: 记-0005 | G11: 人民币 | H11: 发放本月职工薪酬 | I11: 2026-01-14 | K11: 管理费用-职工薪酬 | L11: 6602.03
A12: 14 | B12: 3440000 | C12: 借 | F12: 记-0005 | G12: 人民币 | H12: 发放本月职工薪酬 | I12: 2026-01-14 | K12: 人民币户 | L12: 1002.01 | N12: 60000
A13: 15 | B13: 8000 | C13: 借 | E13: 8000 | F13: 记-0006 | G13: 人民币 | H13: 报销办公费及差旅费 | I13: 2026-01-15 | K13: 管理费用-办公费 | L13: 6602.01
A14: 16 | B14: 15000 | C14: 借 | E14: 15000 | F14: 记-0006 | G14: 人民币 | H14: 报销办公费及差旅费 | I14: 2026-01-15 | K14: 管理费用-差旅费 | L14: 6602.02
A15: 17 | B15: 3417000 | C15: 借 | F15: 记-0006 | G15: 人民币 | H15: 报销办公费及差旅费 | I15: 2026-01-15 | K15: 人民币户 | L15: 1002.01 | N15: 23000
A16: 18 | B16: 1200 | C16: 借 | E16: 1200 | F16: 记-0007 | G16: 人民币 | H16: 支付银行手续费 | I16: 2026-01-16 | K16: 财务费用-手续费 | L16: 6603.01
A17: 19 | B17: 3415800 | C17: 借 | F17: 记-0007 | G17: 人民币 | H17: 支付银行手续费 | I17: 2026-01-16 | K17: 人民币户 | L17: 1002.01 | N17: 1200
A18: 20 | B18: 3027200 | C18: 借 | E18: 427200 | F18: 记-0008 | G18: 人民币 | H18: 进口采购-美元供应商 | I18: 2026-01-18 | K18: 库存商品 | L18: 1405
A19: 21 | B19: 607200 | C19: 贷 | F19: 记-0008 | G19: 美元 | H19: 进口采购-美元供应商 | I19: 2026-01-18 | J19: 7.12 | K19: 应付账款-美元供应商 | L19: 2202.02 | M19: 60000 | N19: 427200
A20: 22 | B20: 3327200 | C20: 借 | E20: 300000 | F20: 记-0009 | G20: 人民币 | H20: 国内采购商品入库 | I20: 2026-01-20 | K20: 库存商品 | L20: 1405
A21: 23 | B21: 39000 | C21: 借 | E21: 39000 | F21: 记-0009 | G21: 人民币 | H21: 国内采购商品入库 | I21: 2026-01-20 | K21: 应交增值税-进项税额 | L21: 2221.01
A22: 24 | B22: 979000 | C22: 贷 | F22: 记-0009 | G22: 人民币 | H22: 国内采购商品入库 | I22: 2026-01-20 | K22: 应付账款-国内 | L22: 2202.01 | N22: 339000
A23: 25 | B23: 251200 | C23: 贷 | D23: 50000 | E23: 356000 | F23: 记-0010 | G23: 美元 | H23: 支付美元供应商货款 | I23: 2026-01-22 | J23: 7.12 | K23: 应付账款-美元供应商 | L23: 2202.02
A24: 26 | B24: 556000 | C24: 借 | F24: 记-0010 | G24: 美元 | H24: 支付美元供应商货款 | I24: 2026-01-22 | J24: 7.12 | K24: 美元户 | L24: 1002.02 | M24: 50000 | N24: 356000
A25: 27 | B25: 36400 | C25: 借 | D25: 40000 | E25: 36400 | F25: 记-0011 | G25: 港币 | H25: 计提香港货代运费 | I25: 2026-01-23 | J25: 0.91 | K25: 运杂费(港币) | L25: 6601.02
A26: 28 | B26: 336400 | C26: 贷 | F26: 记-0011 | G26: 港币 | H26: 计提香港货代运费 | I26: 2026-01-23 | J26: 0.91 | K26: 应付账款-港币供应商 | L26: 2202.03 | M26: 40000 | N26: 36400
A27: 29 | B27: 300000 | C27: 贷 | D27: 40000 | E27: 36400 | F27: 记-0012 | G27: 港币 | H27: 支付香港货代运费 | I27: 2026-01-24 | J27: 0.91 | K27: 应付账款-港币供应商 | L27: 2202.03
A28: 30 | B28: 463600 | C28: 借 | F28: 记-0012 | G28: 港币 | H28: 支付香港货代运费 | I28: 2026-01-24 | J28: 0.91 | K28: 港币户 | L28: 1002.03 | M28: 40000 | N28: 36400
A29: 31 | B29: 3844800 | C29: 借 | E29: 429000 | F29: 记-0013 | G29: 人民币 | H29: 美元结汇 | I29: 2026-01-25 | K29: 人民币户 | L29: 1002.01
A30: 32 | B30: 128800 | C30: 借 | F30: 记-0013 | G30: 美元 | H30: 美元结汇 | I30: 2026-01-25 | J30: 7.12 | K30: 美元户 | L30: 1002.02 | M30: 60000 | N30: 427200
A31: 33 | B31: 1800 | C31: 贷 | F31: 记-0013 | G31: 人民币 | H31: 美元结汇 | I31: 2026-01-25 | K31: 财务费用-汇兑损益 | L31: 6603.02 | N31: 1800
A32: 34 | B32: 342400 | C32: 借 | D32: 30000 | E32: 213600 | F32: 记-0014 | G32: 美元 | H32: 购汇美元 | I32: 2026-01-26 | J32: 7.12 | K32: 美元户 | L32: 1002.02
A33: 35 | B33: 3630600 | C33: 借 | F33: 记-0014 | G33: 人民币 | H33: 购汇美元 | I33: 2026-01-26 | K33: 人民币户 | L33: 1002.01 | N33: 214200
A34: 36 | B34: 1200 | C34: 贷 | E34: 600 | F34: 记-0014 | G34: 人民币 | H34: 购汇美元 | I34: 2026-01-26 | K34: 财务费用-汇兑损益 | L34: 6603.02
A35: 37 | B35: 640000 | C35: 贷 | E35: 339000 | F35: 记-0015 | G35: 人民币 | H35: 支付本月国内供应商货款 | I35: 2026-01-27 | K35: 应付账款-国内 | L35: 2202.01
A36: 38 | B36: 3291600 | C36: 借 | F36: 记-0015 | G36: 人民币 | H36: 支付本月国内供应商货款 | I36: 2026-01-27 | K36: 人民币户 | L36: 1002.01 | N36: 339000
A37: 39 | B37: 800000 | C37: 借 | E37: 800000 | F37: 记-0016 | G37: 人民币 | H37: 结转本月销售成本 | I37: 2026-01-28 | K37: 主营业务成本 | L37: 6401
A38: 40 | B38: 2527200 | C38: 借 | F38: 记-0016 | G38: 人民币 | H38: 结转本月销售成本 | I38: 2026-01-28 | K38: 库存商品 | L38: 1405 | N38: 800000
A39: 41 | B39: 0 | C39: 平 | D39: 200000 | E39: 1424000 | F39: 记-0017 | G39: 美元 | H39: 月末损益结转 | I39: 2026-01-31 | J39: 7.12 | K39: 出口收入(美元) | L39: 6001.01
A40: 42 | B40: 0 | C40: 平 | E40: 200000 | F40: 记-0017 | G40: 人民币 | H40: 月末损益结转 | I40: 2026-01-31 | K40: 内销收入(人民币) | L40: 6001.02
A41: 43 | B41: 0 | C41: 平 | F41: 记-0017 | G41: 人民币 | H41: 月末损益结转 | I41: 2026-01-31 | K41: 主营业务成本 | L41: 6401 | N41: 800000
A42: 44 | B42: 0 | C42: 平 | F42: 记-0017 | G42: 港币 | H42: 月末损益结转 | I42: 2026-01-31 | J42: 0.91 | K42: 运杂费(港币) | L42: 6601.02 | M42: 40000 | N42: 36400
A43: 45 | B43: 0 | C43: 平 | F43: 记-0017 | G43: 人民币 | H43: 月末损益结转 | I43: 2026-01-31 | K43: 管理费用-办公费 | L43: 6602.01 | N43: 8000
A44: 46 | B44: 0 | C44: 平 | F44: 记-0017 | G44: 人民币 | H44: 月末损益结转 | I44: 2026-01-31 | K44: 管理费用-差旅费 | L44: 6602.02 | N44: 15000
A45: 47 | B45: 0 | C45: 平 | F45: 记-0017 | G45: 人民币 | H45: 月末损益结转 | I45: 2026-01-31 | K45: 管理费用-职工薪酬 | L45: 6602.03 | N45: 60000
A46: 48 | B46: 0 | C46: 平 | F46: 记-0017 | G46: 人民币 | H46: 月末损益结转 | I46: 2026-01-31 | K46: 财务费用-手续费 | L46: 6603.01 | N46: 1200
A47: 49 | B47: 0 | C47: 平 | E47: 1200 | F47: 记-0017 | G47: 人民币 | H47: 月末损益结转 | I47: 2026-01-31 | K47: 财务费用-汇兑损益 | L47: 6603.02
A48: 50 | B48: 704600 | C48: 贷 | F48: 记-0017 | G48: 人民币 | H48: 月末损益结转 | I48: 2026-01-31 | K48: 本年利润 | L48: 4103 | N48: 704600
A49: 51 | B49: 1601600 | C49: 借 | D49: 80000 | E49: 569600 | F49: 记-0018 | G49: 美元 | H49: 出口销售-美国客户A | I49: 2026-02-05 | J49: 7.12 | K49: 应收账款-美元客户 | L49: 1122.02
A50: 52 | B50: 569600 | C50: 贷 | F50: 记-0018 | G50: 美元 | H50: 出口销售-美国客户A | I50: 2026-02-05 | J50: 7.12 | K50: 出口收入(美元) | L50: 6001.01 | M50: 80000 | N50: 569600
A51: 53 | B51: 484800 | C51: 借 | D51: 20000 | E51: 142400 | F51: 记-0019 | G51: 美元 | H51: 收到美国客户B预收货款 | I51: 2026-02-08 | J51: 7.12 | K51: 美元户 | L51: 1002.02
A52: 54 | B52: 182400 | C52: 贷 | F52: 记-0019 | G52: 美元 | H52: 收到美国客户B预收货款 | I52: 2026-02-08 | J52: 7.12 | K52: 预收款项-美元 | L52: 2203.02 | M52: 20000 | N52: 142400
A53: 55 | B53: 71200 | C53: 借 | D53: 10000 | E53: 71200 | F53: 记-0020 | G53: 美元 | H53: 预付美元供应商货款 | I53: 2026-02-09 | J53: 7.12 | K53: 预付款项-美元 | L53: 1123.03
A54: 56 | B54: 413600 | C54: 借 | F54: 记-0020 | G54: 美元 | H54: 预付美元供应商货款 | I54: 2026-02-09 | J54: 7.12 | K54: 美元户 | L54: 1002.02 | M54: 10000 | N54: 71200
A55: 57 | B55: 3491600 | C55: 借 | E55: 200000 | F55: 记-0021 | G55: 人民币 | H55: 收到内销客户货款 | I55: 2026-02-10 | K55: 人民币户 | L55: 1002.01
A56: 58 | B56: 886000 | C56: 借 | F56: 记-0021 | G56: 人民币 | H56: 收到内销客户货款 | I56: 2026-02-10 | K56: 应收账款-国内 | L56: 1122.01 | N56: 200000
A57: 59 | B57: 1125600 | C57: 借 | D57: 100000 | E57: 712000 | F57: 记-0022 | G57: usd | H57: 收到美国客户A货款 | I57: 2026-02-12 | J57: 7.12 | K57: 美元户 | L57: 1002.02
A58: 60 | B58: 889600 | C58: 借 | F58: 记-0022 | G58: 美元 | H58: 收到美国客户A货款 | I58: 2026-02-12 | J58: 7.12 | K58: 应收账款-美元客户 | L58: 1122.02 | M58: 100000 | N58: 712000
A59: 61 | B59: 60000 | C59: 借 | E59: 60000 | F59: 记-0023 | G59: 人民币 | H59: 发放本月职工薪酬 | I59: 2026-02-14 | K59: 管理费用-职工薪酬 | L59: 6602.03
A60: 62 | B60: 3431600 | C60: 借 | F60: 记-0023 | G60: 人民币 | H60: 发放本月职工薪酬 | I60: 2026-02-14 | K60: 人民币户 | L60: 1002.01 | N60: 60000
A61: 63 | B61: 8000 | C61: 借 | E61: 8000 | F61: 记-0024 | G61: 人民币 | H61: 报销办公费及差旅费 | I61: 2026-02-15 | K61: 管理费用-办公费 | L61: 6602.01
A62: 64 | B62: 15000 | C62: 借 | E62: 15000 | F62: 记-0024 | G62: 人民币 | H62: 报销办公费及差旅费 | I62: 2026-02-15 | K62: 管理费用-差旅费 | L62: 6602.02
A63: 65 | B63: 3408600 | C63: 借 | F63: 记-0024 | G63: 人民币 | H63: 报销办公费及差旅费 | I63: 2026-02-15 | K63: 人民币户 | L63: 1002.01 | N63: 23000
A64: 66 | B64: 900 | C64: 借 | E64: 900 | F64: 记-0025 | G64: 人民币 | H64: 支付银行手续费 | I64: 2026-02-16 | K64: 财务费用-手续费 | L64: 6603.01
A65: 67 | B65: 3407700 | C65: 借 | F65: 记-0025 | G65: 人民币 | H65: 支付银行手续费 | I65: 2026-02-16 | K65: 人民币户 | L65: 1002.01 | N65: 900
A66: 68 | B66: 3603950 | C66: 借 | E66: 196250 | F66: 记-0026 | G66: 人民币 | H66: 收到欧元客户货款并结汇 | I66: 2026-02-17 | K66: 人民币户 | L66: 1002.01
A67: 69 | B67: 45750 | C67: 贷 | F67: 记-0026 | G67: 欧元 | H67: 收到欧元客户货款并结汇 | I67: 2026-02-17 | J67: 7.83 | K67: 应收账款-欧元客户 | L67: 1122.03 | M67: 25000 | N67: 195750
A68: 70 | B68: 500 | C68: 贷 | F68: 记-0026 | G68: 人民币 | H68: 收到欧元客户货款并结汇 | I68: 2026-02-17 | K68: 财务费用-汇兑损益 | L68: 6603.02 | N68: 500
A69: 71 | B69: 2812000 | C69: 借 | E69: 284800 | F69: 记-0027 | G69: 人民币 | H69: 进口采购-美元供应商 | I69: 2026-02-18 | K69: 库存商品 | L69: 1405
A70: 72 | B70: 536000 | C70: 贷 | F70: 记-0027 | G70: 美元 | H70: 进口采购-美元供应商 | I70: 2026-02-18 | J70: 7.12 | K70: 应付账款-美元供应商 | L70: 2202.02 | M70: 40000 | N70: 284800
A71: 73 | B71: 3072000 | C71: 借 | E71: 260000 | F71: 记-0028 | G71: 人民币 | H71: 国内采购商品入库 | I71: 2026-02-20 | K71: 库存商品 | L71: 1405
A72: 74 | B72: 72800 | C72: 借 | E72: 33800 | F72: 记-0028 | G72: 人民币 | H72: 国内采购商品入库 | I72: 2026-02-20 | K72: 应交增值税-进项税额 | L72: 2221.01
A73: 75 | B73: 933800 | C73: 贷 | F73: 记-0028 | G73: 人民币 | H73: 国内采购商品入库 | I73: 2026-02-20 | K73: 应付账款-国内 | L73: 2202.01 | N73: 293800
A74: 76 | B74: 322400 | C74: 贷 | D74: 30000 | E74: 213600 | F74: 记-0029 | G74: 美元 | H74: 支付美元供应商货款 | I74: 2026-02-22 | J74: 7.12 | K74: 应付账款-美元供应商 | L74: 2202.02
A75: 77 | B75: 912000 | C75: 借 | F75: 记-0029 | G75: 美元 | H75: 支付美元供应商货款 | I75: 2026-02-22 | J75: 7.12 | K75: 美元户 | L75: 1002.02 | M75: 30000 | N75: 213600
A76: 78 | B76: 27300 | C76: 借 | D76: 30000 | E76: 27300 | F76: 记-0030 | G76: 港币 | H76: 计提香港货代运费 | I76: 2026-02-23 | J76: 0.91 | K76: 运杂费(港币) | L76: 6601.02
A77: 79 | B77: 327300 | C77: 贷 | F77: 记-0030 | G77: 港币 | H77: 计提香港货代运费 | I77: 2026-02-23 | J77: 0.91 | K77: 应付账款-港币供应商 | L77: 2202.03 | M77: 30000 | N77: 27300
A78: 80 | B78: 300000 | C78: 贷 | D78: 30000 | E78: 27300 | F78: 记-0031 | G78: 港币 | H78: 支付香港货代运费 | I78: 2026-02-24 | J78: 0.91 | K78: 应付账款-港币供应商 | L78: 2202.03
A79: 81 | B79: 436300 | C79: 借 | F79: 记-0031 | G79: 港币 | H79: 支付香港货代运费 | I79: 2026-02-24 | J79: 0.91 | K79: 港币户 | L79: 1002.03 | M79: 30000 | N79: 27300
A80: 82 | B80: 3889550 | C80: 借 | E80: 285600 | F80: 记-0032 | G80: 人民币 | H80: 美元结汇 | I80: 2026-02-25 | K80: 人民币户 | L80: 1002.01
A81: 83 | B81: 627200 | C81: 借 | F81: 记-0032 | G81: 美元 | H81: 美元结汇 | I81: 2026-02-25 | J81: 7.12 | K81: 美元户 | L81: 1002.02 | M81: 40000 | N81: 284800
A82: 84 | B82: 1300 | C82: 贷 | F82: 记-0032 | G82: 人民币 | H82: 美元结汇 | I82: 2026-02-25 | K82: 财务费用-汇兑损益 | L82: 6603.02 | N82: 800
A83: 85 | B83: 640000 | C83: 贷 | E83: 293800 | F83: 记-0033 | G83: 人民币 | H83: 支付本月国内供应商货款 | I83: 2026-02-27 | K83: 应付账款-国内 | L83: 2202.01
A84: 86 | B84: 3595750 | C84: 借 | F84: 记-0033 | G84: 人民币 | H84: 支付本月国内供应商货款 | I84: 2026-02-27 | K84: 人民币户 | L84: 1002.01 | N84: 293800
A85: 87 | B85: 700000 | C85: 借 | E85: 700000 | F85: 记-0034 | G85: 人民币 | H85: 结转本月销售成本 | I85: 2026-02-28 | K85: 主营业务成本 | L85: 6401
A86: 88 | B86: 2372000 | C86: 借 | F86: 记-0034 | G86: 人民币 | H86: 结转本月销售成本 | I86: 2026-02-28 | K86: 库存商品 | L86: 1405 | N86: 700000
A87: 89 | B87: 6000 | C87: 借 | E87: 6000 | F87: 记-0035 | G87: 人民币 | H87: 支付国内运杂费 | I87: 2026-02-28 | K87: 运杂费(人民币) | L87: 6601.01
A88: 90 | B88: 3589750 | C88: 借 | F88: 记-0035 | G88: 人民币 | H88: 支付国内运杂费 | I88: 2026-02-28 | K88: 人民币户 | L88: 1002.01 | N88: 6000
A89: 91 | B89: 0 | C89: 平 | D89: 80000 | E89: 569600 | F89: 记-0036 | G89: 美元 | H89: 月末损益结转 | I89: 2026-02-28 | J89: 7.12 | K89: 出口收入(美元) | L89: 6001.01
A90: 92 | B90: 0 | C90: 平 | F90: 记-0036 | G90: 人民币 | H90: 月末损益结转 | I90: 2026-02-28 | K90: 主营业务成本 | L90: 6401 | N90: 700000
A91: 93 | B91: 0 | C91: 平 | F91: 记-0036 | G91: 人民币 | H91: 月末损益结转 | I91: 2026-02-28 | K91: 运杂费(人民币) | L91: 6601.01 | N91: 6000
A92: 94 | B92: 0 | C92: 平 | F92: 记-0036 | G92: 港币 | H92: 月末损益结转 | I92: 2026-02-28 | J92: 0.91 | K92: 运杂费(港币) | L92: 6601.02 | M92: 30000 | N92: 27300
A93: 95 | B93: 0 | C93: 平 | F93: 记-0036 | G93: 人民币 | H93: 月末损益结转 | I93: 2026-02-28 | K93: 管理费用-办公费 | L93: 6602.01 | N93: 8000
A94: 96 | B94: 0 | C94: 平 | F94: 记-0036 | G94: 人民币 | H94: 月末损益结转 | I94: 2026-02-28 | K94: 管理费用-差旅费 | L94: 6602.02 | N94: 15000
A95: 97 | B95: 0 | C95: 平 | F95: 记-0036 | G95: 人民币 | H95: 月末损益结转 | I95: 2026-02-28 | K95: 管理费用-职工薪酬 | L95: 6602.03 | N95: 60000
A96: 98 | B96: 0 | C96: 平 | F96: 记-0036 | G96: 人民币 | H96: 月末损益结转 | I96: 2026-02-28 | K96: 财务费用-手续费 | L96: 6603.01 | N96: 900
A97: 99 | B97: 0 | C97: 平 | E97: 1300 | F97: 记-0036 | G97: 人民币 | H97: 月末损益结转 | I97: 2026-02-28 | K97: 财务费用-汇兑损益 | L97: 6603.02
A98: 100 | B98: 458300 | C98: 贷 | E98: 246300 | F98: 记-0036 | G98: 人民币 | H98: 月末损益结转 | I98: 2026-02-28 | K98: 本年利润 | L98: 4103
A99: 101 | B99: 1744000 | C99: 借 | D99: 120000 | E99: 854400 | F99: 记-0037 | G99: 美元 | H99: 出口销售-美国客户A | I99: 2026-03-05 | J99: 7.12 | K99: 应收账款-美元客户 | L99: 1122.02
A100: 102 | B100: 854400 | C100: 贷 | F100: 记-0037 | G100: 美元 | H100: 出口销售-美国客户A | I100: 2026-03-05 | J100: 7.12 | K100: 出口收入(美元) | L100: 6001.01 | M100: 120000 | N100: 854400
...

Sheet 事件分类
A1: 分类 | B1: 置信度 | C1: 反向证据 | D1: 事件类型 | E1: 命中规则 | F1: 已实现得分 | G1: 规则冲突 | H1: 未实现得分 | I1: 凭证匹配ID
A2: 不构成汇兑事项 | B2: 高（结构判定） | D2: 初始确认 | E2: ["货币性资产或负债为增加方向，属于初始确认，不在确认日计算汇兑损益"] | G2: 否 | I2: 默认主体-2026-01-05-记-0001
A3: 不构成汇兑事项 | B3: 高（结构判定） | D3: 初始确认 | E3: ["货币性资产或负债为增加方向，属于初始确认，不在确认日计算汇兑损益"] | G3: 否 | I3: 默认主体-2026-01-06-记-0002
A4: 已实现 | B4: 高 | D4: 结算或兑换 | E4: ["已有货币性项目结清，或外币与本位币货币资金方向相反"] | G4: 否 | I4: 默认主体-2026-01-12-记-0004
A5: 不构成汇兑事项 | B5: 高（结构判定） | D5: 初始确认 | E5: ["货币性资产或负债为增加方向，属于初始确认，不在确认日计算汇兑损益"] | G5: 否 | I5: 默认主体-2026-01-18-记-0008
A6: 已实现 | B6: 高 | D6: 结算或兑换 | E6: ["已有货币性项目结清，或外币与本位币货币资金方向相反"] | G6: 否 | I6: 默认主体-2026-01-22-记-0010
A7: 不构成汇兑事项 | B7: 高（结构判定） | D7: 初始确认 | E7: ["货币性资产或负债为增加方向，属于初始确认，不在确认日计算汇兑损益"] | G7: 否 | I7: 默认主体-2026-01-23-记-0011
A8: 已实现 | B8: 高 | D8: 结算或兑换 | E8: ["已有货币性项目结清，或外币与本位币货币资金方向相反"] | G8: 否 | I8: 默认主体-2026-01-24-记-0012
A9: 已实现 | B9: 高 | D9: 结算或兑换 | E9: ["已有货币性项目结清，或外币与本位币货币资金方向相反"] | G9: 否 | I9: 默认主体-2026-01-25-记-0013
A10: 已实现 | B10: 高 | D10: 结算或兑换 | E10: ["已有货币性项目结清，或外币与本位币货币资金方向相反"] | G10: 否 | I10: 默认主体-2026-01-26-记-0014
A11: 不构成汇兑事项 | B11: 高 | C11: [] | D11: 期间损益结转 | E11: ["完整凭证含损益结转承接科目，属于期间结转而非汇兑事项"] | F11: 0 | G11: 否 | H11: 0 | I11: 默认主体-2026-01-31-记-0017
A12: 不构成汇兑事项 | B12: 高（结构判定） | D12: 初始确认 | E12: ["货币性资产或负债为增加方向，属于初始确认，不在确认日计算汇兑损益"] | G12: 否 | I12: 默认主体-2026-02-05-记-0018
A13: 不构成汇兑事项 | B13: 高（结构判定） | D13: 初始确认 | E13: ["货币性资产或负债为增加方向，属于初始确认，不在确认日计算汇兑损益"] | G13: 否 | I13: 默认主体-2026-02-08-记-0019
A14: 不构成汇兑事项 | B14: 高（结构判定） | D14: 非汇兑事项 | E14: ["货币性腿全为本位币或对手为非货币性项目：不构成外币汇兑事项"] | G14: 否 | I14: 默认主体-2026-02-09-记-0020
A15: 已实现 | B15: 高 | D15: 结算或兑换 | E15: ["已有货币性项目结清，或外币与本位币货币资金方向相反"] | G15: 否 | I15: 默认主体-2026-02-12-记-0022
A16: 已实现 | B16: 高 | D16: 结算或兑换 | E16: ["已有货币性项目结清，或外币与本位币货币资金方向相反"] | G16: 否 | I16: 默认主体-2026-02-17-记-0026
A17: 不构成汇兑事项 | B17: 高（结构判定） | D17: 初始确认 | E17: ["货币性资产或负债为增加方向，属于初始确认，不在确认日计算汇兑损益"] | G17: 否 | I17: 默认主体-2026-02-18-记-0027
A18: 已实现 | B18: 高 | D18: 结算或兑换 | E18: ["已有货币性项目结清，或外币与本位币货币资金方向相反"] | G18: 否 | I18: 默认主体-2026-02-22-记-0029
A19: 不构成汇兑事项 | B19: 高（结构判定） | D19: 初始确认 | E19: ["货币性资产或负债为增加方向，属于初始确认，不在确认日计算汇兑损益"] | G19: 否 | I19: 默认主体-2026-02-23-记-0030
A20: 已实现 | B20: 高 | D20: 结算或兑换 | E20: ["已有货币性项目结清，或外币与本位币货币资金方向相反"] | G20: 否 | I20: 默认主体-2026-02-24-记-0031
A21: 已实现 | B21: 高 | D21: 结算或兑换 | E21: ["已有货币性项目结清，或外币与本位币货币资金方向相反"] | G21: 否 | I21: 默认主体-2026-02-25-记-0032
A22: 不构成汇兑事项 | B22: 高 | C22: [] | D22: 期间损益结转 | E22: ["完整凭证含损益结转承接科目，属于期间结转而非汇兑事项"] | F22: 0 | G22: 否 | H22: 0 | I22: 默认主体-2026-02-28-记-0036
A23: 不构成汇兑事项 | B23: 高（结构判定） | D23: 初始确认 | E23: ["货币性资产或负债为增加方向，属于初始确认，不在确认日计算汇兑损益"] | G23: 否 | I23: 默认主体-2026-03-05-记-0037
A24: 不构成汇兑事项 | B24: 高（结构判定） | D24: 初始确认 | E24: ["货币性资产或负债为增加方向，属于初始确认，不在确认日计算汇兑损益"] | G24: 否 | I24: 默认主体-2026-03-06-记-0038
A25: 已实现 | B25: 高 | D25: 结算或兑换 | E25: ["已有货币性项目结清，或外币与本位币货币资金方向相反"] | G25: 否 | I25: 默认主体-2026-03-12-记-0040
A26: 不构成汇兑事项 | B26: 高（结构判定） | D26: 非汇兑事项 | E26: ["货币性腿全为本位币或对手为非货币性项目：不构成外币汇兑事项"] | G26: 否 | I26: 默认主体-2026-03-13-记-0041
A27: 不构成汇兑事项 | B27: 高（结构判定） | D27: 初始确认 | E27: ["货币性资产或负债为增加方向，属于初始确认，不在确认日计算汇兑损益"] | G27: 否 | I27: 默认主体-2026-03-18-记-0045
A28: 不构成汇兑事项 | B28: 高（结构判定） | D28: 非汇兑事项 | E28: ["货币性腿全为本位币或对手为非货币性项目：不构成外币汇兑事项"] | G28: 否 | I28: 默认主体-2026-03-19-记-0046
A29: 已实现 | B29: 高 | D29: 结算或兑换 | E29: ["已有货币性项目结清，或外币与本位币货币资金方向相反"] | G29: 否 | I29: 默认主体-2026-03-22-记-0048
A30: 不构成汇兑事项 | B30: 高（结构判定） | D30: 初始确认 | E30: ["货币性资产或负债为增加方向，属于初始确认，不在确认日计算汇兑损益"] | G30: 否 | I30: 默认主体-2026-03-23-记-0049
A31: 已实现 | B31: 高 | D31: 结算或兑换 | E31: ["已有货币性项目结清，或外币与本位币货币资金方向相反"] | G31: 否 | I31: 默认主体-2026-03-24-记-0050
A32: 已实现 | B32: 高 | D32: 结算或兑换 | E32: ["已有货币性项目结清，或外币与本位币货币资金方向相反"] | G32: 否 | I32: 默认主体-2026-03-25-记-0051
A33: 已实现 | B33: 高 | D33: 结算或兑换 | E33: ["已有货币性项目结清，或外币与本位币货币资金方向相反"] | G33: 否 | I33: 默认主体-2026-03-26-记-0052
A34: 不构成汇兑事项 | B34: 高 | C34: [] | D34: 期间损益结转 | E34: ["完整凭证含损益结转承接科目，属于期间结转而非汇兑事项"] | F34: 0 | G34: 否 | H34: 0 | I34: 默认主体-2026-03-31-记-0055
A35: 不构成汇兑事项 | B35: 高（结构判定） | D35: 初始确认 | E35: ["货币性资产或负债为增加方向，属于初始确认，不在确认日计算汇兑损益"] | G35: 否 | I35: 默认主体-2026-04-05-记-0056
A36: 不构成汇兑事项 | B36: 高（结构判定） | D36: 初始确认 | E36: ["货币性资产或负债为增加方向，属于初始确认，不在确认日计算汇兑损益"] | G36: 否 | I36: 默认主体-2026-04-06-记-0057
A37: 不构成汇兑事项 | B37: 高（结构判定） | D37: 非汇兑事项 | E37: ["货币性腿全为本位币或对手为非货币性项目：不构成外币汇兑事项"] | G37: 否 | I37: 默认主体-2026-04-11-记-0059
A38: 已实现 | B38: 高 | D38: 结算或兑换 | E38: ["已有货币性项目结清，或外币与本位币货币资金方向相反"] | G38: 否 | I38: 默认主体-2026-04-12-记-0060
A39: 已实现 | B39: 高 | D39: 结算或兑换 | E39: ["已有货币性项目结清，或外币与本位币货币资金方向相反"] | G39: 否 | I39: 默认主体-2026-04-17-记-0064
A40: 不构成汇兑事项 | B40: 高（结构判定） | D40: 初始确认 | E40: ["货币性资产或负债为增加方向，属于初始确认，不在确认日计算汇兑损益"] | G40: 否 | I40: 默认主体-2026-04-18-记-0065
A41: 已实现 | B41: 高 | D41: 结算或兑换 | E41: ["已有货币性项目结清，或外币与本位币货币资金方向相反"] | G41: 否 | I41: 默认主体-2026-04-22-记-0067
A42: 不构成汇兑事项 | B42: 高（结构判定） | D42: 初始确认 | E42: ["货币性资产或负债为增加方向，属于初始确认，不在确认日计算汇兑损益"] | G42: 否 | I42: 默认主体-2026-04-23-记-0068
A43: 已实现 | B43: 高 | D43: 结算或兑换 | E43: ["已有货币性项目结清，或外币与本位币货币资金方向相反"] | G43: 否 | I43: 默认主体-2026-04-24-记-0069
A44: 已实现 | B44: 高 | D44: 结算或兑换 | E44: ["已有货币性项目结清，或外币与本位币货币资金方向相反"] | G44: 否 | I44: 默认主体-2026-04-25-记-0070
A45: 已实现 | B45: 高 | D45: 结算或兑换 | E45: ["已有货币性项目结清，或外币与本位币货币资金方向相反"] | G45: 否 | I45: 默认主体-2026-04-26-记-0071
A46: 不构成汇兑事项 | B46: 高 | C46: [] | D46: 期间损益结转 | E46: ["完整凭证含损益结转承接科目，属于期间结转而非汇兑事项"] | F46: 0 | G46: 否 | H46: 0 | I46: 默认主体-2026-04-30-记-0074
A47: 不构成汇兑事项 | B47: 高（结构判定） | D47: 初始确认 | E47: ["货币性资产或负债为增加方向，属于初始确认，不在确认日计算汇兑损益"] | G47: 否 | I47: 默认主体-2026-05-05-记-0075
A48: 已实现 | B48: 高 | D48: 结算或兑换 | E48: ["已有货币性项目结清，或外币与本位币货币资金方向相反"] | G48: 否 | I48: 默认主体-2026-05-12-记-0077
A49: 不构成汇兑事项 | B49: 高（结构判定） | D49: 初始确认 | E49: ["货币性资产或负债为增加方向，属于初始确认，不在确认日计算汇兑损益"] | G49: 否 | I49: 默认主体-2026-05-18-记-0081
A50: 已实现 | B50: 高 | D50: 结算或兑换 | E50: ["已有货币性项目结清，或外币与本位币货币资金方向相反"] | G50: 否 | I50: 默认主体-2026-05-22-记-0083
A51: 已实现 | B51: 高 | D51: 结算或兑换 | E51: ["已有货币性项目结清，或外币与本位币货币资金方向相反"] | G51: 否 | I51: 默认主体-2026-05-25-记-0084
A52: 已实现 | B52: 高 | D52: 结算或兑换 | E52: ["已有货币性项目结清，或外币与本位币货币资金方向相反"] | G52: 否 | I52: 默认主体-2026-05-26-记-0085
A53: 已实现 | B53: 高 | D53: 结算或兑换 | E53: ["已有货币性项目结清，或外币与本位币货币资金方向相反"] | G53: 否 | I53: 默认主体-2026-05-26-记-0086
A54: 不构成汇兑事项 | B54: 高 | C54: [] | D54: 期间损益结转 | E54: ["完整凭证含损益结转承接科目，属于期间结转而非汇兑事项"] | F54: 0 | G54: 否 | H54: 0 | I54: 默认主体-2026-05-31-记-0090
A55: 不构成汇兑事项 | B55: 高（结构判定） | D55: 初始确认 | E55: ["货币性资产或负债为增加方向，属于初始确认，不在确认日计算汇兑损益"] | G55: 否 | I55: 默认主体-2026-06-05-记-0091
A56: 不构成汇兑事项 | B56: 高（结构判定） | D56: 初始确认 | E56: ["货币性资产或负债为增加方向，属于初始确认，不在确认日计算汇兑损益"] | G56: 否 | I56: 默认主体-2026-06-06-记-0092
A57: 已实现 | B57: 高 | D57: 结算或兑换 | E57: ["已有货币性项目结清，或外币与本位币货币资金方向相反"] | G57: 否 | I57: 默认主体-2026-06-12-记-0093
A58: 不构成汇兑事项 | B58: 高（结构判定） | D58: 非汇兑事项 | E58: ["货币性腿全为本位币或对手为非货币性项目：不构成外币汇兑事项"] | G58: 否 | I58: 默认主体-2026-06-13-记-0094
A59: 已实现 | B59: 高 | D59: 结算或兑换 | E59: ["已有货币性项目结清，或外币与本位币货币资金方向相反"] | G59: 否 | I59: 默认主体-2026-06-17-记-0098
A60: 不构成汇兑事项 | B60: 高（结构判定） | D60: 初始确认 | E60: ["货币性资产或负债为增加方向，属于初始确认，不在确认日计算汇兑损益"] | G60: 否 | I60: 默认主体-2026-06-18-记-0099
A61: 不构成汇兑事项 | B61: 高（结构判定） | D61: 非汇兑事项 | E61: ["货币性腿全为本位币或对手为非货币性项目：不构成外币汇兑事项"] | G61: 否 | I61: 默认主体-2026-06-19-记-0100
A62: 已实现 | B62: 高 | D62: 结算或兑换 | E62: ["已有货币性项目结清，或外币与本位币货币资金方向相反"] | G62: 否 | I62: 默认主体-2026-06-22-记-0102
A63: 不构成汇兑事项 | B63: 高（结构判定） | D63: 初始确认 | E63: ["货币性资产或负债为增加方向，属于初始确认，不在确认日计算汇兑损益"] | G63: 否 | I63: 默认主体-2026-06-23-记-0103
A64: 已实现 | B64: 高 | D64: 结算或兑换 | E64: ["已有货币性项目结清，或外币与本位币货币资金方向相反"] | G64: 否 | I64: 默认主体-2026-06-24-记-0104
A65: 已实现 | B65: 高 | D65: 结算或兑换 | E65: ["已有货币性项目结清，或外币与本位币货币资金方向相反"] | G65: 否 | I65: 默认主体-2026-06-25-记-0105
A66: 已实现 | B66: 高 | D66: 结算或兑换 | E66: ["已有货币性项目结清，或外币与本位币货币资金方向相反"] | G66: 否 | I66: 默认主体-2026-06-26-记-0106
A67: 不构成汇兑事项 | B67: 高 | C67: [] | D67: 期间损益结转 | E67: ["完整凭证含损益结转承接科目，属于期间结转而非汇兑事项"] | F67: 0 | G67: 否 | H67: 0 | I67: 默认主体-2026-06-30-记-0109
A68: 不构成汇兑事项 | B68: 待复核 | C68: ["对方科目为预付款、存货、固定资产等非货币性项目，不产生外币汇兑损益；账面汇差建议重分类复核"] | E68: ["非货币性项目/异常复核"] | F68: 0 | G68: 否 | H68: 0 | I68: 默认主体-2026-03-13-记-0041
A69: 不构成汇兑事项 | B69: 待复核 | C69: ["对方科目为预付款、存货、固定资产等非货币性项目，不产生外币汇兑损益；账面汇差建议重分类复核"] | E69: ["非货币性项目/异常复核"] | F69: 0 | G69: 否 | H69: 0 | I69: 默认主体-2026-06-13-记-0094

Sheet 已实现测算
A1: 科目 | B1: 测算采用央行中间价 | C1: 审计已实现汇兑损益 | D1: calculationMethod | E1: 审计基础与客户JE账面差异 | F1: 客户JE终止确认本位币账面（仅比对） | G1: 审计滚动本位币基础 | H1: 现金是否为必要条件 | I1: 币种 | J1: 客户隐含汇率 | K1: 客户隐含汇率反推依据 | L1: 客户隐含汇率取得状态 | M1: 客户隐含汇率来源行 | N1: 客户与审计月初汇率差 | O1: 客户与审计交易日汇率差 | P1: 日期 | Q1: 公司/核算主体 | R1: 本位币 | S1: 月初牌价（上月末） | T1: 月初牌价发布日期 | U1: 月初牌价是否口径回退 | V1: 官方汇率 | W1: 汇率公布日期 | X1: 汇率口径 | Y1: rateSource | Z1: 科目角色 | AA1: 结算原币金额 | AB1: 源文件行号 | AC1: targetForeignSigned | AD1: 审计结算本位币金额 | AE1: 凭证匹配ID
A2: 1122.02 应收账款-美元客户 | B2: 7.0108 | C2: 7101.5385 | D2: 已实现：滚动审计本位币基础与本次结算价值比较 | E2: -3818.4615 | F2: 712000 | G2: 708181.54 | H2: 否 | I2: USD | J2: 7.12 | K2: JE本位币金额÷原币金额反推 | L2: 反推 | M2: 12 | N2: 0.0912 | O2: 0.1092 | P2: 2026-01-12 | Q2: 默认主体 | R2: CNY | S2: 7.0288 | T2: 2025-12-31 | U2: 否 | V2: 7.0108 | W2: 2026-01-12 | X2: 交易日央行中间价 | Y2: 国家外汇管理局人民币汇率中间价查询（数据由中国外汇交易中心公布） | Z2: 货币性资产—非货币资金 | AA2: 100000 | AB2: 12 | AC2: -100000 | AD2: 701080 | AE2: 默认主体-2026-01-12-记-0004
A3: 2202.02 应付账款-美元供应商 | B3: 7.0019 | C3: -4502.5 | D3: 已实现：滚动审计本位币基础与本次结算价值比较 | E3: -1402.5 | F3: 356000 | G3: 354597.5 | H3: 否 | I3: USD | J3: 7.12 | K3: JE本位币金额÷原币金额反推 | L3: 反推 | M3: 25 | N3: 0.0912 | O3: 0.1181 | P3: 2026-01-22 | Q3: 默认主体 | R3: CNY | S3: 7.0288 | T3: 2025-12-31 | U3: 否 | V3: 7.0019 | W3: 2026-01-22 | X3: 交易日央行中间价 | Y3: 国家外汇管理局人民币汇率中间价查询（数据由中国外汇交易中心公布） | Z3: 货币性负债 | AA3: 50000 | AB3: 25 | AC3: 50000 | AD3: 350095 | AE3: 默认主体-2026-01-22-记-0010
A4: 2202.03 应付账款-港币供应商 | B4: 0.89676 | C4: -467.29412 | D4: 已实现：滚动审计本位币基础与本次结算价值比较 | E4: -62.305882 | F4: 36400 | G4: 36337.694 | H4: 否 | I4: HKD | J4: 0.91 | K4: JE本位币金额÷原币金额反推 | L4: 反推 | M4: 29 | N4: 0.00678 | O4: 0.01324 | P4: 2026-01-24 | Q4: 默认主体 | R4: CNY | S4: 0.90322 | T4: 2025-12-31 | U4: 否 | V4: 0.89676 | W4: 2026-01-23 | X4: 交易日央行中间价 | Y4: 国家外汇管理局人民币汇率中间价查询（数据由中国外汇交易中心公布） | Z4: 货币性负债 | AA4: 40000 | AB4: 29 | AC4: 40000 | AD4: 35870.4 | AE4: 默认主体-2026-01-24-记-0012
A5: 1002.02 美元户 | B5: 7.15 | C5: -3003.6 | D5: 已实现：滚动审计本位币基础与本次结算价值比较 | E5: -1203.6 | F5: 427200 | G5: 425996.4 | H5: 否 | I5: USD | J5: 7.12 | K5: JE本位币金额÷原币金额反推 | L5: 反推 | M5: 32 | N5: 0.0912 | O5: 0.1271 | P5: 2026-01-25 | Q5: 默认主体 | R5: CNY | S5: 7.0288 | T5: 2025-12-31 | U5: 否 | V5: 6.9929 | W5: 2026-01-23 | X5: 实际人民币收付金额 | Y5: 国家外汇管理局人民币汇率中间价查询（数据由中国外汇交易中心公布） | Z5: 货币性资产—货币资金 | AA5: 60000 | AB5: 32 | AC5: -60000 | AD5: 429000 | AE5: 默认主体-2026-01-25-记-0013
A6: 1002.02 美元户 | B6: 6.9843 | C6: 4671 | D6: 购汇：实际支付本位币减去交易日官方牌价折算额 | F6: 213600 | G6: 209529 | H6: 是 | I6: USD | P6: 2026-01-26 | Q6: 默认主体 | R6: CNY | V6: 6.9843 | W6: 2026-01-26 | X6: 交易日央行中间价 | Y6: 国家外汇管理局人民币汇率中间价查询（数据由中国外汇交易中心公布） | Z6: 货币性资产—货币资金 | AA6: 30000 | AB6: 34 | AC6: 30000 | AD6: 209529 | AE6: 默认主体-2026-01-26-记-0014
A7: 1122.02 应收账款-美元客户 | B7: 6.9457 | C7: 2037.2 | D7: 已实现：滚动审计本位币基础与本次结算价值比较 | E7: -15392.8 | F7: 712000 | G7: 696607.2 | H7: 否 | I7: USD | J7: 7.12 | K7: JE本位币金额÷原币金额反推 | L7: 反推 | M7: 60 | N7: 0.1522 | O7: 0.1743 | P7: 2026-02-12 | Q7: 默认主体 | R7: CNY | S7: 6.9678 | T7: 2026-01-30 | U7: 否 | V7: 6.9457 | W7: 2026-02-12 | X7: 交易日央行中间价 | Y7: 国家外汇管理局人民币汇率中间价查询（数据由中国外汇交易中心公布） | Z7: 货币性资产—非货币资金 | AA7: 100000 | AB7: 60 | AC7: -100000 | AD7: 694570 | AE7: 默认主体-2026-02-12-记-0022
A8: 1122.03 应收账款-欧元客户 | B8: 7.85 | C8: 11860 | D8: 已实现：滚动审计本位币基础与本次结算价值比较 | E8: 12360 | F8: 195750 | G8: 208110 | H8: 否 | I8: EUR | J8: 7.83 | K8: JE本位币金额÷原币金额反推 | L8: 反推 | M8: 69 | N8: -0.4944 | O8: -0.3895 | P8: 2026-02-17 | Q8: 默认主体 | R8: CNY | S8: 8.3244 | T8: 2026-01-30 | U8: 否 | V8: 8.2195 | W8: 2026-02-13 | X8: 实际人民币收付金额 | Y8: 国家外汇管理局人民币汇率中间价查询（数据由中国外汇交易中心公布） | Z8: 货币性资产—非货币资金 | AA8: 25000 | AB8: 69 | AC8: -25000 | AD8: 196250 | AE8: 默认主体-2026-02-17-记-0026
A9: 2202.02 应付账款-美元供应商 | B9: 6.9398 | C9: -693.91304 | D9: 已实现：滚动审计本位币基础与本次结算价值比较 | E9: -4712.087 | F9: 213600 | G9: 208887.91 | H9: 否 | I9: USD | J9: 7.12 | K9: JE本位币金额÷原币金额反推 | L9: 反推 | M9: 76 | N9: 0.1522 | O9: 0.1802 | P9: 2026-02-22 | Q9: 默认主体 | R9: CNY | S9: 6.9678 | T9: 2026-01-30 | U9: 否 | V9: 6.9398 | W9: 2026-02-13 | X9: 交易日央行中间价 | Y9: 国家外汇管理局人民币汇率中间价查询（数据由中国外汇交易中心公布） | Z9: 货币性负债 | AA9: 30000 | AB9: 76 | AC9: 30000 | AD9: 208194 | AE9: 默认主体-2026-02-22-记-0029
A10: 2202.03 应付账款-港币供应商 | B10: 0.88773 | C10: -133.74545 | D10: 已实现：滚动审计本位币基础与本次结算价值比较 | E10: -534.35455 | F10: 27300 | G10: 26765.645 | H10: 否 | I10: HKD | J10: 0.91 | K10: JE本位币金额÷原币金额反推 | L10: 反推 | M10: 80 | N10: 0.01738 | O10: 0.02227 | P10: 2026-02-24 | Q10: 默认主体 | R10: CNY | S10: 0.89262 | T10: 2026-01-30 | U10: 否 | V10: 0.88773 | W10: 2026-02-24 | X10: 交易日央行中间价 | Y10: 国家外汇管理局人民币汇率中间价查询（数据由中国外汇交易中心公布） | Z10: 货币性负债 | AA10: 30000 | AB10: 80 | AC10: 30000 | AD10: 26631.9 | AE10: 默认主体-2026-02-24-记-0031
A11: 1002.02 美元户 | B11: 7.14 | C11: -7073.4667 | D11: 已实现：滚动审计本位币基础与本次结算价值比较 | E11: -6273.4667 | F11: 284800 | G11: 278526.53 | H11: 否 | I11: USD | J11: 7.12 | K11: JE本位币金额÷原币金额反推 | L11: 反推 | M11: 83 | N11: 0.1522 | O11: 0.1879 | P11: 2026-02-25 | Q11: 默认主体 | R11: CNY | S11: 6.9678 | T11: 2026-01-30 | U11: 否 | V11: 6.9321 | W11: 2026-02-25 | X11: 实际人民币收付金额 | Y11: 国家外汇管理局人民币汇率中间价查询（数据由中国外汇交易中心公布） | Z11: 货币性资产—货币资金 | AA11: 40000 | AB11: 83 | AC11: -40000 | AD11: 285600 | AE11: 默认主体-2026-02-25-记-0032
A12: 1122.02 应收账款-美元客户 | B12: 6.8959 | C12: 2372.8 | D12: 已实现：滚动审计本位币基础与本次结算价值比较 | E12: -24519.2 | F12: 854400 | G12: 829880.8 | H12: 否 | I12: USD | J12: 7.12 | K12: JE本位币金额÷原币金额反推 | L12: 反推 | M12: 109 | N12: 0.1972 | O12: 0.2241 | P12: 2026-03-12 | Q12: 默认主体 | R12: CNY | S12: 6.9228 | T12: 2026-02-27 | U12: 否 | V12: 6.8959 | W12: 2026-03-12 | X12: 交易日央行中间价 | Y12: 国家外汇管理局人民币汇率中间价查询（数据由中国外汇交易中心公布） | Z12: 货币性资产—非货币资金 | AA12: 120000 | AB12: 109 | AC12: -120000 | AD12: 827508 | AE12: 默认主体-2026-03-12-记-0040
A13: 2202.02 应付账款-美元供应商 | B13: 6.8898 | C13: -1281.9231 | D13: 已实现：滚动审计本位币基础与本次结算价值比较 | E13: -10228.077 | F13: 356000 | G13: 345771.92 | H13: 否 | I13: USD | J13: 7.12 | K13: JE本位币金额÷原币金额反推 | L13: 反推 | M13: 127 | N13: 0.1972 | O13: 0.2302 | P13: 2026-03-22 | Q13: 默认主体 | R13: CNY | S13: 6.9228 | T13: 2026-02-27 | U13: 否 | V13: 6.8898 | W13: 2026-03-20 | X13: 交易日央行中间价 | Y13: 国家外汇管理局人民币汇率中间价查询（数据由中国外汇交易中心公布） | Z13: 货币性负债 | AA13: 50000 | AB13: 127 | AC13: 50000 | AD13: 344490 | AE13: 默认主体-2026-03-22-记-0048
A14: 2202.03 应付账款-港币供应商 | B14: 0.88015 | C14: -170.18824 | D14: 已实现：滚动审计本位币基础与本次结算价值比较 | E14: -1023.8118 | F14: 36400 | G14: 35376.188 | H14: 否 | I14: HKD | J14: 0.91 | K14: JE本位币金额÷原币金额反推 | L14: 反推 | M14: 131 | N14: 0.02516 | O14: 0.02985 | P14: 2026-03-24 | Q14: 默认主体 | R14: CNY | S14: 0.88484 | T14: 2026-02-27 | U14: 否 | V14: 0.88015 | W14: 2026-03-24 | X14: 交易日央行中间价 | Y14: 国家外汇管理局人民币汇率中间价查询（数据由中国外汇交易中心公布） | Z14: 货币性负债 | AA14: 40000 | AB14: 131 | AC14: 40000 | AD14: 35206 | AE14: 默认主体-2026-03-24-记-0050
A15: 1002.02 美元户 | B15: 7.15 | C15: -13918.909 | D15: 已实现：滚动审计本位币基础与本次结算价值比较 | E15: -12118.909 | F15: 427200 | G15: 415081.09 | H15: 否 | I15: USD | J15: 7.12 | K15: JE本位币金额÷原币金额反推 | L15: 反推 | M15: 134 | N15: 0.1972 | O15: 0.2289 | P15: 2026-03-25 | Q15: 默认主体 | R15: CNY | S15: 6.9228 | T15: 2026-02-27 | U15: 否 | V15: 6.8911 | W15: 2026-03-25 | X15: 实际人民币收付金额 | Y15: 国家外汇管理局人民币汇率中间价查询（数据由中国外汇交易中心公布） | Z15: 货币性资产—货币资金 | AA15: 60000 | AB15: 134 | AC15: -60000 | AD15: 429000 | AE15: 默认主体-2026-03-25-记-0051
A16: 1002.02 美元户 | B16: 6.9056 | C16: 7032 | D16: 购汇：实际支付本位币减去交易日官方牌价折算额 | F16: 213600 | G16: 207168 | H16: 是 | I16: USD | P16: 2026-03-26 | Q16: 默认主体 | R16: CNY | V16: 6.9056 | W16: 2026-03-26 | X16: 交易日央行中间价 | Y16: 国家外汇管理局人民币汇率中间价查询（数据由中国外汇交易中心公布） | Z16: 货币性资产—货币资金 | AA16: 30000 | AB16: 136 | AC16: 30000 | AD16: 207168 | AE16: 默认主体-2026-03-26-记-0052
A17: 1122.02 应收账款-美元客户 | B17: 6.8654 | C17: 7307.4286 | D17: 已实现：滚动审计本位币基础与本次结算价值比较 | E17: -33428.571 | F17: 1139200 | G17: 1105771.4 | H17: 否 | I17: USD | J17: 7.12 | K17: JE本位币金额÷原币金额反推 | L17: 反推 | M17: 161 | N17: 0.2006 | O17: 0.2546 | P17: 2026-04-12 | Q17: 默认主体 | R17: CNY | S17: 6.9194 | T17: 2026-03-31 | U17: 否 | V17: 6.8654 | W17: 2026-04-10 | X17: 交易日央行中间价 | Y17: 国家外汇管理局人民币汇率中间价查询（数据由中国外汇交易中心公布） | Z17: 货币性资产—非货币资金 | AA17: 160000 | AB17: 161 | AC17: -160000 | AD17: 1098464 | AE17: 默认主体-2026-04-12-记-0060
A18: 1122.03 应收账款-欧元客户 | B18: 7.87 | C18: 1505 | D18: 已实现：滚动审计本位币基础与本次结算价值比较 | E18: 2505 | F18: 195750 | G18: 198255 | H18: 否 | I18: EUR | J18: 7.83 | K18: JE本位币金额÷原币金额反推 | L18: 反推 | M18: 170 | N18: -0.1002 | O18: -0.2318 | P18: 2026-04-17 | Q18: 默认主体 | R18: CNY | S18: 7.9302 | T18: 2026-03-31 | U18: 否 | V18: 8.0618 | W18: 2026-04-17 | X18: 实际人民币收付金额 | Y18: 国家外汇管理局人民币汇率中间价查询（数据由中国外汇交易中心公布） | Z18: 货币性资产—非货币资金 | AA18: 25000 | AB18: 170 | AC18: -25000 | AD18: 196750 | AE18: 默认主体-2026-04-17-记-0064
A19: 2202.02 应付账款-美元供应商 | B19: 6.8635 | C19: -2159.4444 | D19: 已实现：滚动审计本位币基础与本次结算价值比较 | E19: -10665.556 | F19: 356000 | G19: 345334.44 | H19: 否 | I19: USD | J19: 7.12 | K19: JE本位币金额÷原币金额反推 | L19: 反推 | M19: 177 | N19: 0.2006 | O19: 0.2565 | P19: 2026-04-22 | Q19: 默认主体 | R19: CNY | S19: 6.9194 | T19: 2026-03-31 | U19: 否 | V19: 6.8635 | W19: 2026-04-22 | X19: 交易日央行中间价 | Y19: 国家外汇管理局人民币汇率中间价查询（数据由中国外汇交易中心公布） | Z19: 货币性负债 | AA19: 50000 | AB19: 177 | AC19: 50000 | AD19: 343175 | AE19: 默认主体-2026-04-22-记-0067
A20: 2202.03 应付账款-港币供应商 | B20: 0.87666 | C20: -221.15294 | D20: 已实现：滚动审计本位币基础与本次结算价值比较 | E20: -1112.4471 | F20: 36400 | G20: 35287.553 | H20: 否 | I20: HKD | J20: 0.91 | K20: JE本位币金额÷原币金额反推 | L20: 反推 | M20: 181 | N20: 0.02705 | O20: 0.03334 | P20: 2026-04-24 | Q20: 默认主体 | R20: CNY | S20: 0.88295 | T20: 2026-03-31 | U20: 否 | V20: 0.87666 | W20: 2026-04-24 | X20: 交易日央行中间价 | Y20: 国家外汇管理局人民币汇率中间价查询（数据由中国外汇交易中心公布） | Z20: 货币性负债 | AA20: 40000 | AB20: 181 | AC20: 40000 | AD20: 35066.4 | AE20: 默认主体-2026-04-24-记-0069
A21: 1002.02 美元户 | B21: 7.16 | C21: -15291.366 | D21: 已实现：滚动审计本位币基础与本次结算价值比较 | E21: -12891.366 | F21: 427200 | G21: 414308.63 | H21: 否 | I21: USD | J21: 7.12 | K21: JE本位币金额÷原币金额反推 | L21: 反推 | M21: 184 | N21: 0.2006 | O21: 0.2526 | P21: 2026-04-25 | Q21: 默认主体 | R21: CNY | S21: 6.9194 | T21: 2026-03-31 | U21: 否 | V21: 6.8674 | W21: 2026-04-24 | X21: 实际人民币收付金额 | Y21: 国家外汇管理局人民币汇率中间价查询（数据由中国外汇交易中心公布） | Z21: 货币性资产—货币资金 | AA21: 60000 | AB21: 184 | AC21: -60000 | AD21: 429600 | AE21: 默认主体-2026-04-25-记-0070
A22: 1002.02 美元户 | B22: 6.8674 | C22: 8478 | D22: 购汇：实际支付本位币减去交易日官方牌价折算额 | F22: 213600 | G22: 206022 | H22: 是 | I22: USD | P22: 2026-04-26 | Q22: 默认主体 | R22: CNY | V22: 6.8674 | W22: 2026-04-24 | X22: 交易日央行中间价 | Y22: 国家外汇管理局人民币汇率中间价查询（数据由中国外汇交易中心公布） | Z22: 货币性资产—货币资金 | AA22: 30000 | AB22: 186 | AC22: 30000 | AD22: 206022 | AE22: 默认主体-2026-04-26-记-0071
A23: 1122.02 应收账款-美元客户 | B23: 6.8426 | C23: 3232 | D23: 已实现：滚动审计本位币基础与本次结算价值比较 | E23: -41152 | F23: 1139200 | G23: 1098048 | H23: 否 | I23: USD | J23: 7.12 | K23: JE本位币金额÷原币金额反推 | L23: 反推 | M23: 208 | N23: 0.2572 | O23: 0.2774 | P23: 2026-05-12 | Q23: 默认主体 | R23: CNY | S23: 6.8628 | T23: 2026-04-30 | U23: 否 | V23: 6.8426 | W23: 2026-05-12 | X23: 交易日央行中间价 | Y23: 国家外汇管理局人民币汇率中间价查询（数据由中国外汇交易中心公布） | Z23: 货币性资产—非货币资金 | AA23: 160000 | AB23: 208 | AC23: -160000 | AD23: 1094816 | AE23: 默认主体-2026-05-12-记-0077
A24: 2202.02 应付账款-美元供应商 | B24: 6.8373 | C24: -1250.4828 | D24: 已实现：滚动审计本位币基础与本次结算价值比较 | E24: -15711.517 | F24: 427200 | G24: 411488.48 | H24: 否 | I24: USD | J24: 7.12 | K24: JE本位币金额÷原币金额反推 | L24: 反推 | M24: 221 | N24: 0.2572 | O24: 0.2827 | P24: 2026-05-22 | Q24: 默认主体 | R24: CNY | S24: 6.8628 | T24: 2026-04-30 | U24: 否 | V24: 6.8373 | W24: 2026-05-22 | X24: 交易日央行中间价 | Y24: 国家外汇管理局人民币汇率中间价查询（数据由中国外汇交易中心公布） | Z24: 货币性负债 | AA24: 60000 | AB24: 221 | AC24: 60000 | AD24: 410238 | AE24: 默认主体-2026-05-22-记-0083
A25: 1002.02 美元户 | B25: 7.15 | C25: -20352.208 | D25: 已实现：滚动审计本位币基础与本次结算价值比较 | E25: -18252.208 | F25: 498400 | G25: 480147.79 | H25: 否 | I25: USD | J25: 7.12 | K25: JE本位币金额÷原币金额反推 | L25: 反推 | M25: 224 | N25: 0.2572 | O25: 0.2882 | P25: 2026-05-25 | Q25: 默认主体 | R25: CNY | S25: 6.8628 | T25: 2026-04-30 | U25: 否 | V25: 6.8318 | W25: 2026-05-25 | X25: 实际人民币收付金额 | Y25: 国家外汇管理局人民币汇率中间价查询（数据由中国外汇交易中心公布） | Z25: 货币性资产—货币资金 | AA25: 70000 | AB25: 224 | AC25: -70000 | AD25: 500500 | AE25: 默认主体-2026-05-25-记-0084
A26: 1002.02 美元户 | B26: 6.8288 | C26: 9336 | D26: 购汇：实际支付本位币减去交易日官方牌价折算额 | F26: 213600 | G26: 204864 | H26: 是 | I26: USD | P26: 2026-05-26 | Q26: 默认主体 | R26: CNY | V26: 6.8288 | W26: 2026-05-26 | X26: 交易日央行中间价 | Y26: 国家外汇管理局人民币汇率中间价查询（数据由中国外汇交易中心公布） | Z26: 货币性资产—货币资金 | AA26: 30000 | AB26: 226 | AC26: 30000 | AD26: 204864 | AE26: 默认主体-2026-05-26-记-0085
A27: 1002.03 港币户 | B27: 0.87155 | C27: 3796 | D27: 购汇：实际支付本位币减去交易日官方牌价折算额 | F27: 72800 | G27: 69724 | H27: 是 | I27: HKD | P27: 2026-05-26 | Q27: 默认主体 | R27: CNY | V27: 0.87155 | W27: 2026-05-26 | X27: 交易日央行中间价 | Y27: 国家外汇管理局人民币汇率中间价查询（数据由中国外汇交易中心公布） | Z27: 货币性资产—货币资金 | AA27: 80000 | AB27: 229 | AC27: 80000 | AD27: 69724 | AE27: 默认主体-2026-05-26-记-0086
A28: 1122.02 应收账款-美元客户 | B28: 6.8109 | C28: 1093.443 | D28: 已实现：滚动审计本位币基础与本次结算价值比较 | E28: -54544.557 | F28: 1281600 | G28: 1227055.4 | H28: 否 | I28: USD | J28: 7.12 | K28: JE本位币金额÷原币金额反推 | L28: 反推 | M28: 253 | N28: 0.3024 | O28: 0.3091 | P28: 2026-06-12 | Q28: 默认主体 | R28: CNY | S28: 6.8176 | T28: 2026-05-29 | U28: 否 | V28: 6.8109 | W28: 2026-06-12 | X28: 交易日央行中间价 | Y28: 国家外汇管理局人民币汇率中间价查询（数据由中国外汇交易中心公布） | Z28: 货币性资产—非货币资金 | AA28: 180000 | AB28: 253 | AC28: -180000 | AD28: 1225962 | AE28: 默认主体-2026-06-12-记-0093
A29: 1122.03 应收账款-欧元客户 | B29: 7.86 | C29: 1400 | D29: 已实现：滚动审计本位币基础与本次结算价值比较 | E29: 2150 | F29: 195750 | G29: 197900 | H29: 否 | I29: EUR | J29: 7.83 | K29: JE本位币金额÷原币金额反推 | L29: 反推 | M29: 265 | N29: -0.086 | O29: -0.0476 | P29: 2026-06-17 | Q29: 默认主体 | R29: CNY | S29: 7.916 | T29: 2026-05-29 | U29: 否 | V29: 7.8776 | W29: 2026-06-17 | X29: 实际人民币收付金额 | Y29: 国家外汇管理局人民币汇率中间价查询（数据由中国外汇交易中心公布） | Z29: 货币性资产—非货币资金 | AA29: 25000 | AB29: 265 | AC29: -25000 | AD29: 196500 | AE29: 默认主体-2026-06-17-记-0098
A30: 2202.02 应付账款-美元供应商 | B30: 6.815 | C30: -91.6 | D30: 已实现：滚动审计本位币基础与本次结算价值比较 | E30: -18208.4 | F30: 427200 | G30: 408991.6 | H30: 否 | I30: USD | J30: 7.12 | K30: JE本位币金额÷原币金额反推 | L30: 反推 | M30: 274 | N30: 0.3024 | O30: 0.305 | P30: 2026-06-22 | Q30: 默认主体 | R30: CNY | S30: 6.8176 | T30: 2026-05-29 | U30: 否 | V30: 6.815 | W30: 2026-06-22 | X30: 交易日央行中间价 | Y30: 国家外汇管理局人民币汇率中间价查询（数据由中国外汇交易中心公布） | Z30: 货币性负债 | AA30: 60000 | AB30: 274 | AC30: 60000 | AD30: 408900 | AE30: 默认主体-2026-06-22-记-0102
A31: 2202.03 应付账款-港币供应商 | B31: 0.86975 | C31: -19.83913 | D31: 已实现：滚动审计本位币基础与本次结算价值比较 | E31: -1791.4109 | F31: 40950 | G31: 39158.589 | H31: 否 | I31: HKD | J31: 0.91 | K31: JE本位币金额÷原币金额反推 | L31: 反推 | M31: 278 | N31: 0.03971 | O31: 0.04025 | P31: 2026-06-24 | Q31: 默认主体 | R31: CNY | S31: 0.87029 | T31: 2026-05-29 | U31: 否 | V31: 0.86975 | W31: 2026-06-24 | X31: 交易日央行中间价 | Y31: 国家外汇管理局人民币汇率中间价查询（数据由中国外汇交易中心公布） | Z31: 货币性负债 | AA31: 45000 | AB31: 278 | AC31: 45000 | AD31: 39138.75 | AE31: 默认主体-2026-06-24-记-0104
A32: 1002.02 美元户 | B32: 7.17 | C32: -24799.25 | D32: 已实现：滚动审计本位币基础与本次结算价值比较 | E32: -21299.25 | F32: 498400 | G32: 477100.75 | H32: 否 | I32: USD | J32: 7.12 | K32: JE本位币金额÷原币金额反推 | L32: 反推 | M32: 281 | N32: 0.3024 | O32: 0.2991 | P32: 2026-06-25 | Q32: 默认主体 | R32: CNY | S32: 6.8176 | T32: 2026-05-29 | U32: 否 | V32: 6.8209 | W32: 2026-06-25 | X32: 实际人民币收付金额 | Y32: 国家外汇管理局人民币汇率中间价查询（数据由中国外汇交易中心公布） | Z32: 货币性资产—货币资金 | AA32: 70000 | AB32: 281 | AC32: -70000 | AD32: 501900 | AE32: 默认主体-2026-06-25-记-0105
A33: 1002.02 美元户 | B33: 6.8166 | C33: 10002 | D33: 购汇：实际支付本位币减去交易日官方牌价折算额 | F33: 213600 | G33: 204498 | H33: 是 | I33: USD | P33: 2026-06-26 | Q33: 默认主体 | R33: CNY | V33: 6.8166 | W33: 2026-06-26 | X33: 交易日央行中间价 | Y33: 国家外汇管理局人民币汇率中间价查询（数据由中国外汇交易中心公布） | Z33: 货币性资产—货币资金 | AA33: 30000 | AB33: 283 | AC33: 30000 | AD33: 204498 | AE33: 默认主体-2026-06-26-记-0106

Sheet 已实现汇总
A1: 是否启用科目名称翻译 | B1: 审计测算汇兑损益 | C1: 自动测算合计 | D1: JE账面净额是否可区分 | E1: 账面汇兑损益取数来源 | F1: 客户已入账未实现汇兑损益 | G1: 自动测算覆盖的账面汇兑损益 | H1: 已覆盖账面已实现汇兑损益 | I1: 已覆盖项目测算差异 | J1: diagnosticMeasuredFxGainLoss | K1: 测算与客户账面差异 | L1: 差异率 | M1: 是否可形成正式测算结果 | N1: 正式测算受限原因 | O1: 低置信度事件数 | P1: 自动测算金额差异 | Q1: 零结果是否需要复核 | R1: notFxEventAmount | S1: notFxEventCount | T1: 待复核项目账面金额 | U1: 待复核项目数 | V1: pendingUnclassifiedCount | W1: pendingUnmeasurableCount | X1: 已实现测算事件数 | Y1: 已实现汇兑损益 | Z1: 已实现测算差异 | AA1: 勾稽是否通过 | AB1: rollforwardIssueCount | AC1: rollforwardPassed | AD1: TB汇兑损益诊断金额（不作为净损益） | AE1: tbFxGainAmount | AF1: TB汇兑损益发生额 | AG1: tbFxGainLossPresentation | AH1: tbFxLossAmount | AI1: tbRealizedGainLoss | AJ1: tbUnrealizedGainLoss | AK1: 已翻译英文科目数 | AL1: 未覆盖账面金额 | AM1: 未实现汇兑损益 | AN1: unrealizedBalanceBasisComplete | AO1: 未实现测算差异 | AP1: unrealizedMissingBalanceKeys | AQ1: 未实现测算行数
A2: 否 | B2: 116703.6 | C2: 116703.6 | D2: 是 | E2: JE剔除损益结转后的净额 | F2: 0 | G2: -10330 | H2: -10330 | I2: 127033.6 | J2: 116703.6 | K2: 124633.6 | L2: 15.716721 | M2: 是 | N2: [] | O2: 0 | P2: 127033.6 | Q2: 否 | R2: 2400 | S2: 2 | T2: 2400 | U2: 2 | V2: 0 | W2: 0 | X2: 32 | Y2: -14206.473 | Z2: -3876.4731 | AA2: 否 | AB2: 0 | AC2: 是 | AD2: 14650 | AE2: 0 | AF2: -7930 | AG2: 已实现＋未实现 | AH2: 14650 | AK2: 0 | AL2: 2400 | AM2: 130910.07 | AN2: 是 | AO2: 130910.07 | AP2: 0 | AQ2: 36

Sheet 未实现凭证识别

Sheet 未实现汇兑损益测算
A1: 主体 | B1: 科目 | C1: 辅助核算 | D1: 币种 | E1: 本位币 | F1: 月末测算日期 | G1: 汇率公布日 | H1: 月末原币余额 | I1: 月末官方中间价 | J1: 审计月末本位币余额 | K1: 测算前本位币余额 | L1: 月末重估损益 | M1: 客户重估凭证 | N1: 期初原币余额 | O1: 年初审计本位币余额 | P1: 正常业务原币发生额 | Q1: 正常业务审计本位币发生额（交易日官方汇率） | R1: 客户凭证对货币性项目余额的调整 | S1: 审计期末折算余额调整 | T1: TB年末本位币余额 | U1: TB勾稽差异 | V1: 已实现腿入账基础差异（账面−审计）
A2: 默认主体 | B2: 1002.02 美元户 | D2: USD | E2: CNY | F2: 2026-01-31 | G2: 2026-01-30 | H2: =N2+P2 -> 220000 | I2: =INDEX('汇率表'!$A:$XFD,MATCH(F2,'汇率表'!$A:$A,0),MATCH(D2,'汇率表'!$1:$1,0)) -> 6.9678 | J2: =H2*I2 -> 1532916 | K2: =O2+Q2 -> 1558517.6 | L2: =K2-J2 -> 25601.6 | N2: 200000 | O2: 1424000 | P2: 20000 | Q2: 134517.6 | R2: 0 | S2: =J2-K2 -> -25601.6 | V2: 7882.4
A3: 默认主体 | B3: 1002.03 港币户 | D3: HKD | E3: CNY | F3: 2026-01-31 | G3: 2026-01-30 | H3: =N3+P3 -> 460000 | I3: =INDEX('汇率表'!$A:$XFD,MATCH(F3,'汇率表'!$A:$A,0),MATCH(D3,'汇率表'!$1:$1,0)) -> 0.89262 | J3: =H3*I3 -> 410605.2 | K3: =O3+Q3 -> 419129.6 | L3: =K3-J3 -> 8524.4 | N3: 500000 | O3: 455000 | P3: -40000 | Q3: -35870.4 | R3: 0 | S3: =J3-K3 -> -8524.4 | V3: -529.6
A4: 默认主体 | B4: 1122.02 应收账款-美元客户 | D4: USD | E4: CNY | F4: 2026-01-31 | G4: 2026-01-30 | H4: =N4+P4 -> 420000 | I4: =INDEX('汇率表'!$A:$XFD,MATCH(F4,'汇率表'!$A:$A,0),MATCH(D4,'汇率表'!$1:$1,0)) -> 6.9678 | J4: =H4*I4 -> 2926476 | K4: =O4+Q4 -> 2974362.5 | L4: =K4-J4 -> 47886.462 | N4: 320000 | O4: 2278400 | P4: 100000 | Q4: 695962.46 | R4: 0 | S4: =J4-K4 -> -47886.462 | V4: 16037.538
A5: 默认主体 | B5: 1122.03 应收账款-欧元客户 | D5: EUR | E5: CNY | F5: 2026-01-31 | G5: 2026-01-30 | H5: =N5+P5 -> 150000 | I5: =INDEX('汇率表'!$A:$XFD,MATCH(F5,'汇率表'!$A:$A,0),MATCH(D5,'汇率表'!$1:$1,0)) -> 8.3244 | J5: =H5*I5 -> 1248660 | K5: =O5+Q5 -> 1174500 | L5: =K5-J5 -> -74160 | N5: 150000 | O5: 1174500 | P5: 0 | Q5: 0 | R5: 0 | S5: =J5-K5 -> 74160 | V5: 0
A6: 默认主体 | B6: 2202.02 应付账款-美元供应商 | D6: USD | E6: CNY | F6: 2026-01-31 | G6: 2026-01-30 | H6: =N6+P6 -> -190000 | I6: =INDEX('汇率表'!$A:$XFD,MATCH(F6,'汇率表'!$A:$A,0),MATCH(D6,'汇率表'!$1:$1,0)) -> 6.9678 | J6: =H6*I6 -> -1323882 | K6: =O6+Q6 -> -1347470.5 | L6: =K6-J6 -> -23588.5 | N6: -180000 | O6: -1281600 | P6: -10000 | Q6: -65870.5 | R6: 0 | S6: =J6-K6 -> 23588.5 | V6: -5329.5
A7: 默认主体 | B7: 2202.03 应付账款-港币供应商 | D7: HKD | E7: CNY | F7: 2026-01-31 | G7: 2026-01-30 | H7: =N7+P7 -> -300000 | I7: =INDEX('汇率表'!$A:$XFD,MATCH(F7,'汇率表'!$A:$A,0),MATCH(D7,'汇率表'!$1:$1,0)) -> 0.89262 | J7: =H7*I7 -> -267786 | K7: =O7+Q7 -> -272532.71 | L7: =K7-J7 -> -4746.7059 | N7: -300000 | O7: -273000 | P7: 0 | Q7: 467.29412 | R7: 0 | S7: =J7-K7 -> 4746.7059 | V7: -467.29412
A8: 默认主体 | B8: 1002.02 美元户 | D8: USD | E8: CNY | F8: 2026-02-28 | G8: 2026-02-27 | H8: =N8+P8 -> 260000 | I8: =INDEX('汇率表'!$A:$XFD,MATCH(F8,'汇率表'!$A:$A,0),MATCH(D8,'汇率表'!$1:$1,0)) -> 6.9228 | J8: =H8*I8 -> 1799928 | K8: =O8+Q8 -> 1810422.5 | L8: =K8-J8 -> 10494.467 | N8: 220000 | O8: 1532916 | P8: 40000 | Q8: 277506.47 | R8: 0 | S8: =J8-K8 -> -10494.467 | V8: 7293.5333
A9: 默认主体 | B9: 1002.03 港币户 | D9: HKD | E9: CNY | F9: 2026-02-28 | G9: 2026-02-27 | H9: =N9+P9 -> 430000 | I9: =INDEX('汇率表'!$A:$XFD,MATCH(F9,'汇率表'!$A:$A,0),MATCH(D9,'汇率表'!$1:$1,0)) -> 0.88484 | J9: =H9*I9 -> 380481.2 | K9: =O9+Q9 -> 383973.3 | L9: =K9-J9 -> 3492.1 | N9: 460000 | O9: 410605.2 | P9: -30000 | Q9: -26631.9 | R9: 0 | S9: =J9-K9 -> -3492.1 | V9: -668.1
A10: 默认主体 | B10: 1122.02 应收账款-美元客户 | D10: USD | E10: CNY | F10: 2026-02-28 | G10: 2026-02-27 | H10: =N10+P10 -> 400000 | I10: =INDEX('汇率表'!$A:$XFD,MATCH(F10,'汇率表'!$A:$A,0),MATCH(D10,'汇率表'!$1:$1,0)) -> 6.9228 | J10: =H10*I10 -> 2769120 | K10: =O10+Q10 -> 2786428.8 | L10: =K10-J10 -> 17308.8 | N10: 420000 | O10: 2926476 | P10: -20000 | Q10: -140047.2 | R10: 0 | S10: =J10-K10 -> -17308.8 | V10: -2352.8
A11: 默认主体 | B11: 1122.03 应收账款-欧元客户 | D11: EUR | E11: CNY | F11: 2026-02-28 | G11: 2026-02-27 | H11: =N11+P11 -> 125000 | I11: =INDEX('汇率表'!$A:$XFD,MATCH(F11,'汇率表'!$A:$A,0),MATCH(D11,'汇率表'!$1:$1,0)) -> 8.1208 | J11: =H11*I11 -> 1015100 | K11: =O11+Q11 -> 1040550 | L11: =K11-J11 -> 25450 | N11: 150000 | O11: 1248660 | P11: -25000 | Q11: -208110 | R11: 0 | S11: =J11-K11 -> -25450 | V11: 12360
A12: 默认主体 | B12: 2202.02 应付账款-美元供应商 | D12: USD | E12: CNY | F12: 2026-02-28 | G12: 2026-02-27 | H12: =N12+P12 -> -200000 | I12: =INDEX('汇率表'!$A:$XFD,MATCH(F12,'汇率表'!$A:$A,0),MATCH(D12,'汇率表'!$1:$1,0)) -> 6.9228 | J12: =H12*I12 -> -1384560 | K12: =O12+Q12 -> -1392586.1 | L12: =K12-J12 -> -8026.087 | N12: -190000 | O12: -1323882 | P12: -10000 | Q12: -68704.087 | R12: 0 | S12: =J12-K12 -> 8026.087 | V12: -2495.913
A13: 默认主体 | B13: 2202.03 应付账款-港币供应商 | D13: HKD | E13: CNY | F13: 2026-02-28 | G13: 2026-02-27 | H13: =N13+P13 -> -300000 | I13: =INDEX('汇率表'!$A:$XFD,MATCH(F13,'汇率表'!$A:$A,0),MATCH(D13,'汇率表'!$1:$1,0)) -> 0.88484 | J13: =H13*I13 -> -265452 | K13: =O13+Q13 -> -267656.45 | L13: =K13-J13 -> -2204.4545 | N13: -300000 | O13: -267786 | P13: 0 | Q13: 129.54545 | R13: 0 | S13: =J13-K13 -> 2204.4545 | V13: -129.54545
... A31: 默认主体 | B31: 2202.03 应付账款-港币供应商 | D31: HKD | E31: CNY | F31: 2026-05-31 | G31: 2026-05-29 | H31: =N31+P31 -> -300000 | I31: =INDEX('汇率表'!$A:$XFD,MATCH(F31,'汇率表'!$A:$A,0),MATCH(D31,'汇率表'!$1:$1,0)) -> 0.87029 | J31: =H31*I31 -> -261087 | K31: =O31+Q31 -> -262743 | L31: =K31-J31 -> -1656 | N31: -300000 | O31: -262743 | P31: 0 | Q31: 0 | R31: 0 | S31: =J31-K31 -> 1656 | V31: 0
A32: 默认主体 | B32: 1002.02 美元户 | D32: USD | E32: CNY | F32: 2026-06-30 | G32: 2026-06-30 | H32: =N32+P32 -> 520000 | I32: =INDEX('汇率表'!$A:$XFD,MATCH(F32,'汇率表'!$A:$A,0),MATCH(D32,'汇率表'!$1:$1,0)) -> 6.8109 | J32: =H32*I32 -> 3541668 | K32: =O32+Q32 -> 3544203.2 | L32: =K32-J32 -> 2535.25 | N32: 440000 | O32: 2999744 | P32: 80000 | Q32: 544459.25 | R32: 0 | S32: =J32-K32 -> -2535.25 | T32: 3702400 | U32: =J32-T32 -> -160732 | V32: 25140.75
A33: 默认主体 | B33: 1002.03 港币户 | D33: HKD | E33: CNY | F33: 2026-06-30 | G33: 2026-06-30 | H33: =N33+P33 -> 385000 | I33: =INDEX('汇率表'!$A:$XFD,MATCH(F33,'汇率表'!$A:$A,0),MATCH(D33,'汇率表'!$1:$1,0)) -> 0.86855 | J33: =H33*I33 -> 334391.75 | K33: =O33+Q33 -> 335085.95 | L33: =K33-J33 -> 694.2 | N33: 430000 | O33: 374224.7 | P33: -45000 | Q33: -39138.75 | R33: 0 | S33: =J33-K33 -> -694.2 | T33: 350350 | U33: =J33-T33 -> -15958.25 | V33: -1811.25
A34: 默认主体 | B34: 1122.02 应收账款-美元客户 | D34: USD | E34: CNY | F34: 2026-06-30 | G34: 2026-06-30 | H34: =N34+P34 -> 610000 | I34: =INDEX('汇率表'!$A:$XFD,MATCH(F34,'汇率表'!$A:$A,0),MATCH(D34,'汇率表'!$1:$1,0)) -> 6.8109 | J34: =H34*I34 -> 4154649 | K34: =O34+Q34 -> 4158354.6 | L34: =K34-J34 -> 3705.557 | N34: 530000 | O34: 3613328 | P34: 80000 | Q34: 545026.56 | R34: 0 | S34: =J34-K34 -> -3705.557 | T34: 4343200 | U34: =J34-T34 -> -188551 | V34: 24573.443
A35: 默认主体 | B35: 1122.03 应收账款-欧元客户 | D35: EUR | E35: CNY | F35: 2026-06-30 | G35: 2026-06-30 | H35: =N35+P35 -> 75000 | I35: =INDEX('汇率表'!$A:$XFD,MATCH(F35,'汇率表'!$A:$A,0),MATCH(D35,'汇率表'!$1:$1,0)) -> 7.7671 | J35: =H35*I35 -> 582532.5 | K35: =O35+Q35 -> 593700 | L35: =K35-J35 -> 11167.5 | N35: 100000 | O35: 791600 | P35: -25000 | Q35: -197900 | R35: 0 | S35: =J35-K35 -> -11167.5 | T35: 587250 | U35: =J35-T35 -> -4717.5 | V35: 2150
A36: 默认主体 | B36: 2202.02 应付账款-美元供应商 | D36: USD | E36: CNY | F36: 2026-06-30 | G36: 2026-06-30 | H36: =N36+P36 -> -240000 | I36: =INDEX('汇率表'!$A:$XFD,MATCH(F36,'汇率表'!$A:$A,0),MATCH(D36,'汇率表'!$1:$1,0)) -> 6.8109 | J36: =H36*I36 -> -1634616 | K36: =O36+Q36 -> -1635966.4 | L36: =K36-J36 -> -1350.4 | N36: -230000 | O36: -1568048 | P36: -10000 | Q36: -67918.4 | R36: 0 | S36: =J36-K36 -> 1350.4 | T36: -1708800 | U36: =J36-T36 -> 74184 | V36: -3281.6
A37: 默认主体 | B37: 2202.03 应付账款-港币供应商 | D37: HKD | E37: CNY | F37: 2026-06-30 | G37: 2026-06-30 | H37: =N37+P37 -> -300000 | I37: =INDEX('汇率表'!$A:$XFD,MATCH(F37,'汇率表'!$A:$A,0),MATCH(D37,'汇率表'!$1:$1,0)) -> 0.86855 | J37: =H37*I37 -> -260565 | K37: =O37+Q37 -> -261057.26 | L37: =K37-J37 -> -492.26087 | N37: -300000 | O37: -261087 | P37: 0 | Q37: 29.73913 | R37: 0 | S37: =J37-K37 -> 492.26087 | T37: -273000 | U37: =J37-T37 -> 12435 | V37: -29.73913

Sheet 客户未实现损益比较
A1: 科目 | B1: 审计期末折算余额调整 | C1: 审计月末本位币余额 | D1: 辅助核算 | E1: 正常业务原币发生额 | F1: 正常业务审计本位币发生额（交易日官方汇率） | G1: 客户已入账未实现汇兑损益 | H1: 客户未实现类凭证对货币性项目余额的调整 | I1: 未实现汇兑损益类凭证信息 | J1: 未实现汇兑损益/冲回凭证号 | K1: 年末原币余额 | L1: 币种 | M1: 客户重估后本位币余额 | N1: 客户重估前本位币余额 | O1: 客户隐含汇率 | P1: 客户隐含汇率反推依据 | Q1: 客户隐含汇率取得状态 | R1: 客户与审计月末汇率差 | S1: 客户与审计汇率影响 | T1: 公司/核算主体 | U1: 本位币 | V1: 测算方法 | W1: 月末测算日期 | X1: 官方汇率 | Y1: 年初审计本位币余额 | Z1: 年初原币余额 | AA1: 未实现损益测算前本位币余额 | AB1: 汇率公布日期 | AC1: 业务入账基础差异（客户账面−审计） | AD1: 建议调整 | AE1: TB年末本位币余额 | AF1: TB勾稽差异 | AG1: 未实现汇兑损益
A2: 1002.02 美元户 | B2: -25601.6 | C2: 1532916 | E2: 20000 | F2: 134517.6 | G2: 0 | H2: 0 | I2: [] | J2: [] | K2: 220000 | L2: USD | M2: 1566400 | N2: 1566400 | O2: 7.12 | P2: TB期初本位币及JE滚动后账面余额÷月末原币余额反推 | Q2: 反推 | R2: 0.1522 | S2: -33484 | T2: 默认主体 | U2: CNY | V2: 外币货币性项目月度余额滚动及月末官方汇率重估 | W2: 2026-01-31 | X2: 6.9678 | Y2: 1424000 | Z2: 200000 | AA2: 1558517.6 | AB2: 2026-01-30 | AC2: 7882.4 | AD2: 25601.6 | AG2: 25601.6
A3: 1002.03 港币户 | B3: -8524.4 | C3: 410605.2 | E3: -40000 | F3: -35870.4 | G3: 0 | H3: 0 | I3: [] | J3: [] | K3: 460000 | L3: HKD | M3: 418600 | N3: 418600 | O3: 0.91 | P3: TB期初本位币及JE滚动后账面余额÷月末原币余额反推 | Q3: 反推 | R3: 0.01738 | S3: -7994.8 | T3: 默认主体 | U3: CNY | V3: 外币货币性项目月度余额滚动及月末官方汇率重估 | W3: 2026-01-31 | X3: 0.89262 | Y3: 455000 | Z3: 500000 | AA3: 419129.6 | AB3: 2026-01-30 | AC3: -529.6 | AD3: 8524.4 | AG3: 8524.4
A4: 1122.02 应收账款-美元客户 | B4: -47886.462 | C4: 2926476 | E4: 100000 | F4: 695962.46 | G4: 0 | H4: 0 | I4: [] | J4: [] | K4: 420000 | L4: USD | M4: 2990400 | N4: 2990400 | O4: 7.12 | P4: TB期初本位币及JE滚动后账面余额÷月末原币余额反推 | Q4: 反推 | R4: 0.1522 | S4: -63924 | T4: 默认主体 | U4: CNY | V4: 外币货币性项目月度余额滚动及月末官方汇率重估 | W4: 2026-01-31 | X4: 6.9678 | Y4: 2278400 | Z4: 320000 | AA4: 2974362.5 | AB4: 2026-01-30 | AC4: 16037.538 | AD4: 47886.462 | AG4: 47886.462
A5: 1122.03 应收账款-欧元客户 | B5: 74160 | C5: 1248660 | E5: 0 | F5: 0 | G5: 0 | H5: 0 | I5: [] | J5: [] | K5: 150000 | L5: EUR | M5: 1174500 | N5: 1174500 | O5: 7.83 | P5: TB期初本位币及JE滚动后账面余额÷月末原币余额反推 | Q5: 反推 | R5: -0.4944 | S5: 74160 | T5: 默认主体 | U5: CNY | V5: 外币货币性项目月度余额滚动及月末官方汇率重估 | W5: 2026-01-31 | X5: 8.3244 | Y5: 1174500 | Z5: 150000 | AA5: 1174500 | AB5: 2026-01-30 | AC5: 0 | AD5: -74160 | AG5: -74160
A6: 2202.02 应付账款-美元供应商 | B6: 23588.5 | C6: -1323882 | E6: -10000 | F6: -65870.5 | G6: 0 | H6: 0 | I6: [] | J6: [] | K6: -190000 | L6: USD | M6: -1352800 | N6: -1352800 | O6: 7.12 | P6: TB期初本位币及JE滚动后账面余额÷月末原币余额反推 | Q6: 反推 | R6: 0.1522 | S6: 28918 | T6: 默认主体 | U6: CNY | V6: 外币货币性项目月度余额滚动及月末官方汇率重估 | W6: 2026-01-31 | X6: 6.9678 | Y6: -1281600 | Z6: -180000 | AA6: -1347470.5 | AB6: 2026-01-30 | AC6: -5329.5 | AD6: -23588.5 | AG6: -23588.5
A7: 2202.03 应付账款-港币供应商 | B7: 4746.7059 | C7: -267786 | E7: 0 | F7: 467.29412 | G7: 0 | H7: 0 | I7: [] | J7: [] | K7: -300000 | L7: HKD | M7: -273000 | N7: -273000 | O7: 0.91 | P7: TB期初本位币及JE滚动后账面余额÷月末原币余额反推 | Q7: 反推 | R7: 0.01738 | S7: 5214 | T7: 默认主体 | U7: CNY | V7: 外币货币性项目月度余额滚动及月末官方汇率重估 | W7: 2026-01-31 | X7: 0.89262 | Y7: -273000 | Z7: -300000 | AA7: -272532.71 | AB7: 2026-01-30 | AC7: -467.29412 | AD7: -4746.7059 | AG7: -4746.7059
A8: 1002.02 美元户 | B8: -10494.467 | C8: 1799928 | E8: 40000 | F8: 277506.47 | G8: 0 | H8: 0 | I8: [] | J8: [] | K8: 260000 | L8: USD | M8: 1851200 | N8: 1851200 | O8: 7.12 | P8: TB期初本位币及JE滚动后账面余额÷月末原币余额反推 | Q8: 反推 | R8: 0.1972 | S8: -51272 | T8: 默认主体 | U8: CNY | V8: 外币货币性项目月度余额滚动及月末官方汇率重估 | W8: 2026-02-28 | X8: 6.9228 | Y8: 1532916 | Z8: 220000 | AA8: 1810422.5 | AB8: 2026-02-27 | AC8: 7293.5333 | AD8: 10494.467 | AG8: 10494.467
A9: 1002.03 港币户 | B9: -3492.1 | C9: 380481.2 | E9: -30000 | F9: -26631.9 | G9: 0 | H9: 0 | I9: [] | J9: [] | K9: 430000 | L9: HKD | M9: 391300 | N9: 391300 | O9: 0.91 | P9: TB期初本位币及JE滚动后账面余额÷月末原币余额反推 | Q9: 反推 | R9: 0.02516 | S9: -10818.8 | T9: 默认主体 | U9: CNY | V9: 外币货币性项目月度余额滚动及月末官方汇率重估 | W9: 2026-02-28 | X9: 0.88484 | Y9: 410605.2 | Z9: 460000 | AA9: 383973.3 | AB9: 2026-02-27 | AC9: -668.1 | AD9: 3492.1 | AG9: 3492.1
A10: 1122.02 应收账款-美元客户 | B10: -17308.8 | C10: 2769120 | E10: -20000 | F10: -140047.2 | G10: 0 | H10: 0 | I10: [] | J10: [] | K10: 400000 | L10: USD | M10: 2848000 | N10: 2848000 | O10: 7.12 | P10: TB期初本位币及JE滚动后账面余额÷月末原币余额反推 | Q10: 反推 | R10: 0.1972 | S10: -78880 | T10: 默认主体 | U10: CNY | V10: 外币货币性项目月度余额滚动及月末官方汇率重估 | W10: 2026-02-28 | X10: 6.9228 | Y10: 2926476 | Z10: 420000 | AA10: 2786428.8 | AB10: 2026-02-27 | AC10: -2352.8 | AD10: 17308.8 | AG10: 17308.8
A11: 1122.03 应收账款-欧元客户 | B11: -25450 | C11: 1015100 | E11: -25000 | F11: -208110 | G11: 0 | H11: 0 | I11: [] | J11: [] | K11: 125000 | L11: EUR | M11: 978750 | N11: 978750 | O11: 7.83 | P11: TB期初本位币及JE滚动后账面余额÷月末原币余额反推 | Q11: 反推 | R11: -0.2908 | S11: 36350 | T11: 默认主体 | U11: CNY | V11: 外币货币性项目月度余额滚动及月末官方汇率重估 | W11: 2026-02-28 | X11: 8.1208 | Y11: 1248660 | Z11: 150000 | AA11: 1040550 | AB11: 2026-02-27 | AC11: 12360 | AD11: 25450 | AG11: 25450
A12: 2202.02 应付账款-美元供应商 | B12: 8026.087 | C12: -1384560 | E12: -10000 | F12: -68704.087 | G12: 0 | H12: 0 | I12: [] | J12: [] | K12: -200000 | L12: USD | M12: -1424000 | N12: -1424000 | O12: 7.12 | P12: TB期初本位币及JE滚动后账面余额÷月末原币余额反推 | Q12: 反推 | R12: 0.1972 | S12: 39440 | T12: 默认主体 | U12: CNY | V12: 外币货币性项目月度余额滚动及月末官方汇率重估 | W12: 2026-02-28 | X12: 6.9228 | Y12: -1323882 | Z12: -190000 | AA12: -1392586.1 | AB12: 2026-02-27 | AC12: -2495.913 | AD12: -8026.087 | AG12: -8026.087
A13: 2202.03 应付账款-港币供应商 | B13: 2204.4545 | C13: -265452 | E13: 0 | F13: 129.54545 | G13: 0 | H13: 0 | I13: [] | J13: [] | K13: -300000 | L13: HKD | M13: -273000 | N13: -273000 | O13: 0.91 | P13: TB期初本位币及JE滚动后账面余额÷月末原币余额反推 | Q13: 反推 | R13: 0.02516 | S13: 7548 | T13: 默认主体 | U13: CNY | V13: 外币货币性项目月度余额滚动及月末官方汇率重估 | W13: 2026-02-28 | X13: 0.88484 | Y13: -267786 | Z13: -300000 | AA13: -267656.45 | AB13: 2026-02-27 | AC13: -129.54545 | AD13: -2204.4545 | AG13: -2204.4545
... A31: 2202.03 应付账款-港币供应商 | B31: 1656 | C31: -261087 | E31: 0 | F31: 0 | G31: 0 | H31: 0 | I31: [] | J31: [] | K31: -300000 | L31: HKD | M31: -273000 | N31: -273000 | O31: 0.91 | P31: TB期初本位币及JE滚动后账面余额÷月末原币余额反推 | Q31: 反推 | R31: 0.03971 | S31: 11913 | T31: 默认主体 | U31: CNY | V31: 外币货币性项目月度余额滚动及月末官方汇率重估 | W31: 2026-05-31 | X31: 0.87029 | Y31: -262743 | Z31: -300000 | AA31: -262743 | AB31: 2026-05-29 | AC31: 0 | AD31: -1656 | AG31: -1656
A32: 1002.02 美元户 | B32: -2535.25 | C32: 3541668 | E32: 80000 | F32: 544459.25 | G32: 0 | H32: 0 | I32: [] | J32: [] | K32: 520000 | L32: USD | M32: 3702400 | N32: 3702400 | O32: 7.12 | P32: TB期初本位币及JE滚动后账面余额÷月末原币余额反推 | Q32: 反推 | R32: 0.3091 | S32: -160732 | T32: 默认主体 | U32: CNY | V32: 外币货币性项目月度余额滚动及月末官方汇率重估 | W32: 2026-06-30 | X32: 6.8109 | Y32: 2999744 | Z32: 440000 | AA32: 3544203.2 | AB32: 2026-06-30 | AC32: 25140.75 | AD32: 2535.25 | AE32: 3702400 | AF32: -160732 | AG32: 2535.25
A33: 1002.03 港币户 | B33: -694.2 | C33: 334391.75 | E33: -45000 | F33: -39138.75 | G33: 0 | H33: 0 | I33: [] | J33: [] | K33: 385000 | L33: HKD | M33: 350350 | N33: 350350 | O33: 0.91 | P33: TB期初本位币及JE滚动后账面余额÷月末原币余额反推 | Q33: 反推 | R33: 0.04145 | S33: -15958.25 | T33: 默认主体 | U33: CNY | V33: 外币货币性项目月度余额滚动及月末官方汇率重估 | W33: 2026-06-30 | X33: 0.86855 | Y33: 374224.7 | Z33: 430000 | AA33: 335085.95 | AB33: 2026-06-30 | AC33: -1811.25 | AD33: 694.2 | AE33: 350350 | AF33: -15958.25 | AG33: 694.2
A34: 1122.02 应收账款-美元客户 | B34: -3705.557 | C34: 4154649 | E34: 80000 | F34: 545026.56 | G34: 0 | H34: 0 | I34: [] | J34: [] | K34: 610000 | L34: USD | M34: 4343200 | N34: 4343200 | O34: 7.12 | P34: TB期初本位币及JE滚动后账面余额÷月末原币余额反推 | Q34: 反推 | R34: 0.3091 | S34: -188551 | T34: 默认主体 | U34: CNY | V34: 外币货币性项目月度余额滚动及月末官方汇率重估 | W34: 2026-06-30 | X34: 6.8109 | Y34: 3613328 | Z34: 530000 | AA34: 4158354.6 | AB34: 2026-06-30 | AC34: 24573.443 | AD34: 3705.557 | AE34: 4343200 | AF34: -188551 | AG34: 3705.557
A35: 1122.03 应收账款-欧元客户 | B35: -11167.5 | C35: 582532.5 | E35: -25000 | F35: -197900 | G35: 0 | H35: 0 | I35: [] | J35: [] | K35: 75000 | L35: EUR | M35: 587250 | N35: 587250 | O35: 7.83 | P35: TB期初本位币及JE滚动后账面余额÷月末原币余额反推 | Q35: 反推 | R35: 0.0629 | S35: -4717.5 | T35: 默认主体 | U35: CNY | V35: 外币货币性项目月度余额滚动及月末官方汇率重估 | W35: 2026-06-30 | X35: 7.7671 | Y35: 791600 | Z35: 100000 | AA35: 593700 | AB35: 2026-06-30 | AC35: 2150 | AD35: 11167.5 | AE35: 587250 | AF35: -4717.5 | AG35: 11167.5
A36: 2202.02 应付账款-美元供应商 | B36: 1350.4 | C36: -1634616 | E36: -10000 | F36: -67918.4 | G36: 0 | H36: 0 | I36: [] | J36: [] | K36: -240000 | L36: USD | M36: -1708800 | N36: -1708800 | O36: 7.12 | P36: TB期初本位币及JE滚动后账面余额÷月末原币余额反推 | Q36: 反推 | R36: 0.3091 | S36: 74184 | T36: 默认主体 | U36: CNY | V36: 外币货币性项目月度余额滚动及月末官方汇率重估 | W36: 2026-06-30 | X36: 6.8109 | Y36: -1568048 | Z36: -230000 | AA36: -1635966.4 | AB36: 2026-06-30 | AC36: -3281.6 | AD36: -1350.4 | AE36: -1708800 | AF36: 74184 | AG36: -1350.4
A37: 2202.03 应付账款-港币供应商 | B37: 492.26087 | C37: -260565 | E37: 0 | F37: 29.73913 | G37: 0 | H37: 0 | I37: [] | J37: [] | K37: -300000 | L37: HKD | M37: -273000 | N37: -273000 | O37: 0.91 | P37: TB期初本位币及JE滚动后账面余额÷月末原币余额反推 | Q37: 反推 | R37: 0.04145 | S37: 12435 | T37: 默认主体 | U37: CNY | V37: 外币货币性项目月度余额滚动及月末官方汇率重估 | W37: 2026-06-30 | X37: 0.86855 | Y37: -261087 | Z37: -300000 | AA37: -261057.26 | AB37: 2026-06-30 | AC37: -29.73913 | AD37: -492.26087 | AE37: -273000 | AF37: 12435 | AG37: -492.26087

Sheet 月度测算
A1: 科目 | B1: 审计期末折算余额调整 | C1: 审计月末本位币余额 | D1: 辅助核算 | E1: 正常业务原币发生额 | F1: 正常业务审计本位币发生额（交易日官方汇率） | G1: 客户已入账未实现汇兑损益 | H1: 客户未实现类凭证对货币性项目余额的调整 | I1: 未实现汇兑损益类凭证信息 | J1: 未实现汇兑损益/冲回凭证号 | K1: 年末原币余额 | L1: 币种 | M1: 客户重估后本位币余额 | N1: 客户重估前本位币余额 | O1: 客户隐含汇率 | P1: 客户隐含汇率反推依据 | Q1: 客户隐含汇率取得状态 | R1: 客户与审计月末汇率差 | S1: 客户与审计汇率影响 | T1: 公司/核算主体 | U1: 本位币 | V1: 测算方法 | W1: 月末测算日期 | X1: 官方汇率 | Y1: 年初审计本位币余额 | Z1: 年初原币余额 | AA1: 未实现损益测算前本位币余额 | AB1: 汇率公布日期 | AC1: 业务入账基础差异（客户账面−审计） | AD1: 建议调整 | AE1: TB年末本位币余额 | AF1: TB勾稽差异 | AG1: 未实现汇兑损益
A2: 1002.02 美元户 | B2: -25601.6 | C2: 1532916 | E2: 20000 | F2: 134517.6 | G2: 0 | H2: 0 | I2: [] | J2: [] | K2: 220000 | L2: USD | M2: 1566400 | N2: 1566400 | O2: 7.12 | P2: TB期初本位币及JE滚动后账面余额÷月末原币余额反推 | Q2: 反推 | R2: 0.1522 | S2: -33484 | T2: 默认主体 | U2: CNY | V2: 外币货币性项目月度余额滚动及月末官方汇率重估 | W2: 2026-01-31 | X2: 6.9678 | Y2: 1424000 | Z2: 200000 | AA2: 1558517.6 | AB2: 2026-01-30 | AC2: 7882.4 | AD2: 25601.6 | AG2: 25601.6
A3: 1002.03 港币户 | B3: -8524.4 | C3: 410605.2 | E3: -40000 | F3: -35870.4 | G3: 0 | H3: 0 | I3: [] | J3: [] | K3: 460000 | L3: HKD | M3: 418600 | N3: 418600 | O3: 0.91 | P3: TB期初本位币及JE滚动后账面余额÷月末原币余额反推 | Q3: 反推 | R3: 0.01738 | S3: -7994.8 | T3: 默认主体 | U3: CNY | V3: 外币货币性项目月度余额滚动及月末官方汇率重估 | W3: 2026-01-31 | X3: 0.89262 | Y3: 455000 | Z3: 500000 | AA3: 419129.6 | AB3: 2026-01-30 | AC3: -529.6 | AD3: 8524.4 | AG3: 8524.4
A4: 1122.02 应收账款-美元客户 | B4: -47886.462 | C4: 2926476 | E4: 100000 | F4: 695962.46 | G4: 0 | H4: 0 | I4: [] | J4: [] | K4: 420000 | L4: USD | M4: 2990400 | N4: 2990400 | O4: 7.12 | P4: TB期初本位币及JE滚动后账面余额÷月末原币余额反推 | Q4: 反推 | R4: 0.1522 | S4: -63924 | T4: 默认主体 | U4: CNY | V4: 外币货币性项目月度余额滚动及月末官方汇率重估 | W4: 2026-01-31 | X4: 6.9678 | Y4: 2278400 | Z4: 320000 | AA4: 2974362.5 | AB4: 2026-01-30 | AC4: 16037.538 | AD4: 47886.462 | AG4: 47886.462
A5: 1122.03 应收账款-欧元客户 | B5: 74160 | C5: 1248660 | E5: 0 | F5: 0 | G5: 0 | H5: 0 | I5: [] | J5: [] | K5: 150000 | L5: EUR | M5: 1174500 | N5: 1174500 | O5: 7.83 | P5: TB期初本位币及JE滚动后账面余额÷月末原币余额反推 | Q5: 反推 | R5: -0.4944 | S5: 74160 | T5: 默认主体 | U5: CNY | V5: 外币货币性项目月度余额滚动及月末官方汇率重估 | W5: 2026-01-31 | X5: 8.3244 | Y5: 1174500 | Z5: 150000 | AA5: 1174500 | AB5: 2026-01-30 | AC5: 0 | AD5: -74160 | AG5: -74160
A6: 2202.02 应付账款-美元供应商 | B6: 23588.5 | C6: -1323882 | E6: -10000 | F6: -65870.5 | G6: 0 | H6: 0 | I6: [] | J6: [] | K6: -190000 | L6: USD | M6: -1352800 | N6: -1352800 | O6: 7.12 | P6: TB期初本位币及JE滚动后账面余额÷月末原币余额反推 | Q6: 反推 | R6: 0.1522 | S6: 28918 | T6: 默认主体 | U6: CNY | V6: 外币货币性项目月度余额滚动及月末官方汇率重估 | W6: 2026-01-31 | X6: 6.9678 | Y6: -1281600 | Z6: -180000 | AA6: -1347470.5 | AB6: 2026-01-30 | AC6: -5329.5 | AD6: -23588.5 | AG6: -23588.5
A7: 2202.03 应付账款-港币供应商 | B7: 4746.7059 | C7: -267786 | E7: 0 | F7: 467.29412 | G7: 0 | H7: 0 | I7: [] | J7: [] | K7: -300000 | L7: HKD | M7: -273000 | N7: -273000 | O7: 0.91 | P7: TB期初本位币及JE滚动后账面余额÷月末原币余额反推 | Q7: 反推 | R7: 0.01738 | S7: 5214 | T7: 默认主体 | U7: CNY | V7: 外币货币性项目月度余额滚动及月末官方汇率重估 | W7: 2026-01-31 | X7: 0.89262 | Y7: -273000 | Z7: -300000 | AA7: -272532.71 | AB7: 2026-01-30 | AC7: -467.29412 | AD7: -4746.7059 | AG7: -4746.7059
A8: 1002.02 美元户 | B8: -10494.467 | C8: 1799928 | E8: 40000 | F8: 277506.47 | G8: 0 | H8: 0 | I8: [] | J8: [] | K8: 260000 | L8: USD | M8: 1851200 | N8: 1851200 | O8: 7.12 | P8: TB期初本位币及JE滚动后账面余额÷月末原币余额反推 | Q8: 反推 | R8: 0.1972 | S8: -51272 | T8: 默认主体 | U8: CNY | V8: 外币货币性项目月度余额滚动及月末官方汇率重估 | W8: 2026-02-28 | X8: 6.9228 | Y8: 1532916 | Z8: 220000 | AA8: 1810422.5 | AB8: 2026-02-27 | AC8: 7293.5333 | AD8: 10494.467 | AG8: 10494.467
A9: 1002.03 港币户 | B9: -3492.1 | C9: 380481.2 | E9: -30000 | F9: -26631.9 | G9: 0 | H9: 0 | I9: [] | J9: [] | K9: 430000 | L9: HKD | M9: 391300 | N9: 391300 | O9: 0.91 | P9: TB期初本位币及JE滚动后账面余额÷月末原币余额反推 | Q9: 反推 | R9: 0.02516 | S9: -10818.8 | T9: 默认主体 | U9: CNY | V9: 外币货币性项目月度余额滚动及月末官方汇率重估 | W9: 2026-02-28 | X9: 0.88484 | Y9: 410605.2 | Z9: 460000 | AA9: 383973.3 | AB9: 2026-02-27 | AC9: -668.1 | AD9: 3492.1 | AG9: 3492.1
A10: 1122.02 应收账款-美元客户 | B10: -17308.8 | C10: 2769120 | E10: -20000 | F10: -140047.2 | G10: 0 | H10: 0 | I10: [] | J10: [] | K10: 400000 | L10: USD | M10: 2848000 | N10: 2848000 | O10: 7.12 | P10: TB期初本位币及JE滚动后账面余额÷月末原币余额反推 | Q10: 反推 | R10: 0.1972 | S10: -78880 | T10: 默认主体 | U10: CNY | V10: 外币货币性项目月度余额滚动及月末官方汇率重估 | W10: 2026-02-28 | X10: 6.9228 | Y10: 2926476 | Z10: 420000 | AA10: 2786428.8 | AB10: 2026-02-27 | AC10: -2352.8 | AD10: 17308.8 | AG10: 17308.8
A11: 1122.03 应收账款-欧元客户 | B11: -25450 | C11: 1015100 | E11: -25000 | F11: -208110 | G11: 0 | H11: 0 | I11: [] | J11: [] | K11: 125000 | L11: EUR | M11: 978750 | N11: 978750 | O11: 7.83 | P11: TB期初本位币及JE滚动后账面余额÷月末原币余额反推 | Q11: 反推 | R11: -0.2908 | S11: 36350 | T11: 默认主体 | U11: CNY | V11: 外币货币性项目月度余额滚动及月末官方汇率重估 | W11: 2026-02-28 | X11: 8.1208 | Y11: 1248660 | Z11: 150000 | AA11: 1040550 | AB11: 2026-02-27 | AC11: 12360 | AD11: 25450 | AG11: 25450
A12: 2202.02 应付账款-美元供应商 | B12: 8026.087 | C12: -1384560 | E12: -10000 | F12: -68704.087 | G12: 0 | H12: 0 | I12: [] | J12: [] | K12: -200000 | L12: USD | M12: -1424000 | N12: -1424000 | O12: 7.12 | P12: TB期初本位币及JE滚动后账面余额÷月末原币余额反推 | Q12: 反推 | R12: 0.1972 | S12: 39440 | T12: 默认主体 | U12: CNY | V12: 外币货币性项目月度余额滚动及月末官方汇率重估 | W12: 2026-02-28 | X12: 6.9228 | Y12: -1323882 | Z12: -190000 | AA12: -1392586.1 | AB12: 2026-02-27 | AC12: -2495.913 | AD12: -8026.087 | AG12: -8026.087
A13: 2202.03 应付账款-港币供应商 | B13: 2204.4545 | C13: -265452 | E13: 0 | F13: 129.54545 | G13: 0 | H13: 0 | I13: [] | J13: [] | K13: -300000 | L13: HKD | M13: -273000 | N13: -273000 | O13: 0.91 | P13: TB期初本位币及JE滚动后账面余额÷月末原币余额反推 | Q13: 反推 | R13: 0.02516 | S13: 7548 | T13: 默认主体 | U13: CNY | V13: 外币货币性项目月度余额滚动及月末官方汇率重估 | W13: 2026-02-28 | X13: 0.88484 | Y13: -267786 | Z13: -300000 | AA13: -267656.45 | AB13: 2026-02-27 | AC13: -129.54545 | AD13: -2204.4545 | AG13: -2204.4545
... A31: 2202.03 应付账款-港币供应商 | B31: 1656 | C31: -261087 | E31: 0 | F31: 0 | G31: 0 | H31: 0 | I31: [] | J31: [] | K31: -300000 | L31: HKD | M31: -273000 | N31: -273000 | O31: 0.91 | P31: TB期初本位币及JE滚动后账面余额÷月末原币余额反推 | Q31: 反推 | R31: 0.03971 | S31: 11913 | T31: 默认主体 | U31: CNY | V31: 外币货币性项目月度余额滚动及月末官方汇率重估 | W31: 2026-05-31 | X31: 0.87029 | Y31: -262743 | Z31: -300000 | AA31: -262743 | AB31: 2026-05-29 | AC31: 0 | AD31: -1656 | AG31: -1656
A32: 1002.02 美元户 | B32: -2535.25 | C32: 3541668 | E32: 80000 | F32: 544459.25 | G32: 0 | H32: 0 | I32: [] | J32: [] | K32: 520000 | L32: USD | M32: 3702400 | N32: 3702400 | O32: 7.12 | P32: TB期初本位币及JE滚动后账面余额÷月末原币余额反推 | Q32: 反推 | R32: 0.3091 | S32: -160732 | T32: 默认主体 | U32: CNY | V32: 外币货币性项目月度余额滚动及月末官方汇率重估 | W32: 2026-06-30 | X32: 6.8109 | Y32: 2999744 | Z32: 440000 | AA32: 3544203.2 | AB32: 2026-06-30 | AC32: 25140.75 | AD32: 2535.25 | AE32: 3702400 | AF32: -160732 | AG32: 2535.25
A33: 1002.03 港币户 | B33: -694.2 | C33: 334391.75 | E33: -45000 | F33: -39138.75 | G33: 0 | H33: 0 | I33: [] | J33: [] | K33: 385000 | L33: HKD | M33: 350350 | N33: 350350 | O33: 0.91 | P33: TB期初本位币及JE滚动后账面余额÷月末原币余额反推 | Q33: 反推 | R33: 0.04145 | S33: -15958.25 | T33: 默认主体 | U33: CNY | V33: 外币货币性项目月度余额滚动及月末官方汇率重估 | W33: 2026-06-30 | X33: 0.86855 | Y33: 374224.7 | Z33: 430000 | AA33: 335085.95 | AB33: 2026-06-30 | AC33: -1811.25 | AD33: 694.2 | AE33: 350350 | AF33: -15958.25 | AG33: 694.2
A34: 1122.02 应收账款-美元客户 | B34: -3705.557 | C34: 4154649 | E34: 80000 | F34: 545026.56 | G34: 0 | H34: 0 | I34: [] | J34: [] | K34: 610000 | L34: USD | M34: 4343200 | N34: 4343200 | O34: 7.12 | P34: TB期初本位币及JE滚动后账面余额÷月末原币余额反推 | Q34: 反推 | R34: 0.3091 | S34: -188551 | T34: 默认主体 | U34: CNY | V34: 外币货币性项目月度余额滚动及月末官方汇率重估 | W34: 2026-06-30 | X34: 6.8109 | Y34: 3613328 | Z34: 530000 | AA34: 4158354.6 | AB34: 2026-06-30 | AC34: 24573.443 | AD34: 3705.557 | AE34: 4343200 | AF34: -188551 | AG34: 3705.557
A35: 1122.03 应收账款-欧元客户 | B35: -11167.5 | C35: 582532.5 | E35: -25000 | F35: -197900 | G35: 0 | H35: 0 | I35: [] | J35: [] | K35: 75000 | L35: EUR | M35: 587250 | N35: 587250 | O35: 7.83 | P35: TB期初本位币及JE滚动后账面余额÷月末原币余额反推 | Q35: 反推 | R35: 0.0629 | S35: -4717.5 | T35: 默认主体 | U35: CNY | V35: 外币货币性项目月度余额滚动及月末官方汇率重估 | W35: 2026-06-30 | X35: 7.7671 | Y35: 791600 | Z35: 100000 | AA35: 593700 | AB35: 2026-06-30 | AC35: 2150 | AD35: 11167.5 | AE35: 587250 | AF35: -4717.5 | AG35: 11167.5
A36: 2202.02 应付账款-美元供应商 | B36: 1350.4 | C36: -1634616 | E36: -10000 | F36: -67918.4 | G36: 0 | H36: 0 | I36: [] | J36: [] | K36: -240000 | L36: USD | M36: -1708800 | N36: -1708800 | O36: 7.12 | P36: TB期初本位币及JE滚动后账面余额÷月末原币余额反推 | Q36: 反推 | R36: 0.3091 | S36: 74184 | T36: 默认主体 | U36: CNY | V36: 外币货币性项目月度余额滚动及月末官方汇率重估 | W36: 2026-06-30 | X36: 6.8109 | Y36: -1568048 | Z36: -230000 | AA36: -1635966.4 | AB36: 2026-06-30 | AC36: -3281.6 | AD36: -1350.4 | AE36: -1708800 | AF36: 74184 | AG36: -1350.4
A37: 2202.03 应付账款-港币供应商 | B37: 492.26087 | C37: -260565 | E37: 0 | F37: 29.73913 | G37: 0 | H37: 0 | I37: [] | J37: [] | K37: -300000 | L37: HKD | M37: -273000 | N37: -273000 | O37: 0.91 | P37: TB期初本位币及JE滚动后账面余额÷月末原币余额反推 | Q37: 反推 | R37: 0.04145 | S37: 12435 | T37: 默认主体 | U37: CNY | V37: 外币货币性项目月度余额滚动及月末官方汇率重估 | W37: 2026-06-30 | X37: 0.86855 | Y37: -261087 | Z37: -300000 | AA37: -261057.26 | AB37: 2026-06-30 | AC37: -29.73913 | AD37: -492.26087 | AE37: -273000 | AF37: 12435 | AG37: -492.26087

Sheet 全年汇总
A1: 是否启用科目名称翻译 | B1: 审计测算汇兑损益 | C1: 自动测算合计 | D1: JE账面净额是否可区分 | E1: 账面汇兑损益取数来源 | F1: 客户已入账未实现汇兑损益 | G1: 自动测算覆盖的账面汇兑损益 | H1: 已覆盖账面已实现汇兑损益 | I1: 已覆盖项目测算差异 | J1: diagnosticMeasuredFxGainLoss | K1: 测算与客户账面差异 | L1: 差异率 | M1: 是否可形成正式测算结果 | N1: 正式测算受限原因 | O1: 低置信度事件数 | P1: 自动测算金额差异 | Q1: 零结果是否需要复核 | R1: notFxEventAmount | S1: notFxEventCount | T1: 待复核项目账面金额 | U1: 待复核项目数 | V1: pendingUnclassifiedCount | W1: pendingUnmeasurableCount | X1: 已实现测算事件数 | Y1: 已实现汇兑损益 | Z1: 已实现测算差异 | AA1: 勾稽是否通过 | AB1: rollforwardIssueCount | AC1: rollforwardPassed | AD1: TB汇兑损益诊断金额（不作为净损益） | AE1: tbFxGainAmount | AF1: TB汇兑损益发生额 | AG1: tbFxGainLossPresentation | AH1: tbFxLossAmount | AI1: tbRealizedGainLoss | AJ1: tbUnrealizedGainLoss | AK1: 已翻译英文科目数 | AL1: 未覆盖账面金额 | AM1: 未实现汇兑损益 | AN1: unrealizedBalanceBasisComplete | AO1: 未实现测算差异 | AP1: unrealizedMissingBalanceKeys | AQ1: 未实现测算行数
A2: 否 | B2: 116703.6 | C2: 116703.6 | D2: 是 | E2: JE剔除损益结转后的净额 | F2: 0 | G2: -10330 | H2: -10330 | I2: 127033.6 | J2: 116703.6 | K2: 124633.6 | L2: 15.716721 | M2: 是 | N2: [] | O2: 0 | P2: 127033.6 | Q2: 否 | R2: 2400 | S2: 2 | T2: 2400 | U2: 2 | V2: 0 | W2: 0 | X2: 32 | Y2: -14206.473 | Z2: -3876.4731 | AA2: 否 | AB2: 0 | AC2: 是 | AD2: 14650 | AE2: 0 | AF2: -7930 | AG2: 已实现＋未实现 | AH2: 14650 | AK2: 0 | AL2: 2400 | AM2: 130910.07 | AN2: 是 | AO2: 130910.07 | AP2: 0 | AQ2: 36

Sheet TB勾稽
A1: 账面汇兑损益净额 | B1: JE账面净额是否可区分 | C1: 账面汇兑损益取数来源 | D1: 覆盖勾稽差异 | E1: 自动测算覆盖的账面汇兑损益 | F1: 剔除损益结转行数 | G1: JE剔除损益结转后汇兑损益 | H1: JE与TB差异 | I1: 待复核项目账面金额 | J1: 待复核项目数 | K1: TB汇兑损益诊断金额（不作为净损益） | L1: TB诊断金额列示方式 | M1: TB诊断已实现汇兑损益 | N1: TB诊断未实现汇兑损益 | O1: tbFxGainAmount | P1: TB汇兑损益发生额 | Q1: tbFxGainLossPresentation | R1: tbFxLossAmount | S1: tbRealizedGainLoss | T1: TB汇兑损益取数明细 | U1: tbUnrealizedGainLoss
A2: -7930 | B2: 是 | C2: JE剔除损益结转后的净额 | D2: 0 | E2: -10330 | F2: 5 | G2: -7930 | H2: -22580 | I2: 2400 | J2: 2 | K2: 14650 | L2: 已实现＋未实现 | O2: 0 | P2: -7930 | Q2: 已实现＋未实现 | R2: 14650 | T2: [{"basis":"本年累计借贷发生额","nature":"汇兑损失","分类":"无法区分","源文件行号":43,"科目":"6603.02 财务费用-汇兑损益","金额":14650.0,"金额口径":"借贷发生额；已结转同额时按收益／损失及红字方向还原"}]

Sheet 汇兑事项复核
A1: 类型 | B1: 日期 | C1: 凭证号 | D1: 凭证类型 | E1: 系统分类 | F1: 借贷科目组合 | G1: 借方科目 | H1: 贷方科目 | I1: 账面汇兑损益 | J1: 处理状态 | K1: 复核原因 | L1: 凭证摘要
A2: 非货币性项目产生了账面汇兑损益 | B2: 2026-03-13 | C2: 默认主体-2026-03-13-记-0041 | E2: 不构成汇兑事项 | F2: 借：1123.02、6603.02；贷：1002.01 | G2: 1123.02、6603.02 | H2: 1002.01 | I2: 1200 | J2: 不构成汇兑事项，账面汇差已剔除 | K2: 对方科目为预付款、存货、固定资产等非货币性项目，不产生外币汇兑损益；账面汇差建议重分类复核 | L2: 购汇日元预付日本供应商货款
A3: 非货币性项目产生了账面汇兑损益 | B3: 2026-06-13 | C3: 默认主体-2026-06-13-记-0094 | E3: 不构成汇兑事项 | F3: 借：1123.02、6603.02；贷：1002.01 | G3: 1123.02、6603.02 | H3: 1002.01 | I3: 1200 | J3: 不构成汇兑事项，账面汇差已剔除 | K3: 对方科目为预付款、存货、固定资产等非货币性项目，不产生外币汇兑损益；账面汇差建议重分类复核 | L3: 购汇日元预付日本供应商货款
A4: 合计 2 张 | I4: 2400
